Workbook

Sheet Resumen
A1: Consolidated Income | C1: DIA | D1: =COUNT(C7:C37) -> 0
A3: =+'Biyemas S.A.'!A3 -> Reporte Flash Agosto 26
D4: SLOTS | L4: ELECTRONIC ROULLETTE - ON LINE | T4: Win | U4: Total | V4: MAQUINA POKER | AD4: On line | AE4: Win | AG4: BINGO | AL4: FOOD & BEVERAGE | AN4: PARKING | AQ4: EGA | AY4: Positions | BA4: Customers | BC4: Vehicles | BE4: Revenues vs. Budget (w/seasonality) | BJ4: Revenues
D5: ON LINE | O5: on line | P5: % win/ | Q5: % win/ | T5: (Slot + RE) | U5: electronic | V5: ON LINE | AD5: Electronic | AE5: Financial | AF5: Difference | AG5: nº | AI5: Net | AK5: Total | AV5: TOTAL NET | AY5: on line | AZ5: vs. Budget | BA5: Budget | BB5: Deviation | BC5: Budget | BD5: Desviation | BE5: Total | BF5: Electronic | BG5: Bingo | BH5: F&B | BI5: Parking | BJ5: Total | BK5: Electronic | BL5: Bingo | BM5: F&B | BN5: Parking
A6: Day | B6: Fecha | C6: Custom. | D6: Units | E6: Coin in | F6: Drop | G6: Win | H6: coin in | I6: Drop | J6: /Cust. | K6: /Units. | L6: Seats | M6: Coin in | N6: Drop | O6: Win | P6: coin in | Q6: Drop | R6: /Cust. | S6: /Seat | T6: / Stand | U6: positions | V6: Units | W6: Coin in | X6: Drop | Y6: Win | Z6: coin in | AA6: Drop | AB6: /Cust. | AC6: /Units. | AD6: Win | AE6: Win | AG6: Cards | AH6: Sales | AI6: win | AJ6: /Cust. | AK6: Gaming | AL6: Sales | AM6: /Cust. | AN6: Vehicles | AO6: Sales | AP6: /Vehic | AQ6: Simulador | AR6: PlayStation | AS6: Arcade | AT6: Total EGA | AU6: Total PRM | AV6: REVENUES | AW6: /Cust. | AZ6: =+'Biyemas S.A.'!AZ6+'Kandiko S.A'!AZ6+'Rebisco S.A.'!AZ6 -> 0 | BJ6: =+'Biyemas S.A.'!BJ6+'Kandiko S.A'!BJ6+'Rebisco S.A.'!BJ6 -> 0 | BK6: =+'Biyemas S.A.'!BK6+'Kandiko S.A'!BK6+'Rebisco S.A.'!BK6 -> 0 | BL6: =+'Biyemas S.A.'!BL6+'Kandiko S.A'!BL6+'Rebisco S.A.'!BL6 -> 0 | BM6: =+'Biyemas S.A.'!BM6+'Kandiko S.A'!BM6+'Rebisco S.A.'!BM6 -> 0 | BN6: =+'Biyemas S.A.'!BN6+'Kandiko S.A'!BN6+'Rebisco S.A.'!BN6 -> 0
A7: =IF(BP7='Datos Biyemas'!A9,'Datos Biyemas'!A9,"") | B7: =IF(BP7=A7,'Datos Biyemas'!B9,"") | C7: =IF(A7=BP7,+'Biyemas S.A.'!C7+'Kandiko S.A'!C7+'Rebisco S.A.'!C7,"") | D7: =IF(A7=BP7,+'Biyemas S.A.'!D7+'Kandiko S.A'!D7+'Rebisco S.A.'!D7,"") | E7: =IF(A7=BP7,+'Biyemas S.A.'!E7+'Kandiko S.A'!E7+'Rebisco S.A.'!E7,"") | F7: =IF(A7=BP7,+'Biyemas S.A.'!F7+'Kandiko S.A'!F7+'Rebisco S.A.'!F7,"") | G7: =IF(A7=BP7,+'Biyemas S.A.'!G7+'Kandiko S.A'!G7+'Rebisco S.A.'!G7,"") | H7: =IF(BP7=A7,IF(E7>0,+G7/E7,0),"") | I7: =IF(A7="","",IF(F7>0,+G7/F7,0)) | J7: =IF(A7="","",IF(G7>0,+G7/C7,0)) | K7: =IF(A7="","",IF(G7>0,+G7/D7,0)) | L7: =IF(A7=BP7,+'Biyemas S.A.'!L7+'Kandiko S.A'!L7+'Rebisco S.A.'!L7,"") | M7: =IF(A7=BP7,+'Biyemas S.A.'!M7+'Kandiko S.A'!M7+'Rebisco S.A.'!M7,"") | N7: =IF(A7=BP7,+'Biyemas S.A.'!N7+'Kandiko S.A'!N7+'Rebisco S.A.'!N7,"") | O7: =IF(A7=BP7,+'Biyemas S.A.'!O7+'Kandiko S.A'!O7+'Rebisco S.A.'!O7,"") | P7: =IF(A7="","",IF(M7>0,+O7/M7,0)) | Q7: =IF(A7="","",IF(N7>0,+O7/N7,0)) | R7: =IF(A7="","",IF(C7>0,+O7/C7,0)) | S7: =IF(A7="","",IF(C7>0,+O7/L7,0)) | T7: =IF(A7="","",IF(G7>0,(G7+O7)/(D7+L7),0)) | U7: =IF(A7="","",IF(D7>0,+L7+D7,0)) | V7: =+'Biyemas S.A.'!V7 | W7: =+'Biyemas S.A.'!W7 | X7: =+'Biyemas S.A.'!X7 | Y7: =+'Biyemas S.A.'!Y7 | Z7: =IF(A7="","",IF(W7>0,+Y7/W7,0)) | AA7: =IF(A7="","",IF(X7>0,+Y7/X7,0)) | AB7: =IF(A7="","",IF(Y7>0,+Y7/K7,0)) | AC7: =IF(A7="","",IF(Y7>0,+Y7/V7,0)) | AD7: =IF(A7=BP7,+G7+O7+Y7,"") | AE7: =IF(A7=BP7,+'Biyemas S.A.'!AE7+'Kandiko S.A'!AE7+'Rebisco S.A.'!AE7,"") | AF7: =IF(A7="","",+AD7-AE7) | AG7: =IF(A7=BP7,+'Biyemas S.A.'!AG7+'Kandiko S.A'!AG7+'Rebisco S.A.'!AG7,"") | AH7: =IF(A7=BP7,+'Biyemas S.A.'!AH7+'Kandiko S.A'!AH7+'Rebisco S.A.'!AH7,"") | AI7: =IF(A7=BP7,+'Biyemas S.A.'!AI7+'Kandiko S.A'!AI7+'Rebisco S.A.'!AI7,"") | AJ7: =IF(A7="","",IF(AI7>0,+AI7/C7,0)) | AK7: =IF(A7="","",+G7+O7+AI7+Y7) | AL7: =IF(A7=BP7,+'Biyemas S.A.'!AL7+'Kandiko S.A'!AL7+'Rebisco S.A.'!AL7,"") | AM7: =IF(A7="","",IF(AL7>0,+AL7/C7,0)) | AN7: =IF(A7=BP7,+'Biyemas S.A.'!AN7+'Kandiko S.A'!AN7+'Rebisco S.A.'!AN7,"") | AO7: =IF(A7=BP7,+'Biyemas S.A.'!AO7+'Kandiko S.A'!AO7+'Rebisco S.A.'!AO7,"") | AP7: =IF(A7="","",IF(AN7>0,+AO7/AN7,0)) | AQ7: =IF(A7=BP7,+'Biyemas S.A.'!AQ7+'Kandiko S.A'!AQ7+'Rebisco S.A.'!AQ7,"") | AR7: =IF(A7=BP7,+'Biyemas S.A.'!AR7+'Kandiko S.A'!AR7+'Rebisco S.A.'!AR7,"") | AS7: =IF(A7=BP7,+'Biyemas S.A.'!AS7+'Kandiko S.A'!AS7+'Rebisco S.A.'!AS7,"") | AT7: =IF(A7=BP7,+'Biyemas S.A.'!AT7+'Kandiko S.A'!AT7+'Rebisco S.A.'!AT7,"") | AU7: =IFERROR('Biyemas S.A.'!AU7+'Kandiko S.A'!AU7+'Rebisco S.A.'!AU7,0) -> 0 | AV7: =IF(A7="","",+AD7+AI7+AL7+AO7) | AW7: =IF(A7="","",IF(AV7>0,+AV7/C7,0)) | AY7: =IF(A7=BP7,+'Biyemas S.A.'!AY7+'Kandiko S.A'!AY7+'Rebisco S.A.'!AY7,"") | AZ7: =IF(A7="","",IF($AZ$6>0,+AY7-$AZ$6,)) | BA7: =IF(A7=BP7,+'Biyemas S.A.'!BA7+'Kandiko S.A'!BA7+'Rebisco S.A.'!BA7,"") | BB7: =IF(A7="","",IF(BA7>0,(C7-BA7)/BA7,100%)) | BC7: =IF(A7=BP7,+'Biyemas S.A.'!BC7+'Kandiko S.A'!BC7+'Rebisco S.A.'!BC7,"") | BD7: =IF(A7="","",IF(AN7=BC7,0,IF(BC7>0,(AN7-BC7)/BC7,1))) | BE7: =IF(A7="","",VLOOKUP(B7,'Datos Consolidados'!B9:BF46,53,0)) | BF7: =IF(A7="","",VLOOKUP(B7,'Datos Consolidados'!B9:BF46,54,0)) | BG7: =IF(A7="","",VLOOKUP(B7,'Datos Consolidados'!B9:BF46,55,0)) | BH7: =IF(A7="","",VLOOKUP(B7,'Datos Consolidados'!B9:BF46,51,0)) | BI7: =IF(A7="","",VLOOKUP(B7,'Datos Consolidados'!B9:BF46,52,0)) | BJ7: =IF(A7="","",+AV7/$BJ$6-1) | BK7: =IF(A7="","",+AD7/$BK$6-1) | BL7: =IF(A7="","",+AI7/$BL$6-1) | BM7: =IF(A7="","",AL7/$BM$6-1) | BN7: =+'Biyemas S.A.'!BN7 | BP7: =+'Biyemas S.A.'!BP7 -> Sab/Sat
A8: =IF(BP8='Datos Biyemas'!A10,'Datos Biyemas'!A10,"") | B8: =IF(BP8=A8,'Datos Biyemas'!B10,"") | C8: =IF(A8=BP8,+'Biyemas S.A.'!C8+'Kandiko S.A'!C8+'Rebisco S.A.'!C8,"") | D8: =IF(A8=BP8,+'Biyemas S.A.'!D8+'Kandiko S.A'!D8+'Rebisco S.A.'!D8,"") | E8: =IF(A8=BP8,+'Biyemas S.A.'!E8+'Kandiko S.A'!E8+'Rebisco S.A.'!E8,"") | F8: =IF(A8=BP8,+'Biyemas S.A.'!F8+'Kandiko S.A'!F8+'Rebisco S.A.'!F8,"") | G8: =IF(A8=BP8,+'Biyemas S.A.'!G8+'Kandiko S.A'!G8+'Rebisco S.A.'!G8,"") | H8: =IF(BP8=A8,IF(E8>0,+G8/E8,0),"") | I8: =IF(A8="","",IF(F8>0,+G8/F8,0)) | J8: =IF(A8="","",IF(G8>0,+G8/C8,0)) | K8: =IF(A8="","",IF(G8>0,+G8/D8,0)) | L8: =IF(A8=BP8,+'Biyemas S.A.'!L8+'Kandiko S.A'!L8+'Rebisco S.A.'!L8,"") | M8: =IF(A8=BP8,+'Biyemas S.A.'!M8+'Kandiko S.A'!M8+'Rebisco S.A.'!M8,"") | N8: =IF(A8=BP8,+'Biyemas S.A.'!N8+'Kandiko S.A'!N8+'Rebisco S.A.'!N8,"") | O8: =IF(A8=BP8,+'Biyemas S.A.'!O8+'Kandiko S.A'!O8+'Rebisco S.A.'!O8,"") | P8: =IF(A8="","",IF(M8>0,+O8/M8,0)) | Q8: =IF(A8="","",IF(N8>0,+O8/N8,0)) | R8: =IF(A8="","",IF(C8>0,+O8/C8,0)) | S8: =IF(A8="","",IF(C8>0,+O8/L8,0)) | T8: =IF(A8="","",IF(G8>0,(G8+O8)/(D8+L8),0)) | U8: =IF(A8="","",IF(D8>0,+L8+D8,0)) | V8: =IF(A8="","",VLOOKUP(B8,'Datos Biyemas'!B10:BB47,21,0)) | W8: =IF(A8="","",VLOOKUP(B8,'Datos Biyemas'!B10:BB47,22,0)) | X8: =IF(A8="","",VLOOKUP(B8,'Datos Biyemas'!B10:BB47,23,0)) | Y8: =IF(A8="","",VLOOKUP(B8,'Datos Biyemas'!B10:BB47,24,0)) | Z8: =IF(A8="","",IF(W8>0,+Y8/W8,0)) | AA8: =IF(A8="","",IF(X8>0,+Y8/X8,0)) | AB8: =IF(A8="","",IF(Y8>0,+Y8/K8,0)) | AC8: =IF(A8="","",IF(Y8>0,+Y8/V8,0)) | AD8: =IF(A8=BP8,+G8+O8+Y8,"") | AE8: =IF(A8=BP8,+'Biyemas S.A.'!AE8+'Kandiko S.A'!AE8+'Rebisco S.A.'!AE8,"") | AF8: =IF(A8="","",+AD8-AE8) | AG8: =IF(A8=BP8,+'Biyemas S.A.'!AG8+'Kandiko S.A'!AG8+'Rebisco S.A.'!AG8,"") | AH8: =IF(A8=BP8,+'Biyemas S.A.'!AH8+'Kandiko S.A'!AH8+'Rebisco S.A.'!AH8,"") | AI8: =IF(A8=BP8,+'Biyemas S.A.'!AI8+'Kandiko S.A'!AI8+'Rebisco S.A.'!AI8,"") | AJ8: =IF(A8="","",IF(AI8>0,+AI8/C8,0)) | AK8: =IF(A8="","",+G8+O8+AI8+Y8) | AL8: =IF(A8=BP8,+'Biyemas S.A.'!AL8+'Kandiko S.A'!AL8+'Rebisco S.A.'!AL8,"") | AM8: =IF(A8="","",IF(AL8>0,+AL8/C8,0)) | AN8: =IF(A8=BP8,+'Biyemas S.A.'!AN8+'Kandiko S.A'!AN8+'Rebisco S.A.'!AN8,"") | AO8: =IF(A8=BP8,+'Biyemas S.A.'!AO8+'Kandiko S.A'!AO8+'Rebisco S.A.'!AO8,"") | AP8: =IF(A8="","",IF(AN8>0,+AO8/AN8,0)) | AQ8: =IF(A8=BP8,+'Biyemas S.A.'!AQ8+'Kandiko S.A'!AQ8+'Rebisco S.A.'!AQ8,"") | AR8: =IF(A8=BP8,+'Biyemas S.A.'!AR8+'Kandiko S.A'!AR8+'Rebisco S.A.'!AR8,"") | AS8: =IF(A8=BP8,+'Biyemas S.A.'!AS8+'Kandiko S.A'!AS8+'Rebisco S.A.'!AS8,"") | AT8: =IF(A8=BP8,+'Biyemas S.A.'!AT8+'Kandiko S.A'!AT8+'Rebisco S.A.'!AT8,"") | AU8: =IFERROR('Biyemas S.A.'!AU8+'Kandiko S.A'!AU8+'Rebisco S.A.'!AU8,0) -> 0 | AV8: =IF(A8="","",+AD8+AI8+AL8+AO8) | AW8: =IF(A8="","",IF(AV8>0,+AV8/C8,0)) | AY8: =IF(A8=BP8,+'Biyemas S.A.'!AY8+'Kandiko S.A'!AY8+'Rebisco S.A.'!AY8,"") | AZ8: =IF(A8="","",IF($AZ$6>0,+AY8-$AZ$6,)) | BA8: =IF(A8=BP8,+'Biyemas S.A.'!BA8+'Kandiko S.A'!BA8+'Rebisco S.A.'!BA8,"") | BB8: =IF(A8="","",IF(BA8>0,(C8-BA8)/BA8,100%)) | BC8: =IF(A8=BP8,+'Biyemas S.A.'!BC8+'Kandiko S.A'!BC8+'Rebisco S.A.'!BC8,"") | BD8: =IF(A8="","",IF(AN8=BC8,0,IF(BC8>0,(AN8-BC8)/BC8,1))) | BE8: =IF(A8="","",VLOOKUP(B8,'Datos Consolidados'!B10:BF47,53,0)) | BF8: =IF(A8="","",VLOOKUP(B8,'Datos Consolidados'!B10:BF47,54,0)) | BG8: =IF(A8="","",VLOOKUP(B8,'Datos Consolidados'!B10:BF47,55,0)) | BH8: =IF(A8="","",VLOOKUP(B8,'Datos Consolidados'!B10:BF47,51,0)) | BI8: =IF(A8="","",VLOOKUP(B8,'Datos Consolidados'!B10:BF47,52,0)) | BJ8: =IF(A8="","",+AV8/$BJ$6-1) | BK8: =IF(A8="","",+AD8/$BK$6-1) | BL8: =IF(A8="","",+AI8/$BL$6-1) | BM8: =IF(A8="","",AL8/$BM$6-1) | BN8: =+'Biyemas S.A.'!BN8 | BP8: =+'Biyemas S.A.'!BP8 -> Dom/Sun
A9: =IF(BP9='Datos Biyemas'!A11,'Datos Biyemas'!A11,"") | B9: =IF(BP9=A9,'Datos Biyemas'!B11,"") | C9: =IF(A9=BP9,+'Biyemas S.A.'!C9+'Kandiko S.A'!C9+'Rebisco S.A.'!C9,"") | D9: =IF(A9=BP9,+'Biyemas S.A.'!D9+'Kandiko S.A'!D9+'Rebisco S.A.'!D9,"") | E9: =IF(A9=BP9,+'Biyemas S.A.'!E9+'Kandiko S.A'!E9+'Rebisco S.A.'!E9,"") | F9: =IF(A9=BP9,+'Biyemas S.A.'!F9+'Kandiko S.A'!F9+'Rebisco S.A.'!F9,"") | G9: =IF(A9=BP9,+'Biyemas S.A.'!G9+'Kandiko S.A'!G9+'Rebisco S.A.'!G9,"") | H9: =IF(BP9=A9,IF(E9>0,+G9/E9,0),"") | I9: =IF(A9="","",IF(F9>0,+G9/F9,0)) | J9: =IF(A9="","",IF(G9>0,+G9/C9,0)) | K9: =IF(A9="","",IF(G9>0,+G9/D9,0)) | L9: =IF(A9=BP9,+'Biyemas S.A.'!L9+'Kandiko S.A'!L9+'Rebisco S.A.'!L9,"") | M9: =IF(A9=BP9,+'Biyemas S.A.'!M9+'Kandiko S.A'!M9+'Rebisco S.A.'!M9,"") | N9: =IF(A9=BP9,+'Biyemas S.A.'!N9+'Kandiko S.A'!N9+'Rebisco S.A.'!N9,"") | O9: =IF(A9=BP9,+'Biyemas S.A.'!O9+'Kandiko S.A'!O9+'Rebisco S.A.'!O9,"") | P9: =IF(A9="","",IF(M9>0,+O9/M9,0)) | Q9: =IF(A9="","",IF(N9>0,+O9/N9,0)) | R9: =IF(A9="","",IF(C9>0,+O9/C9,0)) | S9: =IF(A9="","",IF(C9>0,+O9/L9,0)) | T9: =IF(A9="","",IF(G9>0,(G9+O9)/(D9+L9),0)) | U9: =IF(A9="","",IF(D9>0,+L9+D9,0)) | V9: =IF(A9="","",VLOOKUP(B9,'Datos Biyemas'!B11:BB48,21,0)) | W9: =IF(A9="","",VLOOKUP(B9,'Datos Biyemas'!B11:BB48,22,0)) | X9: =IF(A9="","",VLOOKUP(B9,'Datos Biyemas'!B11:BB48,23,0)) | Y9: =IF(A9="","",VLOOKUP(B9,'Datos Biyemas'!B11:BB48,24,0)) | Z9: =IF(A9="","",IF(W9>0,+Y9/W9,0)) | AA9: =IF(A9="","",IF(X9>0,+Y9/X9,0)) | AB9: =IF(A9="","",IF(Y9>0,+Y9/K9,0)) | AC9: =IF(A9="","",IF(Y9>0,+Y9/V9,0)) | AD9: =IF(A9=BP9,+G9+O9+Y9,"") | AE9: =IF(A9=BP9,+'Biyemas S.A.'!AE9+'Kandiko S.A'!AE9+'Rebisco S.A.'!AE9,"") | AF9: =IF(A9="","",+AD9-AE9) | AG9: =IF(A9=BP9,+'Biyemas S.A.'!AG9+'Kandiko S.A'!AG9+'Rebisco S.A.'!AG9,"") | AH9: =IF(A9=BP9,+'Biyemas S.A.'!AH9+'Kandiko S.A'!AH9+'Rebisco S.A.'!AH9,"") | AI9: =IF(A9=BP9,+'Biyemas S.A.'!AI9+'Kandiko S.A'!AI9+'Rebisco S.A.'!AI9,"") | AJ9: =IF(A9="","",IF(AI9>0,+AI9/C9,0)) | AK9: =IF(A9="","",+G9+O9+AI9+Y9) | AL9: =IF(A9=BP9,+'Biyemas S.A.'!AL9+'Kandiko S.A'!AL9+'Rebisco S.A.'!AL9,"") | AM9: =IF(A9="","",IF(AL9>0,+AL9/C9,0)) | AN9: =IF(A9=BP9,+'Biyemas S.A.'!AN9+'Kandiko S.A'!AN9+'Rebisco S.A.'!AN9,"") | AO9: =IF(A9=BP9,+'Biyemas S.A.'!AO9+'Kandiko S.A'!AO9+'Rebisco S.A.'!AO9,"") | AP9: =IF(A9="","",IF(AN9>0,+AO9/AN9,0)) | AQ9: =IF(A9=BP9,+'Biyemas S.A.'!AQ9+'Kandiko S.A'!AQ9+'Rebisco S.A.'!AQ9,"") | AR9: =IF(A9=BP9,+'Biyemas S.A.'!AR9+'Kandiko S.A'!AR9+'Rebisco S.A.'!AR9,"") | AS9: =IF(A9=BP9,+'Biyemas S.A.'!AS9+'Kandiko S.A'!AS9+'Rebisco S.A.'!AS9,"") | AT9: =IF(A9=BP9,+'Biyemas S.A.'!AT9+'Kandiko S.A'!AT9+'Rebisco S.A.'!AT9,"") | AU9: =IFERROR('Biyemas S.A.'!AU9+'Kandiko S.A'!AU9+'Rebisco S.A.'!AU9,0) -> 0 | AV9: =IF(A9="","",+AD9+AI9+AL9+AO9) | AW9: =IF(A9="","",IF(AV9>0,+AV9/C9,0)) | AY9: =IF(A9=BP9,+'Biyemas S.A.'!AY9+'Kandiko S.A'!AY9+'Rebisco S.A.'!AY9,"") | AZ9: =IF(A9="","",IF($AZ$6>0,+AY9-$AZ$6,)) | BA9: =IF(A9=BP9,+'Biyemas S.A.'!BA9+'Kandiko S.A'!BA9+'Rebisco S.A.'!BA9,"") | BB9: =IF(A9="","",IF(BA9>0,(C9-BA9)/BA9,100%)) | BC9: =IF(A9=BP9,+'Biyemas S.A.'!BC9+'Kandiko S.A'!BC9+'Rebisco S.A.'!BC9,"") | BD9: =IF(A9="","",IF(AN9=BC9,0,IF(BC9>0,(AN9-BC9)/BC9,1))) | BE9: =IF(A9="","",VLOOKUP(B9,'Datos Consolidados'!B11:BF48,53,0)) | BF9: =IF(A9="","",VLOOKUP(B9,'Datos Consolidados'!B11:BF48,54,0)) | BG9: =IF(A9="","",VLOOKUP(B9,'Datos Consolidados'!B11:BF48,55,0)) | BH9: =IF(A9="","",VLOOKUP(B9,'Datos Consolidados'!B11:BF48,51,0)) | BI9: =IF(A9="","",VLOOKUP(B9,'Datos Consolidados'!B11:BF48,52,0)) | BJ9: =IF(A9="","",+AV9/$BJ$6-1) | BK9: =IF(A9="","",+AD9/$BK$6-1) | BL9: =IF(A9="","",+AI9/$BL$6-1) | BM9: =IF(A9="","",AL9/$BM$6-1) | BN9: =+'Biyemas S.A.'!BN9 | BP9: =+'Biyemas S.A.'!BP9 -> Lun/Mon
A10: =IF(BP10='Datos Biyemas'!A12,'Datos Biyemas'!A12,"") | B10: =IF(BP10=A10,'Datos Biyemas'!B12,"") | C10: =IF(A10=BP10,+'Biyemas S.A.'!C10+'Kandiko S.A'!C10+'Rebisco S.A.'!C10,"") | D10: =IF(A10=BP10,+'Biyemas S.A.'!D10+'Kandiko S.A'!D10+'Rebisco S.A.'!D10,"") | E10: =IF(A10=BP10,+'Biyemas S.A.'!E10+'Kandiko S.A'!E10+'Rebisco S.A.'!E10,"") | F10: =IF(A10=BP10,+'Biyemas S.A.'!F10+'Kandiko S.A'!F10+'Rebisco S.A.'!F10,"") | G10: =IF(A10=BP10,+'Biyemas S.A.'!G10+'Kandiko S.A'!G10+'Rebisco S.A.'!G10,"") | H10: =IF(BP10=A10,IF(E10>0,+G10/E10,0),"") | I10: =IF(A10="","",IF(F10>0,+G10/F10,0)) | J10: =IF(A10="","",IF(G10>0,+G10/C10,0)) | K10: =IF(A10="","",IF(G10>0,+G10/D10,0)) | L10: =IF(A10=BP10,+'Biyemas S.A.'!L10+'Kandiko S.A'!L10+'Rebisco S.A.'!L10,"") | M10: =IF(A10=BP10,+'Biyemas S.A.'!M10+'Kandiko S.A'!M10+'Rebisco S.A.'!M10,"") | N10: =IF(A10=BP10,+'Biyemas S.A.'!N10+'Kandiko S.A'!N10+'Rebisco S.A.'!N10,"") | O10: =IF(A10=BP10,+'Biyemas S.A.'!O10+'Kandiko S.A'!O10+'Rebisco S.A.'!O10,"") | P10: =IF(A10="","",IF(M10>0,+O10/M10,0)) | Q10: =IF(A10="","",IF(N10>0,+O10/N10,0)) | R10: =IF(A10="","",IF(C10>0,+O10/C10,0)) | S10: =IF(A10="","",IF(C10>0,+O10/L10,0)) | T10: =IF(A10="","",IF(G10>0,(G10+O10)/(D10+L10),0)) | U10: =IF(A10="","",IF(D10>0,+L10+D10,0)) | V10: =IF(A10="","",VLOOKUP(B10,'Datos Biyemas'!B12:BB49,21,0)) | W10: =IF(A10="","",VLOOKUP(B10,'Datos Biyemas'!B12:BB49,22,0)) | X10: =IF(A10="","",VLOOKUP(B10,'Datos Biyemas'!B12:BB49,23,0)) | Y10: =IF(A10="","",VLOOKUP(B10,'Datos Biyemas'!B12:BB49,24,0)) | Z10: =IF(A10="","",IF(W10>0,+Y10/W10,0)) | AA10: =IF(A10="","",IF(X10>0,+Y10/X10,0)) | AB10: =IF(A10="","",IF(Y10>0,+Y10/K10,0)) | AC10: =IF(A10="","",IF(Y10>0,+Y10/V10,0)) | AD10: =IF(A10=BP10,+G10+O10+Y10,"") | AE10: =IF(A10=BP10,+'Biyemas S.A.'!AE10+'Kandiko S.A'!AE10+'Rebisco S.A.'!AE10,"") | AF10: =IF(A10="","",+AD10-AE10) | AG10: =IF(A10=BP10,+'Biyemas S.A.'!AG10+'Kandiko S.A'!AG10+'Rebisco S.A.'!AG10,"") | AH10: =IF(A10=BP10,+'Biyemas S.A.'!AH10+'Kandiko S.A'!AH10+'Rebisco S.A.'!AH10,"") | AI10: =IF(A10=BP10,+'Biyemas S.A.'!AI10+'Kandiko S.A'!AI10+'Rebisco S.A.'!AI10,"") | AJ10: =IF(A10="","",IF(AI10>0,+AI10/C10,0)) | AK10: =IF(A10="","",+G10+O10+AI10+Y10) | AL10: =IF(A10=BP10,+'Biyemas S.A.'!AL10+'Kandiko S.A'!AL10+'Rebisco S.A.'!AL10,"") | AM10: =IF(A10="","",IF(AL10>0,+AL10/C10,0)) | AN10: =IF(A10=BP10,+'Biyemas S.A.'!AN10+'Kandiko S.A'!AN10+'Rebisco S.A.'!AN10,"") | AO10: =IF(A10=BP10,+'Biyemas S.A.'!AO10+'Kandiko S.A'!AO10+'Rebisco S.A.'!AO10,"") | AP10: =IF(A10="","",IF(AN10>0,+AO10/AN10,0)) | AQ10: =IF(A10=BP10,+'Biyemas S.A.'!AQ10+'Kandiko S.A'!AQ10+'Rebisco S.A.'!AQ10,"") | AR10: =IF(A10=BP10,+'Biyemas S.A.'!AR10+'Kandiko S.A'!AR10+'Rebisco S.A.'!AR10,"") | AS10: =IF(A10=BP10,+'Biyemas S.A.'!AS10+'Kandiko S.A'!AS10+'Rebisco S.A.'!AS10,"") | AT10: =IF(A10=BP10,+'Biyemas S.A.'!AT10+'Kandiko S.A'!AT10+'Rebisco S.A.'!AT10,"") | AU10: =IFERROR('Biyemas S.A.'!AU10+'Kandiko S.A'!AU10+'Rebisco S.A.'!AU10,0) -> 0 | AV10: =IF(A10="","",+AD10+AI10+AL10+AO10) | AW10: =IF(A10="","",IF(AV10>0,+AV10/C10,0)) | AY10: =IF(A10=BP10,+'Biyemas S.A.'!AY10+'Kandiko S.A'!AY10+'Rebisco S.A.'!AY10,"") | AZ10: =IF(A10="","",IF($AZ$6>0,+AY10-$AZ$6,)) | BA10: =IF(A10=BP10,+'Biyemas S.A.'!BA10+'Kandiko S.A'!BA10+'Rebisco S.A.'!BA10,"") | BB10: =IF(A10="","",IF(BA10>0,(C10-BA10)/BA10,100%)) | BC10: =IF(A10=BP10,+'Biyemas S.A.'!BC10+'Kandiko S.A'!BC10+'Rebisco S.A.'!BC10,"") | BD10: =IF(A10="","",IF(AN10=BC10,0,IF(BC10>0,(AN10-BC10)/BC10,1))) | BE10: =IF(A10="","",VLOOKUP(B10,'Datos Consolidados'!B12:BF49,53,0)) | BF10: =IF(A10="","",VLOOKUP(B10,'Datos Consolidados'!B12:BF49,54,0)) | BG10: =IF(A10="","",VLOOKUP(B10,'Datos Consolidados'!B12:BF49,55,0)) | BH10: =IF(A10="","",VLOOKUP(B10,'Datos Consolidados'!B12:BF49,51,0)) | BI10: =IF(A10="","",VLOOKUP(B10,'Datos Consolidados'!B12:BF49,52,0)) | BJ10: =IF(A10="","",+AV10/$BJ$6-1) | BK10: =IF(A10="","",+AD10/$BK$6-1) | BL10: =IF(A10="","",+AI10/$BL$6-1) | BM10: =IF(A10="","",AL10/$BM$6-1) | BN10: =+'Biyemas S.A.'!BN10 | BP10: =+'Biyemas S.A.'!BP10 -> Mar/Tue
A11: =IF(BP11='Datos Biyemas'!A13,'Datos Biyemas'!A13,"") | B11: =IF(BP11=A11,'Datos Biyemas'!B13,"") | C11: =IF(A11=BP11,+'Biyemas S.A.'!C11+'Kandiko S.A'!C11+'Rebisco S.A.'!C11,"") | D11: =IF(A11=BP11,+'Biyemas S.A.'!D11+'Kandiko S.A'!D11+'Rebisco S.A.'!D11,"") | E11: =IF(A11=BP11,+'Biyemas S.A.'!E11+'Kandiko S.A'!E11+'Rebisco S.A.'!E11,"") | F11: =IF(A11=BP11,+'Biyemas S.A.'!F11+'Kandiko S.A'!F11+'Rebisco S.A.'!F11,"") | G11: =IF(A11=BP11,+'Biyemas S.A.'!G11+'Kandiko S.A'!G11+'Rebisco S.A.'!G11,"") | H11: =IF(BP11=A11,IF(E11>0,+G11/E11,0),"") | I11: =IF(A11="","",IF(F11>0,+G11/F11,0)) | J11: =IF(A11="","",IF(G11>0,+G11/C11,0)) | K11: =IF(A11="","",IF(G11>0,+G11/D11,0)) | L11: =IF(A11=BP11,+'Biyemas S.A.'!L11+'Kandiko S.A'!L11+'Rebisco S.A.'!L11,"") | M11: =IF(A11=BP11,+'Biyemas S.A.'!M11+'Kandiko S.A'!M11+'Rebisco S.A.'!M11,"") | N11: =IF(A11=BP11,+'Biyemas S.A.'!N11+'Kandiko S.A'!N11+'Rebisco S.A.'!N11,"") | O11: =IF(A11=BP11,+'Biyemas S.A.'!O11+'Kandiko S.A'!O11+'Rebisco S.A.'!O11,"") | P11: =IF(A11="","",IF(M11>0,+O11/M11,0)) | Q11: =IF(A11="","",IF(N11>0,+O11/N11,0)) | R11: =IF(A11="","",IF(C11>0,+O11/C11,0)) | S11: =IF(A11="","",IF(C11>0,+O11/L11,0)) | T11: =IF(A11="","",IF(G11>0,(G11+O11)/(D11+L11),0)) | U11: =IF(A11="","",IF(D11>0,+L11+D11,0)) | V11: =IF(A11="","",VLOOKUP(B11,'Datos Biyemas'!B13:BB50,21,0)) | W11: =IF(A11="","",VLOOKUP(B11,'Datos Biyemas'!B13:BB50,22,0)) | X11: =IF(A11="","",VLOOKUP(B11,'Datos Biyemas'!B13:BB50,23,0)) | Y11: =IF(A11="","",VLOOKUP(B11,'Datos Biyemas'!B13:BB50,24,0)) | Z11: =IF(A11="","",IF(W11>0,+Y11/W11,0)) | AA11: =IF(A11="","",IF(X11>0,+Y11/X11,0)) | AB11: =IF(A11="","",IF(Y11>0,+Y11/K11,0)) | AC11: =IF(A11="","",IF(Y11>0,+Y11/V11,0)) | AD11: =IF(A11=BP11,+G11+O11+Y11,"") | AE11: =IF(A11=BP11,+'Biyemas S.A.'!AE11+'Kandiko S.A'!AE11+'Rebisco S.A.'!AE11,"") | AF11: =IF(A11="","",+AD11-AE11) | AG11: =IF(A11=BP11,+'Biyemas S.A.'!AG11+'Kandiko S.A'!AG11+'Rebisco S.A.'!AG11,"") | AH11: =IF(A11=BP11,+'Biyemas S.A.'!AH11+'Kandiko S.A'!AH11+'Rebisco S.A.'!AH11,"") | AI11: =IF(A11=BP11,+'Biyemas S.A.'!AI11+'Kandiko S.A'!AI11+'Rebisco S.A.'!AI11,"") | AJ11: =IF(A11="","",IF(AI11>0,+AI11/C11,0)) | AK11: =IF(A11="","",+G11+O11+AI11+Y11) | AL11: =IF(A11=BP11,+'Biyemas S.A.'!AL11+'Kandiko S.A'!AL11+'Rebisco S.A.'!AL11,"") | AM11: =IF(A11="","",IF(AL11>0,+AL11/C11,0)) | AN11: =IF(A11=BP11,+'Biyemas S.A.'!AN11+'Kandiko S.A'!AN11+'Rebisco S.A.'!AN11,"") | AO11: =IF(A11=BP11,+'Biyemas S.A.'!AO11+'Kandiko S.A'!AO11+'Rebisco S.A.'!AO11,"") | AP11: =IF(A11="","",IF(AN11>0,+AO11/AN11,0)) | AQ11: =IF(A11=BP11,+'Biyemas S.A.'!AQ11+'Kandiko S.A'!AQ11+'Rebisco S.A.'!AQ11,"") | AR11: =IF(A11=BP11,+'Biyemas S.A.'!AR11+'Kandiko S.A'!AR11+'Rebisco S.A.'!AR11,"") | AS11: =IF(A11=BP11,+'Biyemas S.A.'!AS11+'Kandiko S.A'!AS11+'Rebisco S.A.'!AS11,"") | AT11: =IF(A11=BP11,+'Biyemas S.A.'!AT11+'Kandiko S.A'!AT11+'Rebisco S.A.'!AT11,"") | AU11: =IFERROR('Biyemas S.A.'!AU11+'Kandiko S.A'!AU11+'Rebisco S.A.'!AU11,0) -> 0 | AV11: =IF(A11="","",+AD11+AI11+AL11+AO11) | AW11: =IF(A11="","",IF(AV11>0,+AV11/C11,0)) | AY11: =IF(A11=BP11,+'Biyemas S.A.'!AY11+'Kandiko S.A'!AY11+'Rebisco S.A.'!AY11,"") | AZ11: =IF(A11="","",IF($AZ$6>0,+AY11-$AZ$6,)) | BA11: =IF(A11=BP11,+'Biyemas S.A.'!BA11+'Kandiko S.A'!BA11+'Rebisco S.A.'!BA11,"") | BB11: =IF(A11="","",IF(BA11>0,(C11-BA11)/BA11,100%)) | BC11: =IF(A11=BP11,+'Biyemas S.A.'!BC11+'Kandiko S.A'!BC11+'Rebisco S.A.'!BC11,"") | BD11: =IF(A11="","",IF(AN11=BC11,0,IF(BC11>0,(AN11-BC11)/BC11,1))) | BE11: =IF(A11="","",VLOOKUP(B11,'Datos Consolidados'!B13:BF50,53,0)) | BF11: =IF(A11="","",VLOOKUP(B11,'Datos Consolidados'!B13:BF50,54,0)) | BG11: =IF(A11="","",VLOOKUP(B11,'Datos Consolidados'!B13:BF50,55,0)) | BH11: =IF(A11="","",VLOOKUP(B11,'Datos Consolidados'!B13:BF50,51,0)) | BI11: =IF(A11="","",VLOOKUP(B11,'Datos Consolidados'!B13:BF50,52,0)) | BJ11: =IF(A11="","",+AV11/$BJ$6-1) | BK11: =IF(A11="","",+AD11/$BK$6-1) | BL11: =IF(A11="","",+AI11/$BL$6-1) | BM11: =IF(A11="","",AL11/$BM$6-1) | BN11: =+'Biyemas S.A.'!BN11 | BP11: =+'Biyemas S.A.'!BP11 -> Mie/Wed
A12: =IF(BP12='Datos Biyemas'!A14,'Datos Biyemas'!A14,"") | B12: =IF(BP12=A12,'Datos Biyemas'!B14,"") | C12: =IF(A12=BP12,+'Biyemas S.A.'!C12+'Kandiko S.A'!C12+'Rebisco S.A.'!C12,"") | D12: =IF(A12=BP12,+'Biyemas S.A.'!D12+'Kandiko S.A'!D12+'Rebisco S.A.'!D12,"") | E12: =IF(A12=BP12,+'Biyemas S.A.'!E12+'Kandiko S.A'!E12+'Rebisco S.A.'!E12,"") | F12: =IF(A12=BP12,+'Biyemas S.A.'!F12+'Kandiko S.A'!F12+'Rebisco S.A.'!F12,"") | G12: =IF(A12=BP12,+'Biyemas S.A.'!G12+'Kandiko S.A'!G12+'Rebisco S.A.'!G12,"") | H12: =IF(BP12=A12,IF(E12>0,+G12/E12,0),"") | I12: =IF(A12="","",IF(F12>0,+G12/F12,0)) | J12: =IF(A12="","",IF(G12>0,+G12/C12,0)) | K12: =IF(A12="","",IF(G12>0,+G12/D12,0)) | L12: =IF(A12=BP12,+'Biyemas S.A.'!L12+'Kandiko S.A'!L12+'Rebisco S.A.'!L12,"") | M12: =IF(A12=BP12,+'Biyemas S.A.'!M12+'Kandiko S.A'!M12+'Rebisco S.A.'!M12,"") | N12: =IF(A12=BP12,+'Biyemas S.A.'!N12+'Kandiko S.A'!N12+'Rebisco S.A.'!N12,"") | O12: =IF(A12=BP12,+'Biyemas S.A.'!O12+'Kandiko S.A'!O12+'Rebisco S.A.'!O12,"") | P12: =IF(A12="","",IF(M12>0,+O12/M12,0)) | Q12: =IF(A12="","",IF(N12>0,+O12/N12,0)) | R12: =IF(A12="","",IF(C12>0,+O12/C12,0)) | S12: =IF(A12="","",IF(C12>0,+O12/L12,0)) | T12: =IF(A12="","",IF(G12>0,(G12+O12)/(D12+L12),0)) | U12: =IF(A12="","",IF(D12>0,+L12+D12,0)) | V12: =IF(A12="","",VLOOKUP(B12,'Datos Biyemas'!B14:BB51,21,0)) | W12: =IF(A12="","",VLOOKUP(B12,'Datos Biyemas'!B14:BB51,22,0)) | X12: =IF(A12="","",VLOOKUP(B12,'Datos Biyemas'!B14:BB51,23,0)) | Y12: =IF(A12="","",VLOOKUP(B12,'Datos Biyemas'!B14:BB51,24,0)) | Z12: =IF(A12="","",IF(W12>0,+Y12/W12,0)) | AA12: =IF(A12="","",IF(X12>0,+Y12/X12,0)) | AB12: =IF(A12="","",IF(Y12>0,+Y12/K12,0)) | AC12: =IF(A12="","",IF(Y12>0,+Y12/V12,0)) | AD12: =IF(A12=BP12,+G12+O12+Y12,"") | AE12: =IF(A12=BP12,+'Biyemas S.A.'!AE12+'Kandiko S.A'!AE12+'Rebisco S.A.'!AE12,"") | AF12: =IF(A12="","",+AD12-AE12) | AG12: =IF(A12=BP12,+'Biyemas S.A.'!AG12+'Kandiko S.A'!AG12+'Rebisco S.A.'!AG12,"") | AH12: =IF(A12=BP12,+'Biyemas S.A.'!AH12+'Kandiko S.A'!AH12+'Rebisco S.A.'!AH12,"") | AI12: =IF(A12=BP12,+'Biyemas S.A.'!AI12+'Kandiko S.A'!AI12+'Rebisco S.A.'!AI12,"") | AJ12: =IF(A12="","",IF(AI12>0,+AI12/C12,0)) | AK12: =IF(A12="","",+G12+O12+AI12+Y12) | AL12: =IF(A12=BP12,+'Biyemas S.A.'!AL12+'Kandiko S.A'!AL12+'Rebisco S.A.'!AL12,"") | AM12: =IF(A12="","",IF(AL12>0,+AL12/C12,0)) | AN12: =IF(A12=BP12,+'Biyemas S.A.'!AN12+'Kandiko S.A'!AN12+'Rebisco S.A.'!AN12,"") | AO12: =IF(A12=BP12,+'Biyemas S.A.'!AO12+'Kandiko S.A'!AO12+'Rebisco S.A.'!AO12,"") | AP12: =IF(A12="","",IF(AN12>0,+AO12/AN12,0)) | AQ12: =IF(A12=BP12,+'Biyemas S.A.'!AQ12+'Kandiko S.A'!AQ12+'Rebisco S.A.'!AQ12,"") | AR12: =IF(A12=BP12,+'Biyemas S.A.'!AR12+'Kandiko S.A'!AR12+'Rebisco S.A.'!AR12,"") | AS12: =IF(A12=BP12,+'Biyemas S.A.'!AS12+'Kandiko S.A'!AS12+'Rebisco S.A.'!AS12,"") | AT12: =IF(A12=BP12,+'Biyemas S.A.'!AT12+'Kandiko S.A'!AT12+'Rebisco S.A.'!AT12,"") | AU12: =IFERROR('Biyemas S.A.'!AU12+'Kandiko S.A'!AU12+'Rebisco S.A.'!AU12,0) -> 0 | AV12: =IF(A12="","",+AD12+AI12+AL12+AO12) | AW12: =IF(A12="","",IF(AV12>0,+AV12/C12,0)) | AY12: =IF(A12=BP12,+'Biyemas S.A.'!AY12+'Kandiko S.A'!AY12+'Rebisco S.A.'!AY12,"") | AZ12: =IF(A12="","",IF($AZ$6>0,+AY12-$AZ$6,)) | BA12: =IF(A12=BP12,+'Biyemas S.A.'!BA12+'Kandiko S.A'!BA12+'Rebisco S.A.'!BA12,"") | BB12: =IF(A12="","",IF(BA12>0,(C12-BA12)/BA12,100%)) | BC12: =IF(A12=BP12,+'Biyemas S.A.'!BC12+'Kandiko S.A'!BC12+'Rebisco S.A.'!BC12,"") | BD12: =IF(A12="","",IF(AN12=BC12,0,IF(BC12>0,(AN12-BC12)/BC12,1))) | BE12: =IF(A12="","",VLOOKUP(B12,'Datos Consolidados'!B14:BF51,53,0)) | BF12: =IF(A12="","",VLOOKUP(B12,'Datos Consolidados'!B14:BF51,54,0)) | BG12: =IF(A12="","",VLOOKUP(B12,'Datos Consolidados'!B14:BF51,55,0)) | BH12: =IF(A12="","",VLOOKUP(B12,'Datos Consolidados'!B14:BF51,51,0)) | BI12: =IF(A12="","",VLOOKUP(B12,'Datos Consolidados'!B14:BF51,52,0)) | BJ12: =IF(A12="","",+AV12/$BJ$6-1) | BK12: =IF(A12="","",+AD12/$BK$6-1) | BL12: =IF(A12="","",+AI12/$BL$6-1) | BM12: =IF(A12="","",AL12/$BM$6-1) | BN12: =+'Biyemas S.A.'!BN12 | BP12: =+'Biyemas S.A.'!BP12 -> Jue/Thu
A13: =IF(BP13='Datos Biyemas'!A15,'Datos Biyemas'!A15,"") | B13: =IF(BP13=A13,'Datos Biyemas'!B15,"") | C13: =IF(A13=BP13,+'Biyemas S.A.'!C13+'Kandiko S.A'!C13+'Rebisco S.A.'!C13,"") | D13: =IF(A13=BP13,+'Biyemas S.A.'!D13+'Kandiko S.A'!D13+'Rebisco S.A.'!D13,"") | E13: =IF(A13=BP13,+'Biyemas S.A.'!E13+'Kandiko S.A'!E13+'Rebisco S.A.'!E13,"") | F13: =IF(A13=BP13,+'Biyemas S.A.'!F13+'Kandiko S.A'!F13+'Rebisco S.A.'!F13,"") | G13: =IF(A13=BP13,+'Biyemas S.A.'!G13+'Kandiko S.A'!G13+'Rebisco S.A.'!G13,"") | H13: =IF(BP13=A13,IF(E13>0,+G13/E13,0),"") | I13: =IF(A13="","",IF(F13>0,+G13/F13,0)) | J13: =IF(A13="","",IF(G13>0,+G13/C13,0)) | K13: =IF(A13="","",IF(G13>0,+G13/D13,0)) | L13: =IF(A13=BP13,+'Biyemas S.A.'!L13+'Kandiko S.A'!L13+'Rebisco S.A.'!L13,"") | M13: =IF(A13=BP13,+'Biyemas S.A.'!M13+'Kandiko S.A'!M13+'Rebisco S.A.'!M13,"") | N13: =IF(A13=BP13,+'Biyemas S.A.'!N13+'Kandiko S.A'!N13+'Rebisco S.A.'!N13,"") | O13: =IF(A13=BP13,+'Biyemas S.A.'!O13+'Kandiko S.A'!O13+'Rebisco S.A.'!O13,"") | P13: =IF(A13="","",IF(M13>0,+O13/M13,0)) | Q13: =IF(A13="","",IF(N13>0,+O13/N13,0)) | R13: =IF(A13="","",IF(C13>0,+O13/C13,0)) | S13: =IF(A13="","",IF(C13>0,+O13/L13,0)) | T13: =IF(A13="","",IF(G13>0,(G13+O13)/(D13+L13),0)) | U13: =IF(A13="","",IF(D13>0,+L13+D13,0)) | V13: =IF(A13="","",VLOOKUP(B13,'Datos Biyemas'!B15:BB52,21,0)) | W13: =IF(A13="","",VLOOKUP(B13,'Datos Biyemas'!B15:BB52,22,0)) | X13: =IF(A13="","",VLOOKUP(B13,'Datos Biyemas'!B15:BB52,23,0)) | Y13: =IF(A13="","",VLOOKUP(B13,'Datos Biyemas'!B15:BB52,24,0)) | Z13: =IF(A13="","",IF(W13>0,+Y13/W13,0)) | AA13: =IF(A13="","",IF(X13>0,+Y13/X13,0)) | AB13: =IF(A13="","",IF(Y13>0,+Y13/K13,0)) | AC13: =IF(A13="","",IF(Y13>0,+Y13/V13,0)) | AD13: =IF(A13=BP13,+G13+O13+Y13,"") | AE13: =IF(A13=BP13,+'Biyemas S.A.'!AE13+'Kandiko S.A'!AE13+'Rebisco S.A.'!AE13,"") | AF13: =IF(A13="","",+AD13-AE13) | AG13: =IF(A13=BP13,+'Biyemas S.A.'!AG13+'Kandiko S.A'!AG13+'Rebisco S.A.'!AG13,"") | AH13: =IF(A13=BP13,+'Biyemas S.A.'!AH13+'Kandiko S.A'!AH13+'Rebisco S.A.'!AH13,"") | AI13: =IF(A13=BP13,+'Biyemas S.A.'!AI13+'Kandiko S.A'!AI13+'Rebisco S.A.'!AI13,"") | AJ13: =IF(A13="","",IF(AI13>0,+AI13/C13,0)) | AK13: =IF(A13="","",+G13+O13+AI13+Y13) | AL13: =IF(A13=BP13,+'Biyemas S.A.'!AL13+'Kandiko S.A'!AL13+'Rebisco S.A.'!AL13,"") | AM13: =IF(A13="","",IF(AL13>0,+AL13/C13,0)) | AN13: =IF(A13=BP13,+'Biyemas S.A.'!AN13+'Kandiko S.A'!AN13+'Rebisco S.A.'!AN13,"") | AO13: =IF(A13=BP13,+'Biyemas S.A.'!AO13+'Kandiko S.A'!AO13+'Rebisco S.A.'!AO13,"") | AP13: =IF(A13="","",IF(AN13>0,+AO13/AN13,0)) | AQ13: =IF(A13=BP13,+'Biyemas S.A.'!AQ13+'Kandiko S.A'!AQ13+'Rebisco S.A.'!AQ13,"") | AR13: =IF(A13=BP13,+'Biyemas S.A.'!AR13+'Kandiko S.A'!AR13+'Rebisco S.A.'!AR13,"") | AS13: =IF(A13=BP13,+'Biyemas S.A.'!AS13+'Kandiko S.A'!AS13+'Rebisco S.A.'!AS13,"") | AT13: =IF(A13=BP13,+'Biyemas S.A.'!AT13+'Kandiko S.A'!AT13+'Rebisco S.A.'!AT13,"") | AU13: =IFERROR('Biyemas S.A.'!AU13+'Kandiko S.A'!AU13+'Rebisco S.A.'!AU13,0) -> 0 | AV13: =IF(A13="","",+AD13+AI13+AL13+AO13) | AW13: =IF(A13="","",IF(AV13>0,+AV13/C13,0)) | AY13: =IF(A13=BP13,+'Biyemas S.A.'!AY13+'Kandiko S.A'!AY13+'Rebisco S.A.'!AY13,"") | AZ13: =IF(A13="","",IF($AZ$6>0,+AY13-$AZ$6,)) | BA13: =IF(A13=BP13,+'Biyemas S.A.'!BA13+'Kandiko S.A'!BA13+'Rebisco S.A.'!BA13,"") | BB13: =IF(A13="","",IF(BA13>0,(C13-BA13)/BA13,100%)) | BC13: =IF(A13=BP13,+'Biyemas S.A.'!BC13+'Kandiko S.A'!BC13+'Rebisco S.A.'!BC13,"") | BD13: =IF(A13="","",IF(AN13=BC13,0,IF(BC13>0,(AN13-BC13)/BC13,1))) | BE13: =IF(A13="","",VLOOKUP(B13,'Datos Consolidados'!B15:BF52,53,0)) | BF13: =IF(A13="","",VLOOKUP(B13,'Datos Consolidados'!B15:BF52,54,0)) | BG13: =IF(A13="","",VLOOKUP(B13,'Datos Consolidados'!B15:BF52,55,0)) | BH13: =IF(A13="","",VLOOKUP(B13,'Datos Consolidados'!B15:BF52,51,0)) | BI13: =IF(A13="","",VLOOKUP(B13,'Datos Consolidados'!B15:BF52,52,0)) | BJ13: =IF(A13="","",+AV13/$BJ$6-1) | BK13: =IF(A13="","",+AD13/$BK$6-1) | BL13: =IF(A13="","",+AI13/$BL$6-1) | BM13: =IF(A13="","",AL13/$BM$6-1) | BN13: =+'Biyemas S.A.'!BN13 | BP13: =+'Biyemas S.A.'!BP13 -> Vie/Fri
A14: =IF(BP14='Datos Biyemas'!A16,'Datos Biyemas'!A16,"") | B14: =IF(BP14=A14,'Datos Biyemas'!B16,"") | C14: =IF(A14=BP14,+'Biyemas S.A.'!C14+'Kandiko S.A'!C14+'Rebisco S.A.'!C14,"") | D14: =IF(A14=BP14,+'Biyemas S.A.'!D14+'Kandiko S.A'!D14+'Rebisco S.A.'!D14,"") | E14: =IF(A14=BP14,+'Biyemas S.A.'!E14+'Kandiko S.A'!E14+'Rebisco S.A.'!E14,"") | F14: =IF(A14=BP14,+'Biyemas S.A.'!F14+'Kandiko S.A'!F14+'Rebisco S.A.'!F14,"") | G14: =IF(A14=BP14,+'Biyemas S.A.'!G14+'Kandiko S.A'!G14+'Rebisco S.A.'!G14,"") | H14: =IF(BP14=A14,IF(E14>0,+G14/E14,0),"") | I14: =IF(A14="","",IF(F14>0,+G14/F14,0)) | J14: =IF(A14="","",IF(G14>0,+G14/C14,0)) | K14: =IF(A14="","",IF(G14>0,+G14/D14,0)) | L14: =IF(A14=BP14,+'Biyemas S.A.'!L14+'Kandiko S.A'!L14+'Rebisco S.A.'!L14,"") | M14: =IF(A14=BP14,+'Biyemas S.A.'!M14+'Kandiko S.A'!M14+'Rebisco S.A.'!M14,"") | N14: =IF(A14=BP14,+'Biyemas S.A.'!N14+'Kandiko S.A'!N14+'Rebisco S.A.'!N14,"") | O14: =IF(A14=BP14,+'Biyemas S.A.'!O14+'Kandiko S.A'!O14+'Rebisco S.A.'!O14,"") | P14: =IF(A14="","",IF(M14>0,+O14/M14,0)) | Q14: =IF(A14="","",IF(N14>0,+O14/N14,0)) | R14: =IF(A14="","",IF(C14>0,+O14/C14,0)) | S14: =IF(A14="","",IF(C14>0,+O14/L14,0)) | T14: =IF(A14="","",IF(G14>0,(G14+O14)/(D14+L14),0)) | U14: =IF(A14="","",IF(D14>0,+L14+D14,0)) | V14: =IF(A14="","",VLOOKUP(B14,'Datos Biyemas'!B16:BB53,21,0)) | W14: =IF(A14="","",VLOOKUP(B14,'Datos Biyemas'!B16:BB53,22,0)) | X14: =IF(A14="","",VLOOKUP(B14,'Datos Biyemas'!B16:BB53,23,0)) | Y14: =IF(A14="","",VLOOKUP(B14,'Datos Biyemas'!B16:BB53,24,0)) | Z14: =IF(A14="","",IF(W14>0,+Y14/W14,0)) | AA14: =IF(A14="","",IF(X14>0,+Y14/X14,0)) | AB14: =IF(A14="","",IF(Y14>0,+Y14/K14,0)) | AC14: =IF(A14="","",IF(Y14>0,+Y14/V14,0)) | AD14: =IF(A14=BP14,+G14+O14+Y14,"") | AE14: =IF(A14=BP14,+'Biyemas S.A.'!AE14+'Kandiko S.A'!AE14+'Rebisco S.A.'!AE14,"") | AF14: =IF(A14="","",+AD14-AE14) | AG14: =IF(A14=BP14,+'Biyemas S.A.'!AG14+'Kandiko S.A'!AG14+'Rebisco S.A.'!AG14,"") | AH14: =IF(A14=BP14,+'Biyemas S.A.'!AH14+'Kandiko S.A'!AH14+'Rebisco S.A.'!AH14,"") | AI14: =IF(A14=BP14,+'Biyemas S.A.'!AI14+'Kandiko S.A'!AI14+'Rebisco S.A.'!AI14,"") | AJ14: =IF(A14="","",IF(AI14>0,+AI14/C14,0)) | AK14: =IF(A14="","",+G14+O14+AI14+Y14) | AL14: =IF(A14=BP14,+'Biyemas S.A.'!AL14+'Kandiko S.A'!AL14+'Rebisco S.A.'!AL14,"") | AM14: =IF(A14="","",IF(AL14>0,+AL14/C14,0)) | AN14: =IF(A14=BP14,+'Biyemas S.A.'!AN14+'Kandiko S.A'!AN14+'Rebisco S.A.'!AN14,"") | AO14: =IF(A14=BP14,+'Biyemas S.A.'!AO14+'Kandiko S.A'!AO14+'Rebisco S.A.'!AO14,"") | AP14: =IF(A14="","",IF(AN14>0,+AO14/AN14,0)) | AQ14: =IF(A14=BP14,+'Biyemas S.A.'!AQ14+'Kandiko S.A'!AQ14+'Rebisco S.A.'!AQ14,"") | AR14: =IF(A14=BP14,+'Biyemas S.A.'!AR14+'Kandiko S.A'!AR14+'Rebisco S.A.'!AR14,"") | AS14: =IF(A14=BP14,+'Biyemas S.A.'!AS14+'Kandiko S.A'!AS14+'Rebisco S.A.'!AS14,"") | AT14: =IF(A14=BP14,+'Biyemas S.A.'!AT14+'Kandiko S.A'!AT14+'Rebisco S.A.'!AT14,"") | AU14: =IFERROR('Biyemas S.A.'!AU14+'Kandiko S.A'!AU14+'Rebisco S.A.'!AU14,0) -> 0 | AV14: =IF(A14="","",+AD14+AI14+AL14+AO14) | AW14: =IF(A14="","",IF(AV14>0,+AV14/C14,0)) | AY14: =IF(A14=BP14,+'Biyemas S.A.'!AY14+'Kandiko S.A'!AY14+'Rebisco S.A.'!AY14,"") | AZ14: =IF(A14="","",IF($AZ$6>0,+AY14-$AZ$6,)) | BA14: =IF(A14=BP14,+'Biyemas S.A.'!BA14+'Kandiko S.A'!BA14+'Rebisco S.A.'!BA14,"") | BB14: =IF(A14="","",IF(BA14>0,(C14-BA14)/BA14,100%)) | BC14: =IF(A14=BP14,+'Biyemas S.A.'!BC14+'Kandiko S.A'!BC14+'Rebisco S.A.'!BC14,"") | BD14: =IF(A14="","",IF(AN14=BC14,0,IF(BC14>0,(AN14-BC14)/BC14,1))) | BE14: =IF(A14="","",VLOOKUP(B14,'Datos Consolidados'!B16:BF53,53,0)) | BF14: =IF(A14="","",VLOOKUP(B14,'Datos Consolidados'!B16:BF53,54,0)) | BG14: =IF(A14="","",VLOOKUP(B14,'Datos Consolidados'!B16:BF53,55,0)) | BH14: =IF(A14="","",VLOOKUP(B14,'Datos Consolidados'!B16:BF53,51,0)) | BI14: =IF(A14="","",VLOOKUP(B14,'Datos Consolidados'!B16:BF53,52,0)) | BJ14: =IF(A14="","",+AV14/$BJ$6-1) | BK14: =IF(A14="","",+AD14/$BK$6-1) | BL14: =IF(A14="","",+AI14/$BL$6-1) | BM14: =IF(A14="","",AL14/$BM$6-1) | BN14: =+'Biyemas S.A.'!BN14 | BP14: =+'Biyemas S.A.'!BP14 -> Sab/Sat
A15: =IF(BP15='Datos Biyemas'!A17,'Datos Biyemas'!A17,"") | B15: =IF(BP15=A15,'Datos Biyemas'!B17,"") | C15: =IF(A15=BP15,+'Biyemas S.A.'!C15+'Kandiko S.A'!C15+'Rebisco S.A.'!C15,"") | D15: =IF(A15=BP15,+'Biyemas S.A.'!D15+'Kandiko S.A'!D15+'Rebisco S.A.'!D15,"") | E15: =IF(A15=BP15,+'Biyemas S.A.'!E15+'Kandiko S.A'!E15+'Rebisco S.A.'!E15,"") | F15: =IF(A15=BP15,+'Biyemas S.A.'!F15+'Kandiko S.A'!F15+'Rebisco S.A.'!F15,"") | G15: =IF(A15=BP15,+'Biyemas S.A.'!G15+'Kandiko S.A'!G15+'Rebisco S.A.'!G15,"") | H15: =IF(BP15=A15,IF(E15>0,+G15/E15,0),"") | I15: =IF(A15="","",IF(F15>0,+G15/F15,0)) | J15: =IF(A15="","",IF(G15>0,+G15/C15,0)) | K15: =IF(A15="","",IF(G15>0,+G15/D15,0)) | L15: =IF(A15=BP15,+'Biyemas S.A.'!L15+'Kandiko S.A'!L15+'Rebisco S.A.'!L15,"") | M15: =IF(A15=BP15,+'Biyemas S.A.'!M15+'Kandiko S.A'!M15+'Rebisco S.A.'!M15,"") | N15: =IF(A15=BP15,+'Biyemas S.A.'!N15+'Kandiko S.A'!N15+'Rebisco S.A.'!N15,"") | O15: =IF(A15=BP15,+'Biyemas S.A.'!O15+'Kandiko S.A'!O15+'Rebisco S.A.'!O15,"") | P15: =IF(A15="","",IF(M15>0,+O15/M15,0)) | Q15: =IF(A15="","",IF(N15>0,+O15/N15,0)) | R15: =IF(A15="","",IF(C15>0,+O15/C15,0)) | S15: =IF(A15="","",IF(C15>0,+O15/L15,0)) | T15: =IF(A15="","",IF(G15>0,(G15+O15)/(D15+L15),0)) | U15: =IF(A15="","",IF(D15>0,+L15+D15,0)) | V15: =IF(A15="","",VLOOKUP(B15,'Datos Biyemas'!B17:BB54,21,0)) | W15: =IF(A15="","",VLOOKUP(B15,'Datos Biyemas'!B17:BB54,22,0)) | X15: =IF(A15="","",VLOOKUP(B15,'Datos Biyemas'!B17:BB54,23,0)) | Y15: =IF(A15="","",VLOOKUP(B15,'Datos Biyemas'!B17:BB54,24,0)) | Z15: =IF(A15="","",IF(W15>0,+Y15/W15,0)) | AA15: =IF(A15="","",IF(X15>0,+Y15/X15,0)) | AB15: =IF(A15="","",IF(Y15>0,+Y15/K15,0)) | AC15: =IF(A15="","",IF(Y15>0,+Y15/V15,0)) | AD15: =IF(A15=BP15,+G15+O15+Y15,"") | AE15: =IF(A15=BP15,+'Biyemas S.A.'!AE15+'Kandiko S.A'!AE15+'Rebisco S.A.'!AE15,"") | AF15: =IF(A15="","",+AD15-AE15) | AG15: =IF(A15=BP15,+'Biyemas S.A.'!AG15+'Kandiko S.A'!AG15+'Rebisco S.A.'!AG15,"") | AH15: =IF(A15=BP15,+'Biyemas S.A.'!AH15+'Kandiko S.A'!AH15+'Rebisco S.A.'!AH15,"") | AI15: =IF(A15=BP15,+'Biyemas S.A.'!AI15+'Kandiko S.A'!AI15+'Rebisco S.A.'!AI15,"") | AJ15: =IF(A15="","",IF(AI15>0,+AI15/C15,0)) | AK15: =IF(A15="","",+G15+O15+AI15+Y15) | AL15: =IF(A15=BP15,+'Biyemas S.A.'!AL15+'Kandiko S.A'!AL15+'Rebisco S.A.'!AL15,"") | AM15: =IF(A15="","",IF(AL15>0,+AL15/C15,0)) | AN15: =IF(A15=BP15,+'Biyemas S.A.'!AN15+'Kandiko S.A'!AN15+'Rebisco S.A.'!AN15,"") | AO15: =IF(A15=BP15,+'Biyemas S.A.'!AO15+'Kandiko S.A'!AO15+'Rebisco S.A.'!AO15,"") | AP15: =IF(A15="","",IF(AN15>0,+AO15/AN15,0)) | AQ15: =IF(A15=BP15,+'Biyemas S.A.'!AQ15+'Kandiko S.A'!AQ15+'Rebisco S.A.'!AQ15,"") | AR15: =IF(A15=BP15,+'Biyemas S.A.'!AR15+'Kandiko S.A'!AR15+'Rebisco S.A.'!AR15,"") | AS15: =IF(A15=BP15,+'Biyemas S.A.'!AS15+'Kandiko S.A'!AS15+'Rebisco S.A.'!AS15,"") | AT15: =IF(A15=BP15,+'Biyemas S.A.'!AT15+'Kandiko S.A'!AT15+'Rebisco S.A.'!AT15,"") | AU15: =IFERROR('Biyemas S.A.'!AU15+'Kandiko S.A'!AU15+'Rebisco S.A.'!AU15,0) -> 0 | AV15: =IF(A15="","",+AD15+AI15+AL15+AO15) | AW15: =IF(A15="","",IF(AV15>0,+AV15/C15,0)) | AY15: =IF(A15=BP15,+'Biyemas S.A.'!AY15+'Kandiko S.A'!AY15+'Rebisco S.A.'!AY15,"") | AZ15: =IF(A15="","",IF($AZ$6>0,+AY15-$AZ$6,)) | BA15: =IF(A15=BP15,+'Biyemas S.A.'!BA15+'Kandiko S.A'!BA15+'Rebisco S.A.'!BA15,"") | BB15: =IF(A15="","",IF(BA15>0,(C15-BA15)/BA15,100%)) | BC15: =IF(A15=BP15,+'Biyemas S.A.'!BC15+'Kandiko S.A'!BC15+'Rebisco S.A.'!BC15,"") | BD15: =IF(A15="","",IF(AN15=BC15,0,IF(BC15>0,(AN15-BC15)/BC15,1))) | BE15: =IF(A15="","",VLOOKUP(B15,'Datos Consolidados'!B17:BF54,53,0)) | BF15: =IF(A15="","",VLOOKUP(B15,'Datos Consolidados'!B17:BF54,54,0)) | BG15: =IF(A15="","",VLOOKUP(B15,'Datos Consolidados'!B17:BF54,55,0)) | BH15: =IF(A15="","",VLOOKUP(B15,'Datos Consolidados'!B17:BF54,51,0)) | BI15: =IF(A15="","",VLOOKUP(B15,'Datos Consolidados'!B17:BF54,52,0)) | BJ15: =IF(A15="","",+AV15/$BJ$6-1) | BK15: =IF(A15="","",+AD15/$BK$6-1) | BL15: =IF(A15="","",+AI15/$BL$6-1) | BM15: =IF(A15="","",AL15/$BM$6-1) | BN15: =+'Biyemas S.A.'!BN15 | BP15: =+'Biyemas S.A.'!BP15 -> Dom/Sun
A16: =IF(BP16='Datos Biyemas'!A18,'Datos Biyemas'!A18,"") | B16: =IF(BP16=A16,'Datos Biyemas'!B18,"") | C16: =IF(A16=BP16,+'Biyemas S.A.'!C16+'Kandiko S.A'!C16+'Rebisco S.A.'!C16,"") | D16: =IF(A16=BP16,+'Biyemas S.A.'!D16+'Kandiko S.A'!D16+'Rebisco S.A.'!D16,"") | E16: =IF(A16=BP16,+'Biyemas S.A.'!E16+'Kandiko S.A'!E16+'Rebisco S.A.'!E16,"") | F16: =IF(A16=BP16,+'Biyemas S.A.'!F16+'Kandiko S.A'!F16+'Rebisco S.A.'!F16,"") | G16: =IF(A16=BP16,+'Biyemas S.A.'!G16+'Kandiko S.A'!G16+'Rebisco S.A.'!G16,"") | H16: =IF(BP16=A16,IF(E16>0,+G16/E16,0),"") | I16: =IF(A16="","",IF(F16>0,+G16/F16,0)) | J16: =IF(A16="","",IF(G16>0,+G16/C16,0)) | K16: =IF(A16="","",IF(G16>0,+G16/D16,0)) | L16: =IF(A16=BP16,+'Biyemas S.A.'!L16+'Kandiko S.A'!L16+'Rebisco S.A.'!L16,"") | M16: =IF(A16=BP16,+'Biyemas S.A.'!M16+'Kandiko S.A'!M16+'Rebisco S.A.'!M16,"") | N16: =IF(A16=BP16,+'Biyemas S.A.'!N16+'Kandiko S.A'!N16+'Rebisco S.A.'!N16,"") | O16: =IF(A16=BP16,+'Biyemas S.A.'!O16+'Kandiko S.A'!O16+'Rebisco S.A.'!O16,"") | P16: =IF(A16="","",IF(M16>0,+O16/M16,0)) | Q16: =IF(A16="","",IF(N16>0,+O16/N16,0)) | R16: =IF(A16="","",IF(C16>0,+O16/C16,0)) | S16: =IF(A16="","",IF(C16>0,+O16/L16,0)) | T16: =IF(A16="","",IF(G16>0,(G16+O16)/(D16+L16),0)) | U16: =IF(A16="","",IF(D16>0,+L16+D16,0)) | V16: =IF(A16="","",VLOOKUP(B16,'Datos Biyemas'!B18:BB55,21,0)) | W16: =IF(A16="","",VLOOKUP(B16,'Datos Biyemas'!B18:BB55,22,0)) | X16: =IF(A16="","",VLOOKUP(B16,'Datos Biyemas'!B18:BB55,23,0)) | Y16: =IF(A16="","",VLOOKUP(B16,'Datos Biyemas'!B18:BB55,24,0)) | Z16: =IF(A16="","",IF(W16>0,+Y16/W16,0)) | AA16: =IF(A16="","",IF(X16>0,+Y16/X16,0)) | AB16: =IF(A16="","",IF(Y16>0,+Y16/K16,0)) | AC16: =IF(A16="","",IF(Y16>0,+Y16/V16,0)) | AD16: =IF(A16=BP16,+G16+O16+Y16,"") | AE16: =IF(A16=BP16,+'Biyemas S.A.'!AE16+'Kandiko S.A'!AE16+'Rebisco S.A.'!AE16,"") | AF16: =IF(A16="","",+AD16-AE16) | AG16: =IF(A16=BP16,+'Biyemas S.A.'!AG16+'Kandiko S.A'!AG16+'Rebisco S.A.'!AG16,"") | AH16: =IF(A16=BP16,+'Biyemas S.A.'!AH16+'Kandiko S.A'!AH16+'Rebisco S.A.'!AH16,"") | AI16: =IF(A16=BP16,+'Biyemas S.A.'!AI16+'Kandiko S.A'!AI16+'Rebisco S.A.'!AI16,"") | AJ16: =IF(A16="","",IF(AI16>0,+AI16/C16,0)) | AK16: =IF(A16="","",+G16+O16+AI16+Y16) | AL16: =IF(A16=BP16,+'Biyemas S.A.'!AL16+'Kandiko S.A'!AL16+'Rebisco S.A.'!AL16,"") | AM16: =IF(A16="","",IF(AL16>0,+AL16/C16,0)) | AN16: =IF(A16=BP16,+'Biyemas S.A.'!AN16+'Kandiko S.A'!AN16+'Rebisco S.A.'!AN16,"") | AO16: =IF(A16=BP16,+'Biyemas S.A.'!AO16+'Kandiko S.A'!AO16+'Rebisco S.A.'!AO16,"") | AP16: =IF(A16="","",IF(AN16>0,+AO16/AN16,0)) | AQ16: =IF(A16=BP16,+'Biyemas S.A.'!AQ16+'Kandiko S.A'!AQ16+'Rebisco S.A.'!AQ16,"") | AR16: =IF(A16=BP16,+'Biyemas S.A.'!AR16+'Kandiko S.A'!AR16+'Rebisco S.A.'!AR16,"") | AS16: =IF(A16=BP16,+'Biyemas S.A.'!AS16+'Kandiko S.A'!AS16+'Rebisco S.A.'!AS16,"") | AT16: =IF(A16=BP16,+'Biyemas S.A.'!AT16+'Kandiko S.A'!AT16+'Rebisco S.A.'!AT16,"") | AU16: =IFERROR('Biyemas S.A.'!AU16+'Kandiko S.A'!AU16+'Rebisco S.A.'!AU16,0) -> 0 | AV16: =IF(A16="","",+AD16+AI16+AL16+AO16) | AW16: =IF(A16="","",IF(AV16>0,+AV16/C16,0)) | AY16: =IF(A16=BP16,+'Biyemas S.A.'!AY16+'Kandiko S.A'!AY16+'Rebisco S.A.'!AY16,"") | AZ16: =IF(A16="","",IF($AZ$6>0,+AY16-$AZ$6,)) | BA16: =IF(A16=BP16,+'Biyemas S.A.'!BA16+'Kandiko S.A'!BA16+'Rebisco S.A.'!BA16,"") | BB16: =IF(A16="","",IF(BA16>0,(C16-BA16)/BA16,100%)) | BC16: =IF(A16=BP16,+'Biyemas S.A.'!BC16+'Kandiko S.A'!BC16+'Rebisco S.A.'!BC16,"") | BD16: =IF(A16="","",IF(AN16=BC16,0,IF(BC16>0,(AN16-BC16)/BC16,1))) | BE16: =IF(A16="","",VLOOKUP(B16,'Datos Consolidados'!B18:BF55,53,0)) | BF16: =IF(A16="","",VLOOKUP(B16,'Datos Consolidados'!B18:BF55,54,0)) | BG16: =IF(A16="","",VLOOKUP(B16,'Datos Consolidados'!B18:BF55,55,0)) | BH16: =IF(A16="","",VLOOKUP(B16,'Datos Consolidados'!B18:BF55,51,0)) | BI16: =IF(A16="","",VLOOKUP(B16,'Datos Consolidados'!B18:BF55,52,0)) | BJ16: =IF(A16="","",+AV16/$BJ$6-1) | BK16: =IF(A16="","",+AD16/$BK$6-1) | BL16: =IF(A16="","",+AI16/$BL$6-1) | BM16: =IF(A16="","",AL16/$BM$6-1) | BN16: =+'Biyemas S.A.'!BN16 | BP16: =+'Biyemas S.A.'!BP16 -> Lun/Mon
A17: =IF(BP17='Datos Biyemas'!A19,'Datos Biyemas'!A19,"") | B17: =IF(BP17=A17,'Datos Biyemas'!B19,"") | C17: =IF(A17=BP17,+'Biyemas S.A.'!C17+'Kandiko S.A'!C17+'Rebisco S.A.'!C17,"") | D17: =IF(A17=BP17,+'Biyemas S.A.'!D17+'Kandiko S.A'!D17+'Rebisco S.A.'!D17,"") | E17: =IF(A17=BP17,+'Biyemas S.A.'!E17+'Kandiko S.A'!E17+'Rebisco S.A.'!E17,"") | F17: =IF(A17=BP17,+'Biyemas S.A.'!F17+'Kandiko S.A'!F17+'Rebisco S.A.'!F17,"") | G17: =IF(A17=BP17,+'Biyemas S.A.'!G17+'Kandiko S.A'!G17+'Rebisco S.A.'!G17,"") | H17: =IF(BP17=A17,IF(E17>0,+G17/E17,0),"") | I17: =IF(A17="","",IF(F17>0,+G17/F17,0)) | J17: =IF(A17="","",IF(G17>0,+G17/C17,0)) | K17: =IF(A17="","",IF(G17>0,+G17/D17,0)) | L17: =IF(A17=BP17,+'Biyemas S.A.'!L17+'Kandiko S.A'!L17+'Rebisco S.A.'!L17,"") | M17: =IF(A17=BP17,+'Biyemas S.A.'!M17+'Kandiko S.A'!M17+'Rebisco S.A.'!M17,"") | N17: =IF(A17=BP17,+'Biyemas S.A.'!N17+'Kandiko S.A'!N17+'Rebisco S.A.'!N17,"") | O17: =IF(A17=BP17,+'Biyemas S.A.'!O17+'Kandiko S.A'!O17+'Rebisco S.A.'!O17,"") | P17: =IF(A17="","",IF(M17>0,+O17/M17,0)) | Q17: =IF(A17="","",IF(N17>0,+O17/N17,0)) | R17: =IF(A17="","",IF(C17>0,+O17/C17,0)) | S17: =IF(A17="","",IF(C17>0,+O17/L17,0)) | T17: =IF(A17="","",IF(G17>0,(G17+O17)/(D17+L17),0)) | U17: =IF(A17="","",IF(D17>0,+L17+D17,0)) | V17: =IF(A17="","",VLOOKUP(B17,'Datos Biyemas'!B19:BB56,21,0)) | W17: =IF(A17="","",VLOOKUP(B17,'Datos Biyemas'!B19:BB56,22,0)) | X17: =IF(A17="","",VLOOKUP(B17,'Datos Biyemas'!B19:BB56,23,0)) | Y17: =IF(A17="","",VLOOKUP(B17,'Datos Biyemas'!B19:BB56,24,0)) | Z17: =IF(A17="","",IF(W17>0,+Y17/W17,0)) | AA17: =IF(A17="","",IF(X17>0,+Y17/X17,0)) | AB17: =IF(A17="","",IF(Y17>0,+Y17/K17,0)) | AC17: =IF(A17="","",IF(Y17>0,+Y17/V17,0)) | AD17: =IF(A17=BP17,+G17+O17+Y17,"") | AE17: =IF(A17=BP17,+'Biyemas S.A.'!AE17+'Kandiko S.A'!AE17+'Rebisco S.A.'!AE17,"") | AF17: =IF(A17="","",+AD17-AE17) | AG17: =IF(A17=BP17,+'Biyemas S.A.'!AG17+'Kandiko S.A'!AG17+'Rebisco S.A.'!AG17,"") | AH17: =IF(A17=BP17,+'Biyemas S.A.'!AH17+'Kandiko S.A'!AH17+'Rebisco S.A.'!AH17,"") | AI17: =IF(A17=BP17,+'Biyemas S.A.'!AI17+'Kandiko S.A'!AI17+'Rebisco S.A.'!AI17,"") | AJ17: =IF(A17="","",IF(AI17>0,+AI17/C17,0)) | AK17: =IF(A17="","",+G17+O17+AI17+Y17) | AL17: =IF(A17=BP17,+'Biyemas S.A.'!AL17+'Kandiko S.A'!AL17+'Rebisco S.A.'!AL17,"") | AM17: =IF(A17="","",IF(AL17>0,+AL17/C17,0)) | AN17: =IF(A17=BP17,+'Biyemas S.A.'!AN17+'Kandiko S.A'!AN17+'Rebisco S.A.'!AN17,"") | AO17: =IF(A17=BP17,+'Biyemas S.A.'!AO17+'Kandiko S.A'!AO17+'Rebisco S.A.'!AO17,"") | AP17: =IF(A17="","",IF(AN17>0,+AO17/AN17,0)) | AQ17: =IF(A17=BP17,+'Biyemas S.A.'!AQ17+'Kandiko S.A'!AQ17+'Rebisco S.A.'!AQ17,"") | AR17: =IF(A17=BP17,+'Biyemas S.A.'!AR17+'Kandiko S.A'!AR17+'Rebisco S.A.'!AR17,"") | AS17: =IF(A17=BP17,+'Biyemas S.A.'!AS17+'Kandiko S.A'!AS17+'Rebisco S.A.'!AS17,"") | AT17: =IF(A17=BP17,+'Biyemas S.A.'!AT17+'Kandiko S.A'!AT17+'Rebisco S.A.'!AT17,"") | AU17: =IFERROR('Biyemas S.A.'!AU17+'Kandiko S.A'!AU17+'Rebisco S.A.'!AU17,0) -> 0 | AV17: =IF(A17="","",+AD17+AI17+AL17+AO17) | AW17: =IF(A17="","",IF(AV17>0,+AV17/C17,0)) | AY17: =IF(A17=BP17,+'Biyemas S.A.'!AY17+'Kandiko S.A'!AY17+'Rebisco S.A.'!AY17,"") | AZ17: =IF(A17="","",IF($AZ$6>0,+AY17-$AZ$6,)) | BA17: =IF(A17=BP17,+'Biyemas S.A.'!BA17+'Kandiko S.A'!BA17+'Rebisco S.A.'!BA17,"") | BB17: =IF(A17="","",IF(BA17>0,(C17-BA17)/BA17,100%)) | BC17: =IF(A17=BP17,+'Biyemas S.A.'!BC17+'Kandiko S.A'!BC17+'Rebisco S.A.'!BC17,"") | BD17: =IF(A17="","",IF(AN17=BC17,0,IF(BC17>0,(AN17-BC17)/BC17,1))) | BE17: =IF(A17="","",VLOOKUP(B17,'Datos Consolidados'!B19:BF56,53,0)) | BF17: =IF(A17="","",VLOOKUP(B17,'Datos Consolidados'!B19:BF56,54,0)) | BG17: =IF(A17="","",VLOOKUP(B17,'Datos Consolidados'!B19:BF56,55,0)) | BH17: =IF(A17="","",VLOOKUP(B17,'Datos Consolidados'!B19:BF56,51,0)) | BI17: =IF(A17="","",VLOOKUP(B17,'Datos Consolidados'!B19:BF56,52,0)) | BJ17: =IF(A17="","",+AV17/$BJ$6-1) | BK17: =IF(A17="","",+AD17/$BK$6-1) | BL17: =IF(A17="","",+AI17/$BL$6-1) | BM17: =IF(A17="","",AL17/$BM$6-1) | BN17: =+'Biyemas S.A.'!BN17 | BP17: =+'Biyemas S.A.'!BP17 -> Mar/Tue
A18: =IF(BP18='Datos Biyemas'!A20,'Datos Biyemas'!A20,"") | B18: =IF(BP18=A18,'Datos Biyemas'!B20,"") | C18: =IF(A18=BP18,+'Biyemas S.A.'!C18+'Kandiko S.A'!C18+'Rebisco S.A.'!C18,"") | D18: =IF(A18=BP18,+'Biyemas S.A.'!D18+'Kandiko S.A'!D18+'Rebisco S.A.'!D18,"") | E18: =IF(A18=BP18,+'Biyemas S.A.'!E18+'Kandiko S.A'!E18+'Rebisco S.A.'!E18,"") | F18: =IF(A18=BP18,+'Biyemas S.A.'!F18+'Kandiko S.A'!F18+'Rebisco S.A.'!F18,"") | G18: =IF(A18=BP18,+'Biyemas S.A.'!G18+'Kandiko S.A'!G18+'Rebisco S.A.'!G18,"") | H18: =IF(BP18=A18,IF(E18>0,+G18/E18,0),"") | I18: =IF(A18="","",IF(F18>0,+G18/F18,0)) | J18: =IF(A18="","",IF(G18>0,+G18/C18,0)) | K18: =IF(A18="","",IF(G18>0,+G18/D18,0)) | L18: =IF(A18=BP18,+'Biyemas S.A.'!L18+'Kandiko S.A'!L18+'Rebisco S.A.'!L18,"") | M18: =IF(A18=BP18,+'Biyemas S.A.'!M18+'Kandiko S.A'!M18+'Rebisco S.A.'!M18,"") | N18: =IF(A18=BP18,+'Biyemas S.A.'!N18+'Kandiko S.A'!N18+'Rebisco S.A.'!N18,"") | O18: =IF(A18=BP18,+'Biyemas S.A.'!O18+'Kandiko S.A'!O18+'Rebisco S.A.'!O18,"") | P18: =IF(A18="","",IF(M18>0,+O18/M18,0)) | Q18: =IF(A18="","",IF(N18>0,+O18/N18,0)) | R18: =IF(A18="","",IF(C18>0,+O18/C18,0)) | S18: =IF(A18="","",IF(C18>0,+O18/L18,0)) | T18: =IF(A18="","",IF(G18>0,(G18+O18)/(D18+L18),0)) | U18: =IF(A18="","",IF(D18>0,+L18+D18,0)) | V18: =IF(A18="","",VLOOKUP(B18,'Datos Biyemas'!B20:BB57,21,0)) | W18: =IF(A18="","",VLOOKUP(B18,'Datos Biyemas'!B20:BB57,22,0)) | X18: =IF(A18="","",VLOOKUP(B18,'Datos Biyemas'!B20:BB57,23,0)) | Y18: =IF(A18="","",VLOOKUP(B18,'Datos Biyemas'!B20:BB57,24,0)) | Z18: =IF(A18="","",IF(W18>0,+Y18/W18,0)) | AA18: =IF(A18="","",IF(X18>0,+Y18/X18,0)) | AB18: =IF(A18="","",IF(Y18>0,+Y18/K18,0)) | AC18: =IF(A18="","",IF(Y18>0,+Y18/V18,0)) | AD18: =IF(A18=BP18,+G18+O18+Y18,"") | AE18: =IF(A18=BP18,+'Biyemas S.A.'!AE18+'Kandiko S.A'!AE18+'Rebisco S.A.'!AE18,"") | AF18: =IF(A18="","",+AD18-AE18) | AG18: =IF(A18=BP18,+'Biyemas S.A.'!AG18+'Kandiko S.A'!AG18+'Rebisco S.A.'!AG18,"") | AH18: =IF(A18=BP18,+'Biyemas S.A.'!AH18+'Kandiko S.A'!AH18+'Rebisco S.A.'!AH18,"") | AI18: =IF(A18=BP18,+'Biyemas S.A.'!AI18+'Kandiko S.A'!AI18+'Rebisco S.A.'!AI18,"") | AJ18: =IF(A18="","",IF(AI18>0,+AI18/C18,0)) | AK18: =IF(A18="","",+G18+O18+AI18+Y18) | AL18: =IF(A18=BP18,+'Biyemas S.A.'!AL18+'Kandiko S.A'!AL18+'Rebisco S.A.'!AL18,"") | AM18: =IF(A18="","",IF(AL18>0,+AL18/C18,0)) | AN18: =IF(A18=BP18,+'Biyemas S.A.'!AN18+'Kandiko S.A'!AN18+'Rebisco S.A.'!AN18,"") | AO18: =IF(A18=BP18,+'Biyemas S.A.'!AO18+'Kandiko S.A'!AO18+'Rebisco S.A.'!AO18,"") | AP18: =IF(A18="","",IF(AN18>0,+AO18/AN18,0)) | AQ18: =IF(A18=BP18,+'Biyemas S.A.'!AQ18+'Kandiko S.A'!AQ18+'Rebisco S.A.'!AQ18,"") | AR18: =IF(A18=BP18,+'Biyemas S.A.'!AR18+'Kandiko S.A'!AR18+'Rebisco S.A.'!AR18,"") | AS18: =IF(A18=BP18,+'Biyemas S.A.'!AS18+'Kandiko S.A'!AS18+'Rebisco S.A.'!AS18,"") | AT18: =IF(A18=BP18,+'Biyemas S.A.'!AT18+'Kandiko S.A'!AT18+'Rebisco S.A.'!AT18,"") | AU18: =IFERROR('Biyemas S.A.'!AU18+'Kandiko S.A'!AU18+'Rebisco S.A.'!AU18,0) -> 0 | AV18: =IF(A18="","",+AD18+AI18+AL18+AO18) | AW18: =IF(A18="","",IF(AV18>0,+AV18/C18,0)) | AY18: =IF(A18=BP18,+'Biyemas S.A.'!AY18+'Kandiko S.A'!AY18+'Rebisco S.A.'!AY18,"") | AZ18: =IF(A18="","",IF($AZ$6>0,+AY18-$AZ$6,)) | BA18: =IF(A18=BP18,+'Biyemas S.A.'!BA18+'Kandiko S.A'!BA18+'Rebisco S.A.'!BA18,"") | BB18: =IF(A18="","",IF(BA18>0,(C18-BA18)/BA18,100%)) | BC18: =IF(A18=BP18,+'Biyemas S.A.'!BC18+'Kandiko S.A'!BC18+'Rebisco S.A.'!BC18,"") | BD18: =IF(A18="","",IF(AN18=BC18,0,IF(BC18>0,(AN18-BC18)/BC18,1))) | BE18: =IF(A18="","",VLOOKUP(B18,'Datos Consolidados'!B20:BF57,53,0)) | BF18: =IF(A18="","",VLOOKUP(B18,'Datos Consolidados'!B20:BF57,54,0)) | BG18: =IF(A18="","",VLOOKUP(B18,'Datos Consolidados'!B20:BF57,55,0)) | BH18: =IF(A18="","",VLOOKUP(B18,'Datos Consolidados'!B20:BF57,51,0)) | BI18: =IF(A18="","",VLOOKUP(B18,'Datos Consolidados'!B20:BF57,52,0)) | BJ18: =IF(A18="","",+AV18/$BJ$6-1) | BK18: =IF(A18="","",+AD18/$BK$6-1) | BL18: =IF(A18="","",+AI18/$BL$6-1) | BM18: =IF(A18="","",AL18/$BM$6-1) | BN18: =+'Biyemas S.A.'!BN18 | BP18: =+'Biyemas S.A.'!BP18 -> Mie/Wed
A19: =IF(BP19='Datos Biyemas'!A21,'Datos Biyemas'!A21,"") | B19: =IF(BP19=A19,'Datos Biyemas'!B21,"") | C19: =IF(A19=BP19,+'Biyemas S.A.'!C19+'Kandiko S.A'!C19+'Rebisco S.A.'!C19,"") | D19: =IF(A19=BP19,+'Biyemas S.A.'!D19+'Kandiko S.A'!D19+'Rebisco S.A.'!D19,"") | E19: =IF(A19=BP19,+'Biyemas S.A.'!E19+'Kandiko S.A'!E19+'Rebisco S.A.'!E19,"") | F19: =IF(A19=BP19,+'Biyemas S.A.'!F19+'Kandiko S.A'!F19+'Rebisco S.A.'!F19,"") | G19: =IF(A19=BP19,+'Biyemas S.A.'!G19+'Kandiko S.A'!G19+'Rebisco S.A.'!G19,"") | H19: =IF(BP19=A19,IF(E19>0,+G19/E19,0),"") | I19: =IF(A19="","",IF(F19>0,+G19/F19,0)) | J19: =IF(A19="","",IF(G19>0,+G19/C19,0)) | K19: =IF(A19="","",IF(G19>0,+G19/D19,0)) | L19: =IF(A19=BP19,+'Biyemas S.A.'!L19+'Kandiko S.A'!L19+'Rebisco S.A.'!L19,"") | M19: =IF(A19=BP19,+'Biyemas S.A.'!M19+'Kandiko S.A'!M19+'Rebisco S.A.'!M19,"") | N19: =IF(A19=BP19,+'Biyemas S.A.'!N19+'Kandiko S.A'!N19+'Rebisco S.A.'!N19,"") | O19: =IF(A19=BP19,+'Biyemas S.A.'!O19+'Kandiko S.A'!O19+'Rebisco S.A.'!O19,"") | P19: =IF(A19="","",IF(M19>0,+O19/M19,0)) | Q19: =IF(A19="","",IF(N19>0,+O19/N19,0)) | R19: =IF(A19="","",IF(C19>0,+O19/C19,0)) | S19: =IF(A19="","",IF(C19>0,+O19/L19,0)) | T19: =IF(A19="","",IF(G19>0,(G19+O19)/(D19+L19),0)) | U19: =IF(A19="","",IF(D19>0,+L19+D19,0)) | V19: =IF(A19="","",VLOOKUP(B19,'Datos Biyemas'!B21:BB58,21,0)) | W19: =IF(A19="","",VLOOKUP(B19,'Datos Biyemas'!B21:BB58,22,0)) | X19: =IF(A19="","",VLOOKUP(B19,'Datos Biyemas'!B21:BB58,23,0)) | Y19: =IF(A19="","",VLOOKUP(B19,'Datos Biyemas'!B21:BB58,24,0)) | Z19: =IF(A19="","",IF(W19>0,+Y19/W19,0)) | AA19: =IF(A19="","",IF(X19>0,+Y19/X19,0)) | AB19: =IF(A19="","",IF(Y19>0,+Y19/K19,0)) | AC19: =IF(A19="","",IF(Y19>0,+Y19/V19,0)) | AD19: =IF(A19=BP19,+G19+O19+Y19,"") | AE19: =IF(A19=BP19,+'Biyemas S.A.'!AE19+'Kandiko S.A'!AE19+'Rebisco S.A.'!AE19,"") | AF19: =IF(A19="","",+AD19-AE19) | AG19: =IF(A19=BP19,+'Biyemas S.A.'!AG19+'Kandiko S.A'!AG19+'Rebisco S.A.'!AG19,"") | AH19: =IF(A19=BP19,+'Biyemas S.A.'!AH19+'Kandiko S.A'!AH19+'Rebisco S.A.'!AH19,"") | AI19: =IF(A19=BP19,+'Biyemas S.A.'!AI19+'Kandiko S.A'!AI19+'Rebisco S.A.'!AI19,"") | AJ19: =IF(A19="","",IF(AI19>0,+AI19/C19,0)) | AK19: =IF(A19="","",+G19+O19+AI19+Y19) | AL19: =IF(A19=BP19,+'Biyemas S.A.'!AL19+'Kandiko S.A'!AL19+'Rebisco S.A.'!AL19,"") | AM19: =IF(A19="","",IF(AL19>0,+AL19/C19,0)) | AN19: =IF(A19=BP19,+'Biyemas S.A.'!AN19+'Kandiko S.A'!AN19+'Rebisco S.A.'!AN19,"") | AO19: =IF(A19=BP19,+'Biyemas S.A.'!AO19+'Kandiko S.A'!AO19+'Rebisco S.A.'!AO19,"") | AP19: =IF(A19="","",IF(AN19>0,+AO19/AN19,0)) | AQ19: =IF(A19=BP19,+'Biyemas S.A.'!AQ19+'Kandiko S.A'!AQ19+'Rebisco S.A.'!AQ19,"") | AR19: =IF(A19=BP19,+'Biyemas S.A.'!AR19+'Kandiko S.A'!AR19+'Rebisco S.A.'!AR19,"") | AS19: =IF(A19=BP19,+'Biyemas S.A.'!AS19+'Kandiko S.A'!AS19+'Rebisco S.A.'!AS19,"") | AT19: =IF(A19=BP19,+'Biyemas S.A.'!AT19+'Kandiko S.A'!AT19+'Rebisco S.A.'!AT19,"") | AU19: =IFERROR('Biyemas S.A.'!AU19+'Kandiko S.A'!AU19+'Rebisco S.A.'!AU19,0) -> 0 | AV19: =IF(A19="","",+AD19+AI19+AL19+AO19) | AW19: =IF(A19="","",IF(AV19>0,+AV19/C19,0)) | AY19: =IF(A19=BP19,+'Biyemas S.A.'!AY19+'Kandiko S.A'!AY19+'Rebisco S.A.'!AY19,"") | AZ19: =IF(A19="","",IF($AZ$6>0,+AY19-$AZ$6,)) | BA19: =IF(A19=BP19,+'Biyemas S.A.'!BA19+'Kandiko S.A'!BA19+'Rebisco S.A.'!BA19,"") | BB19: =IF(A19="","",IF(BA19>0,(C19-BA19)/BA19,100%)) | BC19: =IF(A19=BP19,+'Biyemas S.A.'!BC19+'Kandiko S.A'!BC19+'Rebisco S.A.'!BC19,"") | BD19: =IF(A19="","",IF(AN19=BC19,0,IF(BC19>0,(AN19-BC19)/BC19,1))) | BE19: =IF(A19="","",VLOOKUP(B19,'Datos Consolidados'!B21:BF58,53,0)) | BF19: =IF(A19="","",VLOOKUP(B19,'Datos Consolidados'!B21:BF58,54,0)) | BG19: =IF(A19="","",VLOOKUP(B19,'Datos Consolidados'!B21:BF58,55,0)) | BH19: =IF(A19="","",VLOOKUP(B19,'Datos Consolidados'!B21:BF58,51,0)) | BI19: =IF(A19="","",VLOOKUP(B19,'Datos Consolidados'!B21:BF58,52,0)) | BJ19: =IF(A19="","",+AV19/$BJ$6-1) | BK19: =IF(A19="","",+AD19/$BK$6-1) | BL19: =IF(A19="","",+AI19/$BL$6-1) | BM19: =IF(A19="","",AL19/$BM$6-1) | BN19: =+'Biyemas S.A.'!BN19 | BP19: =+'Biyemas S.A.'!BP19 -> Jue/Thu
... A37: =IF(BP37='Datos Biyemas'!A39,'Datos Biyemas'!A39,"") | B37: =IF(BP37=A37,'Datos Biyemas'!B39,"") | C37: =IF(A37=BP37,+'Biyemas S.A.'!C37+'Kandiko S.A'!C37+'Rebisco S.A.'!C37,"") | D37: =IF(A37=BP37,+'Biyemas S.A.'!D37+'Kandiko S.A'!D37+'Rebisco S.A.'!D37,"") | E37: =IF(A37=BP37,+'Biyemas S.A.'!E37+'Kandiko S.A'!E37+'Rebisco S.A.'!E37,"") | F37: =IF(A37=BP37,+'Biyemas S.A.'!F37+'Kandiko S.A'!F37+'Rebisco S.A.'!F37,"") | G37: =IF(A37=BP37,+'Biyemas S.A.'!G37+'Kandiko S.A'!G37+'Rebisco S.A.'!G37,"") | H37: =IF(BP37=A37,IF(E37>0,+G37/E37,0),"") | I37: =IF(A37="","",IF(F37>0,+G37/F37,0)) | J37: =IF(A37="","",IF(G37>0,+G37/C37,0)) | K37: =IF(A37="","",IF(G37>0,+G37/D37,0)) | L37: =IF(A37=BP37,+'Biyemas S.A.'!L37+'Kandiko S.A'!L37+'Rebisco S.A.'!L37,"") | M37: =IF(A37=BP37,+'Biyemas S.A.'!M37+'Kandiko S.A'!M37+'Rebisco S.A.'!M37,"") | N37: =IF(A37=BP37,+'Biyemas S.A.'!N37+'Kandiko S.A'!N37+'Rebisco S.A.'!N37,"") | O37: =IF(A37=BP37,+'Biyemas S.A.'!O37+'Kandiko S.A'!O37+'Rebisco S.A.'!O37,"") | P37: =IF(A37="","",IF(M37>0,+O37/M37,0)) | Q37: =IF(A37="","",IF(N37>0,+O37/N37,0)) | R37: =IF(A37="","",IF(C37>0,+O37/C37,0)) | S37: =IF(A37="","",IF(C37>0,+O37/L37,0)) | T37: =IF(A37="","",IF(G37>0,(G37+O37)/(D37+L37),0)) | U37: =IF(A37="","",IF(D37>0,+L37+D37,0)) | V37: =IF(A37="","",VLOOKUP(B37,'Datos Biyemas'!B39:BB76,21,0)) | W37: =IF(A37="","",VLOOKUP(B37,'Datos Biyemas'!B39:BB76,22,0)) | X37: =IF(A37="","",VLOOKUP(B37,'Datos Biyemas'!B39:BB76,23,0)) | Y37: =IF(A37="","",VLOOKUP(B37,'Datos Biyemas'!B39:BB76,24,0)) | Z37: =IF(A37="","",IF(W37>0,+Y37/W37,0)) | AA37: =IF(A37="","",IF(X37>0,+Y37/X37,0)) | AB37: =IF(A37="","",IF(Y37>0,+Y37/K37,0)) | AC37: =IF(A37="","",IF(Y37>0,+Y37/V37,0)) | AD37: =IF(A37=BP37,+G37+O37+Y37,"") | AE37: =IF(A37=BP37,+'Biyemas S.A.'!AE37+'Kandiko S.A'!AE37+'Rebisco S.A.'!AE37,"") | AF37: =IF(A37="","",+AD37-AE37) | AG37: =IF(A37=BP37,+'Biyemas S.A.'!AG37+'Kandiko S.A'!AG37+'Rebisco S.A.'!AG37,"") | AH37: =IF(A37=BP37,+'Biyemas S.A.'!AH37+'Kandiko S.A'!AH37+'Rebisco S.A.'!AH37,"") | AI37: =IF(A37=BP37,+'Biyemas S.A.'!AI37+'Kandiko S.A'!AI37+'Rebisco S.A.'!AI37,"") | AJ37: =IF(A37="","",IF(AI37>0,+AI37/C37,0)) | AK37: =IF(A37="","",+G37+O37+AI37+Y37) | AL37: =IF(A37=BP37,+'Biyemas S.A.'!AL37+'Kandiko S.A'!AL37+'Rebisco S.A.'!AL37,"") | AM37: =IF(A37="","",IF(AL37>0,+AL37/C37,0)) | AN37: =IF(A37=BP37,+'Biyemas S.A.'!AN37+'Kandiko S.A'!AN37+'Rebisco S.A.'!AN37,"") | AO37: =IF(A37=BP37,+'Biyemas S.A.'!AO37+'Kandiko S.A'!AO37+'Rebisco S.A.'!AO37,"") | AP37: =IF(A37="","",IF(AN37>0,+AO37/AN37,0)) | AQ37: =IF(A37=BP37,+'Biyemas S.A.'!AQ37+'Kandiko S.A'!AQ37+'Rebisco S.A.'!AQ37,"") | AR37: =IF(A37=BP37,+'Biyemas S.A.'!AR37+'Kandiko S.A'!AR37+'Rebisco S.A.'!AR37,"") | AS37: =IF(A37=BP37,+'Biyemas S.A.'!AS37+'Kandiko S.A'!AS37+'Rebisco S.A.'!AS37,"") | AT37: =IF(A37=BP37,+'Biyemas S.A.'!AT37+'Kandiko S.A'!AT37+'Rebisco S.A.'!AT37,"") | AU37: =IFERROR('Biyemas S.A.'!AU37+'Kandiko S.A'!AU37+'Rebisco S.A.'!AU37,0) -> 0 | AV37: =IF(A37="","",+AD37+AI37+AL37+AO37) | AW37: =IF(A37="","",IF(AV37>0,+AV37/C37,0)) | AY37: =IF(A37=BP37,+'Biyemas S.A.'!AY37+'Kandiko S.A'!AY37+'Rebisco S.A.'!AY37,"") | AZ37: =IF(A37="","",IF($AZ$6>0,+AY37-$AZ$6,)) | BA37: =IF(A37=BP37,+'Biyemas S.A.'!BA37+'Kandiko S.A'!BA37+'Rebisco S.A.'!BA37,"") | BB37: =IF(A37="","",IF(BA37>0,(C37-BA37)/BA37,100%)) | BC37: =IF(A37=BP37,+'Biyemas S.A.'!BC37+'Kandiko S.A'!BC37+'Rebisco S.A.'!BC37,"") | BD37: =IF(A37="","",IF(AN37=BC37,0,IF(BC37>0,(AN37-BC37)/BC37,1))) | BE37: =IF(A37="","",VLOOKUP(B37,'Datos Consolidados'!B39:BF76,53,0)) | BF37: =IF(A37="","",VLOOKUP(B37,'Datos Consolidados'!B39:BF76,54,0)) | BG37: =IF(A37="","",VLOOKUP(B37,'Datos Consolidados'!B39:BF76,55,0)) | BH37: =IF(A37="","",VLOOKUP(B37,'Datos Consolidados'!B39:BF76,51,0)) | BI37: =IF(A37="","",VLOOKUP(B37,'Datos Consolidados'!B39:BF76,52,0)) | BJ37: =IF(A37="","",+AV37/$BJ$6-1) | BK37: =IF(A37="","",+AD37/$BK$6-1) | BL37: =IF(A37="","",+AI37/$BL$6-1) | BM37: =IF(A37="","",AL37/$BM$6-1) | BN37: =+'Biyemas S.A.'!BN37 | BP37: =+'Biyemas S.A.'!BP37 -> Lun/Mon
AU38: =IF(B38=BP38,+'Biyemas S.A.'!AU38+'Kandiko S.A'!AU38+'Rebisco S.A.'!AU38,"") -> 0 | AZ38: =IF(A38="","",IF($AZ$6>0,+AY38-$AZ$6,)) | BB38: =IF(A38="","",IF(BA38>0,(C38-BA38)/BA38,100%)) | BE38: =IF(A38="","",VLOOKUP(B38,'Datos Consolidados'!B40:BF77,53,0)) | BF38: =IF(A38="","",VLOOKUP(B38,'Datos Consolidados'!B40:BF77,54,0)) | BG38: =IF(A38="","",VLOOKUP(B38,'Datos Consolidados'!B40:BF77,55,0)) | BH38: =IF(A38="","",VLOOKUP(B38,'Datos Consolidados'!B40:BF77,51,0)) | BI38: =IF(A38="","",VLOOKUP(B38,'Datos Consolidados'!B40:BF77,52,0))
A39: Total final | C39: =SUM(C7:C38) -> 0 | E39: =SUM(E7:E38) -> 0 | F39: =SUM(F7:F38) -> 0 | G39: =SUM(G7:G38) -> 0 | M39: =SUM(M7:M38) -> 0 | N39: =SUM(N7:N38) -> 0 | O39: =SUM(O7:O38) -> 0 | W39: =SUM(W7:W38) -> 0 | X39: =SUM(X7:X38) -> 0 | Y39: =SUM(Y7:Y38) -> 0 | AD39: =SUM(AD7:AD38) -> 0 | AE39: =SUM(AE7:AE38) -> 0 | AF39: =SUM(AF7:AF38) -> 0 | AG39: =SUM(AG7:AG38) -> 0 | AH39: =SUM(AH7:AH38) -> 0 | AI39: =SUM(AI7:AI38) -> 0 | AK39: =SUM(AK7:AK38) -> 0 | AL39: =SUM(AL7:AL38) -> 0 | AN39: =SUM(AN7:AN38) -> 0 | AO39: =SUM(AO7:AO38) -> 0 | AQ39: =SUM(AQ7:AQ38) -> 0 | AR39: =SUM(AR7:AR38) -> 0 | AS39: =SUM(AS7:AS38) -> 0 | AT39: =SUM(AT7:AT38) -> 0 | AV39: =SUM(AV7:AV38) -> 0 | AY39: =SUM(AY7:AY38)/COUNT(AY7:AY38) -> #DIV/0! | AZ39: =AY39-AZ6 -> #DIV/0! | BA39: =SUM(BA7:BA38) -> 0 | BB39: =IF($AK39>0,(C39-($BA39))/($BA$39),) -> 0 | BC39: =SUM(BC7:BC38) -> 0 | BD39: =IF($BC39>0,(AN39-($BC39))/($BC$39),IF(AN39>0,1)) -> FALSE | BE39: =VLOOKUP("Total final",'Datos Consolidados'!A9:BF142,54,0) -> #N/A | BF39: =VLOOKUP("Total final",'Datos Consolidados'!A9:BF142,55,0) -> #N/A | BG39: =VLOOKUP("Total final",'Datos Consolidados'!A9:BF142,56,0) -> #N/A | BH39: =VLOOKUP("Total final",'Datos Consolidados'!A9:BF142,52,0) -> #N/A | BI39: =+'Biyemas S.A.'!BI39 -> #N/A | BJ39: =+BJ40/BJ6-1 -> #N/A | BK39: =+BK40/BK6-1 -> #N/A | BL39: =+BL40/BL6-1 -> #N/A | BM39: =+BM40/BM6-1 -> #N/A | BN39: =+'Biyemas S.A.'!BN39 -> #N/A
A40: MTD Average | C40: =+'Biyemas S.A.'!C40+'Kandiko S.A'!C40+'Rebisco S.A.'!C40 -> #N/A | D40: =SUM(D7:D37)/$D$1 -> #DIV/0! | E40: =SUM(E7:E37)/$D$1 -> #DIV/0! | F40: =SUM(F7:F37)/$D$1 -> #DIV/0! | G40: =SUM(G7:G37)/$D$1 -> #DIV/0! | H40: =+G40/E40 -> #DIV/0! | I40: =+G40/F40 -> #DIV/0! | J40: =+G40/C40 -> #DIV/0! | K40: =+G40/D40 -> #DIV/0! | L40: =SUM(L7:L37)/$D$1 -> #DIV/0! | M40: =SUM(M7:M37)/$D$1 -> #DIV/0! | N40: =SUM(N7:N37)/$D$1 -> #DIV/0! | O40: =SUM(O7:O37)/$D$1 -> #DIV/0! | P40: =+O40/M40 -> #DIV/0! | Q40: =+O40/N40 -> #DIV/0! | R40: =+O40/C40 -> #DIV/0! | S40: =+O40/L40 -> #DIV/0! | T40: =SUM(T7:T37)/$D$1 -> #DIV/0! | U40: =SUM(U7:U37)/$D$1 -> #DIV/0! | V40: =SUM(V7:V37)/$D$1 -> #DIV/0! | W40: =SUM(W7:W37)/$D$1 -> #DIV/0! | X40: =SUM(X7:X37)/$D$1 -> #DIV/0! | Y40: =SUM(Y7:Y37)/$D$1 -> #DIV/0! | Z40: =+Y40/W40 -> #DIV/0! | AA40: =+Y40/X40 -> #DIV/0! | AB40: =+Y40/K40 -> #DIV/0! | AC40: =+Y40/V40 -> #DIV/0! | AD40: =SUM(AD7:AD37)/$D$1 -> #DIV/0! | AE40: =SUM(AE7:AE37)/$D$1 -> #DIV/0! | AF40: =SUM(AF7:AF37)/$D$1 -> #DIV/0! | AG40: =SUM(AG7:AG37)/$D$1 -> #DIV/0! | AH40: =SUM(AH7:AH37)/$D$1 -> #DIV/0! | AI40: =SUM(AI7:AI37)/$D$1 -> #DIV/0! | AJ40: =+AI40/C40 -> #DIV/0! | AK40: =SUM(AK7:AK37)/$D$1 -> #DIV/0! | AL40: =SUM(AL7:AL37)/$D$1 -> #DIV/0! | AM40: =+AL40/C40 -> #DIV/0! | AN40: =SUM(AN7:AN37)/$D$1 -> #DIV/0! | AO40: =SUM(AO7:AO37)/$D$1 -> #DIV/0! | AP40: =+AO40/AN40 -> #DIV/0! | AQ40: =SUM(AQ7:AQ37)/$D$1 -> #DIV/0! | AR40: =SUM(AR7:AR37)/$D$1 -> #DIV/0! | AS40: =SUM(AS7:AS37)/$D$1 -> #DIV/0! | AT40: =SUM(AT7:AT37)/$D$1 -> #DIV/0! | AV40: =SUM(AV7:AV37)/$D$1 -> #DIV/0! | AW40: =+AV40/C40 -> #DIV/0! | BB40: MTD average: | BE40: =+'Biyemas S.A.'!BE40+'Kandiko S.A'!BE40+'Rebisco S.A.'!BE40 -> #N/A | BF40: =+'Biyemas S.A.'!BF40+'Kandiko S.A'!BF40+'Rebisco S.A.'!BF40 -> #N/A | BG40: =+'Biyemas S.A.'!BG40+'Kandiko S.A'!BG40+'Rebisco S.A.'!BG40 -> #N/A | BH40: =+'Biyemas S.A.'!BH40+'Kandiko S.A'!BH40+'Rebisco S.A.'!BH40 -> #N/A | BI40: =+'Biyemas S.A.'!BI40+'Kandiko S.A'!BI40+'Rebisco S.A.'!BI40 -> #N/A | BJ40: =+'Biyemas S.A.'!BJ40+'Kandiko S.A'!BJ40+'Rebisco S.A.'!BJ40 -> #N/A | BK40: =+'Biyemas S.A.'!BK40+'Kandiko S.A'!BK40+'Rebisco S.A.'!BK40 -> #N/A | BL40: =+'Biyemas S.A.'!BL40+'Kandiko S.A'!BL40+'Rebisco S.A.'!BL40 -> #N/A | ... BN40: =+'Biyemas S.A.'!BN40+'Kandiko S.A'!BN40+'Rebisco S.A.'!BN40 -> #N/A
BB41: Dev from budget: | BE41: =+'Biyemas S.A.'!BE41+'Kandiko S.A'!BE41+'Rebisco S.A.'!BE41 -> #N/A | BF41: =+'Biyemas S.A.'!BF41+'Kandiko S.A'!BF41+'Rebisco S.A.'!BF41 -> #N/A | BG41: =+'Biyemas S.A.'!BG41+'Kandiko S.A'!BG41+'Rebisco S.A.'!BG41 -> #N/A | BH41: =+'Biyemas S.A.'!BH41+'Kandiko S.A'!BH41+'Rebisco S.A.'!BH41 -> #N/A | BI41: =+'Biyemas S.A.'!BI41+'Kandiko S.A'!BI41+'Rebisco S.A.'!BI41 -> #N/A | BJ41: =+'Biyemas S.A.'!BJ41+'Kandiko S.A'!BJ41+'Rebisco S.A.'!BJ41 -> #N/A | BK41: =+'Biyemas S.A.'!BK41+'Kandiko S.A'!BK41+'Rebisco S.A.'!BK41 -> #N/A | BL41: =+'Biyemas S.A.'!BL41+'Kandiko S.A'!BL41+'Rebisco S.A.'!BL41 -> #N/A | ... BN41: =+'Biyemas S.A.'!BN41+'Kandiko S.A'!BN41+'Rebisco S.A.'!BN41 -> #N/A
A44: =+'Biyemas S.A.'!A44 -> Reporte Flash Julio 2026
A45: Total final | C45: =+'Biyemas S.A.'!C45+'Kandiko S.A'!C45+'Rebisco S.A.'!C45 -> #N/A | D45: =+'Biyemas S.A.'!D45+'Kandiko S.A'!D45+'Rebisco S.A.'!D45 -> 0 | E45: =+'Biyemas S.A.'!E45+'Kandiko S.A'!E45+'Rebisco S.A.'!E45 -> #N/A | F45: =+'Biyemas S.A.'!F45+'Kandiko S.A'!F45+'Rebisco S.A.'!F45 -> #N/A | G45: =+'Biyemas S.A.'!G45+'Kandiko S.A'!G45+'Rebisco S.A.'!G45 -> #N/A | H45: =+'Biyemas S.A.'!H45+'Kandiko S.A'!H45+'Rebisco S.A.'!H45 -> 0 | I45: =+'Biyemas S.A.'!I45+'Kandiko S.A'!I45+'Rebisco S.A.'!I45 -> 0 | J45: =+'Biyemas S.A.'!J45+'Kandiko S.A'!J45+'Rebisco S.A.'!J45 -> 0 | L45: =+'Biyemas S.A.'!L45+'Kandiko S.A'!L45+'Rebisco S.A.'!L45 -> 0 | M45: =+'Biyemas S.A.'!M45+'Kandiko S.A'!M45+'Rebisco S.A.'!M45 -> #N/A | N45: =+'Biyemas S.A.'!N45+'Kandiko S.A'!N45+'Rebisco S.A.'!N45 -> #N/A | O45: =+'Biyemas S.A.'!O45+'Kandiko S.A'!O45+'Rebisco S.A.'!O45 -> #N/A | P45: =+'Biyemas S.A.'!P45+'Kandiko S.A'!P45+'Rebisco S.A.'!P45 -> 0 | Q45: =+'Biyemas S.A.'!Q45+'Kandiko S.A'!Q45+'Rebisco S.A.'!Q45 -> 0 | R45: =+'Biyemas S.A.'!R45+'Kandiko S.A'!R45+'Rebisco S.A.'!R45 -> 0 | S45: =+'Biyemas S.A.'!S45+'Kandiko S.A'!S45+'Rebisco S.A.'!S45 -> 0 | ... AM45: =+'Biyemas S.A.'!AM45+'Kandiko S.A'!AM45+'Rebisco S.A.'!AM45 -> 0 | AN45: =+'Biyemas S.A.'!AN45+'Kandiko S.A'!AN39+'Rebisco S.A.'!AN45 -> #N/A | AO45: =+'Biyemas S.A.'!AO45+'Kandiko S.A'!AO45+'Rebisco S.A.'!AO45 -> #N/A | AQ45: =+'Biyemas S.A.'!AQ45+'Kandiko S.A'!AQ39+'Rebisco S.A.'!AQ45 -> #N/A | AR45: =+'Biyemas S.A.'!AR45+'Kandiko S.A'!AR39+'Rebisco S.A.'!AR45 -> #N/A | AS45: =+'Biyemas S.A.'!AS45+'Kandiko S.A'!AS39+'Rebisco S.A.'!AS45 -> #N/A | AT45: =+'Biyemas S.A.'!AT45+'Kandiko S.A'!AT39+'Rebisco S.A.'!AT45 -> #N/A | AU45: =+'Biyemas S.A.'!AU45+'Kandiko S.A'!AU39+'Rebisco S.A.'!AU45 -> #N/A | AV45: =+'Biyemas S.A.'!AV45+'Kandiko S.A'!AV45+'Rebisco S.A.'!AV45 -> #N/A | BA45: =+'Biyemas S.A.'!BA45+'Kandiko S.A'!BA45+'Rebisco S.A.'!BA45 -> #N/A | BB45: =IF($AK45>0,(C45-($BA45))/($BA$45),) -> #N/A | BC45: =+'Biyemas S.A.'!BC45+'Kandiko S.A'!BC45+'Rebisco S.A.'!BC45 -> #N/A | BD45: =IF($BC45>0,(AN45-($BC45))/($BC$45),IF(AN45>0,1)) -> #N/A | BE45: =IF(A45="","",+AV45/SUM(('Biyemas S.A.'!AV45/(1+'Biyemas S.A.'!BE45)),('Kandiko S.A'!AV45/(1+'Kandiko S.A'!BE45)),('Rebisco S.A.'!AV45/(1+'Rebisco S.A.'!BE45)))-1) -> #N/A | BF45: =IF(A45="","",+AD45/(SUM(('Biyemas S.A.'!AD45/(1+'Biyemas S.A.'!BF45)),('Kandiko S.A'!AD45/(1+'Kandiko S.A'!BF45)),('Rebisco S.A.'!AD45/(1+'Rebisco S.A.'!BF45))))-1) -> #N/A | BG45: =IF(A45="","",+AI45/SUM(('Biyemas S.A.'!AI45/(1+'Biyemas S.A.'!BG45)),(+'Kandiko S.A'!AI45/(1+'Kandiko S.A'!BG45)),('Rebisco S.A.'!AI45/(1+'Rebisco S.A.'!BG45)))-1) -> #N/A | BH45: =IF(A45="","",+AL45/SUM(('Biyemas S.A.'!AL45/(1+'Biyemas S.A.'!BH45)),('Kandiko S.A'!AL45/(1+'Kandiko S.A'!BH45)),('Rebisco S.A.'!AL45/(1+'Rebisco S.A.'!BH45)))-1) -> #N/A | BI45: =+'Biyemas S.A.'!BI45 -> #N/A | BJ45: =BJ46/SUM(BJ46-BJ47)-1 -> #N/A | BK45: =BK46/SUM(BK46-BK47)-1 -> #N/A | BL45: =BL46/SUM(BL46-BL47)-1 -> #N/A | BM45: =BM46/SUM(BM46-BM47)-1 -> #N/A | BN45: =+'Biyemas S.A.'!BN45 -> #N/A | BP45: Total final mes ant.
A46: MTD Average | C46: =+C45/$D$1 -> #N/A | D46: =+'Biyemas S.A.'!D46+'Kandiko S.A'!D46+'Rebisco S.A.'!D46 -> #N/A | E46: =+'Biyemas S.A.'!E46+'Kandiko S.A'!E46+'Rebisco S.A.'!E46 -> #N/A | F46: =+'Biyemas S.A.'!F46+'Kandiko S.A'!F46+'Rebisco S.A.'!F46 -> #N/A | G46: =+'Biyemas S.A.'!G46+'Kandiko S.A'!G46+'Rebisco S.A.'!G46 -> #N/A | H46: =+G46/E46 -> #N/A | I46: =+G46/F46 -> #N/A | J46: =+G46/C46 -> #N/A | K46: =+G46/D46 -> #N/A | L46: =+'Biyemas S.A.'!L46+'Kandiko S.A'!L46+'Rebisco S.A.'!L46 -> #N/A | M46: =+'Biyemas S.A.'!M46+'Kandiko S.A'!M46+'Rebisco S.A.'!M46 -> #N/A | N46: =+'Biyemas S.A.'!N46+'Kandiko S.A'!N46+'Rebisco S.A.'!N46 -> #N/A | O46: =+'Biyemas S.A.'!O46+'Kandiko S.A'!O46+'Rebisco S.A.'!O46 -> #N/A | P46: =+O46/M46 -> #N/A | Q46: =+O46/N46 -> #N/A | R46: =+O46/C46 -> #N/A | S46: =IF(A46="","",IF(C46>0,+O46/L46,0)) -> #N/A | T46: =IF(A46="","",IF(G46>0,(G46+O46)/(D46+L46),0)) -> #N/A | U46: =+'Biyemas S.A.'!U46+'Kandiko S.A'!U46+'Rebisco S.A.'!U46 -> #N/A | V46: =+'Biyemas S.A.'!V46+'Kandiko S.A'!V46+'Rebisco S.A.'!V46 -> #N/A | W46: =+'Biyemas S.A.'!W46+'Kandiko S.A'!W46+'Rebisco S.A.'!W46 -> #N/A | X46: =+'Biyemas S.A.'!X46+'Kandiko S.A'!X46+'Rebisco S.A.'!X46 -> #N/A | Y46: =+'Biyemas S.A.'!Y46+'Kandiko S.A'!Y46+'Rebisco S.A.'!Y46 -> #N/A | Z46: =+Y46/W46 -> #N/A | AA46: =+Y46/X46 -> #N/A | AB46: =+Y46/M46 -> #N/A | AC46: =+Y46/V46 -> #N/A | AD46: =+'Biyemas S.A.'!AD46+'Kandiko S.A'!AD46+'Rebisco S.A.'!AD46 -> #N/A | AE46: =+'Biyemas S.A.'!AE46+'Kandiko S.A'!AE46+'Rebisco S.A.'!AE46 -> #N/A | AF46: =+AF45/$D$1 -> #N/A | AG46: =+'Biyemas S.A.'!AG46+'Kandiko S.A'!AG46+'Rebisco S.A.'!AG46 -> #N/A | AH46: =+'Biyemas S.A.'!AH46+'Kandiko S.A'!AH46+'Rebisco S.A.'!AH46 -> #N/A | AI46: =+'Biyemas S.A.'!AI46+'Kandiko S.A'!AI46+'Rebisco S.A.'!AI46 -> #N/A | AJ46: =+AI46/C46 -> #N/A | AK46: =+'Biyemas S.A.'!AK46+'Kandiko S.A'!AK46+'Rebisco S.A.'!AK46 -> #N/A | AL46: =+'Biyemas S.A.'!AL46+'Kandiko S.A'!AL46+'Rebisco S.A.'!AL46 -> #N/A | AM46: =+AL46/C46 -> #N/A | AN46: =+AN45/D1 -> #N/A | AO46: =+'Kandiko S.A'!AO46+'Rebisco S.A.'!AO46+'Biyemas S.A.'!AO46 -> #N/A | AP46: =+AO46/AN46 -> #N/A | AQ46: =+'Kandiko S.A'!AQ46+'Rebisco S.A.'!AQ46+'Biyemas S.A.'!AQ46 -> #N/A | AR46: =+'Kandiko S.A'!AR46+'Rebisco S.A.'!AR46+'Biyemas S.A.'!AR46 -> #N/A | AS46: =+'Kandiko S.A'!AS46+'Rebisco S.A.'!AS46+'Biyemas S.A.'!AS46 -> #N/A | AT46: =+'Kandiko S.A'!AT46+'Rebisco S.A.'!AT46+'Biyemas S.A.'!AT46 -> #N/A | AU46: =+'Kandiko S.A'!AU46+'Rebisco S.A.'!AU46+'Biyemas S.A.'!AU46 -> #N/A | AV46: =+'Biyemas S.A.'!AV46+'Kandiko S.A'!AV46+'Rebisco S.A.'!AV46 -> #N/A | AW46: =+AV46/C46 -> #N/A | BB46: MTD average: | BE46: =+'Biyemas S.A.'!BE46+'Kandiko S.A'!BE46+'Rebisco S.A.'!BE46 -> #N/A | BF46: =+'Biyemas S.A.'!BF46+'Kandiko S.A'!BF46+'Rebisco S.A.'!BF46 -> #N/A | BG46: =+'Biyemas S.A.'!BG46+'Kandiko S.A'!BG46+'Rebisco S.A.'!BG46 -> #N/A | BH46: =+'Biyemas S.A.'!BH46+'Kandiko S.A'!BH46+'Rebisco S.A.'!BH46 -> #N/A | BI46: =+'Biyemas S.A.'!BI46+'Kandiko S.A'!BI46+'Rebisco S.A.'!BI46 -> #N/A | BJ46: =+'Biyemas S.A.'!BJ46+'Kandiko S.A'!BJ46+'Rebisco S.A.'!BJ46 -> #N/A | BK46: =+'Biyemas S.A.'!BK46+'Kandiko S.A'!BK46+'Rebisco S.A.'!BK46 -> #N/A | BL46: =+'Biyemas S.A.'!BL46+'Kandiko S.A'!BL46+'Rebisco S.A.'!BL46 -> #N/A | ... BN46: =+'Biyemas S.A.'!BN46+'Kandiko S.A'!BN46+'Rebisco S.A.'!BN46 -> #N/A | BP46: MTD average mes ant.
BB47: Dev from budget: | BE47: =+'Biyemas S.A.'!BE47+'Kandiko S.A'!BE47+'Rebisco S.A.'!BE47 -> #N/A | BF47: =+'Biyemas S.A.'!BF47+'Kandiko S.A'!BF47+'Rebisco S.A.'!BF47 -> #N/A | BG47: =+'Biyemas S.A.'!BG47+'Kandiko S.A'!BG47+'Rebisco S.A.'!BG47 -> #N/A | BH47: =+'Biyemas S.A.'!BH47+'Kandiko S.A'!BH47+'Rebisco S.A.'!BH47 -> #N/A | BI47: =+'Biyemas S.A.'!BI47+'Kandiko S.A'!BI47+'Rebisco S.A.'!BI47 -> #N/A | BJ47: =+'Biyemas S.A.'!BJ47+'Kandiko S.A'!BJ47+'Rebisco S.A.'!BJ47 -> #N/A | BK47: =+'Biyemas S.A.'!BK47+'Kandiko S.A'!BK47+'Rebisco S.A.'!BK47 -> #N/A | BL47: =+'Biyemas S.A.'!BL47+'Kandiko S.A'!BL47+'Rebisco S.A.'!BL47 -> #N/A | ... BN47: =+'Biyemas S.A.'!BN47+'Kandiko S.A'!BN47+'Rebisco S.A.'!BN47 -> #N/A | BP47: Dev from budget mes ant.
A48: ▲ Prom diario % | C48: =(+C40-C46)/C46 -> #N/A | E48: =(+E40-E46)/E46 -> #DIV/0! | F48: =(+F40-F46)/F46 -> #DIV/0! | G48: =(+G40-G46)/G46 -> #DIV/0! | K48: =(+K40-K46)/K46 -> #DIV/0! | M48: =(+M40-M46)/M46 -> #DIV/0! | N48: =(+N40-N46)/N46 -> #DIV/0! | O48: =(+O40-O46)/O46 -> #DIV/0! | S48: =(+S40-S46)/S46 -> #DIV/0! | T48: =(+T40-T46)/T46 -> #DIV/0! | U48: =(+U40-U46)/U46 -> #DIV/0! | W48: =(+W40-W46)/W46 -> #DIV/0! | X48: =(+X40-X46)/X46 -> #DIV/0! | Y48: =(+Y40-Y46)/Y46 -> #DIV/0! | AD48: =(+AD40-AD46)/AD46 -> #DIV/0! | AE48: =(+AE40-AE46)/AE46 -> #DIV/0! | AF48: =(+AF40-AF46)/AF46 -> #DIV/0! | AG48: =(+AG40-AG46)/AG46 -> #DIV/0! | AH48: =(+AH40-AH46)/AH46 -> #DIV/0! | AI48: =(+AI40-AI46)/AI46 -> #DIV/0! | AK48: =(+AK40-AK46)/AK46 -> #DIV/0! | AL48: =(+AL40-AL46)/AL46 -> #DIV/0! | AN48: =(+AN40-AN46)/AN46 -> #DIV/0! | AO48: =(+AO40-AO46)/AO46 -> #DIV/0! | AQ48: =(+AQ40-AQ46)/AQ46 -> #DIV/0! | AR48: =(+AR40-AR46)/AR46 -> #DIV/0! | AS48: =(+AS40-AS46)/AS46 -> #DIV/0! | AT48: =(+AT40-AT46)/AT46 -> #DIV/0! | AU48: =(+AU40-AU46)/AU46 -> #N/A | AV48: =(+AV40-AV46)/AV46 -> #DIV/0!
A49: ▲ Prom diario $ | E49: =+E40-E46 -> #DIV/0! | F49: =+F40-F46 -> #DIV/0! | G49: =+G40-G46 -> #DIV/0! | K49: =+K40-K46 -> #DIV/0! | M49: =+M40-M46 -> #DIV/0! | N49: =+N40-N46 -> #DIV/0! | O49: =+O40-O46 -> #DIV/0! | S49: =+S40-S46 -> #DIV/0! | T49: =+T40-T46 -> #DIV/0! | U49: =+U40-U46 -> #DIV/0! | W49: =+W40-W46 -> #DIV/0! | X49: =+X40-X46 -> #DIV/0! | Y49: =+Y40-Y46 -> #DIV/0! | AD49: =+AD40-AD46 -> #DIV/0! | AE49: =+AE40-AE46 -> #DIV/0! | AF49: =+AF40-AF46 -> #DIV/0! | AG49: =+AG40-AG46 -> #DIV/0! | AH49: =+AH40-AH46 -> #DIV/0! | AI49: =+AI40-AI46 -> #DIV/0! | AK49: =+AK40-AK46 -> #DIV/0! | AL49: =+AL40-AL46 -> #DIV/0! | AN49: =+AN40-AN46 -> #DIV/0! | AO49: =+AO40-AO46 -> #DIV/0! | AQ49: =+AQ40-AQ46 -> #DIV/0! | AR49: =+AR40-AR46 -> #DIV/0! | AS49: =+AS40-AS46 -> #DIV/0! | AT49: =+AT40-AT46 -> #DIV/0! | AU49: =+AU40-AU46 -> #N/A | AV49: =+AV40-AV46 -> #DIV/0!
A53: =+'Biyemas S.A.'!A53 -> Reporte Flash Agosto 25
A54: 0 | C54: =+'Biyemas S.A.'!C54+'Kandiko S.A'!C54+'Rebisco S.A.'!C54 -> #N/A | E54: =+'Biyemas S.A.'!E54+'Kandiko S.A'!E54+'Rebisco S.A.'!E54 -> #N/A | F54: =+'Biyemas S.A.'!F54+'Kandiko S.A'!F54+'Rebisco S.A.'!F54 -> #N/A | G54: =+'Biyemas S.A.'!G54+'Kandiko S.A'!G54+'Rebisco S.A.'!G54 -> #N/A | H54: =+'Biyemas S.A.'!H54+'Kandiko S.A'!H54+'Rebisco S.A.'!H54 -> 0 | I54: =+'Biyemas S.A.'!I54+'Kandiko S.A'!I54+'Rebisco S.A.'!I54 -> 0 | J54: =+'Biyemas S.A.'!J54+'Kandiko S.A'!J54+'Rebisco S.A.'!J54 -> 0 | L54: =+'Biyemas S.A.'!L54+'Kandiko S.A'!L54+'Rebisco S.A.'!L54 -> 0 | M54: =+'Biyemas S.A.'!M54+'Kandiko S.A'!M54+'Rebisco S.A.'!M54 -> #N/A | N54: =+'Biyemas S.A.'!N54+'Kandiko S.A'!N54+'Rebisco S.A.'!N54 -> #N/A | O54: =+'Biyemas S.A.'!O54+'Kandiko S.A'!O54+'Rebisco S.A.'!O54 -> #N/A | P54: =+'Biyemas S.A.'!P54+'Kandiko S.A'!P54+'Rebisco S.A.'!P54 -> 0 | W54: =VLOOKUP(+BP54,'Datos Biyemas'!A9:BB145,23,0) -> #N/A | X54: =VLOOKUP(+BP54,'Datos Biyemas'!A9:BB145,24,0) -> #N/A | Y54: =VLOOKUP(+BP54,'Datos Biyemas'!A9:BB145,25,0) -> #N/A | AD54: =+'Biyemas S.A.'!AD54+'Kandiko S.A'!AD54+'Rebisco S.A.'!AD54 -> #N/A | AE54: =+'Biyemas S.A.'!AE54+'Kandiko S.A'!AE54+'Rebisco S.A.'!AE54 -> #N/A | AF54: =+'Biyemas S.A.'!AF54+'Kandiko S.A'!AF54+'Rebisco S.A.'!AF54 -> #N/A | AG54: =+'Biyemas S.A.'!AG54+'Kandiko S.A'!AG54+'Rebisco S.A.'!AG54 -> #N/A | AH54: =+'Biyemas S.A.'!AH54+'Kandiko S.A'!AH54+'Rebisco S.A.'!AH54 -> #N/A | AI54: =+'Biyemas S.A.'!AI54+'Kandiko S.A'!AI54+'Rebisco S.A.'!AI54 -> #N/A | AJ54: =+'Biyemas S.A.'!AJ54+'Kandiko S.A'!AJ54+'Rebisco S.A.'!AJ54 -> 0 | AK54: =+'Biyemas S.A.'!AK54+'Kandiko S.A'!AK54+'Rebisco S.A.'!AK54 -> #N/A | ... AO54: =+'Biyemas S.A.'!AO54+'Kandiko S.A'!AO54+'Rebisco S.A.'!AO54 -> #N/A | AV54: =+'Biyemas S.A.'!AV54+'Kandiko S.A'!AV54+'Rebisco S.A.'!AV54 -> #N/A | BA54: =+'Biyemas S.A.'!BA54+'Kandiko S.A'!BA54+'Rebisco S.A.'!BA54 -> #N/A | BB54: =IF($AK54>0,(C54-($BA54))/($BA$54),) -> #N/A | BC54: =+'Biyemas S.A.'!BC54+'Kandiko S.A'!BC54+'Rebisco S.A.'!BC54 -> #N/A | BD54: =IF($BC54>0,(AN54-($BC54))/($BC$54),IF(AN54>0,1)) -> #N/A | BE54: =IF(A54="","",+AV54/SUM(('Biyemas S.A.'!AV54/(1+'Biyemas S.A.'!BE54)),('Kandiko S.A'!AV54/(1+'Kandiko S.A'!BE54)),('Rebisco S.A.'!AV54/(1+'Rebisco S.A.'!BE54)))-1) -> #N/A | BF54: =IF(A54="","",+AD54/(SUM(('Biyemas S.A.'!AD54/(1+'Biyemas S.A.'!BF54)),('Kandiko S.A'!AD54/(1+'Kandiko S.A'!BF54)),('Rebisco S.A.'!AD54/(1+'Rebisco S.A.'!BF54))))-1) -> #N/A | BG54: =IF(A54="","",+AI54/SUM(('Biyemas S.A.'!AI54/(1+'Biyemas S.A.'!BG54)),(+'Kandiko S.A'!AI54/(1+'Kandiko S.A'!BG54)),('Rebisco S.A.'!AI54/(1+'Rebisco S.A.'!BG54)))-1) -> #N/A | BH54: =IF(A54="","",+AL54/SUM(('Biyemas S.A.'!AL54/(1+'Biyemas S.A.'!BH54)),('Kandiko S.A'!AL54/(1+'Kandiko S.A'!BH54)),('Rebisco S.A.'!AL54/(1+'Rebisco S.A.'!BH54)))-1) -> #N/A | BI54: =+'Biyemas S.A.'!BI54 -> #N/A | BJ54: =BJ55/SUM(BJ55-BJ56)-1 -> #N/A | BK54: =BK55/SUM(BK55-BK56)-1 -> #N/A | BL54: =BL55/SUM(BL55-BL56)-1 -> #N/A | BM54: =BM55/SUM(BM55-BM56)-1 -> #N/A | BN54: =+'Biyemas S.A.'!BN54 -> #N/A | BP54: Total final anio ant.
A55: MTD Average | C55: =+C54/$D$1 -> #N/A | D55: =+'Biyemas S.A.'!D55+'Kandiko S.A'!D55+'Rebisco S.A.'!D55 -> #N/A | E55: =+E54/$D$1 -> #N/A | F55: =+F54/$D$1 -> #N/A | G55: =+G54/$D$1 -> #N/A | H55: =+G55/E55 -> #N/A | I55: =+G55/F55 -> #N/A | J55: =+G55/C55 -> #N/A | K55: =+G55/D55 -> #N/A | L55: =+'Biyemas S.A.'!L55+'Kandiko S.A'!L55+'Rebisco S.A.'!L55 -> #N/A | M55: =+M54/$D$1 -> #N/A | N55: =+N54/$D$1 -> #N/A | O55: =+O54/$D$1 -> #N/A | P55: =+O55/M55 -> #N/A | Q55: =+O55/N55 -> #N/A | R55: =+O55/C55 -> #N/A | S55: =IF(A55="","",IF(C55>0,+O55/L55,0)) -> #N/A | T55: =IF(A55="","",IF(G55>0,(G55+O55)/(D55+L55),0)) -> #N/A | U55: =+'Biyemas S.A.'!U55+'Kandiko S.A'!U55+'Rebisco S.A.'!U55 -> #N/A | V55: =VLOOKUP(+BP55,'Datos Biyemas'!A9:BB145,22,0) -> #N/A | W55: =VLOOKUP(+BP55,'Datos Biyemas'!A9:BB145,23,0) -> #N/A | X55: =VLOOKUP(+BP55,'Datos Biyemas'!A9:BB145,24,0) -> #N/A | Y55: =VLOOKUP(+BP55,'Datos Biyemas'!A9:BB145,25,0) -> #N/A | Z55: =+Y55/W55 -> #N/A | AA55: =+Y55/X55 -> #N/A | AB55: =+Y55/M55 -> #N/A | AC55: =+Y55/V55 -> #N/A | AD55: =+AD54/$D$1 -> #N/A | AE55: =+AE54/$D$1 -> #N/A | AF55: =+AF54/$D$1 -> #N/A | AG55: =+AG54/$D$1 -> #N/A | AH55: =+AH54/$D$1 -> #N/A | AI55: =+AI54/$D$1 -> #N/A | AJ55: =+AI55/C55 -> #N/A | AK55: =+AK54/$D$1 -> #N/A | AL55: =+AL54/$D$1 -> #N/A | AM55: =+AL55/C55 -> #N/A | AN55: =+AN54/D1 -> #N/A | AO55: =+'Biyemas S.A.'!AO55+'Kandiko S.A'!AO55+'Rebisco S.A.'!AO55 -> #N/A | AP55: =+AO55/AN55 -> #N/A | AV55: =+'Biyemas S.A.'!AV55+'Kandiko S.A'!AV55+'Rebisco S.A.'!AV55 -> #N/A | AW55: =+AV55/C55 -> #N/A | BB55: MTD average: | BE55: =+'Biyemas S.A.'!BE55+'Kandiko S.A'!BE55+'Rebisco S.A.'!BE55 -> #N/A | BF55: =+'Biyemas S.A.'!BF55+'Kandiko S.A'!BF55+'Rebisco S.A.'!BF55 -> #N/A | BG55: =+'Biyemas S.A.'!BG55+'Kandiko S.A'!BG55+'Rebisco S.A.'!BG55 -> #N/A | BH55: =+'Biyemas S.A.'!BH55+'Kandiko S.A'!BH55+'Rebisco S.A.'!BH55 -> #N/A | BI55: =+'Biyemas S.A.'!BI55+'Kandiko S.A'!BI55+'Rebisco S.A.'!BI55 -> #N/A | BJ55: =+'Biyemas S.A.'!BJ55+'Kandiko S.A'!BJ55+'Rebisco S.A.'!BJ55 -> #N/A | BK55: =+'Biyemas S.A.'!BK55+'Kandiko S.A'!BK55+'Rebisco S.A.'!BK55 -> #N/A | BL55: =+'Biyemas S.A.'!BL55+'Kandiko S.A'!BL55+'Rebisco S.A.'!BL55 -> #N/A | ... BN55: =+'Biyemas S.A.'!BN55+'Kandiko S.A'!BN55+'Rebisco S.A.'!BN55 -> #N/A | BP55: MTD average anio ant.
BB56: Dev from budget: | BE56: =+'Biyemas S.A.'!BE56+'Kandiko S.A'!BE56+'Rebisco S.A.'!BE56 -> #N/A | BF56: =+'Biyemas S.A.'!BF56+'Kandiko S.A'!BF56+'Rebisco S.A.'!BF56 -> #N/A | BG56: =+'Biyemas S.A.'!BG56+'Kandiko S.A'!BG56+'Rebisco S.A.'!BG56 -> #N/A | BH56: =+'Biyemas S.A.'!BH56+'Kandiko S.A'!BH56+'Rebisco S.A.'!BH56 -> #N/A | BI56: =+'Biyemas S.A.'!BI56+'Kandiko S.A'!BI56+'Rebisco S.A.'!BI56 -> #N/A | BJ56: =+'Biyemas S.A.'!BJ56+'Kandiko S.A'!BJ56+'Rebisco S.A.'!BJ56 -> #N/A | BK56: =+'Biyemas S.A.'!BK56+'Kandiko S.A'!BK56+'Rebisco S.A.'!BK56 -> #N/A | BL56: =+'Biyemas S.A.'!BL56+'Kandiko S.A'!BL56+'Rebisco S.A.'!BL56 -> #N/A | ... BN56: =+'Biyemas S.A.'!BN56+'Kandiko S.A'!BN56+'Rebisco S.A.'!BN56 -> #N/A | BP56: Dev from budget anio ant.
A57: ▲ Prom diario % | C57: =(+C40-C55)/C55 -> #N/A | E57: =(+E40-E55)/E55 -> #DIV/0! | F57: =(+F40-F55)/F55 -> #DIV/0! | G57: =(+G40-G55)/G55 -> #DIV/0! | K57: =(+K40-K55)/K55 -> #DIV/0! | M57: =(+M40-M55)/M55 -> #DIV/0! | N57: =(+N40-N55)/N55 -> #DIV/0! | O57: =(+O40-O55)/O55 -> #DIV/0! | S57: =(+S40-S55)/S55 -> #DIV/0! | T57: =(+T40-T55)/T55 -> #DIV/0! | U57: =(+U40-U55)/U55 -> #DIV/0! | W57: =(+W40-W55)/W55 -> #DIV/0! | X57: =(+X40-X55)/X55 -> #DIV/0! | Y57: =(+Y40-Y55)/Y55 -> #DIV/0! | AD57: =(+AD40-AD55)/AD55 -> #DIV/0! | AE57: =(+AE40-AE55)/AE55 -> #DIV/0! | AF57: =(+AF40-AF55)/AF55 -> #DIV/0! | AG57: =(+AG40-AG55)/AG55 -> #DIV/0! | AH57: =(+AH40-AH55)/AH55 -> #DIV/0! | AI57: =(+AI40-AI55)/AI55 -> #DIV/0! | AK57: =(+AK40-AK55)/AK55 -> #DIV/0! | AL57: =(+AL40-AL55)/AL55 -> #DIV/0! | AN57: =(+AN40-AN55)/AN55 -> #DIV/0! | AO57: =(+AO40-AO55)/AO55 -> #DIV/0! | AV57: =(+AV40-AV55)/AV55 -> #DIV/0!
A58: ▲ Prom diario $ | E58: =+E40-E55 -> #DIV/0! | F58: =+F40-F55 -> #DIV/0! | G58: =+G40-G55 -> #DIV/0! | K58: =+K40-K55 -> #DIV/0! | M58: =+M40-M55 -> #DIV/0! | N58: =+N40-N55 -> #DIV/0! | O58: =+O40-O55 -> #DIV/0! | S58: =+S40-S55 -> #DIV/0! | T58: =+T40-T55 -> #DIV/0! | U58: =+U40-U55 -> #DIV/0! | W58: =+W40-W55 -> #DIV/0! | X58: =+X40-X55 -> #DIV/0! | Y58: =+Y40-Y55 -> #DIV/0! | AD58: =+AD40-AD55 -> #DIV/0! | AE58: =+AE40-AE55 -> #DIV/0! | AF58: =+AF40-AF55 -> #DIV/0! | AG58: =+AG40-AG55 -> #DIV/0! | AH58: =+AH40-AH55 -> #DIV/0! | AI58: =+AI40-AI55 -> #DIV/0! | AK58: =+AK40-AK55 -> #DIV/0! | AL58: =+AL40-AL55 -> #DIV/0! | AN58: =+AN40-AN55 -> #DIV/0! | AO58: =+AO40-AO55 -> #DIV/0! | AV58: =+AV40-AV55 -> #DIV/0!

Sheet Biyemas S.A.
A1: BIYEMAS S.A. | C1: DIA | D1: =COUNT(C7:C37) -> 0
A3: Reporte Flash Agosto 26
D4: SLOTS | L4: ELECTRONIC ROULLETTE - ON LINE | T4: Win | U4: Total | V4: MAQUINA POKER | AD4: On line | AE4: Win | AG4: BINGO | AL4: FOOD & BEVERAGE | AN4: PARKING | AQ4: EGA | AY4: Positions | BA4: Customers | BC4: Vehicles | BE4: Revenues vs. Budget (w/seasonality) | BJ4: Revenues
D5: ON LINE | O5: on line | P5: % win/ | Q5: % win/ | T5: (Slot + RE) | U5: electronic | V5: ON LINE | AD5: Electronic | AE5: Financial | AF5: Difference | AG5: nº | AI5: Net | AK5: Total | AV5: TOTAL NET | AY5: on line | AZ5: vs. Budget | BA5: Budget | BB5: Deviation | BC5: Budget | BD5: Deviation | BE5: Total | BF5: Electronic | BG5: Bingo | BH5: F&B | BI5: Parking | BJ5: Total | BK5: Electronic | BL5: Bingo | BM5: F&B | BN5: Parking
A6: Day | B6: Fecha | C6: Custom. | D6: Units | E6: Coin in | F6: Drop | G6: Win | H6: coin in | I6: Drop | J6: /Cust. | K6: /Units. | L6: Seats | M6: Coin in | N6: Drop | O6: Win | P6: coin in | Q6: Drop | R6: /Cust. | S6: /Seat | T6: / Stand | U6: positions | V6: Units | W6: Coin in | X6: Drop | Y6: Win | Z6: coin in | AA6: Drop | AB6: /Cust. | AC6: /Units. | AD6: Win | AE6: Win | AG6: Cards | AH6: Sales | AI6: win | AJ6: /Cust. | AK6: Gaming | AL6: Sales | AM6: /Cust. | AN6: Vehicles | AO6: Sales | AP6: /Vehic | AQ6: Simulador | AR6: PlayStation | AS6: Arcade | AT6: Total EGA | AU6: Total PRM | AV6: REVENUES | AW6: /Cust. | AZ6: =+'Datos Biyemas'!AT8 -> 0 | BJ6: =+BK6+BL6+BM6+BN6 -> 0 | BK6: =+'Datos Biyemas'!BH8 -> 0 | BL6: =+'Datos Biyemas'!BD8 -> 0 | BM6: =+'Datos Biyemas'!BE8 -> 0 | BN6: =+'Datos Biyemas'!BF8 -> 0
A7: =IF(BP7='Datos Biyemas'!A9,'Datos Biyemas'!A9,"") | B7: =IF(BP7=A7,'Datos Biyemas'!B9,"") | C7: =IF(BP7=A7,'Datos Biyemas'!C9,"") | D7: =IF(BP7=A7,VLOOKUP(B7,'Datos Biyemas'!B9:BB46,3,0),"") | E7: =IF(BP7=A7,VLOOKUP(B7,'Datos Biyemas'!B9:BB46,4,0),"") | F7: =IF(BP7=A7,VLOOKUP(B7,'Datos Biyemas'!B9:BB46,5,0),"") | G7: =IF(BP7=A7,VLOOKUP(B7,'Datos Biyemas'!B9:BB46,6,0),"") | H7: =IF(BP7=A7,IF(E7>0,+G7/E7,0),"") | I7: =IF(A7="","",IF(F7>0,+G7/F7,0)) | J7: =IF(A7="","",IF(G7>0,+G7/C7,0)) | K7: =IF(A7="","",IF(G7>0,+G7/D7,0)) | L7: =IF(A7="","",VLOOKUP(B7,'Datos Biyemas'!B9:BB46,11,0)) | M7: =IF(A7="","",VLOOKUP(B7,'Datos Biyemas'!B9:BB46,12,0)) | N7: =IF(A7="","",VLOOKUP(B7,'Datos Biyemas'!B9:BB46,13,0)) | O7: =IF(A7="","",VLOOKUP(B7,'Datos Biyemas'!B9:BB46,14,0)) | P7: =IF(A7="","",IF(M7>0,+O7/M7,0)) | Q7: =IF(A7="","",IF(N7>0,+O7/N7,0)) | R7: =IF(A7="","",IF(C7>0,+O7/C7,0)) | S7: =IF(A7="","",IF(C7>0,+O7/L7,0)) | T7: =IF(A7="","",IF(G7>0,(G7+O7)/(D7+L7),0)) | U7: =IF(A7="","",IF(D7>0,+L7+D7,0)) | V7: =IF(A7="","",VLOOKUP(B7,'Datos Biyemas'!B9:BB46,21,0)) | W7: =IF(A7="","",VLOOKUP(B7,'Datos Biyemas'!B9:BB46,22,0)) | X7: =IF(A7="","",VLOOKUP(B7,'Datos Biyemas'!B9:BB46,23,0)) | Y7: =IF(A7="","",VLOOKUP(B7,'Datos Biyemas'!B9:BB46,24,0)) | Z7: =IF(A7="","",IF(W7>0,+Y7/W7,0)) | AA7: =IF(A7="","",IF(X7>0,+Y7/X7,0)) | AB7: =IF(A7="","",IF(Y7>0,+Y7/K7,0)) | AC7: =IF(A7="","",IF(Y7>0,+Y7/V7,0)) | AD7: =IF(A7="","",+G7+O7+Y7) | AE7: =IF(A7="","",VLOOKUP(B7,'Datos Biyemas'!B9:BB46,30,0)) | AF7: =IF(A7="","",+AD7-AE7) | AG7: =IF(A7="","",VLOOKUP(B7,'Datos Biyemas'!B9:BB46,32,0)) | AH7: =IF(A7="","",VLOOKUP(B7,'Datos Biyemas'!B9:BB46,33,0)) | AI7: =IF(A7="","",VLOOKUP(B7,'Datos Biyemas'!B9:BB46,34,0)) | AJ7: =IF(A7="","",IF(AI7>0,+AI7/C7,0)) | AK7: =IF(A7="","",+G7+O7+AI7+Y7) | AL7: =IF(A7="","",VLOOKUP(B7,'Datos Biyemas'!B9:BB46,37,0)) | AM7: =IF(A7="","",IF(AL7>0,+AL7/C7,0)) | AN7: =IF(BP7=A7,'Datos Biyemas'!BL9,"") | AO7: =IF(A7="","",VLOOKUP(B7,'Datos Biyemas'!B9:BF46,39,0)) | AP7: =IF(A7="","",IF(AN7>0,+AO7/AN7,0)) | AQ7: =IF(A7="","",VLOOKUP(B7,'Datos Biyemas'!B9:BH46,41,0)) | AR7: =IF(A7="","",VLOOKUP(B7,'Datos Biyemas'!B9:BI46,42,0)) | AS7: =IF(A7="","",VLOOKUP(B7,'Datos Biyemas'!B9:BJ46,43,0)) | AT7: =IF(A7="","",VLOOKUP(B7,'Datos Biyemas'!B9:BK46,44,0)) | AU7: =IF(A7="","",VLOOKUP(C7,'Datos Biyemas'!C9:BL46,44,0)) | AV7: =IF(A7="","",+AD7+AI7+AL7+AO7) | AW7: =IF(A7="","",IF(AV7>0,+AV7/C7,0)) | AY7: =IF(A7="","",+'Datos Biyemas'!AY9) | AZ7: =IF(A7="","",IF($AZ$6>0,+AY7-$AZ$6,)) | BA7: =IF(A7="","",VLOOKUP(B7,'Datos Biyemas'!B9:BF46,51,0)) | BB7: =IF(A7="","",IF(BA7>0,(C7-BA7)/BA7,100%)) | BC7: =IF(BP7=A7,'Datos Biyemas'!BL9,"") | BD7: =IF(A7="","",IF(AN7=BC7,0,IF(BC7>0,(AN7-BC7)/BC7,1))) | BE7: =IF(A7="","",VLOOKUP(B7,'Datos Biyemas'!B9:BF46,53,0)) | BF7: =IF(A7="","",VLOOKUP(B7,'Datos Biyemas'!B9:BF46,54,0)) | BG7: =IF(A7="","",VLOOKUP(B7,'Datos Biyemas'!B9:BF46,55,0)) | BH7: =IF(A7="","",VLOOKUP(B7,'Datos Biyemas'!B9:BF46,51,0)) | BI7: =IF(A7="","",VLOOKUP(B7,'Datos Biyemas'!B9:BF46,52,0)) | BJ7: =IF(A7="","",VLOOKUP(B7,'Datos Biyemas'!B9:BH46,58,0)) | BK7: =IF(A7="","",VLOOKUP(B7,'Datos Biyemas'!B9:BH46,59,0)) | BL7: =IF(A7="","",VLOOKUP(B7,'Datos Biyemas'!B9:BF46,55,0)) | BM7: =IF(A7="","",VLOOKUP(B7,'Datos Biyemas'!B9:BF46,56,0)) | BN7: =IF(A7="","",VLOOKUP(B7,'Datos Biyemas'!B9:BF46,57,0)) | BP7: Sab/Sat
A8: =IF(BP8='Datos Biyemas'!A10,'Datos Biyemas'!A10,"") | B8: =IF(BP8=A8,'Datos Biyemas'!B10,"") | C8: =IF(BP8=A8,'Datos Biyemas'!C10,"") | D8: =IF(BP8=A8,VLOOKUP(B8,'Datos Biyemas'!B10:BB47,3,0),"") | E8: =IF(BP8=A8,VLOOKUP(B8,'Datos Biyemas'!B10:BB47,4,0),"") | F8: =IF(BP8=A8,VLOOKUP(B8,'Datos Biyemas'!B10:BB47,5,0),"") | G8: =IF(BP8=A8,VLOOKUP(B8,'Datos Biyemas'!B10:BB47,6,0),"") | H8: =IF(BP8=A8,IF(E8>0,+G8/E8,0),"") | I8: =IF(A8="","",IF(F8>0,+G8/F8,0)) | J8: =IF(A8="","",IF(G8>0,+G8/C8,0)) | K8: =IF(A8="","",IF(G8>0,+G8/D8,0)) | L8: =IF(A8="","",VLOOKUP(B8,'Datos Biyemas'!B10:BB47,11,0)) | M8: =IF(A8="","",VLOOKUP(B8,'Datos Biyemas'!B10:BB47,12,0)) | N8: =IF(A8="","",VLOOKUP(B8,'Datos Biyemas'!B10:BB47,13,0)) | O8: =IF(A8="","",VLOOKUP(B8,'Datos Biyemas'!B10:BB47,14,0)) | P8: =IF(A8="","",IF(M8>0,+O8/M8,0)) | Q8: =IF(A8="","",IF(N8>0,+O8/N8,0)) | R8: =IF(A8="","",IF(C8>0,+O8/C8,0)) | S8: =IF(A8="","",IF(C8>0,+O8/L8,0)) | T8: =IF(A8="","",IF(G8>0,(G8+O8)/(D8+L8),0)) | U8: =IF(A8="","",IF(D8>0,+L8+D8,0)) | V8: =IF(A8="","",VLOOKUP(B8,'Datos Biyemas'!B10:BB47,21,0)) | W8: =IF(A8="","",VLOOKUP(B8,'Datos Biyemas'!B10:BB47,22,0)) | X8: =IF(A8="","",VLOOKUP(B8,'Datos Biyemas'!B10:BB47,23,0)) | Y8: =IF(A8="","",VLOOKUP(B8,'Datos Biyemas'!B10:BB47,24,0)) | Z8: =IF(A8="","",IF(W8>0,+Y8/W8,0)) | AA8: =IF(A8="","",IF(X8>0,+Y8/X8,0)) | AB8: =IF(A8="","",IF(Y8>0,+Y8/K8,0)) | AC8: =IF(A8="","",IF(Y8>0,+Y8/V8,0)) | AD8: =IF(A8="","",+G8+O8+Y8) | AE8: =IF(A8="","",VLOOKUP(B8,'Datos Biyemas'!B10:BB47,30,0)) | AF8: =IF(A8="","",+AD8-AE8) | AG8: =IF(A8="","",VLOOKUP(B8,'Datos Biyemas'!B10:BB47,32,0)) | AH8: =IF(A8="","",VLOOKUP(B8,'Datos Biyemas'!B10:BB47,33,0)) | AI8: =IF(A8="","",VLOOKUP(B8,'Datos Biyemas'!B10:BB47,34,0)) | AJ8: =IF(A8="","",IF(AI8>0,+AI8/C8,0)) | AK8: =IF(A8="","",+G8+O8+AI8+Y8) | AL8: =IF(A8="","",VLOOKUP(B8,'Datos Biyemas'!B10:BB47,37,0)) | AM8: =IF(A8="","",IF(AL8>0,+AL8/C8,0)) | AN8: =IF(BP8=A8,'Datos Biyemas'!BL10,"") | AO8: =IF(A8="","",VLOOKUP(B8,'Datos Biyemas'!B10:BF47,39,0)) | AP8: =IF(A8="","",IF(AN8>0,+AO8/AN8,0)) | AQ8: =IF(A8="","",VLOOKUP(B8,'Datos Biyemas'!B10:BH47,41,0)) | AR8: =IF(A8="","",VLOOKUP(B8,'Datos Biyemas'!B10:BI47,42,0)) | AS8: =IF(A8="","",VLOOKUP(B8,'Datos Biyemas'!B10:BJ47,43,0)) | AT8: =IF(A8="","",VLOOKUP(B8,'Datos Biyemas'!B10:BK47,44,0)) | AU8: =IF(A8="","",VLOOKUP(C8,'Datos Biyemas'!C10:BL47,44,0)) | AV8: =IF(A8="","",+AD8+AI8+AL8+AO8) | AW8: =IF(A8="","",IF(AV8>0,+AV8/C8,0)) | AY8: =IF(A8="","",+'Datos Biyemas'!AY10) | AZ8: =IF(A8="","",IF($AZ$6>0,+AY8-$AZ$6,)) | BA8: =IF(A8="","",VLOOKUP(B8,'Datos Biyemas'!B10:BF47,51,0)) | BB8: =IF(A8="","",IF(BA8>0,(C8-BA8)/BA8,100%)) | BC8: =IF(BP8=A8,'Datos Biyemas'!BL10,"") | BD8: =IF(A8="","",IF(AN8=BC8,0,IF(BC8>0,(AN8-BC8)/BC8,1))) | BE8: =IF(A8="","",VLOOKUP(B8,'Datos Biyemas'!B10:BF47,53,0)) | BF8: =IF(A8="","",VLOOKUP(B8,'Datos Biyemas'!B10:BF47,54,0)) | BG8: =IF(A8="","",VLOOKUP(B8,'Datos Biyemas'!B10:BF47,55,0)) | BH8: =IF(A8="","",VLOOKUP(B8,'Datos Biyemas'!B10:BF47,51,0)) | BI8: =IF(A8="","",VLOOKUP(B8,'Datos Biyemas'!B10:BF47,52,0)) | BJ8: =IF(A8="","",VLOOKUP(B8,'Datos Biyemas'!B10:BH47,58,0)) | BK8: =IF(A8="","",VLOOKUP(B8,'Datos Biyemas'!B10:BH47,59,0)) | BL8: =IF(A8="","",VLOOKUP(B8,'Datos Biyemas'!B10:BF47,55,0)) | BM8: =IF(A8="","",VLOOKUP(B8,'Datos Biyemas'!B10:BF47,56,0)) | BN8: =IF(A8="","",VLOOKUP(B8,'Datos Biyemas'!B10:BF47,57,0)) | BP8: Dom/Sun
A9: =IF(BP9='Datos Biyemas'!A11,'Datos Biyemas'!A11,"") | B9: =IF(BP9=A9,'Datos Biyemas'!B11,"") | C9: =IF(BP9=A9,'Datos Biyemas'!C11,"") | D9: =IF(BP9=A9,VLOOKUP(B9,'Datos Biyemas'!B11:BB48,3,0),"") | E9: =IF(BP9=A9,VLOOKUP(B9,'Datos Biyemas'!B11:BB48,4,0),"") | F9: =IF(BP9=A9,VLOOKUP(B9,'Datos Biyemas'!B11:BB48,5,0),"") | G9: =IF(BP9=A9,VLOOKUP(B9,'Datos Biyemas'!B11:BB48,6,0),"") | H9: =IF(BP9=A9,IF(E9>0,+G9/E9,0),"") | I9: =IF(A9="","",IF(F9>0,+G9/F9,0)) | J9: =IF(A9="","",IF(G9>0,+G9/C9,0)) | K9: =IF(A9="","",IF(G9>0,+G9/D9,0)) | L9: =IF(A9="","",VLOOKUP(B9,'Datos Biyemas'!B11:BB48,11,0)) | M9: =IF(A9="","",VLOOKUP(B9,'Datos Biyemas'!B11:BB48,12,0)) | N9: =IF(A9="","",VLOOKUP(B9,'Datos Biyemas'!B11:BB48,13,0)) | O9: =IF(A9="","",VLOOKUP(B9,'Datos Biyemas'!B11:BB48,14,0)) | P9: =IF(A9="","",IF(M9>0,+O9/M9,0)) | Q9: =IF(A9="","",IF(N9>0,+O9/N9,0)) | R9: =IF(A9="","",IF(C9>0,+O9/C9,0)) | S9: =IF(A9="","",IF(C9>0,+O9/L9,0)) | T9: =IF(A9="","",IF(G9>0,(G9+O9)/(D9+L9),0)) | U9: =IF(A9="","",IF(D9>0,+L9+D9,0)) | V9: =IF(A9="","",VLOOKUP(B9,'Datos Biyemas'!B11:BB48,21,0)) | W9: =IF(A9="","",VLOOKUP(B9,'Datos Biyemas'!B11:BB48,22,0)) | X9: =IF(A9="","",VLOOKUP(B9,'Datos Biyemas'!B11:BB48,23,0)) | Y9: =IF(A9="","",VLOOKUP(B9,'Datos Biyemas'!B11:BB48,24,0)) | Z9: =IF(A9="","",IF(W9>0,+Y9/W9,0)) | AA9: =IF(A9="","",IF(X9>0,+Y9/X9,0)) | AB9: =IF(A9="","",IF(Y9>0,+Y9/K9,0)) | AC9: =IF(A9="","",IF(Y9>0,+Y9/V9,0)) | AD9: =IF(A9="","",+G9+O9+Y9) | AE9: =IF(A9="","",VLOOKUP(B9,'Datos Biyemas'!B11:BB48,30,0)) | AF9: =IF(A9="","",+AD9-AE9) | AG9: =IF(A9="","",VLOOKUP(B9,'Datos Biyemas'!B11:BB48,32,0)) | AH9: =IF(A9="","",VLOOKUP(B9,'Datos Biyemas'!B11:BB48,33,0)) | AI9: =IF(A9="","",VLOOKUP(B9,'Datos Biyemas'!B11:BB48,34,0)) | AJ9: =IF(A9="","",IF(AI9>0,+AI9/C9,0)) | AK9: =IF(A9="","",+G9+O9+AI9+Y9) | AL9: =IF(A9="","",VLOOKUP(B9,'Datos Biyemas'!B11:BB48,37,0)) | AM9: =IF(A9="","",IF(AL9>0,+AL9/C9,0)) | AN9: =IF(BP9=A9,'Datos Biyemas'!BL11,"") | AO9: =IF(A9="","",VLOOKUP(B9,'Datos Biyemas'!B11:BF48,39,0)) | AP9: =IF(A9="","",IF(AN9>0,+AO9/AN9,0)) | AQ9: =IF(A9="","",VLOOKUP(B9,'Datos Biyemas'!B11:BH48,41,0)) | AR9: =IF(A9="","",VLOOKUP(B9,'Datos Biyemas'!B11:BI48,42,0)) | AS9: =IF(A9="","",VLOOKUP(B9,'Datos Biyemas'!B11:BJ48,43,0)) | AT9: =IF(A9="","",VLOOKUP(B9,'Datos Biyemas'!B11:BK48,44,0)) | AU9: =IF(A9="","",VLOOKUP(C9,'Datos Biyemas'!C11:BL48,44,0)) | AV9: =IF(A9="","",+AD9+AI9+AL9+AO9) | AW9: =IF(A9="","",IF(AV9>0,+AV9/C9,0)) | AY9: =IF(A9="","",+'Datos Biyemas'!AY11) | AZ9: =IF(A9="","",IF($AZ$6>0,+AY9-$AZ$6,)) | BA9: =IF(A9="","",VLOOKUP(B9,'Datos Biyemas'!B11:BF48,51,0)) | BB9: =IF(A9="","",IF(BA9>0,(C9-BA9)/BA9,100%)) | BC9: =IF(BP9=A9,'Datos Biyemas'!BL11,"") | BD9: =IF(A9="","",IF(AN9=BC9,0,IF(BC9>0,(AN9-BC9)/BC9,1))) | BE9: =IF(A9="","",VLOOKUP(B9,'Datos Biyemas'!B11:BF48,53,0)) | BF9: =IF(A9="","",VLOOKUP(B9,'Datos Biyemas'!B11:BF48,54,0)) | BG9: =IF(A9="","",VLOOKUP(B9,'Datos Biyemas'!B11:BF48,55,0)) | BH9: =IF(A9="","",VLOOKUP(B9,'Datos Biyemas'!B11:BF48,51,0)) | BI9: =IF(A9="","",VLOOKUP(B9,'Datos Biyemas'!B11:BF48,52,0)) | BJ9: =IF(A9="","",VLOOKUP(B9,'Datos Biyemas'!B11:BH48,58,0)) | BK9: =IF(A9="","",VLOOKUP(B9,'Datos Biyemas'!B11:BH48,59,0)) | BL9: =IF(A9="","",VLOOKUP(B9,'Datos Biyemas'!B11:BF48,55,0)) | BM9: =IF(A9="","",VLOOKUP(B9,'Datos Biyemas'!B11:BF48,56,0)) | BN9: =IF(A9="","",VLOOKUP(B9,'Datos Biyemas'!B11:BF48,57,0)) | BP9: Lun/Mon
A10: =IF(BP10='Datos Biyemas'!A12,'Datos Biyemas'!A12,"") | B10: =IF(BP10=A10,'Datos Biyemas'!B12,"") | C10: =IF(BP10=A10,'Datos Biyemas'!C12,"") | D10: =IF(BP10=A10,VLOOKUP(B10,'Datos Biyemas'!B12:BB49,3,0),"") | E10: =IF(BP10=A10,VLOOKUP(B10,'Datos Biyemas'!B12:BB49,4,0),"") | F10: =IF(BP10=A10,VLOOKUP(B10,'Datos Biyemas'!B12:BB49,5,0),"") | G10: =IF(BP10=A10,VLOOKUP(B10,'Datos Biyemas'!B12:BB49,6,0),"") | H10: =IF(BP10=A10,IF(E10>0,+G10/E10,0),"") | I10: =IF(A10="","",IF(F10>0,+G10/F10,0)) | J10: =IF(A10="","",IF(G10>0,+G10/C10,0)) | K10: =IF(A10="","",IF(G10>0,+G10/D10,0)) | L10: =IF(A10="","",VLOOKUP(B10,'Datos Biyemas'!B12:BB49,11,0)) | M10: =IF(A10="","",VLOOKUP(B10,'Datos Biyemas'!B12:BB49,12,0)) | N10: =IF(A10="","",VLOOKUP(B10,'Datos Biyemas'!B12:BB49,13,0)) | O10: =IF(A10="","",VLOOKUP(B10,'Datos Biyemas'!B12:BB49,14,0)) | P10: =IF(A10="","",IF(M10>0,+O10/M10,0)) | Q10: =IF(A10="","",IF(N10>0,+O10/N10,0)) | R10: =IF(A10="","",IF(C10>0,+O10/C10,0)) | S10: =IF(A10="","",IF(C10>0,+O10/L10,0)) | T10: =IF(A10="","",IF(G10>0,(G10+O10)/(D10+L10),0)) | U10: =IF(A10="","",IF(D10>0,+L10+D10,0)) | V10: =IF(A10="","",VLOOKUP(B10,'Datos Biyemas'!B12:BB49,21,0)) | W10: =IF(A10="","",VLOOKUP(B10,'Datos Biyemas'!B12:BB49,22,0)) | X10: =IF(A10="","",VLOOKUP(B10,'Datos Biyemas'!B12:BB49,23,0)) | Y10: =IF(A10="","",VLOOKUP(B10,'Datos Biyemas'!B12:BB49,24,0)) | Z10: =IF(A10="","",IF(W10>0,+Y10/W10,0)) | AA10: =IF(A10="","",IF(X10>0,+Y10/X10,0)) | AB10: =IF(A10="","",IF(Y10>0,+Y10/K10,0)) | AC10: =IF(A10="","",IF(Y10>0,+Y10/V10,0)) | AD10: =IF(A10="","",+G10+O10+Y10) | AE10: =IF(A10="","",VLOOKUP(B10,'Datos Biyemas'!B12:BB49,30,0)) | AF10: =IF(A10="","",+AD10-AE10) | AG10: =IF(A10="","",VLOOKUP(B10,'Datos Biyemas'!B12:BB49,32,0)) | AH10: =IF(A10="","",VLOOKUP(B10,'Datos Biyemas'!B12:BB49,33,0)) | AI10: =IF(A10="","",VLOOKUP(B10,'Datos Biyemas'!B12:BB49,34,0)) | AJ10: =IF(A10="","",IF(AI10>0,+AI10/C10,0)) | AK10: =IF(A10="","",+G10+O10+AI10+Y10) | AL10: =IF(A10="","",VLOOKUP(B10,'Datos Biyemas'!B12:BB49,37,0)) | AM10: =IF(A10="","",IF(AL10>0,+AL10/C10,0)) | AN10: =IF(BP10=A10,'Datos Biyemas'!BL12,"") | AO10: =IF(A10="","",VLOOKUP(B10,'Datos Biyemas'!B12:BF49,39,0)) | AP10: =IF(A10="","",IF(AN10>0,+AO10/AN10,0)) | AQ10: =IF(A10="","",VLOOKUP(B10,'Datos Biyemas'!B12:BH49,41,0)) | AR10: =IF(A10="","",VLOOKUP(B10,'Datos Biyemas'!B12:BI49,42,0)) | AS10: =IF(A10="","",VLOOKUP(B10,'Datos Biyemas'!B12:BJ49,43,0)) | AT10: =IF(A10="","",VLOOKUP(B10,'Datos Biyemas'!B12:BK49,44,0)) | AU10: =IF(A10="","",VLOOKUP(C10,'Datos Biyemas'!C12:BL49,44,0)) | AV10: =IF(A10="","",+AD10+AI10+AL10+AO10) | AW10: =IF(A10="","",IF(AV10>0,+AV10/C10,0)) | AY10: =IF(A10="","",+'Datos Biyemas'!AY12) | AZ10: =IF(A10="","",IF($AZ$6>0,+AY10-$AZ$6,)) | BA10: =IF(A10="","",VLOOKUP(B10,'Datos Biyemas'!B12:BF49,51,0)) | BB10: =IF(A10="","",IF(BA10>0,(C10-BA10)/BA10,100%)) | BC10: =IF(BP10=A10,'Datos Biyemas'!BL12,"") | BD10: =IF(A10="","",IF(AN10=BC10,0,IF(BC10>0,(AN10-BC10)/BC10,1))) | BE10: =IF(A10="","",VLOOKUP(B10,'Datos Biyemas'!B12:BF49,53,0)) | BF10: =IF(A10="","",VLOOKUP(B10,'Datos Biyemas'!B12:BF49,54,0)) | BG10: =IF(A10="","",VLOOKUP(B10,'Datos Biyemas'!B12:BF49,55,0)) | BH10: =IF(A10="","",VLOOKUP(B10,'Datos Biyemas'!B12:BF49,51,0)) | BI10: =IF(A10="","",VLOOKUP(B10,'Datos Biyemas'!B12:BF49,52,0)) | BJ10: =IF(A10="","",VLOOKUP(B10,'Datos Biyemas'!B12:BH49,58,0)) | BK10: =IF(A10="","",VLOOKUP(B10,'Datos Biyemas'!B12:BH49,59,0)) | BL10: =IF(A10="","",VLOOKUP(B10,'Datos Biyemas'!B12:BF49,55,0)) | BM10: =IF(A10="","",VLOOKUP(B10,'Datos Biyemas'!B12:BF49,56,0)) | BN10: =IF(A10="","",VLOOKUP(B10,'Datos Biyemas'!B12:BF49,57,0)) | BP10: Mar/Tue
A11: =IF(BP11='Datos Biyemas'!A13,'Datos Biyemas'!A13,"") | B11: =IF(BP11=A11,'Datos Biyemas'!B13,"") | C11: =IF(BP11=A11,'Datos Biyemas'!C13,"") | D11: =IF(BP11=A11,VLOOKUP(B11,'Datos Biyemas'!B13:BB50,3,0),"") | E11: =IF(BP11=A11,VLOOKUP(B11,'Datos Biyemas'!B13:BB50,4,0),"") | F11: =IF(BP11=A11,VLOOKUP(B11,'Datos Biyemas'!B13:BB50,5,0),"") | G11: =IF(BP11=A11,VLOOKUP(B11,'Datos Biyemas'!B13:BB50,6,0),"") | H11: =IF(BP11=A11,IF(E11>0,+G11/E11,0),"") | I11: =IF(A11="","",IF(F11>0,+G11/F11,0)) | J11: =IF(A11="","",IF(G11>0,+G11/C11,0)) | K11: =IF(A11="","",IF(G11>0,+G11/D11,0)) | L11: =IF(A11="","",VLOOKUP(B11,'Datos Biyemas'!B13:BB50,11,0)) | M11: =IF(A11="","",VLOOKUP(B11,'Datos Biyemas'!B13:BB50,12,0)) | N11: =IF(A11="","",VLOOKUP(B11,'Datos Biyemas'!B13:BB50,13,0)) | O11: =IF(A11="","",VLOOKUP(B11,'Datos Biyemas'!B13:BB50,14,0)) | P11: =IF(A11="","",IF(M11>0,+O11/M11,0)) | Q11: =IF(A11="","",IF(N11>0,+O11/N11,0)) | R11: =IF(A11="","",IF(C11>0,+O11/C11,0)) | S11: =IF(A11="","",IF(C11>0,+O11/L11,0)) | T11: =IF(A11="","",IF(G11>0,(G11+O11)/(D11+L11),0)) | U11: =IF(A11="","",IF(D11>0,+L11+D11,0)) | V11: =IF(A11="","",VLOOKUP(B11,'Datos Biyemas'!B13:BB50,21,0)) | W11: =IF(A11="","",VLOOKUP(B11,'Datos Biyemas'!B13:BB50,22,0)) | X11: =IF(A11="","",VLOOKUP(B11,'Datos Biyemas'!B13:BB50,23,0)) | Y11: =IF(A11="","",VLOOKUP(B11,'Datos Biyemas'!B13:BB50,24,0)) | Z11: =IF(A11="","",IF(W11>0,+Y11/W11,0)) | AA11: =IF(A11="","",IF(X11>0,+Y11/X11,0)) | AB11: =IF(A11="","",IF(Y11>0,+Y11/K11,0)) | AC11: =IF(A11="","",IF(Y11>0,+Y11/V11,0)) | AD11: =IF(A11="","",+G11+O11+Y11) | AE11: =IF(A11="","",VLOOKUP(B11,'Datos Biyemas'!B13:BB50,30,0)) | AF11: =IF(A11="","",+AD11-AE11) | AG11: =IF(A11="","",VLOOKUP(B11,'Datos Biyemas'!B13:BB50,32,0)) | AH11: =IF(A11="","",VLOOKUP(B11,'Datos Biyemas'!B13:BB50,33,0)) | AI11: =IF(A11="","",VLOOKUP(B11,'Datos Biyemas'!B13:BB50,34,0)) | AJ11: =IF(A11="","",IF(AI11>0,+AI11/C11,0)) | AK11: =IF(A11="","",+G11+O11+AI11+Y11) | AL11: =IF(A11="","",VLOOKUP(B11,'Datos Biyemas'!B13:BB50,37,0)) | AM11: =IF(A11="","",IF(AL11>0,+AL11/C11,0)) | AN11: =IF(BP11=A11,'Datos Biyemas'!BL13,"") | AO11: =IF(A11="","",VLOOKUP(B11,'Datos Biyemas'!B13:BF50,39,0)) | AP11: =IF(A11="","",IF(AN11>0,+AO11/AN11,0)) | AQ11: =IF(A11="","",VLOOKUP(B11,'Datos Biyemas'!B13:BH50,41,0)) | AR11: =IF(A11="","",VLOOKUP(B11,'Datos Biyemas'!B13:BI50,42,0)) | AS11: =IF(A11="","",VLOOKUP(B11,'Datos Biyemas'!B13:BJ50,43,0)) | AT11: =IF(A11="","",VLOOKUP(B11,'Datos Biyemas'!B13:BK50,44,0)) | AU11: =IF(A11="","",VLOOKUP(C11,'Datos Biyemas'!C13:BL50,44,0)) | AV11: =IF(A11="","",+AD11+AI11+AL11+AO11) | AW11: =IF(A11="","",IF(AV11>0,+AV11/C11,0)) | AY11: =IF(A11="","",+'Datos Biyemas'!AY13) | AZ11: =IF(A11="","",IF($AZ$6>0,+AY11-$AZ$6,)) | BA11: =IF(A11="","",VLOOKUP(B11,'Datos Biyemas'!B13:BF50,51,0)) | BB11: =IF(A11="","",IF(BA11>0,(C11-BA11)/BA11,100%)) | BC11: =IF(BP11=A11,'Datos Biyemas'!BL13,"") | BD11: =IF(A11="","",IF(AN11=BC11,0,IF(BC11>0,(AN11-BC11)/BC11,1))) | BE11: =IF(A11="","",VLOOKUP(B11,'Datos Biyemas'!B13:BF50,53,0)) | BF11: =IF(A11="","",VLOOKUP(B11,'Datos Biyemas'!B13:BF50,54,0)) | BG11: =IF(A11="","",VLOOKUP(B11,'Datos Biyemas'!B13:BF50,55,0)) | BH11: =IF(A11="","",VLOOKUP(B11,'Datos Biyemas'!B13:BF50,51,0)) | BI11: =IF(A11="","",VLOOKUP(B11,'Datos Biyemas'!B13:BF50,52,0)) | BJ11: =IF(A11="","",VLOOKUP(B11,'Datos Biyemas'!B13:BH50,58,0)) | BK11: =IF(A11="","",VLOOKUP(B11,'Datos Biyemas'!B13:BH50,59,0)) | BL11: =IF(A11="","",VLOOKUP(B11,'Datos Biyemas'!B13:BF50,55,0)) | BM11: =IF(A11="","",VLOOKUP(B11,'Datos Biyemas'!B13:BF50,56,0)) | BN11: =IF(A11="","",VLOOKUP(B11,'Datos Biyemas'!B13:BF50,57,0)) | BP11: Mie/Wed
A12: =IF(BP12='Datos Biyemas'!A14,'Datos Biyemas'!A14,"") | B12: =IF(BP12=A12,'Datos Biyemas'!B14,"") | C12: =IF(BP12=A12,'Datos Biyemas'!C14,"") | D12: =IF(BP12=A12,VLOOKUP(B12,'Datos Biyemas'!B14:BB51,3,0),"") | E12: =IF(BP12=A12,VLOOKUP(B12,'Datos Biyemas'!B14:BB51,4,0),"") | F12: =IF(BP12=A12,VLOOKUP(B12,'Datos Biyemas'!B14:BB51,5,0),"") | G12: =IF(BP12=A12,VLOOKUP(B12,'Datos Biyemas'!B14:BB51,6,0),"") | H12: =IF(BP12=A12,IF(E12>0,+G12/E12,0),"") | I12: =IF(A12="","",IF(F12>0,+G12/F12,0)) | J12: =IF(A12="","",IF(G12>0,+G12/C12,0)) | K12: =IF(A12="","",IF(G12>0,+G12/D12,0)) | L12: =IF(A12="","",VLOOKUP(B12,'Datos Biyemas'!B14:BB51,11,0)) | M12: =IF(A12="","",VLOOKUP(B12,'Datos Biyemas'!B14:BB51,12,0)) | N12: =IF(A12="","",VLOOKUP(B12,'Datos Biyemas'!B14:BB51,13,0)) | O12: =IF(A12="","",VLOOKUP(B12,'Datos Biyemas'!B14:BB51,14,0)) | P12: =IF(A12="","",IF(M12>0,+O12/M12,0)) | Q12: =IF(A12="","",IF(N12>0,+O12/N12,0)) | R12: =IF(A12="","",IF(C12>0,+O12/C12,0)) | S12: =IF(A12="","",IF(C12>0,+O12/L12,0)) | T12: =IF(A12="","",IF(G12>0,(G12+O12)/(D12+L12),0)) | U12: =IF(A12="","",IF(D12>0,+L12+D12,0)) | V12: =IF(A12="","",VLOOKUP(B12,'Datos Biyemas'!B14:BB51,21,0)) | W12: =IF(A12="","",VLOOKUP(B12,'Datos Biyemas'!B14:BB51,22,0)) | X12: =IF(A12="","",VLOOKUP(B12,'Datos Biyemas'!B14:BB51,23,0)) | Y12: =IF(A12="","",VLOOKUP(B12,'Datos Biyemas'!B14:BB51,24,0)) | Z12: =IF(A12="","",IF(W12>0,+Y12/W12,0)) | AA12: =IF(A12="","",IF(X12>0,+Y12/X12,0)) | AB12: =IF(A12="","",IF(Y12>0,+Y12/K12,0)) | AC12: =IF(A12="","",IF(Y12>0,+Y12/V12,0)) | AD12: =IF(A12="","",+G12+O12+Y12) | AE12: =IF(A12="","",VLOOKUP(B12,'Datos Biyemas'!B14:BB51,30,0)) | AF12: =IF(A12="","",+AD12-AE12) | AG12: =IF(A12="","",VLOOKUP(B12,'Datos Biyemas'!B14:BB51,32,0)) | AH12: =IF(A12="","",VLOOKUP(B12,'Datos Biyemas'!B14:BB51,33,0)) | AI12: =IF(A12="","",VLOOKUP(B12,'Datos Biyemas'!B14:BB51,34,0)) | AJ12: =IF(A12="","",IF(AI12>0,+AI12/C12,0)) | AK12: =IF(A12="","",+G12+O12+AI12+Y12) | AL12: =IF(A12="","",VLOOKUP(B12,'Datos Biyemas'!B14:BB51,37,0)) | AM12: =IF(A12="","",IF(AL12>0,+AL12/C12,0)) | AN12: =IF(BP12=A12,'Datos Biyemas'!BL14,"") | AO12: =IF(A12="","",VLOOKUP(B12,'Datos Biyemas'!B14:BF51,39,0)) | AP12: =IF(A12="","",IF(AN12>0,+AO12/AN12,0)) | AQ12: =IF(A12="","",VLOOKUP(B12,'Datos Biyemas'!B14:BH51,41,0)) | AR12: =IF(A12="","",VLOOKUP(B12,'Datos Biyemas'!B14:BI51,42,0)) | AS12: =IF(A12="","",VLOOKUP(B12,'Datos Biyemas'!B14:BJ51,43,0)) | AT12: =IF(A12="","",VLOOKUP(B12,'Datos Biyemas'!B14:BK51,44,0)) | AU12: =IF(A12="","",VLOOKUP(C12,'Datos Biyemas'!C14:BL51,44,0)) | AV12: =IF(A12="","",+AD12+AI12+AL12+AO12) | AW12: =IF(A12="","",IF(AV12>0,+AV12/C12,0)) | AY12: =IF(A12="","",+'Datos Biyemas'!AY14) | AZ12: =IF(A12="","",IF($AZ$6>0,+AY12-$AZ$6,)) | BA12: =IF(A12="","",VLOOKUP(B12,'Datos Biyemas'!B14:BF51,51,0)) | BB12: =IF(A12="","",IF(BA12>0,(C12-BA12)/BA12,100%)) | BC12: =IF(BP12=A12,'Datos Biyemas'!BL14,"") | BD12: =IF(A12="","",IF(AN12=BC12,0,IF(BC12>0,(AN12-BC12)/BC12,1))) | BE12: =IF(A12="","",VLOOKUP(B12,'Datos Biyemas'!B14:BF51,53,0)) | BF12: =IF(A12="","",VLOOKUP(B12,'Datos Biyemas'!B14:BF51,54,0)) | BG12: =IF(A12="","",VLOOKUP(B12,'Datos Biyemas'!B14:BF51,55,0)) | BH12: =IF(A12="","",VLOOKUP(B12,'Datos Biyemas'!B14:BF51,51,0)) | BI12: =IF(A12="","",VLOOKUP(B12,'Datos Biyemas'!B14:BF51,52,0)) | BJ12: =IF(A12="","",VLOOKUP(B12,'Datos Biyemas'!B14:BH51,58,0)) | BK12: =IF(A12="","",VLOOKUP(B12,'Datos Biyemas'!B14:BH51,59,0)) | BL12: =IF(A12="","",VLOOKUP(B12,'Datos Biyemas'!B14:BF51,55,0)) | BM12: =IF(A12="","",VLOOKUP(B12,'Datos Biyemas'!B14:BF51,56,0)) | BN12: =IF(A12="","",VLOOKUP(B12,'Datos Biyemas'!B14:BF51,57,0)) | BP12: Jue/Thu
A13: =IF(BP13='Datos Biyemas'!A15,'Datos Biyemas'!A15,"") | B13: =IF(BP13=A13,'Datos Biyemas'!B15,"") | C13: =IF(BP13=A13,'Datos Biyemas'!C15,"") | D13: =IF(BP13=A13,VLOOKUP(B13,'Datos Biyemas'!B15:BB52,3,0),"") | E13: =IF(BP13=A13,VLOOKUP(B13,'Datos Biyemas'!B15:BB52,4,0),"") | F13: =IF(BP13=A13,VLOOKUP(B13,'Datos Biyemas'!B15:BB52,5,0),"") | G13: =IF(BP13=A13,VLOOKUP(B13,'Datos Biyemas'!B15:BB52,6,0),"") | H13: =IF(BP13=A13,IF(E13>0,+G13/E13,0),"") | I13: =IF(A13="","",IF(F13>0,+G13/F13,0)) | J13: =IF(A13="","",IF(G13>0,+G13/C13,0)) | K13: =IF(A13="","",IF(G13>0,+G13/D13,0)) | L13: =IF(A13="","",VLOOKUP(B13,'Datos Biyemas'!B15:BB52,11,0)) | M13: =IF(A13="","",VLOOKUP(B13,'Datos Biyemas'!B15:BB52,12,0)) | N13: =IF(A13="","",VLOOKUP(B13,'Datos Biyemas'!B15:BB52,13,0)) | O13: =IF(A13="","",VLOOKUP(B13,'Datos Biyemas'!B15:BB52,14,0)) | P13: =IF(A13="","",IF(M13>0,+O13/M13,0)) | Q13: =IF(A13="","",IF(N13>0,+O13/N13,0)) | R13: =IF(A13="","",IF(C13>0,+O13/C13,0)) | S13: =IF(A13="","",IF(C13>0,+O13/L13,0)) | T13: =IF(A13="","",IF(G13>0,(G13+O13)/(D13+L13),0)) | U13: =IF(A13="","",IF(D13>0,+L13+D13,0)) | V13: =IF(A13="","",VLOOKUP(B13,'Datos Biyemas'!B15:BB52,21,0)) | W13: =IF(A13="","",VLOOKUP(B13,'Datos Biyemas'!B15:BB52,22,0)) | X13: =IF(A13="","",VLOOKUP(B13,'Datos Biyemas'!B15:BB52,23,0)) | Y13: =IF(A13="","",VLOOKUP(B13,'Datos Biyemas'!B15:BB52,24,0)) | Z13: =IF(A13="","",IF(W13>0,+Y13/W13,0)) | AA13: =IF(A13="","",IF(X13>0,+Y13/X13,0)) | AB13: =IF(A13="","",IF(Y13>0,+Y13/K13,0)) | AC13: =IF(A13="","",IF(Y13>0,+Y13/V13,0)) | AD13: =IF(A13="","",+G13+O13+Y13) | AE13: =IF(A13="","",VLOOKUP(B13,'Datos Biyemas'!B15:BB52,30,0)) | AF13: =IF(A13="","",+AD13-AE13) | AG13: =IF(A13="","",VLOOKUP(B13,'Datos Biyemas'!B15:BB52,32,0)) | AH13: =IF(A13="","",VLOOKUP(B13,'Datos Biyemas'!B15:BB52,33,0)) | AI13: =IF(A13="","",VLOOKUP(B13,'Datos Biyemas'!B15:BB52,34,0)) | AJ13: =IF(A13="","",IF(AI13>0,+AI13/C13,0)) | AK13: =IF(A13="","",+G13+O13+AI13+Y13) | AL13: =IF(A13="","",VLOOKUP(B13,'Datos Biyemas'!B15:BB52,37,0)) | AM13: =IF(A13="","",IF(AL13>0,+AL13/C13,0)) | AN13: =IF(BP13=A13,'Datos Biyemas'!BL15,"") | AO13: =IF(A13="","",VLOOKUP(B13,'Datos Biyemas'!B15:BF52,39,0)) | AP13: =IF(A13="","",IF(AN13>0,+AO13/AN13,0)) | AQ13: =IF(A13="","",VLOOKUP(B13,'Datos Biyemas'!B15:BH52,41,0)) | AR13: =IF(A13="","",VLOOKUP(B13,'Datos Biyemas'!B15:BI52,42,0)) | AS13: =IF(A13="","",VLOOKUP(B13,'Datos Biyemas'!B15:BJ52,43,0)) | AT13: =IF(A13="","",VLOOKUP(B13,'Datos Biyemas'!B15:BK52,44,0)) | AU13: =IF(A13="","",VLOOKUP(C13,'Datos Biyemas'!C15:BL52,44,0)) | AV13: =IF(A13="","",+AD13+AI13+AL13+AO13) | AW13: =IF(A13="","",IF(AV13>0,+AV13/C13,0)) | AY13: =IF(A13="","",+'Datos Biyemas'!AY15) | AZ13: =IF(A13="","",IF($AZ$6>0,+AY13-$AZ$6,)) | BA13: =IF(A13="","",VLOOKUP(B13,'Datos Biyemas'!B15:BF52,51,0)) | BB13: =IF(A13="","",IF(BA13>0,(C13-BA13)/BA13,100%)) | BC13: =IF(BP13=A13,'Datos Biyemas'!BL15,"") | BD13: =IF(A13="","",IF(AN13=BC13,0,IF(BC13>0,(AN13-BC13)/BC13,1))) | BE13: =IF(A13="","",VLOOKUP(B13,'Datos Biyemas'!B15:BF52,53,0)) | BF13: =IF(A13="","",VLOOKUP(B13,'Datos Biyemas'!B15:BF52,54,0)) | BG13: =IF(A13="","",VLOOKUP(B13,'Datos Biyemas'!B15:BF52,55,0)) | BH13: =IF(A13="","",VLOOKUP(B13,'Datos Biyemas'!B15:BF52,51,0)) | BI13: =IF(A13="","",VLOOKUP(B13,'Datos Biyemas'!B15:BF52,52,0)) | BJ13: =IF(A13="","",VLOOKUP(B13,'Datos Biyemas'!B15:BH52,58,0)) | BK13: =IF(A13="","",VLOOKUP(B13,'Datos Biyemas'!B15:BH52,59,0)) | BL13: =IF(A13="","",VLOOKUP(B13,'Datos Biyemas'!B15:BF52,55,0)) | BM13: =IF(A13="","",VLOOKUP(B13,'Datos Biyemas'!B15:BF52,56,0)) | BN13: =IF(A13="","",VLOOKUP(B13,'Datos Biyemas'!B15:BF52,57,0)) | BP13: Vie/Fri
A14: =IF(BP14='Datos Biyemas'!A16,'Datos Biyemas'!A16,"") | B14: =IF(BP14=A14,'Datos Biyemas'!B16,"") | C14: =IF(BP14=A14,'Datos Biyemas'!C16,"") | D14: =IF(BP14=A14,VLOOKUP(B14,'Datos Biyemas'!B16:BB53,3,0),"") | E14: =IF(BP14=A14,VLOOKUP(B14,'Datos Biyemas'!B16:BB53,4,0),"") | F14: =IF(BP14=A14,VLOOKUP(B14,'Datos Biyemas'!B16:BB53,5,0),"") | G14: =IF(BP14=A14,VLOOKUP(B14,'Datos Biyemas'!B16:BB53,6,0),"") | H14: =IF(BP14=A14,IF(E14>0,+G14/E14,0),"") | I14: =IF(A14="","",IF(F14>0,+G14/F14,0)) | J14: =IF(A14="","",IF(G14>0,+G14/C14,0)) | K14: =IF(A14="","",IF(G14>0,+G14/D14,0)) | L14: =IF(A14="","",VLOOKUP(B14,'Datos Biyemas'!B16:BB53,11,0)) | M14: =IF(A14="","",VLOOKUP(B14,'Datos Biyemas'!B16:BB53,12,0)) | N14: =IF(A14="","",VLOOKUP(B14,'Datos Biyemas'!B16:BB53,13,0)) | O14: =IF(A14="","",VLOOKUP(B14,'Datos Biyemas'!B16:BB53,14,0)) | P14: =IF(A14="","",IF(M14>0,+O14/M14,0)) | Q14: =IF(A14="","",IF(N14>0,+O14/N14,0)) | R14: =IF(A14="","",IF(C14>0,+O14/C14,0)) | S14: =IF(A14="","",IF(C14>0,+O14/L14,0)) | T14: =IF(A14="","",IF(G14>0,(G14+O14)/(D14+L14),0)) | U14: =IF(A14="","",IF(D14>0,+L14+D14,0)) | V14: =IF(A14="","",VLOOKUP(B14,'Datos Biyemas'!B16:BB53,21,0)) | W14: =IF(A14="","",VLOOKUP(B14,'Datos Biyemas'!B16:BB53,22,0)) | X14: =IF(A14="","",VLOOKUP(B14,'Datos Biyemas'!B16:BB53,23,0)) | Y14: =IF(A14="","",VLOOKUP(B14,'Datos Biyemas'!B16:BB53,24,0)) | Z14: =IF(A14="","",IF(W14>0,+Y14/W14,0)) | AA14: =IF(A14="","",IF(X14>0,+Y14/X14,0)) | AB14: =IF(A14="","",IF(Y14>0,+Y14/K14,0)) | AC14: =IF(A14="","",IF(Y14>0,+Y14/V14,0)) | AD14: =IF(A14="","",+G14+O14+Y14) | AE14: =IF(A14="","",VLOOKUP(B14,'Datos Biyemas'!B16:BB53,30,0)) | AF14: =IF(A14="","",+AD14-AE14) | AG14: =IF(A14="","",VLOOKUP(B14,'Datos Biyemas'!B16:BB53,32,0)) | AH14: =IF(A14="","",VLOOKUP(B14,'Datos Biyemas'!B16:BB53,33,0)) | AI14: =IF(A14="","",VLOOKUP(B14,'Datos Biyemas'!B16:BB53,34,0)) | AJ14: =IF(A14="","",IF(AI14>0,+AI14/C14,0)) | AK14: =IF(A14="","",+G14+O14+AI14+Y14) | AL14: =IF(A14="","",VLOOKUP(B14,'Datos Biyemas'!B16:BB53,37,0)) | AM14: =IF(A14="","",IF(AL14>0,+AL14/C14,0)) | AN14: =IF(BP14=A14,'Datos Biyemas'!BL16,"") | AO14: =IF(A14="","",VLOOKUP(B14,'Datos Biyemas'!B16:BF53,39,0)) | AP14: =IF(A14="","",IF(AN14>0,+AO14/AN14,0)) | AQ14: =IF(A14="","",VLOOKUP(B14,'Datos Biyemas'!B16:BH53,41,0)) | AR14: =IF(A14="","",VLOOKUP(B14,'Datos Biyemas'!B16:BI53,42,0)) | AS14: =IF(A14="","",VLOOKUP(B14,'Datos Biyemas'!B16:BJ53,43,0)) | AT14: =IF(A14="","",VLOOKUP(B14,'Datos Biyemas'!B16:BK53,44,0)) | AU14: =IF(A14="","",VLOOKUP(C14,'Datos Biyemas'!C16:BL53,44,0)) | AV14: =IF(A14="","",+AD14+AI14+AL14+AO14) | AW14: =IF(A14="","",IF(AV14>0,+AV14/C14,0)) | AY14: =IF(A14="","",+'Datos Biyemas'!AY16) | AZ14: =IF(A14="","",IF($AZ$6>0,+AY14-$AZ$6,)) | BA14: =IF(A14="","",VLOOKUP(B14,'Datos Biyemas'!B16:BF53,51,0)) | BB14: =IF(A14="","",IF(BA14>0,(C14-BA14)/BA14,100%)) | BC14: =IF(BP14=A14,'Datos Biyemas'!BL16,"") | BD14: =IF(A14="","",IF(AN14=BC14,0,IF(BC14>0,(AN14-BC14)/BC14,1))) | BE14: =IF(A14="","",VLOOKUP(B14,'Datos Biyemas'!B16:BF53,53,0)) | BF14: =IF(A14="","",VLOOKUP(B14,'Datos Biyemas'!B16:BF53,54,0)) | BG14: =IF(A14="","",VLOOKUP(B14,'Datos Biyemas'!B16:BF53,55,0)) | BH14: =IF(A14="","",VLOOKUP(B14,'Datos Biyemas'!B16:BF53,51,0)) | BI14: =IF(A14="","",VLOOKUP(B14,'Datos Biyemas'!B16:BF53,52,0)) | BJ14: =IF(A14="","",VLOOKUP(B14,'Datos Biyemas'!B16:BH53,58,0)) | BK14: =IF(A14="","",VLOOKUP(B14,'Datos Biyemas'!B16:BH53,59,0)) | BL14: =IF(A14="","",VLOOKUP(B14,'Datos Biyemas'!B16:BF53,55,0)) | BM14: =IF(A14="","",VLOOKUP(B14,'Datos Biyemas'!B16:BF53,56,0)) | BN14: =IF(A14="","",VLOOKUP(B14,'Datos Biyemas'!B16:BF53,57,0)) | BP14: Sab/Sat
A15: =IF(BP15='Datos Biyemas'!A17,'Datos Biyemas'!A17,"") | B15: =IF(BP15=A15,'Datos Biyemas'!B17,"") | C15: =IF(BP15=A15,'Datos Biyemas'!C17,"") | D15: =IF(BP15=A15,VLOOKUP(B15,'Datos Biyemas'!B17:BB54,3,0),"") | E15: =IF(BP15=A15,VLOOKUP(B15,'Datos Biyemas'!B17:BB54,4,0),"") | F15: =IF(BP15=A15,VLOOKUP(B15,'Datos Biyemas'!B17:BB54,5,0),"") | G15: =IF(BP15=A15,VLOOKUP(B15,'Datos Biyemas'!B17:BB54,6,0),"") | H15: =IF(BP15=A15,IF(E15>0,+G15/E15,0),"") | I15: =IF(A15="","",IF(F15>0,+G15/F15,0)) | J15: =IF(A15="","",IF(G15>0,+G15/C15,0)) | K15: =IF(A15="","",IF(G15>0,+G15/D15,0)) | L15: =IF(A15="","",VLOOKUP(B15,'Datos Biyemas'!B17:BB54,11,0)) | M15: =IF(A15="","",VLOOKUP(B15,'Datos Biyemas'!B17:BB54,12,0)) | N15: =IF(A15="","",VLOOKUP(B15,'Datos Biyemas'!B17:BB54,13,0)) | O15: =IF(A15="","",VLOOKUP(B15,'Datos Biyemas'!B17:BB54,14,0)) | P15: =IF(A15="","",IF(M15>0,+O15/M15,0)) | Q15: =IF(A15="","",IF(N15>0,+O15/N15,0)) | R15: =IF(A15="","",IF(C15>0,+O15/C15,0)) | S15: =IF(A15="","",IF(C15>0,+O15/L15,0)) | T15: =IF(A15="","",IF(G15>0,(G15+O15)/(D15+L15),0)) | U15: =IF(A15="","",IF(D15>0,+L15+D15,0)) | V15: =IF(A15="","",VLOOKUP(B15,'Datos Biyemas'!B17:BB54,21,0)) | W15: =IF(A15="","",VLOOKUP(B15,'Datos Biyemas'!B17:BB54,22,0)) | X15: =IF(A15="","",VLOOKUP(B15,'Datos Biyemas'!B17:BB54,23,0)) | Y15: =IF(A15="","",VLOOKUP(B15,'Datos Biyemas'!B17:BB54,24,0)) | Z15: =IF(A15="","",IF(W15>0,+Y15/W15,0)) | AA15: =IF(A15="","",IF(X15>0,+Y15/X15,0)) | AB15: =IF(A15="","",IF(Y15>0,+Y15/K15,0)) | AC15: =IF(A15="","",IF(Y15>0,+Y15/V15,0)) | AD15: =IF(A15="","",+G15+O15+Y15) | AE15: =IF(A15="","",VLOOKUP(B15,'Datos Biyemas'!B17:BB54,30,0)) | AF15: =IF(A15="","",+AD15-AE15) | AG15: =IF(A15="","",VLOOKUP(B15,'Datos Biyemas'!B17:BB54,32,0)) | AH15: =IF(A15="","",VLOOKUP(B15,'Datos Biyemas'!B17:BB54,33,0)) | AI15: =IF(A15="","",VLOOKUP(B15,'Datos Biyemas'!B17:BB54,34,0)) | AJ15: =IF(A15="","",IF(AI15>0,+AI15/C15,0)) | AK15: =IF(A15="","",+G15+O15+AI15+Y15) | AL15: =IF(A15="","",VLOOKUP(B15,'Datos Biyemas'!B17:BB54,37,0)) | AM15: =IF(A15="","",IF(AL15>0,+AL15/C15,0)) | AN15: =IF(BP15=A15,'Datos Biyemas'!BL17,"") | AO15: =IF(A15="","",VLOOKUP(B15,'Datos Biyemas'!B17:BF54,39,0)) | AP15: =IF(A15="","",IF(AN15>0,+AO15/AN15,0)) | AQ15: =IF(A15="","",VLOOKUP(B15,'Datos Biyemas'!B17:BH54,41,0)) | AR15: =IF(A15="","",VLOOKUP(B15,'Datos Biyemas'!B17:BI54,42,0)) | AS15: =IF(A15="","",VLOOKUP(B15,'Datos Biyemas'!B17:BJ54,43,0)) | AT15: =IF(A15="","",VLOOKUP(B15,'Datos Biyemas'!B17:BK54,44,0)) | AU15: =IF(A15="","",VLOOKUP(C15,'Datos Biyemas'!C17:BL54,44,0)) | AV15: =IF(A15="","",+AD15+AI15+AL15+AO15) | AW15: =IF(A15="","",IF(AV15>0,+AV15/C15,0)) | AY15: =IF(A15="","",+'Datos Biyemas'!AY17) | AZ15: =IF(A15="","",IF($AZ$6>0,+AY15-$AZ$6,)) | BA15: =IF(A15="","",VLOOKUP(B15,'Datos Biyemas'!B17:BF54,51,0)) | BB15: =IF(A15="","",IF(BA15>0,(C15-BA15)/BA15,100%)) | BC15: =IF(BP15=A15,'Datos Biyemas'!BL17,"") | BD15: =IF(A15="","",IF(AN15=BC15,0,IF(BC15>0,(AN15-BC15)/BC15,1))) | BE15: =IF(A15="","",VLOOKUP(B15,'Datos Biyemas'!B17:BF54,53,0)) | BF15: =IF(A15="","",VLOOKUP(B15,'Datos Biyemas'!B17:BF54,54,0)) | BG15: =IF(A15="","",VLOOKUP(B15,'Datos Biyemas'!B17:BF54,55,0)) | BH15: =IF(A15="","",VLOOKUP(B15,'Datos Biyemas'!B17:BF54,51,0)) | BI15: =IF(A15="","",VLOOKUP(B15,'Datos Biyemas'!B17:BF54,52,0)) | BJ15: =IF(A15="","",VLOOKUP(B15,'Datos Biyemas'!B17:BH54,58,0)) | BK15: =IF(A15="","",VLOOKUP(B15,'Datos Biyemas'!B17:BH54,59,0)) | BL15: =IF(A15="","",VLOOKUP(B15,'Datos Biyemas'!B17:BF54,55,0)) | BM15: =IF(A15="","",VLOOKUP(B15,'Datos Biyemas'!B17:BF54,56,0)) | BN15: =IF(A15="","",VLOOKUP(B15,'Datos Biyemas'!B17:BF54,57,0)) | BP15: Dom/Sun
A16: =IF(BP16='Datos Biyemas'!A18,'Datos Biyemas'!A18,"") | B16: =IF(BP16=A16,'Datos Biyemas'!B18,"") | C16: =IF(BP16=A16,'Datos Biyemas'!C18,"") | D16: =IF(BP16=A16,VLOOKUP(B16,'Datos Biyemas'!B18:BB55,3,0),"") | E16: =IF(BP16=A16,VLOOKUP(B16,'Datos Biyemas'!B18:BB55,4,0),"") | F16: =IF(BP16=A16,VLOOKUP(B16,'Datos Biyemas'!B18:BB55,5,0),"") | G16: =IF(BP16=A16,VLOOKUP(B16,'Datos Biyemas'!B18:BB55,6,0),"") | H16: =IF(BP16=A16,IF(E16>0,+G16/E16,0),"") | I16: =IF(A16="","",IF(F16>0,+G16/F16,0)) | J16: =IF(A16="","",IF(G16>0,+G16/C16,0)) | K16: =IF(A16="","",IF(G16>0,+G16/D16,0)) | L16: =IF(A16="","",VLOOKUP(B16,'Datos Biyemas'!B18:BB55,11,0)) | M16: =IF(A16="","",VLOOKUP(B16,'Datos Biyemas'!B18:BB55,12,0)) | N16: =IF(A16="","",VLOOKUP(B16,'Datos Biyemas'!B18:BB55,13,0)) | O16: =IF(A16="","",VLOOKUP(B16,'Datos Biyemas'!B18:BB55,14,0)) | P16: =IF(A16="","",IF(M16>0,+O16/M16,0)) | Q16: =IF(A16="","",IF(N16>0,+O16/N16,0)) | R16: =IF(A16="","",IF(C16>0,+O16/C16,0)) | S16: =IF(A16="","",IF(C16>0,+O16/L16,0)) | T16: =IF(A16="","",IF(G16>0,(G16+O16)/(D16+L16),0)) | U16: =IF(A16="","",IF(D16>0,+L16+D16,0)) | V16: =IF(A16="","",VLOOKUP(B16,'Datos Biyemas'!B18:BB55,21,0)) | W16: =IF(A16="","",VLOOKUP(B16,'Datos Biyemas'!B18:BB55,22,0)) | X16: =IF(A16="","",VLOOKUP(B16,'Datos Biyemas'!B18:BB55,23,0)) | Y16: =IF(A16="","",VLOOKUP(B16,'Datos Biyemas'!B18:BB55,24,0)) | Z16: =IF(A16="","",IF(W16>0,+Y16/W16,0)) | AA16: =IF(A16="","",IF(X16>0,+Y16/X16,0)) | AB16: =IF(A16="","",IF(Y16>0,+Y16/K16,0)) | AC16: =IF(A16="","",IF(Y16>0,+Y16/V16,0)) | AD16: =IF(A16="","",+G16+O16+Y16) | AE16: =IF(A16="","",VLOOKUP(B16,'Datos Biyemas'!B18:BB55,30,0)) | AF16: =IF(A16="","",+AD16-AE16) | AG16: =IF(A16="","",VLOOKUP(B16,'Datos Biyemas'!B18:BB55,32,0)) | AH16: =IF(A16="","",VLOOKUP(B16,'Datos Biyemas'!B18:BB55,33,0)) | AI16: =IF(A16="","",VLOOKUP(B16,'Datos Biyemas'!B18:BB55,34,0)) | AJ16: =IF(A16="","",IF(AI16>0,+AI16/C16,0)) | AK16: =IF(A16="","",+G16+O16+AI16+Y16) | AL16: =IF(A16="","",VLOOKUP(B16,'Datos Biyemas'!B18:BB55,37,0)) | AM16: =IF(A16="","",IF(AL16>0,+AL16/C16,0)) | AN16: =IF(BP16=A16,'Datos Biyemas'!BL18,"") | AO16: =IF(A16="","",VLOOKUP(B16,'Datos Biyemas'!B18:BF55,39,0)) | AP16: =IF(A16="","",IF(AN16>0,+AO16/AN16,0)) | AQ16: =IF(A16="","",VLOOKUP(B16,'Datos Biyemas'!B18:BH55,41,0)) | AR16: =IF(A16="","",VLOOKUP(B16,'Datos Biyemas'!B18:BI55,42,0)) | AS16: =IF(A16="","",VLOOKUP(B16,'Datos Biyemas'!B18:BJ55,43,0)) | AT16: =IF(A16="","",VLOOKUP(B16,'Datos Biyemas'!B18:BK55,44,0)) | AU16: =IF(A16="","",VLOOKUP(C16,'Datos Biyemas'!C18:BL55,44,0)) | AV16: =IF(A16="","",+AD16+AI16+AL16+AO16) | AW16: =IF(A16="","",IF(AV16>0,+AV16/C16,0)) | AY16: =IF(A16="","",+'Datos Biyemas'!AY18) | AZ16: =IF(A16="","",IF($AZ$6>0,+AY16-$AZ$6,)) | BA16: =IF(A16="","",VLOOKUP(B16,'Datos Biyemas'!B18:BF55,51,0)) | BB16: =IF(A16="","",IF(BA16>0,(C16-BA16)/BA16,100%)) | BC16: =IF(BP16=A16,'Datos Biyemas'!BL18,"") | BD16: =IF(A16="","",IF(AN16=BC16,0,IF(BC16>0,(AN16-BC16)/BC16,1))) | BE16: =IF(A16="","",VLOOKUP(B16,'Datos Biyemas'!B18:BF55,53,0)) | BF16: =IF(A16="","",VLOOKUP(B16,'Datos Biyemas'!B18:BF55,54,0)) | BG16: =IF(A16="","",VLOOKUP(B16,'Datos Biyemas'!B18:BF55,55,0)) | BH16: =IF(A16="","",VLOOKUP(B16,'Datos Biyemas'!B18:BF55,51,0)) | BI16: =IF(A16="","",VLOOKUP(B16,'Datos Biyemas'!B18:BF55,52,0)) | BJ16: =IF(A16="","",VLOOKUP(B16,'Datos Biyemas'!B18:BH55,58,0)) | BK16: =IF(A16="","",VLOOKUP(B16,'Datos Biyemas'!B18:BH55,59,0)) | BL16: =IF(A16="","",VLOOKUP(B16,'Datos Biyemas'!B18:BF55,55,0)) | BM16: =IF(A16="","",VLOOKUP(B16,'Datos Biyemas'!B18:BF55,56,0)) | BN16: =IF(A16="","",VLOOKUP(B16,'Datos Biyemas'!B18:BF55,57,0)) | BP16: Lun/Mon
A17: =IF(BP17='Datos Biyemas'!A19,'Datos Biyemas'!A19,"") | B17: =IF(BP17=A17,'Datos Biyemas'!B19,"") | C17: =IF(BP17=A17,'Datos Biyemas'!C19,"") | D17: =IF(BP17=A17,VLOOKUP(B17,'Datos Biyemas'!B19:BB56,3,0),"") | E17: =IF(BP17=A17,VLOOKUP(B17,'Datos Biyemas'!B19:BB56,4,0),"") | F17: =IF(BP17=A17,VLOOKUP(B17,'Datos Biyemas'!B19:BB56,5,0),"") | G17: =IF(BP17=A17,VLOOKUP(B17,'Datos Biyemas'!B19:BB56,6,0),"") | H17: =IF(BP17=A17,IF(E17>0,+G17/E17,0),"") | I17: =IF(A17="","",IF(F17>0,+G17/F17,0)) | J17: =IF(A17="","",IF(G17>0,+G17/C17,0)) | K17: =IF(A17="","",IF(G17>0,+G17/D17,0)) | L17: =IF(A17="","",VLOOKUP(B17,'Datos Biyemas'!B19:BB56,11,0)) | M17: =IF(A17="","",VLOOKUP(B17,'Datos Biyemas'!B19:BB56,12,0)) | N17: =IF(A17="","",VLOOKUP(B17,'Datos Biyemas'!B19:BB56,13,0)) | O17: =IF(A17="","",VLOOKUP(B17,'Datos Biyemas'!B19:BB56,14,0)) | P17: =IF(A17="","",IF(M17>0,+O17/M17,0)) | Q17: =IF(A17="","",IF(N17>0,+O17/N17,0)) | R17: =IF(A17="","",IF(C17>0,+O17/C17,0)) | S17: =IF(A17="","",IF(C17>0,+O17/L17,0)) | T17: =IF(A17="","",IF(G17>0,(G17+O17)/(D17+L17),0)) | U17: =IF(A17="","",IF(D17>0,+L17+D17,0)) | V17: =IF(A17="","",VLOOKUP(B17,'Datos Biyemas'!B19:BB56,21,0)) | W17: =IF(A17="","",VLOOKUP(B17,'Datos Biyemas'!B19:BB56,22,0)) | X17: =IF(A17="","",VLOOKUP(B17,'Datos Biyemas'!B19:BB56,23,0)) | Y17: =IF(A17="","",VLOOKUP(B17,'Datos Biyemas'!B19:BB56,24,0)) | Z17: =IF(A17="","",IF(W17>0,+Y17/W17,0)) | AA17: =IF(A17="","",IF(X17>0,+Y17/X17,0)) | AB17: =IF(A17="","",IF(Y17>0,+Y17/K17,0)) | AC17: =IF(A17="","",IF(Y17>0,+Y17/V17,0)) | AD17: =IF(A17="","",+G17+O17+Y17) | AE17: =IF(A17="","",VLOOKUP(B17,'Datos Biyemas'!B19:BB56,30,0)) | AF17: =IF(A17="","",+AD17-AE17) | AG17: =IF(A17="","",VLOOKUP(B17,'Datos Biyemas'!B19:BB56,32,0)) | AH17: =IF(A17="","",VLOOKUP(B17,'Datos Biyemas'!B19:BB56,33,0)) | AI17: =IF(A17="","",VLOOKUP(B17,'Datos Biyemas'!B19:BB56,34,0)) | AJ17: =IF(A17="","",IF(AI17>0,+AI17/C17,0)) | AK17: =IF(A17="","",+G17+O17+AI17+Y17) | AL17: =IF(A17="","",VLOOKUP(B17,'Datos Biyemas'!B19:BB56,37,0)) | AM17: =IF(A17="","",IF(AL17>0,+AL17/C17,0)) | AN17: =IF(BP17=A17,'Datos Biyemas'!BL19,"") | AO17: =IF(A17="","",VLOOKUP(B17,'Datos Biyemas'!B19:BF56,39,0)) | AP17: =IF(A17="","",IF(AN17>0,+AO17/AN17,0)) | AQ17: =IF(A17="","",VLOOKUP(B17,'Datos Biyemas'!B19:BH56,41,0)) | AR17: =IF(A17="","",VLOOKUP(B17,'Datos Biyemas'!B19:BI56,42,0)) | AS17: =IF(A17="","",VLOOKUP(B17,'Datos Biyemas'!B19:BJ56,43,0)) | AT17: =IF(A17="","",VLOOKUP(B17,'Datos Biyemas'!B19:BK56,44,0)) | AU17: =IF(A17="","",VLOOKUP(C17,'Datos Biyemas'!C19:BL56,44,0)) | AV17: =IF(A17="","",+AD17+AI17+AL17+AO17) | AW17: =IF(A17="","",IF(AV17>0,+AV17/C17,0)) | AY17: =IF(A17="","",+'Datos Biyemas'!AY19) | AZ17: =IF(A17="","",IF($AZ$6>0,+AY17-$AZ$6,)) | BA17: =IF(A17="","",VLOOKUP(B17,'Datos Biyemas'!B19:BF56,51,0)) | BB17: =IF(A17="","",IF(BA17>0,(C17-BA17)/BA17,100%)) | BC17: =IF(BP17=A17,'Datos Biyemas'!BL19,"") | BD17: =IF(A17="","",IF(AN17=BC17,0,IF(BC17>0,(AN17-BC17)/BC17,1))) | BE17: =IF(A17="","",VLOOKUP(B17,'Datos Biyemas'!B19:BF56,53,0)) | BF17: =IF(A17="","",VLOOKUP(B17,'Datos Biyemas'!B19:BF56,54,0)) | BG17: =IF(A17="","",VLOOKUP(B17,'Datos Biyemas'!B19:BF56,55,0)) | BH17: =IF(A17="","",VLOOKUP(B17,'Datos Biyemas'!B19:BF56,51,0)) | BI17: =IF(A17="","",VLOOKUP(B17,'Datos Biyemas'!B19:BF56,52,0)) | BJ17: =IF(A17="","",VLOOKUP(B17,'Datos Biyemas'!B19:BH56,58,0)) | BK17: =IF(A17="","",VLOOKUP(B17,'Datos Biyemas'!B19:BH56,59,0)) | BL17: =IF(A17="","",VLOOKUP(B17,'Datos Biyemas'!B19:BF56,55,0)) | BM17: =IF(A17="","",VLOOKUP(B17,'Datos Biyemas'!B19:BF56,56,0)) | BN17: =IF(A17="","",VLOOKUP(B17,'Datos Biyemas'!B19:BF56,57,0)) | BP17: Mar/Tue
A18: =IF(BP18='Datos Biyemas'!A20,'Datos Biyemas'!A20,"") | B18: =IF(BP18=A18,'Datos Biyemas'!B20,"") | C18: =IF(BP18=A18,'Datos Biyemas'!C20,"") | D18: =IF(BP18=A18,VLOOKUP(B18,'Datos Biyemas'!B20:BB57,3,0),"") | E18: =IF(BP18=A18,VLOOKUP(B18,'Datos Biyemas'!B20:BB57,4,0),"") | F18: =IF(BP18=A18,VLOOKUP(B18,'Datos Biyemas'!B20:BB57,5,0),"") | G18: =IF(BP18=A18,VLOOKUP(B18,'Datos Biyemas'!B20:BB57,6,0),"") | H18: =IF(BP18=A18,IF(E18>0,+G18/E18,0),"") | I18: =IF(A18="","",IF(F18>0,+G18/F18,0)) | J18: =IF(A18="","",IF(G18>0,+G18/C18,0)) | K18: =IF(A18="","",IF(G18>0,+G18/D18,0)) | L18: =IF(A18="","",VLOOKUP(B18,'Datos Biyemas'!B20:BB57,11,0)) | M18: =IF(A18="","",VLOOKUP(B18,'Datos Biyemas'!B20:BB57,12,0)) | N18: =IF(A18="","",VLOOKUP(B18,'Datos Biyemas'!B20:BB57,13,0)) | O18: =IF(A18="","",VLOOKUP(B18,'Datos Biyemas'!B20:BB57,14,0)) | P18: =IF(A18="","",IF(M18>0,+O18/M18,0)) | Q18: =IF(A18="","",IF(N18>0,+O18/N18,0)) | R18: =IF(A18="","",IF(C18>0,+O18/C18,0)) | S18: =IF(A18="","",IF(C18>0,+O18/L18,0)) | T18: =IF(A18="","",IF(G18>0,(G18+O18)/(D18+L18),0)) | U18: =IF(A18="","",IF(D18>0,+L18+D18,0)) | V18: =IF(A18="","",VLOOKUP(B18,'Datos Biyemas'!B20:BB57,21,0)) | W18: =IF(A18="","",VLOOKUP(B18,'Datos Biyemas'!B20:BB57,22,0)) | X18: =IF(A18="","",VLOOKUP(B18,'Datos Biyemas'!B20:BB57,23,0)) | Y18: =IF(A18="","",VLOOKUP(B18,'Datos Biyemas'!B20:BB57,24,0)) | Z18: =IF(A18="","",IF(W18>0,+Y18/W18,0)) | AA18: =IF(A18="","",IF(X18>0,+Y18/X18,0)) | AB18: =IF(A18="","",IF(Y18>0,+Y18/K18,0)) | AC18: =IF(A18="","",IF(Y18>0,+Y18/V18,0)) | AD18: =IF(A18="","",+G18+O18+Y18) | AE18: =IF(A18="","",VLOOKUP(B18,'Datos Biyemas'!B20:BB57,30,0)) | AF18: =IF(A18="","",+AD18-AE18) | AG18: =IF(A18="","",VLOOKUP(B18,'Datos Biyemas'!B20:BB57,32,0)) | AH18: =IF(A18="","",VLOOKUP(B18,'Datos Biyemas'!B20:BB57,33,0)) | AI18: =IF(A18="","",VLOOKUP(B18,'Datos Biyemas'!B20:BB57,34,0)) | AJ18: =IF(A18="","",IF(AI18>0,+AI18/C18,0)) | AK18: =IF(A18="","",+G18+O18+AI18+Y18) | AL18: =IF(A18="","",VLOOKUP(B18,'Datos Biyemas'!B20:BB57,37,0)) | AM18: =IF(A18="","",IF(AL18>0,+AL18/C18,0)) | AN18: =IF(BP18=A18,'Datos Biyemas'!BL20,"") | AO18: =IF(A18="","",VLOOKUP(B18,'Datos Biyemas'!B20:BF57,39,0)) | AP18: =IF(A18="","",IF(AN18>0,+AO18/AN18,0)) | AQ18: =IF(A18="","",VLOOKUP(B18,'Datos Biyemas'!B20:BH57,41,0)) | AR18: =IF(A18="","",VLOOKUP(B18,'Datos Biyemas'!B20:BI57,42,0)) | AS18: =IF(A18="","",VLOOKUP(B18,'Datos Biyemas'!B20:BJ57,43,0)) | AT18: =IF(A18="","",VLOOKUP(B18,'Datos Biyemas'!B20:BK57,44,0)) | AU18: =IF(A18="","",VLOOKUP(C18,'Datos Biyemas'!C20:BL57,44,0)) | AV18: =IF(A18="","",+AD18+AI18+AL18+AO18) | AW18: =IF(A18="","",IF(AV18>0,+AV18/C18,0)) | AY18: =IF(A18="","",+'Datos Biyemas'!AY20) | AZ18: =IF(A18="","",IF($AZ$6>0,+AY18-$AZ$6,)) | BA18: =IF(A18="","",VLOOKUP(B18,'Datos Biyemas'!B20:BF57,51,0)) | BB18: =IF(A18="","",IF(BA18>0,(C18-BA18)/BA18,100%)) | BC18: =IF(BP18=A18,'Datos Biyemas'!BL20,"") | BD18: =IF(A18="","",IF(AN18=BC18,0,IF(BC18>0,(AN18-BC18)/BC18,1))) | BE18: =IF(A18="","",VLOOKUP(B18,'Datos Biyemas'!B20:BF57,53,0)) | BF18: =IF(A18="","",VLOOKUP(B18,'Datos Biyemas'!B20:BF57,54,0)) | BG18: =IF(A18="","",VLOOKUP(B18,'Datos Biyemas'!B20:BF57,55,0)) | BH18: =IF(A18="","",VLOOKUP(B18,'Datos Biyemas'!B20:BF57,51,0)) | BI18: =IF(A18="","",VLOOKUP(B18,'Datos Biyemas'!B20:BF57,52,0)) | BJ18: =IF(A18="","",VLOOKUP(B18,'Datos Biyemas'!B20:BH57,58,0)) | BK18: =IF(A18="","",VLOOKUP(B18,'Datos Biyemas'!B20:BH57,59,0)) | BL18: =IF(A18="","",VLOOKUP(B18,'Datos Biyemas'!B20:BF57,55,0)) | BM18: =IF(A18="","",VLOOKUP(B18,'Datos Biyemas'!B20:BF57,56,0)) | BN18: =IF(A18="","",VLOOKUP(B18,'Datos Biyemas'!B20:BF57,57,0)) | BP18: Mie/Wed
... A30: =IF(BP30='Datos Biyemas'!A32,'Datos Biyemas'!A32,"") | B30: =IF(BP30=A30,'Datos Biyemas'!B32,"") | C30: =IF(BP30=A30,'Datos Biyemas'!C32,"") | D30: =IF(BP30=A30,VLOOKUP(B30,'Datos Biyemas'!B32:BB69,3,0),"") | E30: =IF(BP30=A30,VLOOKUP(B30,'Datos Biyemas'!B32:BB69,4,0),"") | F30: =IF(BP30=A30,VLOOKUP(B30,'Datos Biyemas'!B32:BB69,5,0),"") | G30: =IF(BP30=A30,VLOOKUP(B30,'Datos Biyemas'!B32:BB69,6,0),"") | H30: =IF(BP30=A30,IF(E30>0,+G30/E30,0),"") | I30: =IF(A30="","",IF(F30>0,+G30/F30,0)) | J30: =IF(A30="","",IF(G30>0,+G30/C30,0)) | K30: =IF(A30="","",IF(G30>0,+G30/D30,0)) | L30: =IF(A30="","",VLOOKUP(B30,'Datos Biyemas'!B32:BB69,11,0)) | M30: =IF(A30="","",VLOOKUP(B30,'Datos Biyemas'!B32:BB69,12,0)) | N30: =IF(A30="","",VLOOKUP(B30,'Datos Biyemas'!B32:BB69,13,0)) | O30: =IF(A30="","",VLOOKUP(B30,'Datos Biyemas'!B32:BB69,14,0)) | P30: =IF(A30="","",IF(M30>0,+O30/M30,0)) | Q30: =IF(A30="","",IF(N30>0,+O30/N30,0)) | R30: =IF(A30="","",IF(C30>0,+O30/C30,0)) | S30: =IF(A30="","",IF(C30>0,+O30/L30,0)) | T30: =IF(A30="","",IF(G30>0,(G30+O30)/(D30+L30),0)) | U30: =IF(A30="","",IF(D30>0,+L30+D30,0)) | V30: =IF(A30="","",VLOOKUP(B30,'Datos Biyemas'!B32:BB69,21,0)) | W30: =IF(A30="","",VLOOKUP(B30,'Datos Biyemas'!B32:BB69,22,0)) | X30: =IF(A30="","",VLOOKUP(B30,'Datos Biyemas'!B32:BB69,23,0)) | Y30: =IF(A30="","",VLOOKUP(B30,'Datos Biyemas'!B32:BB69,24,0)) | Z30: =IF(A30="","",IF(W30>0,+Y30/W30,0)) | AA30: =IF(A30="","",IF(X30>0,+Y30/X30,0)) | AB30: =IF(A30="","",IF(Y30>0,+Y30/K30,0)) | AC30: =IF(A30="","",IF(Y30>0,+Y30/V30,0)) | AD30: =IF(A30="","",+G30+O30+Y30) | AE30: =IF(A30="","",VLOOKUP(B30,'Datos Biyemas'!B32:BB69,30,0)) | AF30: =IF(A30="","",+AD30-AE30) | AG30: =IF(A30="","",VLOOKUP(B30,'Datos Biyemas'!B32:BB69,32,0)) | AH30: =IF(A30="","",VLOOKUP(B30,'Datos Biyemas'!B32:BB69,33,0)) | AI30: =IF(A30="","",VLOOKUP(B30,'Datos Biyemas'!B32:BB69,34,0)) | AJ30: =IF(A30="","",IF(AI30>0,+AI30/C30,0)) | AK30: =IF(A30="","",+G30+O30+AI30+Y30) | AL30: =IF(A30="","",VLOOKUP(B30,'Datos Biyemas'!B32:BB69,37,0)) | AM30: =IF(A30="","",IF(AL30>0,+AL30/C30,0)) | AN30: =IF(BP30=A30,'Datos Biyemas'!BL32,"") | AO30: =IF(A30="","",VLOOKUP(B30,'Datos Biyemas'!B32:BF69,39,0)) | AP30: =IF(A30="","",IF(AN30>0,+AO30/AN30,0)) | AQ30: =IF(A30="","",VLOOKUP(B30,'Datos Biyemas'!B32:BH69,41,0)) | AR30: =IF(A30="","",VLOOKUP(B30,'Datos Biyemas'!B32:BI69,42,0)) | AS30: =IF(A30="","",VLOOKUP(B30,'Datos Biyemas'!B32:BJ69,43,0)) | AT30: =IF(A30="","",VLOOKUP(B30,'Datos Biyemas'!B32:BK69,44,0)) | AU30: =IF(A30="","",VLOOKUP(C30,'Datos Biyemas'!C32:BL69,44,0)) | AV30: =IF(A30="","",+AD30+AI30+AL30+AO30) | AW30: =IF(A30="","",IF(AV30>0,+AV30/C30,0)) | AY30: =IF(A30="","",+'Datos Biyemas'!AY32) | AZ30: =IF(A30="","",IF($AZ$6>0,+AY30-$AZ$6,)) | BA30: =IF(A30="","",VLOOKUP(B30,'Datos Biyemas'!B32:BF69,51,0)) | BB30: =IF(A30="","",IF(BA30>0,(C30-BA30)/BA30,100%)) | BC30: =IF(BP30=A30,'Datos Biyemas'!BL32,"") | BD30: =IF(A30="","",IF(AN30=BC30,0,IF(BC30>0,(AN30-BC30)/BC30,1))) | BE30: =IF(A30="","",VLOOKUP(B30,'Datos Biyemas'!B32:BF69,53,0)) | BF30: =IF(A30="","",VLOOKUP(B30,'Datos Biyemas'!B32:BF69,54,0)) | BG30: =IF(A30="","",VLOOKUP(B30,'Datos Biyemas'!B32:BF69,55,0)) | BH30: =IF(A30="","",VLOOKUP(B30,'Datos Biyemas'!B32:BF69,51,0)) | BI30: =IF(A30="","",VLOOKUP(B30,'Datos Biyemas'!B32:BF69,52,0)) | BJ30: =IF(A30="","",VLOOKUP(B30,'Datos Biyemas'!B32:BH69,58,0)) | BK30: =IF(A30="","",VLOOKUP(B30,'Datos Biyemas'!B32:BH69,59,0)) | BL30: =IF(A30="","",VLOOKUP(B30,'Datos Biyemas'!B32:BF69,55,0)) | BM30: =IF(A30="","",VLOOKUP(B30,'Datos Biyemas'!B32:BF69,56,0)) | BN30: =IF(A30="","",VLOOKUP(B30,'Datos Biyemas'!B32:BF69,57,0)) | BP30: Lun/Mon
A31: =IF(BP31='Datos Biyemas'!A33,'Datos Biyemas'!A33,"") | B31: =IF(BP31=A31,'Datos Biyemas'!B33,"") | C31: =IF(BP31=A31,'Datos Biyemas'!C33,"") | D31: =IF(BP31=A31,VLOOKUP(B31,'Datos Biyemas'!B33:BB70,3,0),"") | E31: =IF(BP31=A31,VLOOKUP(B31,'Datos Biyemas'!B33:BB70,4,0),"") | F31: =IF(BP31=A31,VLOOKUP(B31,'Datos Biyemas'!B33:BB70,5,0),"") | G31: =IF(BP31=A31,VLOOKUP(B31,'Datos Biyemas'!B33:BB70,6,0),"") | H31: =IF(BP31=A31,IF(E31>0,+G31/E31,0),"") | I31: =IF(A31="","",IF(F31>0,+G31/F31,0)) | J31: =IF(A31="","",IF(G31>0,+G31/C31,0)) | K31: =IF(A31="","",IF(G31>0,+G31/D31,0)) | L31: =IF(A31="","",VLOOKUP(B31,'Datos Biyemas'!B33:BB70,11,0)) | M31: =IF(A31="","",VLOOKUP(B31,'Datos Biyemas'!B33:BB70,12,0)) | N31: =IF(A31="","",VLOOKUP(B31,'Datos Biyemas'!B33:BB70,13,0)) | O31: =IF(A31="","",VLOOKUP(B31,'Datos Biyemas'!B33:BB70,14,0)) | P31: =IF(A31="","",IF(M31>0,+O31/M31,0)) | Q31: =IF(A31="","",IF(N31>0,+O31/N31,0)) | R31: =IF(A31="","",IF(C31>0,+O31/C31,0)) | S31: =IF(A31="","",IF(C31>0,+O31/L31,0)) | T31: =IF(A31="","",IF(G31>0,(G31+O31)/(D31+L31),0)) | U31: =IF(A31="","",IF(D31>0,+L31+D31,0)) | V31: =IF(A31="","",VLOOKUP(B31,'Datos Biyemas'!B33:BB70,21,0)) | W31: =IF(A31="","",VLOOKUP(B31,'Datos Biyemas'!B33:BB70,22,0)) | X31: =IF(A31="","",VLOOKUP(B31,'Datos Biyemas'!B33:BB70,23,0)) | Y31: =IF(A31="","",VLOOKUP(B31,'Datos Biyemas'!B33:BB70,24,0)) | Z31: =IF(A31="","",IF(W31>0,+Y31/W31,0)) | AA31: =IF(A31="","",IF(X31>0,+Y31/X31,0)) | AB31: =IF(A31="","",IF(Y31>0,+Y31/K31,0)) | AC31: =IF(A31="","",IF(Y31>0,+Y31/V31,0)) | AD31: =IF(A31="","",+G31+O31+Y31) | AE31: =IF(A31="","",VLOOKUP(B31,'Datos Biyemas'!B33:BB70,30,0)) | AF31: =IF(A31="","",+AD31-AE31) | AG31: =IF(A31="","",VLOOKUP(B31,'Datos Biyemas'!B33:BB70,32,0)) | AH31: =IF(A31="","",VLOOKUP(B31,'Datos Biyemas'!B33:BB70,33,0)) | AI31: =IF(A31="","",VLOOKUP(B31,'Datos Biyemas'!B33:BB70,34,0)) | AJ31: =IF(A31="","",IF(AI31>0,+AI31/C31,0)) | AK31: =IF(A31="","",+G31+O31+AI31+Y31) | AL31: =IF(A31="","",VLOOKUP(B31,'Datos Biyemas'!B33:BB70,37,0)) | AM31: =IF(A31="","",IF(AL31>0,+AL31/C31,0)) | AN31: =IF(BP31=A31,'Datos Biyemas'!BL33,"") | AO31: =IF(A31="","",VLOOKUP(B31,'Datos Biyemas'!B33:BF70,39,0)) | AP31: =IF(A31="","",IF(AN31>0,+AO31/AN31,0)) | AQ31: =IF(A31="","",VLOOKUP(B31,'Datos Biyemas'!B33:BH70,41,0)) | AR31: =IF(A31="","",VLOOKUP(B31,'Datos Biyemas'!B33:BI70,42,0)) | AS31: =IF(A31="","",VLOOKUP(B31,'Datos Biyemas'!B33:BJ70,43,0)) | AT31: =IF(A31="","",VLOOKUP(B31,'Datos Biyemas'!B33:BK70,44,0)) | AU31: =IF(A31="","",VLOOKUP(C31,'Datos Biyemas'!C33:BL70,44,0)) | AV31: =IF(A31="","",+AD31+AI31+AL31+AO31) | AW31: =IF(A31="","",IF(AV31>0,+AV31/C31,0)) | AY31: =IF(A31="","",+'Datos Biyemas'!AY33) | AZ31: =IF(A31="","",IF($AZ$6>0,+AY31-$AZ$6,)) | BA31: =IF(A31="","",VLOOKUP(B31,'Datos Biyemas'!B33:BF70,51,0)) | BB31: =IF(A31="","",IF(BA31>0,(C31-BA31)/BA31,100%)) | BC31: =IF(BP31=A31,'Datos Biyemas'!BL33,"") | BD31: =IF(A31="","",IF(BC31>0,(AN31-BC31)/BC31,1)) | BE31: =IF(A31="","",VLOOKUP(B31,'Datos Biyemas'!B33:BF70,53,0)) | BF31: =IF(A31="","",VLOOKUP(B31,'Datos Biyemas'!B33:BF70,54,0)) | BG31: =IF(A31="","",VLOOKUP(B31,'Datos Biyemas'!B33:BF70,55,0)) | BH31: =IF(A31="","",VLOOKUP(B31,'Datos Biyemas'!B33:BF70,51,0)) | BI31: =IF(A31="","",VLOOKUP(B31,'Datos Biyemas'!B33:BF70,52,0)) | BJ31: =IF(A31="","",VLOOKUP(B31,'Datos Biyemas'!B33:BH70,58,0)) | BK31: =IF(A31="","",VLOOKUP(B31,'Datos Biyemas'!B33:BH70,59,0)) | BL31: =IF(A31="","",VLOOKUP(B31,'Datos Biyemas'!B33:BF70,55,0)) | BM31: =IF(A31="","",VLOOKUP(B31,'Datos Biyemas'!B33:BF70,56,0)) | BN31: =IF(A31="","",VLOOKUP(B31,'Datos Biyemas'!B33:BF70,57,0)) | BP31: Mar/Tue
A32: =IF(BP32='Datos Biyemas'!A34,'Datos Biyemas'!A34,"") | B32: =IF(BP32=A32,'Datos Biyemas'!B34,"") | C32: =IF(BP32=A32,'Datos Biyemas'!C34,"") | D32: =IF(BP32=A32,VLOOKUP(B32,'Datos Biyemas'!B34:BB71,3,0),"") | E32: =IF(BP32=A32,VLOOKUP(B32,'Datos Biyemas'!B34:BB71,4,0),"") | F32: =IF(BP32=A32,VLOOKUP(B32,'Datos Biyemas'!B34:BB71,5,0),"") | G32: =IF(BP32=A32,VLOOKUP(B32,'Datos Biyemas'!B34:BB71,6,0),"") | H32: =IF(BP32=A32,IF(E32>0,+G32/E32,0),"") | I32: =IF(A32="","",IF(F32>0,+G32/F32,0)) | J32: =IF(A32="","",IF(G32>0,+G32/C32,0)) | K32: =IF(A32="","",IF(G32>0,+G32/D32,0)) | L32: =IF(A32="","",VLOOKUP(B32,'Datos Biyemas'!B34:BB71,11,0)) | M32: =IF(A32="","",VLOOKUP(B32,'Datos Biyemas'!B34:BB71,12,0)) | N32: =IF(A32="","",VLOOKUP(B32,'Datos Biyemas'!B34:BB71,13,0)) | O32: =IF(A32="","",VLOOKUP(B32,'Datos Biyemas'!B34:BB71,14,0)) | P32: =IF(A32="","",IF(M32>0,+O32/M32,0)) | Q32: =IF(A32="","",IF(N32>0,+O32/N32,0)) | R32: =IF(A32="","",IF(C32>0,+O32/C32,0)) | S32: =IF(A32="","",IF(C32>0,+O32/L32,0)) | T32: =IF(A32="","",IF(G32>0,(G32+O32)/(D32+L32),0)) | U32: =IF(A32="","",IF(D32>0,+L32+D32,0)) | V32: =IF(A32="","",VLOOKUP(B32,'Datos Biyemas'!B34:BB71,21,0)) | W32: =IF(A32="","",VLOOKUP(B32,'Datos Biyemas'!B34:BB71,22,0)) | X32: =IF(A32="","",VLOOKUP(B32,'Datos Biyemas'!B34:BB71,23,0)) | Y32: =IF(A32="","",VLOOKUP(B32,'Datos Biyemas'!B34:BB71,24,0)) | Z32: =IF(A32="","",IF(W32>0,+Y32/W32,0)) | AA32: =IF(A32="","",IF(X32>0,+Y32/X32,0)) | AB32: =IF(A32="","",IF(Y32>0,+Y32/K32,0)) | AC32: =IF(A32="","",IF(Y32>0,+Y32/V32,0)) | AD32: =IF(A32="","",+G32+O32+Y32) | AE32: =IF(A32="","",VLOOKUP(B32,'Datos Biyemas'!B34:BB71,30,0)) | AF32: =IF(A32="","",+AD32-AE32) | AG32: =IF(A32="","",VLOOKUP(B32,'Datos Biyemas'!B34:BB71,32,0)) | AH32: =IF(A32="","",VLOOKUP(B32,'Datos Biyemas'!B34:BB71,33,0)) | AI32: =IF(A32="","",VLOOKUP(B32,'Datos Biyemas'!B34:BB71,34,0)) | AJ32: =IF(A32="","",IF(AI32>0,+AI32/C32,0)) | AK32: =IF(A32="","",+G32+O32+AI32+Y32) | AL32: =IF(A32="","",VLOOKUP(B32,'Datos Biyemas'!B34:BB71,37,0)) | AM32: =IF(A32="","",IF(AL32>0,+AL32/C32,0)) | AN32: =IF(BP32=A32,'Datos Biyemas'!BL34,"") | AO32: =IF(A32="","",VLOOKUP(B32,'Datos Biyemas'!B34:BF71,39,0)) | AP32: =IF(A32="","",IF(AN32>0,+AO32/AN32,0)) | AQ32: =IF(A32="","",VLOOKUP(B32,'Datos Biyemas'!B34:BH71,41,0)) | AR32: =IF(A32="","",VLOOKUP(B32,'Datos Biyemas'!B34:BI71,42,0)) | AS32: =IF(A32="","",VLOOKUP(B32,'Datos Biyemas'!B34:BJ71,43,0)) | AT32: =IF(A32="","",VLOOKUP(B32,'Datos Biyemas'!B34:BK71,44,0)) | AU32: =IF(A32="","",VLOOKUP(C32,'Datos Biyemas'!C34:BL71,44,0)) | AV32: =IF(A32="","",+AD32+AI32+AL32+AO32) | AW32: =IF(A32="","",IF(AV32>0,+AV32/C32,0)) | AY32: =IF(A32="","",+'Datos Biyemas'!AY34) | AZ32: =IF(A32="","",IF($AZ$6>0,+AY32-$AZ$6,)) | BA32: =IF(A32="","",VLOOKUP(B32,'Datos Biyemas'!B34:BF71,51,0)) | BB32: =IF(A32="","",IF(BA32>0,(C32-BA32)/BA32,100%)) | BC32: =IF(BP32=A32,'Datos Biyemas'!BL34,"") | BD32: =IF(A32="","",IF(BC32>0,(AN32-BC32)/BC32,1)) | BE32: =IF(A32="","",VLOOKUP(B32,'Datos Biyemas'!B34:BF71,53,0)) | BF32: =IF(A32="","",VLOOKUP(B32,'Datos Biyemas'!B34:BF71,54,0)) | BG32: =IF(A32="","",VLOOKUP(B32,'Datos Biyemas'!B34:BF71,55,0)) | BH32: =IF(A32="","",VLOOKUP(B32,'Datos Biyemas'!B34:BF71,51,0)) | BI32: =IF(A32="","",VLOOKUP(B32,'Datos Biyemas'!B34:BF71,52,0)) | BJ32: =IF(A32="","",VLOOKUP(B32,'Datos Biyemas'!B34:BH71,58,0)) | BK32: =IF(A32="","",VLOOKUP(B32,'Datos Biyemas'!B34:BH71,59,0)) | BL32: =IF(A32="","",VLOOKUP(B32,'Datos Biyemas'!B34:BF71,55,0)) | BM32: =IF(A32="","",VLOOKUP(B32,'Datos Biyemas'!B34:BF71,56,0)) | BN32: =IF(A32="","",VLOOKUP(B32,'Datos Biyemas'!B34:BF71,57,0)) | BP32: Mie/Wed
A33: =IF(BP33='Datos Biyemas'!A35,'Datos Biyemas'!A35,"") | B33: =IF(BP33=A33,'Datos Biyemas'!B35,"") | C33: =IF(BP33=A33,'Datos Biyemas'!C35,"") | D33: =IF(BP33=A33,VLOOKUP(B33,'Datos Biyemas'!B35:BB72,3,0),"") | E33: =IF(BP33=A33,VLOOKUP(B33,'Datos Biyemas'!B35:BB72,4,0),"") | F33: =IF(BP33=A33,VLOOKUP(B33,'Datos Biyemas'!B35:BB72,5,0),"") | G33: =IF(BP33=A33,VLOOKUP(B33,'Datos Biyemas'!B35:BB72,6,0),"") | H33: =IF(BP33=A33,IF(E33>0,+G33/E33,0),"") | I33: =IF(A33="","",IF(F33>0,+G33/F33,0)) | J33: =IF(A33="","",IF(G33>0,+G33/C33,0)) | K33: =IF(A33="","",IF(G33>0,+G33/D33,0)) | L33: =IF(A33="","",VLOOKUP(B33,'Datos Biyemas'!B35:BB72,11,0)) | M33: =IF(A33="","",VLOOKUP(B33,'Datos Biyemas'!B35:BB72,12,0)) | N33: =IF(A33="","",VLOOKUP(B33,'Datos Biyemas'!B35:BB72,13,0)) | O33: =IF(A33="","",VLOOKUP(B33,'Datos Biyemas'!B35:BB72,14,0)) | P33: =IF(A33="","",IF(M33>0,+O33/M33,0)) | Q33: =IF(A33="","",IF(N33>0,+O33/N33,0)) | R33: =IF(A33="","",IF(C33>0,+O33/C33,0)) | S33: =IF(A33="","",IF(C33>0,+O33/L33,0)) | T33: =IF(A33="","",IF(G33>0,(G33+O33)/(D33+L33),0)) | U33: =IF(A33="","",IF(D33>0,+L33+D33,0)) | V33: =IF(A33="","",VLOOKUP(B33,'Datos Biyemas'!B35:BB72,21,0)) | W33: =IF(A33="","",VLOOKUP(B33,'Datos Biyemas'!B35:BB72,22,0)) | X33: =IF(A33="","",VLOOKUP(B33,'Datos Biyemas'!B35:BB72,23,0)) | Y33: =IF(A33="","",VLOOKUP(B33,'Datos Biyemas'!B35:BB72,24,0)) | Z33: =IF(A33="","",IF(W33>0,+Y33/W33,0)) | AA33: =IF(A33="","",IF(X33>0,+Y33/X33,0)) | AB33: =IF(A33="","",IF(Y33>0,+Y33/K33,0)) | AC33: =IF(A33="","",IF(Y33>0,+Y33/V33,0)) | AD33: =IF(A33="","",+G33+O33+Y33) | AE33: =IF(A33="","",VLOOKUP(B33,'Datos Biyemas'!B35:BB72,30,0)) | AF33: =IF(A33="","",+AD33-AE33) | AG33: =IF(A33="","",VLOOKUP(B33,'Datos Biyemas'!B35:BB72,32,0)) | AH33: =IF(A33="","",VLOOKUP(B33,'Datos Biyemas'!B35:BB72,33,0)) | AI33: =IF(A33="","",VLOOKUP(B33,'Datos Biyemas'!B35:BB72,34,0)) | AJ33: =IF(A33="","",IF(AI33>0,+AI33/C33,0)) | AK33: =IF(A33="","",+G33+O33+AI33+Y33) | AL33: =IF(A33="","",VLOOKUP(B33,'Datos Biyemas'!B35:BB72,37,0)) | AM33: =IF(A33="","",IF(AL33>0,+AL33/C33,0)) | AN33: =IF(BP33=A33,'Datos Biyemas'!BL35,"") | AO33: =IF(A33="","",VLOOKUP(B33,'Datos Biyemas'!B35:BF72,39,0)) | AP33: =IF(A33="","",IF(AN33>0,+AO33/AN33,0)) | AQ33: =IF(A33="","",VLOOKUP(B33,'Datos Biyemas'!B35:BH72,41,0)) | AR33: =IF(A33="","",VLOOKUP(B33,'Datos Biyemas'!B35:BI72,42,0)) | AS33: =IF(A33="","",VLOOKUP(B33,'Datos Biyemas'!B35:BJ72,43,0)) | AT33: =IF(A33="","",VLOOKUP(B33,'Datos Biyemas'!B35:BK72,44,0)) | AU33: =IF(A33="","",VLOOKUP(C33,'Datos Biyemas'!C35:BL72,44,0)) | AV33: =IF(A33="","",+AD33+AI33+AL33+AO33) | AW33: =IF(A33="","",IF(AV33>0,+AV33/C33,0)) | AY33: =IF(A33="","",+'Datos Biyemas'!AY35) | AZ33: =IF(A33="","",IF($AZ$6>0,+AY33-$AZ$6,)) | BA33: =IF(A33="","",VLOOKUP(B33,'Datos Biyemas'!B35:BF72,51,0)) | BB33: =IF(A33="","",IF(BA33>0,(C33-BA33)/BA33,100%)) | BC33: =IF(BP33=A33,'Datos Biyemas'!BL35,"") | BD33: =IF(A33="","",IF(BC33>0,(AN33-BC33)/BC33,1)) | BE33: =IF(A33="","",VLOOKUP(B33,'Datos Biyemas'!B35:BF72,53,0)) | BF33: =IF(A33="","",VLOOKUP(B33,'Datos Biyemas'!B35:BF72,54,0)) | BG33: =IF(A33="","",VLOOKUP(B33,'Datos Biyemas'!B35:BF72,55,0)) | BH33: =IF(A33="","",VLOOKUP(B33,'Datos Biyemas'!B35:BF72,51,0)) | BI33: =IF(A33="","",VLOOKUP(B33,'Datos Biyemas'!B35:BF72,52,0)) | BJ33: =IF(A33="","",VLOOKUP(B33,'Datos Biyemas'!B35:BH72,58,0)) | BK33: =IF(A33="","",VLOOKUP(B33,'Datos Biyemas'!B35:BH72,59,0)) | BL33: =IF(A33="","",VLOOKUP(B33,'Datos Biyemas'!B35:BF72,55,0)) | BM33: =IF(A33="","",VLOOKUP(B33,'Datos Biyemas'!B35:BF72,56,0)) | BN33: =IF(A33="","",VLOOKUP(B33,'Datos Biyemas'!B35:BF72,57,0)) | BP33: Jue/Thu
A34: =IF(BP34='Datos Biyemas'!A36,'Datos Biyemas'!A36,"") | B34: =IF(BP34=A34,'Datos Biyemas'!B36,"") | C34: =IF(BP34=A34,'Datos Biyemas'!C36,"") | D34: =IF(BP34=A34,VLOOKUP(B34,'Datos Biyemas'!B36:BB73,3,0),"") | E34: =IF(BP34=A34,VLOOKUP(B34,'Datos Biyemas'!B36:BB73,4,0),"") | F34: =IF(BP34=A34,VLOOKUP(B34,'Datos Biyemas'!B36:BB73,5,0),"") | G34: =IF(BP34=A34,VLOOKUP(B34,'Datos Biyemas'!B36:BB73,6,0),"") | H34: =IF(BP34=A34,IF(E34>0,+G34/E34,0),"") | I34: =IF(A34="","",IF(F34>0,+G34/F34,0)) | J34: =IF(A34="","",IF(G34>0,+G34/C34,0)) | K34: =IF(A34="","",IF(G34>0,+G34/D34,0)) | L34: =IF(A34="","",VLOOKUP(B34,'Datos Biyemas'!B36:BB73,11,0)) | M34: =IF(A34="","",VLOOKUP(B34,'Datos Biyemas'!B36:BB73,12,0)) | N34: =IF(A34="","",VLOOKUP(B34,'Datos Biyemas'!B36:BB73,13,0)) | O34: =IF(A34="","",VLOOKUP(B34,'Datos Biyemas'!B36:BB73,14,0)) | P34: =IF(A34="","",IF(M34>0,+O34/M34,0)) | Q34: =IF(A34="","",IF(N34>0,+O34/N34,0)) | R34: =IF(A34="","",IF(C34>0,+O34/C34,0)) | S34: =IF(A34="","",IF(C34>0,+O34/L34,0)) | T34: =IF(A34="","",IF(G34>0,(G34+O34)/(D34+L34),0)) | U34: =IF(A34="","",IF(D34>0,+L34+D34,0)) | V34: =IF(A34="","",VLOOKUP(B34,'Datos Biyemas'!B36:BB73,21,0)) | W34: =IF(A34="","",VLOOKUP(B34,'Datos Biyemas'!B36:BB73,22,0)) | X34: =IF(A34="","",VLOOKUP(B34,'Datos Biyemas'!B36:BB73,23,0)) | Y34: =IF(A34="","",VLOOKUP(B34,'Datos Biyemas'!B36:BB73,24,0)) | Z34: =IF(A34="","",IF(W34>0,+Y34/W34,0)) | AA34: =IF(A34="","",IF(X34>0,+Y34/X34,0)) | AB34: =IF(A34="","",IF(Y34>0,+Y34/K34,0)) | AC34: =IF(A34="","",IF(Y34>0,+Y34/V34,0)) | AD34: =IF(A34="","",+G34+O34+Y34) | AE34: =IF(A34="","",VLOOKUP(B34,'Datos Biyemas'!B36:BB73,30,0)) | AF34: =IF(A34="","",+AD34-AE34) | AG34: =IF(A34="","",VLOOKUP(B34,'Datos Biyemas'!B36:BB73,32,0)) | AH34: =IF(A34="","",VLOOKUP(B34,'Datos Biyemas'!B36:BB73,33,0)) | AI34: =IF(A34="","",VLOOKUP(B34,'Datos Biyemas'!B36:BB73,34,0)) | AJ34: =IF(A34="","",IF(AI34>0,+AI34/C34,0)) | AK34: =IF(A34="","",+G34+O34+AI34+Y34) | AL34: =IF(A34="","",VLOOKUP(B34,'Datos Biyemas'!B36:BB73,37,0)) | AM34: =IF(A34="","",IF(AL34>0,+AL34/C34,0)) | AN34: =IF(BP34=A34,'Datos Biyemas'!BL36,"") | AO34: =IF(A34="","",VLOOKUP(B34,'Datos Biyemas'!B36:BF73,39,0)) | AP34: =IF(A34="","",IF(AN34>0,+AO34/AN34,0)) | AQ34: =IF(A34="","",VLOOKUP(B34,'Datos Biyemas'!B36:BH73,41,0)) | AR34: =IF(A34="","",VLOOKUP(B34,'Datos Biyemas'!B36:BI73,42,0)) | AS34: =IF(A34="","",VLOOKUP(B34,'Datos Biyemas'!B36:BJ73,43,0)) | AT34: =IF(A34="","",VLOOKUP(B34,'Datos Biyemas'!B36:BK73,44,0)) | AU34: =IF(A34="","",VLOOKUP(C34,'Datos Biyemas'!C36:BL73,44,0)) | AV34: =IF(A34="","",+AD34+AI34+AL34+AO34) | AW34: =IF(A34="","",IF(AV34>0,+AV34/C34,0)) | AY34: =IF(A34="","",+'Datos Biyemas'!AY36) | AZ34: =IF(A34="","",IF($AZ$6>0,+AY34-$AZ$6,)) | BA34: =IF(A34="","",VLOOKUP(B34,'Datos Biyemas'!B36:BF73,51,0)) | BB34: =IF(A34="","",IF(BA34>0,(C34-BA34)/BA34,100%)) | BC34: =IF(BP34=A34,'Datos Biyemas'!BL36,"") | BD34: =IF(A34="","",IF(BC34>0,(AN34-BC34)/BC34,1)) | BE34: =IF(A34="","",VLOOKUP(B34,'Datos Biyemas'!B36:BF73,53,0)) | BF34: =IF(A34="","",VLOOKUP(B34,'Datos Biyemas'!B36:BF73,54,0)) | BG34: =IF(A34="","",VLOOKUP(B34,'Datos Biyemas'!B36:BF73,55,0)) | BH34: =IF(A34="","",VLOOKUP(B34,'Datos Biyemas'!B36:BF73,51,0)) | BI34: =IF(A34="","",VLOOKUP(B34,'Datos Biyemas'!B36:BF73,52,0)) | BJ34: =IF(A34="","",VLOOKUP(B34,'Datos Biyemas'!B36:BH73,58,0)) | BK34: =IF(A34="","",VLOOKUP(B34,'Datos Biyemas'!B36:BH73,59,0)) | BL34: =IF(A34="","",VLOOKUP(B34,'Datos Biyemas'!B36:BF73,55,0)) | BM34: =IF(A34="","",VLOOKUP(B34,'Datos Biyemas'!B36:BF73,56,0)) | BN34: =IF(A34="","",VLOOKUP(B34,'Datos Biyemas'!B36:BF73,57,0)) | BP34: Vie/Fri
A35: =IF(BP35='Datos Biyemas'!A37,'Datos Biyemas'!A37,"") | B35: =IF(BP35=A35,'Datos Biyemas'!B37,"") | C35: =IF(BP35=A35,'Datos Biyemas'!C37,"") | D35: =IF(BP35=A35,VLOOKUP(B35,'Datos Biyemas'!B37:BB74,3,0),"") | E35: =IF(BP35=A35,VLOOKUP(B35,'Datos Biyemas'!B37:BB74,4,0),"") | F35: =IF(BP35=A35,VLOOKUP(B35,'Datos Biyemas'!B37:BB74,5,0),"") | G35: =IF(BP35=A35,VLOOKUP(B35,'Datos Biyemas'!B37:BB74,6,0),"") | H35: =IF(BP35=A35,IF(E35>0,+G35/E35,0),"") | I35: =IF(A35="","",IF(F35>0,+G35/F35,0)) | J35: =IF(A35="","",IF(G35>0,+G35/C35,0)) | K35: =IF(A35="","",IF(G35>0,+G35/D35,0)) | L35: =IF(A35="","",VLOOKUP(B35,'Datos Biyemas'!B37:BB74,11,0)) | M35: =IF(A35="","",VLOOKUP(B35,'Datos Biyemas'!B37:BB74,12,0)) | N35: =IF(A35="","",VLOOKUP(B35,'Datos Biyemas'!B37:BB74,13,0)) | O35: =IF(A35="","",VLOOKUP(B35,'Datos Biyemas'!B37:BB74,14,0)) | P35: =IF(A35="","",IF(M35>0,+O35/M35,0)) | Q35: =IF(A35="","",IF(N35>0,+O35/N35,0)) | R35: =IF(A35="","",IF(C35>0,+O35/C35,0)) | S35: =IF(A35="","",IF(C35>0,+O35/L35,0)) | T35: =IF(A35="","",IF(G35>0,(G35+O35)/(D35+L35),0)) | U35: =IF(A35="","",IF(D35>0,+L35+D35,0)) | V35: =IF(A35="","",VLOOKUP(B35,'Datos Biyemas'!B37:BB74,21,0)) | W35: =IF(A35="","",VLOOKUP(B35,'Datos Biyemas'!B37:BB74,22,0)) | X35: =IF(A35="","",VLOOKUP(B35,'Datos Biyemas'!B37:BB74,23,0)) | Y35: =IF(A35="","",VLOOKUP(B35,'Datos Biyemas'!B37:BB74,24,0)) | Z35: =IF(A35="","",IF(W35>0,+Y35/W35,0)) | AA35: =IF(A35="","",IF(X35>0,+Y35/X35,0)) | AB35: =IF(A35="","",IF(Y35>0,+Y35/K35,0)) | AC35: =IF(A35="","",IF(Y35>0,+Y35/V35,0)) | AD35: =IF(A35="","",+G35+O35+Y35) | AE35: =IF(A35="","",VLOOKUP(B35,'Datos Biyemas'!B37:BB74,30,0)) | AF35: =IF(A35="","",+AD35-AE35) | AG35: =IF(A35="","",VLOOKUP(B35,'Datos Biyemas'!B37:BB74,32,0)) | AH35: =IF(A35="","",VLOOKUP(B35,'Datos Biyemas'!B37:BB74,33,0)) | AI35: =IF(A35="","",VLOOKUP(B35,'Datos Biyemas'!B37:BB74,34,0)) | AJ35: =IF(A35="","",IF(AI35>0,+AI35/C35,0)) | AK35: =IF(A35="","",+G35+O35+AI35+Y35) | AL35: =IF(A35="","",VLOOKUP(B35,'Datos Biyemas'!B37:BB74,37,0)) | AM35: =IF(A35="","",IF(AL35>0,+AL35/C35,0)) | AN35: =IF(BP35=A35,'Datos Biyemas'!BL37,"") | AO35: =IF(A35="","",VLOOKUP(B35,'Datos Biyemas'!B37:BF74,39,0)) | AP35: =IF(A35="","",IF(AN35>0,+AO35/AN35,0)) | AQ35: =IF(A35="","",VLOOKUP(B35,'Datos Biyemas'!B37:BH74,41,0)) | AR35: =IF(A35="","",VLOOKUP(B35,'Datos Biyemas'!B37:BI74,42,0)) | AS35: =IF(A35="","",VLOOKUP(B35,'Datos Biyemas'!B37:BJ74,43,0)) | AT35: =IF(A35="","",VLOOKUP(B35,'Datos Biyemas'!B37:BK74,44,0)) | AU35: =IF(A35="","",VLOOKUP(C35,'Datos Biyemas'!C37:BL74,44,0)) | AV35: =IF(A35="","",+AD35+AI35+AL35+AO35) | AW35: =IF(A35="","",IF(AV35>0,+AV35/C35,0)) | AY35: =IF(A35="","",+'Datos Biyemas'!AY37) | AZ35: =IF(A35="","",IF($AZ$6>0,+AY35-$AZ$6,)) | BA35: =IF(A35="","",VLOOKUP(B35,'Datos Biyemas'!B37:BF74,51,0)) | BB35: =IF(A35="","",IF(BA35>0,(C35-BA35)/BA35,100%)) | BC35: =IF(BP35=A35,'Datos Biyemas'!BL37,"") | BD35: =IF(A35="","",IF(BC35>0,(AN35-BC35)/BC35,1)) | BE35: =IF(A35="","",VLOOKUP(B35,'Datos Biyemas'!B37:BF74,53,0)) | BF35: =IF(A35="","",VLOOKUP(B35,'Datos Biyemas'!B37:BF74,54,0)) | BG35: =IF(A35="","",VLOOKUP(B35,'Datos Biyemas'!B37:BF74,55,0)) | BH35: =IF(A35="","",VLOOKUP(B35,'Datos Biyemas'!B37:BF74,51,0)) | BI35: =IF(A35="","",VLOOKUP(B35,'Datos Biyemas'!B37:BF74,52,0)) | BJ35: =IF(A35="","",VLOOKUP(B35,'Datos Biyemas'!B37:BH74,58,0)) | BK35: =IF(A35="","",VLOOKUP(B35,'Datos Biyemas'!B37:BH74,59,0)) | BL35: =IF(A35="","",VLOOKUP(B35,'Datos Biyemas'!B37:BF74,55,0)) | BM35: =IF(A35="","",VLOOKUP(B35,'Datos Biyemas'!B37:BF74,56,0)) | BN35: =IF(A35="","",VLOOKUP(B35,'Datos Biyemas'!B37:BF74,57,0)) | BP35: Sab/Sat
A36: =IF(BP36='Datos Biyemas'!A38,'Datos Biyemas'!A38,"") | B36: =IF(BP36=A36,'Datos Biyemas'!B38,"") | C36: =IF(BP36=A36,'Datos Biyemas'!C38,"") | D36: =IF(BP36=A36,VLOOKUP(B36,'Datos Biyemas'!B38:BB75,3,0),"") | E36: =IF(BP36=A36,VLOOKUP(B36,'Datos Biyemas'!B38:BB75,4,0),"") | F36: =IF(BP36=A36,VLOOKUP(B36,'Datos Biyemas'!B38:BB75,5,0),"") | G36: =IF(BP36=A36,VLOOKUP(B36,'Datos Biyemas'!B38:BB75,6,0),"") | H36: =IF(BP36=A36,IF(E36>0,+G36/E36,0),"") | I36: =IF(A36="","",IF(F36>0,+G36/F36,0)) | J36: =IF(A36="","",IF(G36>0,+G36/C36,0)) | K36: =IF(A36="","",IF(G36>0,+G36/D36,0)) | L36: =IF(A36="","",VLOOKUP(B36,'Datos Biyemas'!B38:BB75,11,0)) | M36: =IF(A36="","",VLOOKUP(B36,'Datos Biyemas'!B38:BB75,12,0)) | N36: =IF(A36="","",VLOOKUP(B36,'Datos Biyemas'!B38:BB75,13,0)) | O36: =IF(A36="","",VLOOKUP(B36,'Datos Biyemas'!B38:BB75,14,0)) | P36: =IF(A36="","",IF(M36>0,+O36/M36,0)) | Q36: =IF(A36="","",IF(N36>0,+O36/N36,0)) | R36: =IF(A36="","",IF(C36>0,+O36/C36,0)) | S36: =IF(A36="","",IF(C36>0,+O36/L36,0)) | T36: =IF(A36="","",IF(G36>0,(G36+O36)/(D36+L36),0)) | U36: =IF(A36="","",IF(D36>0,+L36+D36,0)) | V36: =IF(A36="","",VLOOKUP(B36,'Datos Biyemas'!B38:BB75,21,0)) | W36: =IF(A36="","",VLOOKUP(B36,'Datos Biyemas'!B38:BB75,22,0)) | X36: =IF(A36="","",VLOOKUP(B36,'Datos Biyemas'!B38:BB75,23,0)) | Y36: =IF(A36="","",VLOOKUP(B36,'Datos Biyemas'!B38:BB75,24,0)) | Z36: =IF(A36="","",IF(W36>0,+Y36/W36,0)) | AA36: =IF(A36="","",IF(X36>0,+Y36/X36,0)) | AB36: =IF(A36="","",IF(Y36>0,+Y36/K36,0)) | AC36: =IF(A36="","",IF(Y36>0,+Y36/V36,0)) | AD36: =IF(A36="","",+G36+O36+Y36) | AE36: =IF(A36="","",VLOOKUP(B36,'Datos Biyemas'!B38:BB75,30,0)) | AF36: =IF(A36="","",+AD36-AE36) | AG36: =IF(A36="","",VLOOKUP(B36,'Datos Biyemas'!B38:BB75,32,0)) | AH36: =IF(A36="","",VLOOKUP(B36,'Datos Biyemas'!B38:BB75,33,0)) | AI36: =IF(A36="","",VLOOKUP(B36,'Datos Biyemas'!B38:BB75,34,0)) | AJ36: =IF(A36="","",IF(AI36>0,+AI36/C36,0)) | AK36: =IF(A36="","",+G36+O36+AI36+Y36) | AL36: =IF(A36="","",VLOOKUP(B36,'Datos Biyemas'!B38:BB75,37,0)) | AM36: =IF(A36="","",IF(AL36>0,+AL36/C36,0)) | AN36: =IF(BP36=A36,'Datos Biyemas'!BL38,"") | AO36: =IF(A36="","",VLOOKUP(B36,'Datos Biyemas'!B38:BF75,39,0)) | AP36: =IF(A36="","",IF(AN36>0,+AO36/AN36,0)) | AQ36: =IF(A36="","",VLOOKUP(B36,'Datos Biyemas'!B38:BH75,41,0)) | AR36: =IF(A36="","",VLOOKUP(B36,'Datos Biyemas'!B38:BI75,42,0)) | AS36: =IF(A36="","",VLOOKUP(B36,'Datos Biyemas'!B38:BJ75,43,0)) | AT36: =IF(A36="","",VLOOKUP(B36,'Datos Biyemas'!B38:BK75,44,0)) | AU36: =IF(A36="","",VLOOKUP(C36,'Datos Biyemas'!C38:BL75,44,0)) | AV36: =IF(A36="","",+AD36+AI36+AL36+AO36) | AW36: =IF(A36="","",IF(AV36>0,+AV36/C36,0)) | AY36: =IF(A36="","",+'Datos Biyemas'!AY38) | AZ36: =IF(A36="","",IF($AZ$6>0,+AY36-$AZ$6,)) | BA36: =IF(A36="","",VLOOKUP(B36,'Datos Biyemas'!B38:BF75,51,0)) | BB36: =IF(A36="","",IF(BA36>0,(C36-BA36)/BA36,100%)) | BC36: =IF(BP36=A36,'Datos Biyemas'!BL38,"") | BD36: =IF(A36="","",IF(BC36>0,(AN36-BC36)/BC36,1)) | BE36: =IF(A36="","",VLOOKUP(B36,'Datos Biyemas'!B38:BF75,53,0)) | BF36: =IF(A36="","",VLOOKUP(B36,'Datos Biyemas'!B38:BF75,54,0)) | BG36: =IF(A36="","",VLOOKUP(B36,'Datos Biyemas'!B38:BF75,55,0)) | BH36: =IF(A36="","",VLOOKUP(B36,'Datos Biyemas'!B38:BF75,51,0)) | BI36: =IF(A36="","",VLOOKUP(B36,'Datos Biyemas'!B38:BF75,52,0)) | BJ36: =IF(A36="","",VLOOKUP(B36,'Datos Biyemas'!B38:BH75,58,0)) | BK36: =IF(A36="","",VLOOKUP(B36,'Datos Biyemas'!B38:BH75,59,0)) | BL36: =IF(A36="","",VLOOKUP(B36,'Datos Biyemas'!B38:BF75,55,0)) | BM36: =IF(A36="","",VLOOKUP(B36,'Datos Biyemas'!B38:BF75,56,0)) | BN36: =IF(A36="","",VLOOKUP(B36,'Datos Biyemas'!B38:BF75,57,0)) | BP36: Dom/Sun
A37: =IF(BP37='Datos Biyemas'!A39,'Datos Biyemas'!A39,"") | B37: =IF(BP37=A37,'Datos Biyemas'!B39,"") | C37: =IF(BP37=A37,'Datos Biyemas'!C39,"") | D37: =IF(BP37=A37,VLOOKUP(B37,'Datos Biyemas'!B39:BB76,3,0),"") | E37: =IF(BP37=A37,VLOOKUP(B37,'Datos Biyemas'!B39:BB76,4,0),"") | F37: =IF(BP37=A37,VLOOKUP(B37,'Datos Biyemas'!B39:BB76,5,0),"") | G37: =IF(BP37=A37,VLOOKUP(B37,'Datos Biyemas'!B39:BB76,6,0),"") | H37: =IF(BP37=A37,IF(E37>0,+G37/E37,0),"") | I37: =IF(A37="","",IF(F37>0,+G37/F37,0)) | J37: =IF(A37="","",IF(G37>0,+G37/C37,0)) | K37: =IF(A37="","",IF(G37>0,+G37/D37,0)) | L37: =IF(A37="","",VLOOKUP(B37,'Datos Biyemas'!B39:BB76,11,0)) | M37: =IF(A37="","",VLOOKUP(B37,'Datos Biyemas'!B39:BB76,12,0)) | N37: =IF(A37="","",VLOOKUP(B37,'Datos Biyemas'!B39:BB76,13,0)) | O37: =IF(A37="","",VLOOKUP(B37,'Datos Biyemas'!B39:BB76,14,0)) | P37: =IF(A37="","",IF(M37>0,+O37/M37,0)) | Q37: =IF(A37="","",IF(N37>0,+O37/N37,0)) | R37: =IF(A37="","",IF(C37>0,+O37/C37,0)) | S37: =IF(A37="","",IF(C37>0,+O37/L37,0)) | T37: =IF(A37="","",IF(G37>0,(G37+O37)/(D37+L37),0)) | U37: =IF(A37="","",IF(D37>0,+L37+D37,0)) | V37: =IF(A37="","",VLOOKUP(B37,'Datos Biyemas'!B39:BB76,21,0)) | W37: =IF(A37="","",VLOOKUP(B37,'Datos Biyemas'!B39:BB76,22,0)) | X37: =IF(A37="","",VLOOKUP(B37,'Datos Biyemas'!B39:BB76,23,0)) | Y37: =IF(A37="","",VLOOKUP(B37,'Datos Biyemas'!B39:BB76,24,0)) | Z37: =IF(A37="","",IF(W37>0,+Y37/W37,0)) | AA37: =IF(A37="","",IF(X37>0,+Y37/X37,0)) | AB37: =IF(A37="","",IF(Y37>0,+Y37/K37,0)) | AC37: =IF(A37="","",IF(Y37>0,+Y37/V37,0)) | AD37: =IF(A37="","",+G37+O37+Y37) | AE37: =IF(A37="","",VLOOKUP(B37,'Datos Biyemas'!B39:BB76,30,0)) | AF37: =IF(A37="","",+AD37-AE37) | AG37: =IF(A37="","",VLOOKUP(B37,'Datos Biyemas'!B39:BB76,32,0)) | AH37: =IF(A37="","",VLOOKUP(B37,'Datos Biyemas'!B39:BB76,33,0)) | AI37: =IF(A37="","",VLOOKUP(B37,'Datos Biyemas'!B39:BB76,34,0)) | AJ37: =IF(A37="","",IF(AI37>0,+AI37/C37,0)) | AK37: =IF(A37="","",+G37+O37+AI37+Y37) | AL37: =IF(A37="","",VLOOKUP(B37,'Datos Biyemas'!B39:BB76,37,0)) | AM37: =IF(A37="","",IF(AL37>0,+AL37/C37,0)) | AN37: =IF(BP37=A37,'Datos Biyemas'!BL39,"") | AO37: =IF(A37="","",VLOOKUP(B37,'Datos Biyemas'!B39:BF76,39,0)) | AP37: =IF(A37="","",IF(AN37>0,+AO37/AN37,0)) | AQ37: =IF(A37="","",VLOOKUP(B37,'Datos Biyemas'!B39:BH76,41,0)) | AR37: =IF(A37="","",VLOOKUP(B37,'Datos Biyemas'!B39:BI76,42,0)) | AS37: =IF(A37="","",VLOOKUP(B37,'Datos Biyemas'!B39:BJ76,43,0)) | AT37: =IF(A37="","",VLOOKUP(B37,'Datos Biyemas'!B39:BK76,44,0)) | AU37: =IF(A37="","",VLOOKUP(C37,'Datos Biyemas'!C39:BL76,44,0)) | AV37: =IF(A37="","",+AD37+AI37+AL37+AO37) | AW37: =IF(A37="","",IF(AV37>0,+AV37/C37,0)) | AY37: =IF(A37="","",+'Datos Biyemas'!AY39) | AZ37: =IF(A37="","",IF($AZ$6>0,+AY37-$AZ$6,)) | BA37: =IF(A37="","",VLOOKUP(B37,'Datos Biyemas'!B39:BF76,51,0)) | BB37: =IF(A37="","",IF(BA37>0,(C37-BA37)/BA37,100%)) | BC37: =IF(BP37=A37,'Datos Biyemas'!BL39,"") | BD37: =IF(A37="","",IF(BC37>0,(AN37-BC37)/BC37,1)) | BE37: =IF(A37="","",VLOOKUP(B37,'Datos Biyemas'!B39:BF76,53,0)) | BF37: =IF(A37="","",VLOOKUP(B37,'Datos Biyemas'!B39:BF76,54,0)) | BG37: =IF(A37="","",VLOOKUP(B37,'Datos Biyemas'!B39:BF76,55,0)) | BH37: =IF(A37="","",VLOOKUP(B37,'Datos Biyemas'!B39:BF76,51,0)) | BI37: =IF(A37="","",VLOOKUP(B37,'Datos Biyemas'!B39:BF76,52,0)) | BJ37: =IF(A37="","",VLOOKUP(B37,'Datos Biyemas'!B39:BH76,58,0)) | BK37: =IF(A37="","",VLOOKUP(B37,'Datos Biyemas'!B39:BH76,59,0)) | BL37: =IF(A37="","",VLOOKUP(B37,'Datos Biyemas'!B39:BF76,55,0)) | BM37: =IF(A37="","",VLOOKUP(B37,'Datos Biyemas'!B39:BF76,56,0)) | BN37: =IF(A37="","",VLOOKUP(B37,'Datos Biyemas'!B39:BF76,57,0)) | BP37: Lun/Mon
AN38: =IF(BP38=A38,'Datos Biyemas'!BL40,"") | AQ38: =IF(A38="","",VLOOKUP(B38,'Datos Biyemas'!B40:BH77,41,0)) | AR38: =IF(A38="","",VLOOKUP(B38,'Datos Biyemas'!B40:BI77,42,0)) | AS38: =IF(A38="","",VLOOKUP(B38,'Datos Biyemas'!B40:BJ77,43,0)) | AT38: =IF(A38="","",VLOOKUP(B38,'Datos Biyemas'!B40:BK77,44,0)) | AY38: =IF(A38="","",+'Datos Biyemas'!AY40) | AZ38: =IF(A38="","",IF($AZ$6>0,+AY38-$AZ$6,)) | BA38: =IF(A38="","",VLOOKUP(B38,'Datos Biyemas'!B40:BF77,51,0)) | BB38: =IF(A38="","",IF(BA38>0,(C38-BA38)/BA38,100%)) | BC38: =IF(BP38=A38,'Datos Biyemas'!BL40,"") | BE38: =IF(A38="","",VLOOKUP(B38,'Datos Biyemas'!B40:BF77,53,0)) | BF38: =IF(A38="","",VLOOKUP(B38,'Datos Biyemas'!B40:BF77,54,0)) | BG38: =IF(A38="","",VLOOKUP(B38,'Datos Biyemas'!B40:BF77,55,0)) | BI38: =IF(A38="","",VLOOKUP(B38,'Datos Biyemas'!B40:BF77,52,0)) | BJ38: =IF(A38="","",VLOOKUP(B38,'Datos Biyemas'!B40:BH77,58,0)) | BK38: =IF(A38="","",VLOOKUP(B38,'Datos Biyemas'!B40:BH77,59,0)) | BN38: =IF(A38="","",VLOOKUP(B38,'Datos Biyemas'!B40:BF77,57,0)) | BP38: Mar/Tue
A39: Total final | C39: =SUM(C7:C38) -> 0 | E39: =SUM(E7:E38) -> 0 | F39: =SUM(F7:F38) -> 0 | G39: =SUM(G7:G38) -> 0 | M39: =SUM(M7:M38) -> 0 | N39: =SUM(N7:N38) -> 0 | O39: =SUM(O7:O38) -> 0 | W39: =SUM(W7:W38) -> 0 | X39: =SUM(X7:X38) -> 0 | Y39: =SUM(Y7:Y38) -> 0 | AD39: =SUM(AD7:AD38) -> 0 | AE39: =SUM(AE7:AE38) -> 0 | AF39: =SUM(AF7:AF38) -> 0 | AG39: =SUM(AG7:AG38) -> 0 | AH39: =SUM(AH7:AH38) -> 0 | AI39: =SUM(AI7:AI38) -> 0 | AK39: =SUM(AK7:AK38) -> 0 | AL39: =SUM(AL7:AL38) -> 0 | AN39: =SUM(AN7:AN38) -> 0 | AO39: =SUM(AO7:AO38) -> 0 | AP39: =SUM(AP7:AP38) -> 0 | AQ39: =SUM(AQ7:AQ38) -> 0 | AR39: =SUM(AR7:AR38) -> 0 | AS39: =SUM(AS7:AS38) -> 0 | AT39: =SUM(AT7:AT38) -> 0 | AU39: =SUM(AU7:AU38) -> 0 | AV39: =SUM(AV7:AV38) -> 0 | AY39: =SUM(AY7:AY38)/COUNT(AY7:AY38) -> #DIV/0! | AZ39: =AY39-AZ6 -> #DIV/0! | BA39: =SUM(BA7:BA38) -> 0 | BB39: =IF($AK39>0,(C39-($BA39))/($BA$39),) -> 0 | BC39: =SUM(BC7:BC38) -> 0 | BD39: =IF($BC39>0,(AN39-($BC39))/($BC$39),IF(AN39>0,1)) -> FALSE | BE39: =VLOOKUP("Total final",'Datos Biyemas'!A9:BF142,54,0) -> #N/A | BF39: =VLOOKUP("Total final",'Datos Biyemas'!A9:BF142,55,0) -> #N/A | BG39: =VLOOKUP("Total final",'Datos Biyemas'!A9:BF142,56,0) -> #N/A | BH39: =VLOOKUP("Total final",'Datos Biyemas'!A9:BF142,52,0) -> #N/A | BI39: =VLOOKUP("Total final",'Datos Biyemas'!A9:BF142,53,0) -> #N/A | BJ39: =VLOOKUP("Total final",'Datos Biyemas'!A9:BH142,59,0) -> #N/A | BK39: =VLOOKUP("Total final",'Datos Biyemas'!A9:BH142,60,0) -> #N/A | BL39: =VLOOKUP("Total final",'Datos Biyemas'!A9:BF142,56,0) -> #N/A | BM39: =VLOOKUP("Total final",'Datos Biyemas'!A9:BF142,57,0) -> #N/A | BN39: =VLOOKUP("Total final",'Datos Biyemas'!A9:BF142,58,0) -> #N/A
A40: MTD Average | C40: =VLOOKUP("MTD Average",'Datos Biyemas'!A9:BB142,3,0) -> #N/A | D40: =VLOOKUP("MTD Average",'Datos Biyemas'!A9:BB142,4,0) -> #N/A | E40: =VLOOKUP("MTD Average",'Datos Biyemas'!A9:BB142,5,0) -> #N/A | F40: =VLOOKUP("MTD Average",'Datos Biyemas'!A9:BB142,6,0) -> #N/A | G40: =VLOOKUP("MTD Average",'Datos Biyemas'!A9:BB142,7,0) -> #N/A | H40: =+G40/E40 -> #N/A | I40: =+G40/F40 -> #N/A | J40: =+G40/C40 -> #N/A | K40: =+G40/D40 -> #N/A | L40: =VLOOKUP("MTD Average",'Datos Biyemas'!A9:BB142,12,0) -> #N/A | M40: =VLOOKUP("MTD Average",'Datos Biyemas'!A9:BB142,13,0) -> #N/A | N40: =VLOOKUP("MTD Average",'Datos Biyemas'!A9:BB142,14,0) -> #N/A | O40: =VLOOKUP("MTD Average",'Datos Biyemas'!A9:BB142,15,0) -> #N/A | P40: =+O40/M40 -> #N/A | Q40: =+O40/N40 -> #N/A | R40: =+O40/C40 -> #N/A | S40: =+O40/L40 -> #N/A | T40: =SUM(T7:T37)/$D$1 -> #DIV/0! | U40: =SUM(U7:U37)/$D$1 -> #DIV/0! | V40: =VLOOKUP("MTD Average",'Datos Biyemas'!A9:BB142,22,0) -> #N/A | W40: =VLOOKUP("MTD Average",'Datos Biyemas'!A9:BB142,23,0) -> #N/A | X40: =VLOOKUP("MTD Average",'Datos Biyemas'!A9:BB142,24,0) -> #N/A | Y40: =VLOOKUP("MTD Average",'Datos Biyemas'!A9:BB142,25,0) -> #N/A | Z40: =+Y40/W40 -> #N/A | AA40: =+Y40/X40 -> #N/A | AB40: =+Y40/K40 -> #N/A | AC40: =+Y40/V40 -> #N/A | AD40: =VLOOKUP("MTD Average",'Datos Biyemas'!A9:BB142,30,0) -> #N/A | AE40: =VLOOKUP("MTD Average",'Datos Biyemas'!A9:BB142,31,0) -> #N/A | AF40: =VLOOKUP("MTD Average",'Datos Biyemas'!A9:BB142,32,0) -> #N/A | AG40: =VLOOKUP("MTD Average",'Datos Biyemas'!A9:BB142,33,0) -> #N/A | AH40: =VLOOKUP("MTD Average",'Datos Biyemas'!A9:BB142,34,0) -> #N/A | AI40: =VLOOKUP("MTD Average",'Datos Biyemas'!A9:BB142,35,0) -> #N/A | AJ40: =+AI40/C40 -> #N/A | AK40: =VLOOKUP("MTD Average",'Datos Biyemas'!A9:BB142,37,0) -> #N/A | AL40: =VLOOKUP("MTD Average",'Datos Biyemas'!A9:BB142,38,0) -> #N/A | AM40: =+AL40/C40 -> #N/A | AN40: =+AN39/Resumen!D1 -> #DIV/0! | AO40: =VLOOKUP("MTD Average",'Datos Biyemas'!A9:BF142,40,0) -> #N/A | AP40: =+AO40/AN40 -> #N/A | AQ40: =VLOOKUP("MTD Average",'Datos Biyemas'!A9:BH142,42,0) -> #N/A | AR40: =VLOOKUP("MTD Average",'Datos Biyemas'!A9:BI142,43,0) -> #N/A | AS40: =VLOOKUP("MTD Average",'Datos Biyemas'!A9:BJ142,44,0) -> #N/A | AT40: =VLOOKUP("MTD Average",'Datos Biyemas'!A9:BK142,45,0) -> #N/A | AU40: =VLOOKUP("MTD Average",'Datos Biyemas'!A9:BK142,46,0) -> #N/A | AV40: =VLOOKUP("MTD Average",'Datos Biyemas'!A9:BB142,47,0) -> #N/A | AW40: =+AV40/C40 -> #N/A | BB40: MTD average: | BE40: =+AV40 -> #N/A | BF40: =+AD40 -> #N/A | BG40: =+AI40 -> #N/A | BH40: =+AL40 -> #N/A | BI40: =+AO40 -> #N/A | BJ40: =(1+BJ39)*BJ6 -> #N/A | BK40: =(1+BK39)*BK6 -> #N/A | BL40: =(1+BL39)*BL6 -> #N/A | BM40: =(1+BM39)*BM6 -> #N/A | BN40: =IF(((1+BN39)*BN6)=0,+BI40,(1+BN39)*BN6) -> #N/A
BB41: Dev from budget: | BE41: =HLOOKUP(BP41,'Datos Biyemas'!AX7:BB110,COUNT(BF7:BF38)+5,0) -> #N/A | BF41: =HLOOKUP(BQ41,'Datos Biyemas'!AY7:BC110,COUNT(BG7:BG38)+5,0) -> #N/A | BG41: =HLOOKUP(BR41,'Datos Biyemas'!AZ7:BD110,COUNT(BH7:BH38)+5,0) -> #N/A | BH41: =HLOOKUP(BS41,'Datos Biyemas'!BA7:BE110,COUNT(BI7:BI38)+5,0) -> #N/A | BI41: =HLOOKUP(BT41,'Datos Biyemas'!BB7:BF110,COUNT(BJ7:BJ38)+5,0) -> #N/A | BJ41: =HLOOKUP(BU41,'Datos Biyemas'!BC7:BG110,COUNT(BK7:BK38)+5,0) -> #N/A | BK41: =HLOOKUP(BV41,'Datos Biyemas'!BD7:BH110,COUNT(BL7:BL38)+5,0) -> #N/A | BL41: =HLOOKUP(BW41,'Datos Biyemas'!BE7:BI110,COUNT(BM7:BM38)+5,0) -> #N/A | ... BN41: =HLOOKUP(BY41,'Datos Biyemas'!BG7:BK110,COUNT(BO7:BO38)+5,0) -> #N/A | BP41: Total | BQ41: Electronic | BR41: Bingo | BS41: F&B | BT41: Total | BU41: Electronic | BV41: Bingo | BW41: F&B | BX41: Parking
A44: Reporte Flash Julio 2026
A45: Total final | C45: =VLOOKUP(+BP45,'Datos Biyemas'!A9:BB145,3,0) -> #N/A | E45: =VLOOKUP(+BP45,'Datos Biyemas'!A9:BB145,5,0) -> #N/A | F45: =VLOOKUP(+BP45,'Datos Biyemas'!A9:BB145,6,0) -> #N/A | G45: =VLOOKUP(+BP45,'Datos Biyemas'!A9:BB145,7,0) -> #N/A | M45: =VLOOKUP(+BP45,'Datos Biyemas'!A9:BB145,13,0) -> #N/A | N45: =VLOOKUP(+BP45,'Datos Biyemas'!A9:BB145,14,0) -> #N/A | O45: =VLOOKUP(+BP45,'Datos Biyemas'!A9:BB145,15,0) -> #N/A | W45: =VLOOKUP(+BP45,'Datos Biyemas'!A9:BB145,23,0) -> #N/A | X45: =VLOOKUP(+BP45,'Datos Biyemas'!A9:BB145,24,0) -> #N/A | Y45: =VLOOKUP(+BP45,'Datos Biyemas'!A9:BB145,25,0) -> #N/A | AD45: =VLOOKUP(+BP45,'Datos Biyemas'!A9:BB145,30,0) -> #N/A | AE45: =VLOOKUP(+BP45,'Datos Biyemas'!A9:BB145,31,0) -> #N/A | AF45: =VLOOKUP(+BP45,'Datos Biyemas'!A9:BB145,32,0) -> #N/A | AG45: =VLOOKUP(+BP45,'Datos Biyemas'!A9:BB145,33,0) -> #N/A | AH45: =VLOOKUP(+BP45,'Datos Biyemas'!A9:BB145,34,0) -> #N/A | AI45: =VLOOKUP(+BP45,'Datos Biyemas'!A9:BB145,35,0) -> #N/A | AK45: =VLOOKUP(+BP45,'Datos Biyemas'!A9:BB145,37,0) -> #N/A | AL45: =VLOOKUP(+BP45,'Datos Biyemas'!A9:BB145,38,0) -> #N/A | AN45: =VLOOKUP(+BP45,'Datos Biyemas'!A9:BL145,64,0) -> #N/A | AO45: =VLOOKUP(+BP45,'Datos Biyemas'!A9:BF145,40,0) -> #N/A | AQ45: =VLOOKUP(+BP45,'Datos Biyemas'!A9:AU100,42,FALSE) -> #N/A | AR45: =VLOOKUP(+BP45,'Datos Biyemas'!A9:AV100,43,FALSE) -> #N/A | AS45: =VLOOKUP(+BP45,'Datos Biyemas'!A9:AW100,44,FALSE) -> #N/A | AT45: =VLOOKUP(+BP45,'Datos Biyemas'!A9:AX100,45,FALSE) -> #N/A | AU45: =VLOOKUP(+BP45,'Datos Biyemas'!A9:AY100,46,FALSE) -> #N/A | AV45: =VLOOKUP(+BP45,'Datos Biyemas'!A9:BF145,47,0) -> #N/A | BA45: =VLOOKUP(+BP45,'Datos Biyemas'!A9:BF145,47,0) -> #N/A | BB45: =IF($AK45>0,(C45-($BA45))/($BA$45),) -> #N/A | BC45: =VLOOKUP(+BP45,'Datos Biyemas'!A9:BH145,60,0) -> #N/A | BD45: =IF($BC45>0,(AN45-($BC45))/($BC$45),IF(AN45>0,1)) -> #N/A | BE45: =VLOOKUP(+BP45,'Datos Biyemas'!A9:BF145,54,0) -> #N/A | BF45: =VLOOKUP(+BP45,'Datos Biyemas'!A9:BF145,55,0) -> #N/A | BG45: =VLOOKUP(+BP45,'Datos Biyemas'!A9:BB145,51,0) -> #N/A | BH45: =VLOOKUP(+BP45,'Datos Biyemas'!A9:BB145,52,0) -> #N/A | BI45: =VLOOKUP(+BP45,'Datos Biyemas'!A9:BB145,53,0) -> #N/A | BJ45: =VLOOKUP(+BP45,'Datos Biyemas'!A9:BH145,59,0) -> #N/A | BK45: =VLOOKUP(+BP45,'Datos Biyemas'!A9:BH145,60,0) -> #N/A | BL45: =VLOOKUP(+BP45,'Datos Biyemas'!A9:BF145,56,0) -> #N/A | BM45: =VLOOKUP(+BP45,'Datos Biyemas'!A9:BF145,57,0) -> #N/A | BN45: =VLOOKUP(+BP45,'Datos Biyemas'!A9:BF145,58,0) -> #N/A | BP45: Total final mes ant.
A46: MTD Average | C46: =VLOOKUP(+BP46,'Datos Biyemas'!A9:BB145,3,0) -> #N/A | D46: =VLOOKUP(+BP46,'Datos Biyemas'!A9:BB145,4,0) -> #N/A | E46: =VLOOKUP(+BP46,'Datos Biyemas'!A9:BB145,5,0) -> #N/A | F46: =VLOOKUP(+BP46,'Datos Biyemas'!A9:BB145,6,0) -> #N/A | G46: =VLOOKUP(+BP46,'Datos Biyemas'!A9:BB145,7,0) -> #N/A | H46: =+G46/E46 -> #N/A | I46: =+G46/F46 -> #N/A | J46: =+G46/C46 -> #N/A | K46: =+G46/D46 -> #N/A | L46: =VLOOKUP(+BP46,'Datos Biyemas'!A9:BB145,12,0) -> #N/A | M46: =VLOOKUP(+BP46,'Datos Biyemas'!A9:BB145,13,0) -> #N/A | N46: =VLOOKUP(+BP46,'Datos Biyemas'!A9:BB145,14,0) -> #N/A | O46: =VLOOKUP(+BP46,'Datos Biyemas'!A9:BB145,15,0) -> #N/A | P46: =+O46/M46 -> #N/A | Q46: =+O46/N46 -> #N/A | R46: =+O46/C46 -> #N/A | S46: =+O46/L46 -> #N/A | T46: =+SUM(O46+G46)/+SUM(D46+L46) -> #N/A | U46: =+D46+L46 -> #N/A | V46: =VLOOKUP(+BP46,'Datos Biyemas'!A9:BB145,22,0) -> #N/A | W46: =VLOOKUP(+BP46,'Datos Biyemas'!A9:BB145,23,0) -> #N/A | X46: =VLOOKUP(+BP46,'Datos Biyemas'!A9:BB145,24,0) -> #N/A | Y46: =VLOOKUP(+BP46,'Datos Biyemas'!A9:BB145,25,0) -> #N/A | Z46: =+Y46/W46 -> #N/A | AA46: =+Y46/X46 -> #N/A | AB46: =+Y46/M46 -> #N/A | AC46: =VLOOKUP(+BP46,'Datos Biyemas'!A9:BB145,29,0) -> #N/A | AD46: =VLOOKUP(+BP46,'Datos Biyemas'!A9:BB145,30,0) -> #N/A | AE46: =VLOOKUP(+BP46,'Datos Biyemas'!A9:BB145,31,0) -> #N/A | AF46: =VLOOKUP(+BP46,'Datos Biyemas'!A9:BB145,32,0) -> #N/A | AG46: =VLOOKUP(+BP46,'Datos Biyemas'!A9:BB145,33,0) -> #N/A | AH46: =VLOOKUP(+BP46,'Datos Biyemas'!A9:BB145,34,0) -> #N/A | AI46: =VLOOKUP(+BP46,'Datos Biyemas'!A9:BB145,35,0) -> #N/A | AJ46: =+AI46/C46 -> #N/A | AK46: =VLOOKUP(+BP46,'Datos Biyemas'!A9:BB145,37,0) -> #N/A | AL46: =VLOOKUP(+BP46,'Datos Biyemas'!A9:BB145,38,0) -> #N/A | AM46: =+AL46/C46 -> #N/A | AN46: =+AN45/Resumen!D1 -> #N/A | AO46: =VLOOKUP(+BP46,'Datos Biyemas'!A9:BF145,40,0) -> #N/A | AP46: =+AO46/AN46 -> #N/A | AQ46: =VLOOKUP(+BP46,'Datos Biyemas'!A9:AU145,42,0) -> #N/A | AR46: =VLOOKUP(+BP46,'Datos Biyemas'!A9:AU145,43,FALSE) -> #N/A | AS46: =VLOOKUP(+BP46,'Datos Biyemas'!A9:AU145,44,FALSE) -> #N/A | AT46: =VLOOKUP(+BP46,'Datos Biyemas'!A9:AU145,45,FALSE) -> #N/A | AU46: =VLOOKUP(+BP46,'Datos Biyemas'!A9:AU145,46,FALSE) -> #N/A | AV46: =VLOOKUP(+BP46,'Datos Biyemas'!A9:BF145,47,0) -> #N/A | AW46: =+AV46/C46 -> #N/A | BB46: MTD average: | BE46: =+AV46 -> #N/A | BF46: =+AD46 -> #N/A | BG46: =+AI46 -> #N/A | BH46: =+AL46 -> #N/A | BI46: =+AO46 -> #N/A | BJ46: =+BE46 -> #N/A | BK46: =+BF46 -> #N/A | BL46: =+BG46 -> #N/A | BM46: =+BH46 -> #N/A | BN46: =+BI46 -> #N/A | BP46: MTD average mes ant.
BB47: Dev from budget: | BE47: =VLOOKUP(+BP47,'Datos Biyemas'!AY4:BG171,4,0) -> #N/A | BF47: =VLOOKUP(+BP47,'Datos Biyemas'!AY4:BG171,5,0) -> #N/A | BG47: =VLOOKUP(+BP47,'Datos Biyemas'!AY4:BG171,6,0) -> #N/A | BH47: =VLOOKUP(+BP47,'Datos Biyemas'!AY4:BG171,7,0) -> #N/A | BI47: =IF(BI45=1,+BI46,VLOOKUP(+BP47,'Datos Biyemas'!AY4:BG171,8,0)) -> #N/A | BJ47: =VLOOKUP(+BP47,'Datos Biyemas'!AY4:BG171,9,0) -> #N/A | BK47: =VLOOKUP(+BP47,'Datos Biyemas'!AY4:BH171,10,0) -> #N/A | BL47: =VLOOKUP(+BP47,'Datos Biyemas'!AY4:BG171,11,0) -> #N/A | BM47: =VLOOKUP(+BP47,'Datos Biyemas'!AY4:BG171,12,0) -> #N/A | BN47: =IF(BN45=1,+BN46,VLOOKUP(+BP47,'Datos Biyemas'!AY4:BG171,13,0)) -> #N/A | BP47: Dev from budget mes ant.
A48: ▲ Prom diario % | C48: =(+C40-C46)/C46 -> #N/A | E48: =(+E40-E46)/E46 -> #N/A | F48: =(+F40-F46)/F46 -> #N/A | G48: =(+G40-G46)/G46 -> #N/A | K48: =(+K40-K46)/K46 -> #N/A | M48: =(+M40-M46)/M46 -> #N/A | N48: =(+N40-N46)/N46 -> #N/A | O48: =(+O40-O46)/O46 -> #N/A | S48: =(+S40-S46)/S46 -> #N/A | T48: =(+T40-T46)/T46 -> #DIV/0! | U48: =(+U40-U46)/U46 -> #DIV/0! | W48: =(+W40-W46)/W46 -> #N/A | X48: =(+X40-X46)/X46 -> #N/A | Y48: =(+Y40-Y46)/Y46 -> #N/A | AD48: =(+AD40-AD46)/AD46 -> #N/A | AE48: =(+AE40-AE46)/AE46 -> #N/A | AF48: =(+AF40-AF46)/AF46 -> #N/A | AG48: =(+AG40-AG46)/AG46 -> #N/A | AH48: =(+AH40-AH46)/AH46 -> #N/A | AI48: =(+AI40-AI46)/AI46 -> #N/A | AK48: =(+AK40-AK46)/AK46 -> #N/A | AL48: =(+AL40-AL46)/AL46 -> #N/A | AN48: =(+AN40-AN46)/AN46 -> #DIV/0! | AO48: =(+AO40-AO46)/AO46 -> #N/A | AQ48: =(+AQ40-AQ46)/AQ46 -> #N/A | AR48: =(+AR40-AR46)/AR46 -> #N/A | AS48: =(+AS40-AS46)/AS46 -> #N/A | AT48: =(+AT40-AT46)/AT46 -> #N/A | AU48: =(+AU40-AU46)/AU46 -> #N/A | AV48: =(+AV40-AV46)/AV46 -> #N/A
A49: ▲ Prom diario $ | E49: =+E40-E46 -> #N/A | F49: =+F40-F46 -> #N/A | G49: =+G40-G46 -> #N/A | K49: =+K40-K46 -> #N/A | M49: =+M40-M46 -> #N/A | N49: =+N40-N46 -> #N/A | O49: =+O40-O46 -> #N/A | S49: =+S40-S46 -> #N/A | T49: =+T40-T46 -> #DIV/0! | U49: =+U40-U46 -> #DIV/0! | W49: =+W40-W46 -> #N/A | X49: =+X40-X46 -> #N/A | Y49: =+Y40-Y46 -> #N/A | AD49: =+AD40-AD46 -> #N/A | AE49: =+AE40-AE46 -> #N/A | AF49: =+AF40-AF46 -> #N/A | AG49: =+AG40-AG46 -> #N/A | AH49: =+AH40-AH46 -> #N/A | AI49: =+AI40-AI46 -> #N/A | AK49: =+AK40-AK46 -> #N/A | AL49: =+AL40-AL46 -> #N/A | AO49: =+AO40-AO46 -> #N/A | AQ49: =+AQ40-AQ46 -> #N/A | AR49: =+AR40-AR46 -> #N/A | AS49: =+AS40-AS46 -> #N/A | AT49: =+AT40-AT46 -> #N/A | AU49: =+AU40-AU46 -> #N/A | AV49: =+AV40-AV46 -> #N/A
A53: Reporte Flash Agosto 25
A54: 0 | C54: =VLOOKUP(+BP54,'Datos Biyemas'!A9:BB145,3,0) -> #N/A | E54: =VLOOKUP(+BP54,'Datos Biyemas'!A9:BB145,5,0) -> #N/A | F54: =VLOOKUP(+BP54,'Datos Biyemas'!A9:BB145,6,0) -> #N/A | G54: =VLOOKUP(+BP54,'Datos Biyemas'!A9:BB145,7,0) -> #N/A | M54: =VLOOKUP(+BP54,'Datos Biyemas'!A9:BB145,13,0) -> #N/A | N54: =VLOOKUP(+BP54,'Datos Biyemas'!A9:BB145,14,0) -> #N/A | O54: =VLOOKUP(+BP54,'Datos Biyemas'!A9:BB145,15,0) -> #N/A | W54: =VLOOKUP(+BP54,'Datos Biyemas'!A9:BB145,23,0) -> #N/A | X54: =VLOOKUP(+BP54,'Datos Biyemas'!A9:BB145,24,0) -> #N/A | Y54: =VLOOKUP(+BP54,'Datos Biyemas'!A9:BB145,25,0) -> #N/A | AD54: =VLOOKUP(+BP54,'Datos Biyemas'!A9:BB145,30,0) -> #N/A | AE54: =VLOOKUP(+BP54,'Datos Biyemas'!A9:BB145,31,0) -> #N/A | AF54: =VLOOKUP(+BP54,'Datos Biyemas'!A9:BB145,32,0) -> #N/A | AG54: =VLOOKUP(+BP54,'Datos Biyemas'!A9:BB145,33,0) -> #N/A | AH54: =VLOOKUP(+BP54,'Datos Biyemas'!A9:BB145,34,0) -> #N/A | AI54: =VLOOKUP(+BP54,'Datos Biyemas'!A9:BB145,35,0) -> #N/A | AK54: =VLOOKUP(+BP54,'Datos Biyemas'!A9:BB145,37,0) -> #N/A | AL54: =VLOOKUP(+BP54,'Datos Biyemas'!A9:BB145,38,0) -> #N/A | AN54: =VLOOKUP(+BP54,'Datos Biyemas'!A9:BL145,64,0) -> #N/A | AO54: =VLOOKUP(+BP54,'Datos Biyemas'!A9:BF145,40,0) -> #N/A | AV54: =VLOOKUP(+BP54,'Datos Biyemas'!A9:BF145,47,0) -> #N/A | BA54: =VLOOKUP(+BP54,'Datos Biyemas'!A9:BB145,47,0) -> #N/A | BB54: =IF($AK54>0,(C54-($BA54))/($BA$54),) -> #N/A | BC54: =VLOOKUP(+BP54,'Datos Biyemas'!A9:BH145,60,0) -> #N/A | BD54: =IF($BC54>0,(AN54-($BC54))/($BC$54),IF(AN54>0,1)) -> #N/A | BE54: =VLOOKUP(+BP54,'Datos Biyemas'!A9:BF145,54,0) -> #N/A | BF54: =VLOOKUP(+BP54,'Datos Biyemas'!A9:BF145,55,0) -> #N/A | BG54: =VLOOKUP(+BP54,'Datos Biyemas'!A9:BB145,51,0) -> #N/A | BH54: =VLOOKUP(+BP54,'Datos Biyemas'!A9:BB145,52,0) -> #N/A | BI54: =VLOOKUP(+BP54,'Datos Biyemas'!A9:BB145,53,0) -> #N/A | BJ54: =BJ55/SUM(BJ55-BJ56)-1 -> #N/A | BK54: =BK55/SUM(BK55-BK56)-1 -> #N/A | BL54: =BL55/SUM(BL55-BL56)-1 -> #N/A | BM54: =BM55/SUM(BM55-BM56)-1 -> #N/A | BN54: =BN55/SUM(BN55-BN56)-1 -> #N/A | BP54: Total final anio ant.
A55: MTD Average | C55: =VLOOKUP(+BP55,'Datos Biyemas'!A9:BB145,3,0) -> #N/A | D55: =VLOOKUP(+BP55,'Datos Biyemas'!A9:BB145,4,0) -> #N/A | E55: =VLOOKUP(+BP55,'Datos Biyemas'!A9:BB145,5,0) -> #N/A | F55: =VLOOKUP(+BP55,'Datos Biyemas'!A9:BB145,6,0) -> #N/A | G55: =VLOOKUP(+BP55,'Datos Biyemas'!A9:BB145,7,0) -> #N/A | H55: =+G55/E55 -> #N/A | I55: =+G55/F55 -> #N/A | J55: =+G55/C55 -> #N/A | K55: =+G55/D55 -> #N/A | L55: =VLOOKUP(+BP55,'Datos Biyemas'!A9:BB145,12,0) -> #N/A | M55: =VLOOKUP(+BP55,'Datos Biyemas'!A9:BB145,13,0) -> #N/A | N55: =VLOOKUP(+BP55,'Datos Biyemas'!A9:BB145,14,0) -> #N/A | O55: =VLOOKUP(+BP55,'Datos Biyemas'!A9:BB145,15,0) -> #N/A | P55: =+O55/M55 -> #N/A | Q55: =+O55/N55 -> #N/A | R55: =+O55/C55 -> #N/A | S55: =+O55/L55 -> #N/A | T55: =+SUM(O55+G55)/+SUM(D55+L55) -> #N/A | U55: =+D55+L55 -> #N/A | V55: =VLOOKUP(+BP55,'Datos Biyemas'!A9:BB145,22,0) -> #N/A | W55: =VLOOKUP(+BP55,'Datos Biyemas'!A9:BB145,23,0) -> #N/A | X55: =VLOOKUP(+BP55,'Datos Biyemas'!A9:BB145,24,0) -> #N/A | Y55: =VLOOKUP(+BP55,'Datos Biyemas'!A9:BB145,25,0) -> #N/A | Z55: =+Y55/W55 -> #N/A | AA55: =+Y55/X55 -> #N/A | AB55: =+Y55/M55 -> #N/A | AC55: =VLOOKUP(+BP55,'Datos Biyemas'!A9:BB145,29,0) -> #N/A | AD55: =VLOOKUP(+BP55,'Datos Biyemas'!A9:BB145,30,0) -> #N/A | AE55: =VLOOKUP(+BP55,'Datos Biyemas'!A9:BB145,31,0) -> #N/A | AF55: =VLOOKUP(+BP55,'Datos Biyemas'!A9:BB145,32,0) -> #N/A | AG55: =VLOOKUP(+BP55,'Datos Biyemas'!A9:BB145,33,0) -> #N/A | AH55: =VLOOKUP(+BP55,'Datos Biyemas'!A9:BB145,34,0) -> #N/A | AI55: =VLOOKUP(+BP55,'Datos Biyemas'!A9:BB145,35,0) -> #N/A | AJ55: =+AI55/C55 -> #N/A | AK55: =VLOOKUP(+BP55,'Datos Biyemas'!A9:BB145,37,0) -> #N/A | AL55: =VLOOKUP(+BP55,'Datos Biyemas'!A9:BB145,38,0) -> #N/A | AM55: =+AL55/C55 -> #N/A | AN55: =+AN54/Resumen!D1 -> #N/A | AO55: =VLOOKUP(+BP55,'Datos Biyemas'!A9:BF145,40,0) -> #N/A | AP55: =+AO55/AN55 -> #N/A | AV55: =VLOOKUP(+BP55,'Datos Biyemas'!A9:BF145,47,0) -> #N/A | AW55: =+AV55/C55 -> #N/A | BB55: MTD average: | BE55: =+AV55 -> #N/A | BF55: =+AD55 -> #N/A | BG55: =+AI55 -> #N/A | BH55: =+AL55 -> #N/A | BI55: =+AO55 -> #N/A | BJ55: =+BE55 -> #N/A | BK55: =+BF55 -> #N/A | BL55: =+BG55 -> #N/A | BM55: =+BH55 -> #N/A | BN55: =+BI55 -> #N/A | BP55: MTD average anio ant.
BB56: Dev from budget: | BE56: =VLOOKUP(+BP56,'Datos Biyemas'!AY4:BG171,4,0) -> #N/A | BF56: =VLOOKUP(+BP56,'Datos Biyemas'!AY4:BG171,5,0) -> #N/A | BG56: =VLOOKUP(+BP56,'Datos Biyemas'!AY4:BG171,6,0) -> #N/A | BH56: =VLOOKUP(+BP56,'Datos Biyemas'!AY4:BG171,7,0) -> #N/A | BI56: =VLOOKUP(+BP56,'Datos Biyemas'!AY4:BG171,8,0) -> #N/A | BJ56: =VLOOKUP(+BP56,'Datos Biyemas'!AY4:BG171,9,0) -> #N/A | BK56: =VLOOKUP(+BP56,'Datos Biyemas'!AY4:BH171,10,0) -> #N/A | BL56: =VLOOKUP(+BP56,'Datos Biyemas'!AY4:BG171,11,0) -> #N/A | BM56: =VLOOKUP(+BP56,'Datos Biyemas'!AY4:BG171,12,0) -> #N/A | BN56: =VLOOKUP(+BP56,'Datos Biyemas'!AY4:BG171,13,0) -> #N/A | BP56: Dev from budget anio ant.
A57: ▲ Prom diario % | C57: =(+C40-C55)/C55 -> #N/A | E57: =(+E40-E55)/E55 -> #N/A | F57: =(+F40-F55)/F55 -> #N/A | G57: =(+G40-G55)/G55 -> #N/A | K57: =(+K40-K55)/K55 -> #N/A | M57: =(+M40-M55)/M55 -> #N/A | N57: =(+N40-N55)/N55 -> #N/A | O57: =(+O40-O55)/O55 -> #N/A | S57: =(+S40-S55)/S55 -> #N/A | T57: =(+T40-T55)/T55 -> #DIV/0! | U57: =(+U40-U55)/U55 -> #DIV/0! | W57: =(+W40-W55)/W55 -> #N/A | X57: =(+X40-X55)/X55 -> #N/A | Y57: =(+Y40-Y55)/Y55 -> #N/A | AD57: =(+AD40-AD55)/AD55 -> #N/A | AE57: =(+AE40-AE55)/AE55 -> #N/A | AF57: =(+AF40-AF55)/AF55 -> #N/A | AG57: =(+AG40-AG55)/AG55 -> #N/A | AH57: =(+AH40-AH55)/AH55 -> #N/A | AI57: =(+AI40-AI55)/AI55 -> #N/A | AK57: =(+AK40-AK55)/AK55 -> #N/A | AL57: =(+AL40-AL55)/AL55 -> #N/A | AN57: =(+AN40-AN55)/AN55 -> #DIV/0! | AO57: =(+AO40-AO55)/AO55 -> #N/A | AV57: =(+AV40-AV55)/AV55 -> #N/A
A58: ▲ Prom diario $ | E58: =+E40-E55 -> #N/A | F58: =+F40-F55 -> #N/A | G58: =+G40-G55 -> #N/A | K58: =+K40-K55 -> #N/A | M58: =+M40-M55 -> #N/A | N58: =+N40-N55 -> #N/A | O58: =+O40-O55 -> #N/A | S58: =+S40-S55 -> #N/A | T58: =+T40-T55 -> #DIV/0! | U58: =+U40-U55 -> #DIV/0! | W58: =+W40-W55 -> #N/A | X58: =+X40-X55 -> #N/A | Y58: =+Y40-Y55 -> #N/A | AD58: =+AD40-AD55 -> #N/A | AE58: =+AE40-AE55 -> #N/A | AF58: =+AF40-AF55 -> #N/A | AG58: =+AG40-AG55 -> #N/A | AH58: =+AH40-AH55 -> #N/A | AI58: =+AI40-AI55 -> #N/A | AK58: =+AK40-AK55 -> #N/A | AL58: =+AL40-AL55 -> #N/A | AN58: =+AN40-AN55 -> #DIV/0! | AO58: =+AO40-AO55 -> #N/A | AV58: =+AV40-AV55 -> #N/A

Sheet Kandiko S.A
A1: KANDIKO S.A. | C1: DIA | D1: =COUNT(C7:C37) -> 0
A3: =+'Biyemas S.A.'!A3 -> Reporte Flash Agosto 26
D4: SLOTS | L4: ELECTRONIC ROULLETTE - ON LINE | T4: Win | U4: Total | V4: MAQUINA POKER | AD4: On line | AE4: Win | AG4: BINGO | AL4: FOOD & BEVERAGE | AN4: PARKING | AQ4: EGA | AY4: Positions | BA4: Customers | BC4: Vehicles | BE4: Revenues vs. Budget (w/seasonality) | BJ4: Revenues
D5: ON LINE | O5: on line | P5: % win/ | Q5: % win/ | T5: (Slot + RE) | U5: electronic | V5: ON LINE | AD5: Electronic | AE5: Financial | AF5: Difference | AG5: nº | AI5: Net | AK5: Total | AV5: TOTAL NET | AY5: on line | AZ5: vs. Budget | BA5: Budget | BB5: Deviation | BC5: Budget | BD5: Deviation | BE5: Total | BF5: Electronic | BG5: Bingo | BH5: F&B | BI5: Parking | BJ5: Total | BK5: Electronic | BL5: Bingo | BM5: F&B | BN5: Parking
A6: Day | B6: Fecha | C6: Custom. | D6: Units | E6: Coin in | F6: Drop | G6: Win | H6: coin in | I6: Drop | J6: /Cust. | K6: /Units. | L6: Seats | M6: Coin in | N6: Drop | O6: Win | P6: coin in | Q6: Drop | R6: /Cust. | S6: /Seat | T6: / Stand | U6: positions | V6: Units | W6: Coin in | X6: Drop | Y6: Win | Z6: coin in | AA6: Drop | AB6: /Cust. | AC6: /Units. | AD6: Win | AE6: Win | AG6: Cards | AH6: Sales | AI6: win | AJ6: /Cust. | AK6: Gaming | AL6: Sales | AM6: /Cust. | AN6: Vehicles | AO6: Sales | AP6: /Vehic | AQ6: Simulador | AR6: PlayStation | AS6: Arcade | AT6: Total EGA | AU6: Total PRM | AV6: REVENUES | AW6: /Cust. | AZ6: =+'Datos Kandiko'!AT8 -> 0 | BJ6: =+BK6+BL6+BM6+BN6 -> 0 | BK6: =+'Datos Kandiko'!BH8 -> 0 | BL6: =+'Datos Kandiko'!BD8 -> 0 | BM6: =+'Datos Kandiko'!BE8 -> 0 | BN6: 0
A7: =IF(BP7='Datos Kandiko'!A9,'Datos Kandiko'!A9,"") | B7: =IF(BP7=A7,'Datos Kandiko'!B9,"") | C7: =IF(BP7=A7,'Datos Kandiko'!C9,"") | D7: =IF(BP7=A7,VLOOKUP(B7,'Datos Kandiko'!B9:BB46,3,0),"") | E7: =IF(BP7=A7,VLOOKUP(B7,'Datos Kandiko'!B9:BB46,4,0),"") | F7: =IF(BP7=A7,VLOOKUP(B7,'Datos Kandiko'!B9:BB46,5,0),"") | G7: =IF(BP7=A7,VLOOKUP(B7,'Datos Kandiko'!B9:BB46,6,0),"") | H7: =IF(BP7=A7,IF(E7>0,+G7/E7,0),"") | I7: =IF(A7="","",IF(F7>0,+G7/F7,0)) | J7: =IF(A7="","",IF(G7>0,+G7/C7,0)) | K7: =IF(A7="","",IF(G7>0,+G7/D7,0)) | L7: =IF(A7="","",VLOOKUP(B7,'Datos Kandiko'!B9:BB46,11,0)) | M7: =IF(A7="","",VLOOKUP(B7,'Datos Kandiko'!B9:BB46,12,0)) | N7: =IF(A7="","",VLOOKUP(B7,'Datos Kandiko'!B9:BB46,13,0)) | O7: =IF(A7="","",VLOOKUP(B7,'Datos Kandiko'!B9:BB46,14,0)) | P7: =IF(A7="","",IF(M7>0,+O7/M7,0)) | Q7: =IF(A7="","",IF(N7>0,+O7/N7,0)) | R7: =IF(A7="","",IF(C7>0,+O7/C7,0)) | S7: =IF(A7="","",IF(C7>0,+O7/L7,0)) | T7: =IF(A7="","",IF(G7>0,(G7+O7)/(D7+L7),0)) | U7: =IF(A7="","",IF(D7>0,+L7+D7,0)) | V7: =IF(A7="","",VLOOKUP(B7,'Datos Kandiko'!B9:BB46,21,0)) | W7: =IF(A7="","",VLOOKUP(B7,'Datos Kandiko'!B9:BB46,22,0)) | X7: =IF(A7="","",VLOOKUP(B7,'Datos Kandiko'!B9:BB46,23,0)) | Y7: =IF(A7="","",VLOOKUP(B7,'Datos Kandiko'!B9:BB46,24,0)) | Z7: =IF(A7="","",IF(W7>0,+Y7/W7,0)) | AA7: =IF(A7="","",IF(X7>0,+Y7/X7,0)) | AB7: =IF(A7="","",IF(Y7>0,+Y7/K7,0)) | AC7: =IF(A7="","",IF(Y7>0,+Y7/V7,0)) | AD7: =IF(A7="","",+G7+O7+Y7) | AE7: =IF(A7="","",VLOOKUP(B7,'Datos Kandiko'!B9:BB46,30,0)) | AF7: =IF(A7="","",+AD7-AE7) | AG7: =IF(A7="","",VLOOKUP(B7,'Datos Kandiko'!B9:BB46,32,0)) | AH7: =IF(A7="","",VLOOKUP(B7,'Datos Kandiko'!B9:BB46,33,0)) | AI7: =IF(A7="","",VLOOKUP(B7,'Datos Kandiko'!B9:BB46,34,0)) | AJ7: =IF(A7="","",IF(AI7>0,+AI7/C7,0)) | AK7: =IF(A7="","",+G7+O7+AI7+Y7) | AL7: =IF(A7="","",VLOOKUP(B7,'Datos Kandiko'!B9:BB46,37,0)) | AM7: =IF(A7="","",IF(AL7>0,+AL7/C7,0)) | AN7: =IF(BP7=A7,'Datos Kandiko'!BL9,"") | AO7: =IF(A7="","",VLOOKUP(B7,'Datos Kandiko'!B9:BF46,39,0)) | AP7: =IF(A7="","",IF(AN7>0,+AO7/AN7,0)) | AQ7: =IF(A7="","",VLOOKUP(B7,'Datos Kandiko'!B9:BH46,41,0)) | AR7: =IF(A7="","",VLOOKUP(B7,'Datos Kandiko'!B9:BI46,42,0)) | AS7: =IF(A7="","",VLOOKUP(B7,'Datos Kandiko'!B9:BJ46,43,0)) | AT7: =IF(A7="","",VLOOKUP(B7,'Datos Kandiko'!B9:BK46,44,0)) | AV7: =IF(A7="","",+AD7+AI7+AL7+AO7) | AW7: =IF(A7="","",IF(AV7>0,+AV7/C7,0)) | AY7: =IF(A7="","",+'Datos Kandiko'!AY9) | AZ7: =IF(A7="","",IF($AZ$6>0,+AY7-$AZ$6,)) | BA7: =IF(A7="","",VLOOKUP(B7,'Datos Kandiko'!B9:BF46,51,0)) | BB7: =IF(A7="","",IF(BA7>0,(C7-BA7)/BA7,100%)) | BC7: =IF(BP7=A7,'Datos Kandiko'!BL9,"") | BD7: =IF(A7="","",IF(AN7=BC7,0,IF(BC7>0,(AN7-BC7)/BC7,1))) | BE7: =IF(A7="","",VLOOKUP(B7,'Datos Kandiko'!B9:BF46,53,0)) | BF7: =IF(A7="","",VLOOKUP(B7,'Datos Kandiko'!B9:BF46,54,0)) | BG7: =IF(A7="","",VLOOKUP(B7,'Datos Kandiko'!B9:BF46,55,0)) | BH7: =IF(A7="","",VLOOKUP(B7,'Datos Kandiko'!B9:BF46,51,0)) | BI7: =IF(A7="","",IF(VLOOKUP(B7,'Datos Kandiko'!B9:BF46,52,0)=0%,IF(AO7>1,1,VLOOKUP(B7,'Datos Kandiko'!B9:BF46,52,0)))) | BJ7: =IF(A7="","",VLOOKUP(B7,'Datos Kandiko'!B9:BH46,58,0)) | BK7: =IF(A7="","",VLOOKUP(B7,'Datos Kandiko'!B9:BH46,59,0)) | BL7: =IF(A7="","",VLOOKUP(B7,'Datos Kandiko'!B9:BF46,55,0)) | BM7: =IF(A7="","",VLOOKUP(B7,'Datos Kandiko'!B9:BF46,56,0)) | BN7: =IF(A7="","",IF(VLOOKUP(B7,'Datos Kandiko'!B9:BF46,57,0)=0,IF(AO7>1,1,VLOOKUP(B7,'Datos Kandiko'!B9:BF46,57,0)))) | BP7: =+'Biyemas S.A.'!BP7 -> Sab/Sat
A8: =IF(BP8='Datos Kandiko'!A10,'Datos Kandiko'!A10,"") | B8: =IF(BP8=A8,'Datos Kandiko'!B10,"") | C8: =IF(BP8=A8,'Datos Kandiko'!C10,"") | D8: =IF(BP8=A8,VLOOKUP(B8,'Datos Kandiko'!B10:BB47,3,0),"") | E8: =IF(BP8=A8,VLOOKUP(B8,'Datos Kandiko'!B10:BB47,4,0),"") | F8: =IF(BP8=A8,VLOOKUP(B8,'Datos Kandiko'!B10:BB47,5,0),"") | G8: =IF(BP8=A8,VLOOKUP(B8,'Datos Kandiko'!B10:BB47,6,0),"") | H8: =IF(BP8=A8,IF(E8>0,+G8/E8,0),"") | I8: =IF(A8="","",IF(F8>0,+G8/F8,0)) | J8: =IF(A8="","",IF(G8>0,+G8/C8,0)) | K8: =IF(A8="","",IF(G8>0,+G8/D8,0)) | L8: =IF(A8="","",VLOOKUP(B8,'Datos Kandiko'!B10:BB47,11,0)) | M8: =IF(A8="","",VLOOKUP(B8,'Datos Kandiko'!B10:BB47,12,0)) | N8: =IF(A8="","",VLOOKUP(B8,'Datos Kandiko'!B10:BB47,13,0)) | O8: =IF(A8="","",VLOOKUP(B8,'Datos Kandiko'!B10:BB47,14,0)) | P8: =IF(A8="","",IF(M8>0,+O8/M8,0)) | Q8: =IF(A8="","",IF(N8>0,+O8/N8,0)) | R8: =IF(A8="","",IF(C8>0,+O8/C8,0)) | S8: =IF(A8="","",IF(C8>0,+O8/L8,0)) | T8: =IF(A8="","",IF(G8>0,(G8+O8)/(D8+L8),0)) | U8: =IF(A8="","",IF(D8>0,+L8+D8,0)) | V8: =IF(A8="","",VLOOKUP(B8,'Datos Kandiko'!B10:BB47,21,0)) | W8: =IF(A8="","",VLOOKUP(B8,'Datos Kandiko'!B10:BB47,22,0)) | X8: =IF(A8="","",VLOOKUP(B8,'Datos Kandiko'!B10:BB47,23,0)) | Y8: =IF(A8="","",VLOOKUP(B8,'Datos Kandiko'!B10:BB47,24,0)) | Z8: =IF(A8="","",IF(W8>0,+Y8/W8,0)) | AA8: =IF(A8="","",IF(X8>0,+Y8/X8,0)) | AB8: =IF(A8="","",IF(Y8>0,+Y8/K8,0)) | AC8: =IF(A8="","",IF(Y8>0,+Y8/V8,0)) | AD8: =IF(A8="","",+G8+O8+Y8) | AE8: =IF(A8="","",VLOOKUP(B8,'Datos Kandiko'!B10:BB47,30,0)) | AF8: =IF(A8="","",+AD8-AE8) | AG8: =IF(A8="","",VLOOKUP(B8,'Datos Kandiko'!B10:BB47,32,0)) | AH8: =IF(A8="","",VLOOKUP(B8,'Datos Kandiko'!B10:BB47,33,0)) | AI8: =IF(A8="","",VLOOKUP(B8,'Datos Kandiko'!B10:BB47,34,0)) | AJ8: =IF(A8="","",IF(AI8>0,+AI8/C8,0)) | AK8: =IF(A8="","",+G8+O8+AI8+Y8) | AL8: =IF(A8="","",VLOOKUP(B8,'Datos Kandiko'!B10:BB47,37,0)) | AM8: =IF(A8="","",IF(AL8>0,+AL8/C8,0)) | AN8: =IF(BP8=A8,'Datos Kandiko'!BL10,"") | AO8: =IF(A8="","",VLOOKUP(B8,'Datos Kandiko'!B10:BF47,39,0)) | AP8: =IF(A8="","",IF(AN8>0,+AO8/AN8,0)) | AQ8: =IF(A8="","",VLOOKUP(B8,'Datos Kandiko'!B10:BH47,41,0)) | AR8: =IF(A8="","",VLOOKUP(B8,'Datos Kandiko'!B10:BI47,42,0)) | AS8: =IF(A8="","",VLOOKUP(B8,'Datos Kandiko'!B10:BJ47,43,0)) | AT8: =IF(A8="","",VLOOKUP(B8,'Datos Kandiko'!B10:BK47,44,0)) | AV8: =IF(A8="","",+AD8+AI8+AL8+AO8) | AW8: =IF(A8="","",IF(AV8>0,+AV8/C8,0)) | AY8: =IF(A8="","",+'Datos Kandiko'!AY10) | AZ8: =IF(A8="","",IF($AZ$6>0,+AY8-$AZ$6,)) | BA8: =IF(A8="","",VLOOKUP(B8,'Datos Kandiko'!B10:BF47,51,0)) | BB8: =IF(A8="","",IF(BA8>0,(C8-BA8)/BA8,100%)) | BC8: =IF(BP8=A8,'Datos Kandiko'!BL10,"") | BD8: =IF(A8="","",IF(AN8=BC8,0,IF(BC8>0,(AN8-BC8)/BC8,1))) | BE8: =IF(A8="","",VLOOKUP(B8,'Datos Kandiko'!B10:BF47,53,0)) | BF8: =IF(A8="","",VLOOKUP(B8,'Datos Kandiko'!B10:BF47,54,0)) | BG8: =IF(A8="","",VLOOKUP(B8,'Datos Kandiko'!B10:BF47,55,0)) | BH8: =IF(A8="","",VLOOKUP(B8,'Datos Kandiko'!B10:BF47,51,0)) | BI8: =IF(A8="","",IF(VLOOKUP(B8,'Datos Kandiko'!B10:BF47,52,0)=0%,IF(AO8>1,1,VLOOKUP(B8,'Datos Kandiko'!B10:BF47,52,0)))) | BJ8: =IF(A8="","",VLOOKUP(B8,'Datos Kandiko'!B10:BH47,58,0)) | BK8: =IF(A8="","",VLOOKUP(B8,'Datos Kandiko'!B10:BH47,59,0)) | BL8: =IF(A8="","",VLOOKUP(B8,'Datos Kandiko'!B10:BF47,55,0)) | BM8: =IF(A8="","",VLOOKUP(B8,'Datos Kandiko'!B10:BF47,56,0)) | BN8: =IF(A8="","",IF(VLOOKUP(B8,'Datos Kandiko'!B10:BF47,57,0)=0,IF(AO8>1,1,VLOOKUP(B8,'Datos Kandiko'!B10:BF47,57,0)))) | BP8: =+'Biyemas S.A.'!BP8 -> Dom/Sun
A9: =IF(BP9='Datos Kandiko'!A11,'Datos Kandiko'!A11,"") | B9: =IF(BP9=A9,'Datos Kandiko'!B11,"") | C9: =IF(BP9=A9,'Datos Kandiko'!C11,"") | D9: =IF(BP9=A9,VLOOKUP(B9,'Datos Kandiko'!B11:BB48,3,0),"") | E9: =IF(BP9=A9,VLOOKUP(B9,'Datos Kandiko'!B11:BB48,4,0),"") | F9: =IF(BP9=A9,VLOOKUP(B9,'Datos Kandiko'!B11:BB48,5,0),"") | G9: =IF(BP9=A9,VLOOKUP(B9,'Datos Kandiko'!B11:BB48,6,0),"") | H9: =IF(BP9=A9,IF(E9>0,+G9/E9,0),"") | I9: =IF(A9="","",IF(F9>0,+G9/F9,0)) | J9: =IF(A9="","",IF(G9>0,+G9/C9,0)) | K9: =IF(A9="","",IF(G9>0,+G9/D9,0)) | L9: =IF(A9="","",VLOOKUP(B9,'Datos Kandiko'!B11:BB48,11,0)) | M9: =IF(A9="","",VLOOKUP(B9,'Datos Kandiko'!B11:BB48,12,0)) | N9: =IF(A9="","",VLOOKUP(B9,'Datos Kandiko'!B11:BB48,13,0)) | O9: =IF(A9="","",VLOOKUP(B9,'Datos Kandiko'!B11:BB48,14,0)) | P9: =IF(A9="","",IF(M9>0,+O9/M9,0)) | Q9: =IF(A9="","",IF(N9>0,+O9/N9,0)) | R9: =IF(A9="","",IF(C9>0,+O9/C9,0)) | S9: =IF(A9="","",IF(C9>0,+O9/L9,0)) | T9: =IF(A9="","",IF(G9>0,(G9+O9)/(D9+L9),0)) | U9: =IF(A9="","",IF(D9>0,+L9+D9,0)) | V9: =IF(A9="","",VLOOKUP(B9,'Datos Kandiko'!B11:BB48,21,0)) | W9: =IF(A9="","",VLOOKUP(B9,'Datos Kandiko'!B11:BB48,22,0)) | X9: =IF(A9="","",VLOOKUP(B9,'Datos Kandiko'!B11:BB48,23,0)) | Y9: =IF(A9="","",VLOOKUP(B9,'Datos Kandiko'!B11:BB48,24,0)) | Z9: =IF(A9="","",IF(W9>0,+Y9/W9,0)) | AA9: =IF(A9="","",IF(X9>0,+Y9/X9,0)) | AB9: =IF(A9="","",IF(Y9>0,+Y9/K9,0)) | AC9: =IF(A9="","",IF(Y9>0,+Y9/V9,0)) | AD9: =IF(A9="","",+G9+O9+Y9) | AE9: =IF(A9="","",VLOOKUP(B9,'Datos Kandiko'!B11:BB48,30,0)) | AF9: =IF(A9="","",+AD9-AE9) | AG9: =IF(A9="","",VLOOKUP(B9,'Datos Kandiko'!B11:BB48,32,0)) | AH9: =IF(A9="","",VLOOKUP(B9,'Datos Kandiko'!B11:BB48,33,0)) | AI9: =IF(A9="","",VLOOKUP(B9,'Datos Kandiko'!B11:BB48,34,0)) | AJ9: =IF(A9="","",IF(AI9>0,+AI9/C9,0)) | AK9: =IF(A9="","",+G9+O9+AI9+Y9) | AL9: =IF(A9="","",VLOOKUP(B9,'Datos Kandiko'!B11:BB48,37,0)) | AM9: =IF(A9="","",IF(AL9>0,+AL9/C9,0)) | AN9: =IF(BP9=A9,'Datos Kandiko'!BL11,"") | AO9: =IF(A9="","",VLOOKUP(B9,'Datos Kandiko'!B11:BF48,39,0)) | AP9: =IF(A9="","",IF(AN9>0,+AO9/AN9,0)) | AQ9: =IF(A9="","",VLOOKUP(B9,'Datos Kandiko'!B11:BH48,41,0)) | AR9: =IF(A9="","",VLOOKUP(B9,'Datos Kandiko'!B11:BI48,42,0)) | AS9: =IF(A9="","",VLOOKUP(B9,'Datos Kandiko'!B11:BJ48,43,0)) | AT9: =IF(A9="","",VLOOKUP(B9,'Datos Kandiko'!B11:BK48,44,0)) | AV9: =IF(A9="","",+AD9+AI9+AL9+AO9) | AW9: =IF(A9="","",IF(AV9>0,+AV9/C9,0)) | AY9: =IF(A9="","",+'Datos Kandiko'!AY11) | AZ9: =IF(A9="","",IF($AZ$6>0,+AY9-$AZ$6,)) | BA9: =IF(A9="","",VLOOKUP(B9,'Datos Kandiko'!B11:BF48,51,0)) | BB9: =IF(A9="","",IF(BA9>0,(C9-BA9)/BA9,100%)) | BC9: =IF(BP9=A9,'Datos Kandiko'!BL11,"") | BD9: =IF(A9="","",IF(AN9=BC9,0,IF(BC9>0,(AN9-BC9)/BC9,1))) | BE9: =IF(A9="","",VLOOKUP(B9,'Datos Kandiko'!B11:BF48,53,0)) | BF9: =IF(A9="","",VLOOKUP(B9,'Datos Kandiko'!B11:BF48,54,0)) | BG9: =IF(A9="","",VLOOKUP(B9,'Datos Kandiko'!B11:BF48,55,0)) | BH9: =IF(A9="","",VLOOKUP(B9,'Datos Kandiko'!B11:BF48,51,0)) | BI9: =IF(A9="","",IF(VLOOKUP(B9,'Datos Kandiko'!B11:BF48,52,0)=0%,IF(AO9>1,1,VLOOKUP(B9,'Datos Kandiko'!B11:BF48,52,0)))) | BJ9: =IF(A9="","",VLOOKUP(B9,'Datos Kandiko'!B11:BH48,58,0)) | BK9: =IF(A9="","",VLOOKUP(B9,'Datos Kandiko'!B11:BH48,59,0)) | BL9: =IF(A9="","",VLOOKUP(B9,'Datos Kandiko'!B11:BF48,55,0)) | BM9: =IF(A9="","",VLOOKUP(B9,'Datos Kandiko'!B11:BF48,56,0)) | BN9: =IF(A9="","",IF(VLOOKUP(B9,'Datos Kandiko'!B11:BF48,57,0)=0,IF(AO9>1,1,VLOOKUP(B9,'Datos Kandiko'!B11:BF48,57,0)))) | BP9: =+'Biyemas S.A.'!BP9 -> Lun/Mon
A10: =IF(BP10='Datos Kandiko'!A12,'Datos Kandiko'!A12,"") | B10: =IF(BP10=A10,'Datos Kandiko'!B12,"") | C10: =IF(BP10=A10,'Datos Kandiko'!C12,"") | D10: =IF(BP10=A10,VLOOKUP(B10,'Datos Kandiko'!B12:BB49,3,0),"") | E10: =IF(BP10=A10,VLOOKUP(B10,'Datos Kandiko'!B12:BB49,4,0),"") | F10: =IF(BP10=A10,VLOOKUP(B10,'Datos Kandiko'!B12:BB49,5,0),"") | G10: =IF(BP10=A10,VLOOKUP(B10,'Datos Kandiko'!B12:BB49,6,0),"") | H10: =IF(BP10=A10,IF(E10>0,+G10/E10,0),"") | I10: =IF(A10="","",IF(F10>0,+G10/F10,0)) | J10: =IF(A10="","",IF(G10>0,+G10/C10,0)) | K10: =IF(A10="","",IF(G10>0,+G10/D10,0)) | L10: =IF(A10="","",VLOOKUP(B10,'Datos Kandiko'!B12:BB49,11,0)) | M10: =IF(A10="","",VLOOKUP(B10,'Datos Kandiko'!B12:BB49,12,0)) | N10: =IF(A10="","",VLOOKUP(B10,'Datos Kandiko'!B12:BB49,13,0)) | O10: =IF(A10="","",VLOOKUP(B10,'Datos Kandiko'!B12:BB49,14,0)) | P10: =IF(A10="","",IF(M10>0,+O10/M10,0)) | Q10: =IF(A10="","",IF(N10>0,+O10/N10,0)) | R10: =IF(A10="","",IF(C10>0,+O10/C10,0)) | S10: =IF(A10="","",IF(C10>0,+O10/L10,0)) | T10: =IF(A10="","",IF(G10>0,(G10+O10)/(D10+L10),0)) | U10: =IF(A10="","",IF(D10>0,+L10+D10,0)) | V10: =IF(A10="","",VLOOKUP(B10,'Datos Kandiko'!B12:BB49,21,0)) | W10: =IF(A10="","",VLOOKUP(B10,'Datos Kandiko'!B12:BB49,22,0)) | X10: =IF(A10="","",VLOOKUP(B10,'Datos Kandiko'!B12:BB49,23,0)) | Y10: =IF(A10="","",VLOOKUP(B10,'Datos Kandiko'!B12:BB49,24,0)) | Z10: =IF(A10="","",IF(W10>0,+Y10/W10,0)) | AA10: =IF(A10="","",IF(X10>0,+Y10/X10,0)) | AB10: =IF(A10="","",IF(Y10>0,+Y10/K10,0)) | AC10: =IF(A10="","",IF(Y10>0,+Y10/V10,0)) | AD10: =IF(A10="","",+G10+O10+Y10) | AE10: =IF(A10="","",VLOOKUP(B10,'Datos Kandiko'!B12:BB49,30,0)) | AF10: =IF(A10="","",+AD10-AE10) | AG10: =IF(A10="","",VLOOKUP(B10,'Datos Kandiko'!B12:BB49,32,0)) | AH10: =IF(A10="","",VLOOKUP(B10,'Datos Kandiko'!B12:BB49,33,0)) | AI10: =IF(A10="","",VLOOKUP(B10,'Datos Kandiko'!B12:BB49,34,0)) | AJ10: =IF(A10="","",IF(AI10>0,+AI10/C10,0)) | AK10: =IF(A10="","",+G10+O10+AI10+Y10) | AL10: =IF(A10="","",VLOOKUP(B10,'Datos Kandiko'!B12:BB49,37,0)) | AM10: =IF(A10="","",IF(AL10>0,+AL10/C10,0)) | AN10: =IF(BP10=A10,'Datos Kandiko'!BL12,"") | AO10: =IF(A10="","",VLOOKUP(B10,'Datos Kandiko'!B12:BF49,39,0)) | AP10: =IF(A10="","",IF(AN10>0,+AO10/AN10,0)) | AQ10: =IF(A10="","",VLOOKUP(B10,'Datos Kandiko'!B12:BH49,41,0)) | AR10: =IF(A10="","",VLOOKUP(B10,'Datos Kandiko'!B12:BI49,42,0)) | AS10: =IF(A10="","",VLOOKUP(B10,'Datos Kandiko'!B12:BJ49,43,0)) | AT10: =IF(A10="","",VLOOKUP(B10,'Datos Kandiko'!B12:BK49,44,0)) | AV10: =IF(A10="","",+AD10+AI10+AL10+AO10) | AW10: =IF(A10="","",IF(AV10>0,+AV10/C10,0)) | AY10: =IF(A10="","",+'Datos Kandiko'!AY12) | AZ10: =IF(A10="","",IF($AZ$6>0,+AY10-$AZ$6,)) | BA10: =IF(A10="","",VLOOKUP(B10,'Datos Kandiko'!B12:BF49,51,0)) | BB10: =IF(A10="","",IF(BA10>0,(C10-BA10)/BA10,100%)) | BC10: =IF(BP10=A10,'Datos Kandiko'!BL12,"") | BD10: =IF(A10="","",IF(AN10=BC10,0,IF(BC10>0,(AN10-BC10)/BC10,1))) | BE10: =IF(A10="","",VLOOKUP(B10,'Datos Kandiko'!B12:BF49,53,0)) | BF10: =IF(A10="","",VLOOKUP(B10,'Datos Kandiko'!B12:BF49,54,0)) | BG10: =IF(A10="","",VLOOKUP(B10,'Datos Kandiko'!B12:BF49,55,0)) | BH10: =IF(A10="","",VLOOKUP(B10,'Datos Kandiko'!B12:BF49,51,0)) | BI10: =IF(A10="","",IF(VLOOKUP(B10,'Datos Kandiko'!B12:BF49,52,0)=0%,IF(AO10>1,1,VLOOKUP(B10,'Datos Kandiko'!B12:BF49,52,0)))) | BJ10: =IF(A10="","",VLOOKUP(B10,'Datos Kandiko'!B12:BH49,58,0)) | BK10: =IF(A10="","",VLOOKUP(B10,'Datos Kandiko'!B12:BH49,59,0)) | BL10: =IF(A10="","",VLOOKUP(B10,'Datos Kandiko'!B12:BF49,55,0)) | BM10: =IF(A10="","",VLOOKUP(B10,'Datos Kandiko'!B12:BF49,56,0)) | BN10: =IF(A10="","",IF(VLOOKUP(B10,'Datos Kandiko'!B12:BF49,57,0)=0,IF(AO10>1,1,VLOOKUP(B10,'Datos Kandiko'!B12:BF49,57,0)))) | BP10: =+'Biyemas S.A.'!BP10 -> Mar/Tue
A11: =IF(BP11='Datos Kandiko'!A13,'Datos Kandiko'!A13,"") | B11: =IF(BP11=A11,'Datos Kandiko'!B13,"") | C11: =IF(BP11=A11,'Datos Kandiko'!C13,"") | D11: =IF(BP11=A11,VLOOKUP(B11,'Datos Kandiko'!B13:BB50,3,0),"") | E11: =IF(BP11=A11,VLOOKUP(B11,'Datos Kandiko'!B13:BB50,4,0),"") | F11: =IF(BP11=A11,VLOOKUP(B11,'Datos Kandiko'!B13:BB50,5,0),"") | G11: =IF(BP11=A11,VLOOKUP(B11,'Datos Kandiko'!B13:BB50,6,0),"") | H11: =IF(BP11=A11,IF(E11>0,+G11/E11,0),"") | I11: =IF(A11="","",IF(F11>0,+G11/F11,0)) | J11: =IF(A11="","",IF(G11>0,+G11/C11,0)) | K11: =IF(A11="","",IF(G11>0,+G11/D11,0)) | L11: =IF(A11="","",VLOOKUP(B11,'Datos Kandiko'!B13:BB50,11,0)) | M11: =IF(A11="","",VLOOKUP(B11,'Datos Kandiko'!B13:BB50,12,0)) | N11: =IF(A11="","",VLOOKUP(B11,'Datos Kandiko'!B13:BB50,13,0)) | O11: =IF(A11="","",VLOOKUP(B11,'Datos Kandiko'!B13:BB50,14,0)) | P11: =IF(A11="","",IF(M11>0,+O11/M11,0)) | Q11: =IF(A11="","",IF(N11>0,+O11/N11,0)) | R11: =IF(A11="","",IF(C11>0,+O11/C11,0)) | S11: =IF(A11="","",IF(C11>0,+O11/L11,0)) | T11: =IF(A11="","",IF(G11>0,(G11+O11)/(D11+L11),0)) | U11: =IF(A11="","",IF(D11>0,+L11+D11,0)) | V11: =IF(A11="","",VLOOKUP(B11,'Datos Kandiko'!B13:BB50,21,0)) | W11: =IF(A11="","",VLOOKUP(B11,'Datos Kandiko'!B13:BB50,22,0)) | X11: =IF(A11="","",VLOOKUP(B11,'Datos Kandiko'!B13:BB50,23,0)) | Y11: =IF(A11="","",VLOOKUP(B11,'Datos Kandiko'!B13:BB50,24,0)) | Z11: =IF(A11="","",IF(W11>0,+Y11/W11,0)) | AA11: =IF(A11="","",IF(X11>0,+Y11/X11,0)) | AB11: =IF(A11="","",IF(Y11>0,+Y11/K11,0)) | AC11: =IF(A11="","",IF(Y11>0,+Y11/V11,0)) | AD11: =IF(A11="","",+G11+O11+Y11) | AE11: =IF(A11="","",VLOOKUP(B11,'Datos Kandiko'!B13:BB50,30,0)) | AF11: =IF(A11="","",+AD11-AE11) | AG11: =IF(A11="","",VLOOKUP(B11,'Datos Kandiko'!B13:BB50,32,0)) | AH11: =IF(A11="","",VLOOKUP(B11,'Datos Kandiko'!B13:BB50,33,0)) | AI11: =IF(A11="","",VLOOKUP(B11,'Datos Kandiko'!B13:BB50,34,0)) | AJ11: =IF(A11="","",IF(AI11>0,+AI11/C11,0)) | AK11: =IF(A11="","",+G11+O11+AI11+Y11) | AL11: =IF(A11="","",VLOOKUP(B11,'Datos Kandiko'!B13:BB50,37,0)) | AM11: =IF(A11="","",IF(AL11>0,+AL11/C11,0)) | AN11: =IF(BP11=A11,'Datos Kandiko'!BL13,"") | AO11: =IF(A11="","",VLOOKUP(B11,'Datos Kandiko'!B13:BF50,39,0)) | AP11: =IF(A11="","",IF(AN11>0,+AO11/AN11,0)) | AQ11: =IF(A11="","",VLOOKUP(B11,'Datos Kandiko'!B13:BH50,41,0)) | AR11: =IF(A11="","",VLOOKUP(B11,'Datos Kandiko'!B13:BI50,42,0)) | AS11: =IF(A11="","",VLOOKUP(B11,'Datos Kandiko'!B13:BJ50,43,0)) | AT11: =IF(A11="","",VLOOKUP(B11,'Datos Kandiko'!B13:BK50,44,0)) | AV11: =IF(A11="","",+AD11+AI11+AL11+AO11) | AW11: =IF(A11="","",IF(AV11>0,+AV11/C11,0)) | AY11: =IF(A11="","",+'Datos Kandiko'!AY13) | AZ11: =IF(A11="","",IF($AZ$6>0,+AY11-$AZ$6,)) | BA11: =IF(A11="","",VLOOKUP(B11,'Datos Kandiko'!B13:BF50,51,0)) | BB11: =IF(A11="","",IF(BA11>0,(C11-BA11)/BA11,100%)) | BC11: =IF(BP11=A11,'Datos Kandiko'!BL13,"") | BD11: =IF(A11="","",IF(AN11=BC11,0,IF(BC11>0,(AN11-BC11)/BC11,1))) | BE11: =IF(A11="","",VLOOKUP(B11,'Datos Kandiko'!B13:BF50,53,0)) | BF11: =IF(A11="","",VLOOKUP(B11,'Datos Kandiko'!B13:BF50,54,0)) | BG11: =IF(A11="","",VLOOKUP(B11,'Datos Kandiko'!B13:BF50,55,0)) | BH11: =IF(A11="","",VLOOKUP(B11,'Datos Kandiko'!B13:BF50,51,0)) | BI11: =IF(A11="","",IF(VLOOKUP(B11,'Datos Kandiko'!B13:BF50,52,0)=0%,IF(AO11>1,1,VLOOKUP(B11,'Datos Kandiko'!B13:BF50,52,0)))) | BJ11: =IF(A11="","",VLOOKUP(B11,'Datos Kandiko'!B13:BH50,58,0)) | BK11: =IF(A11="","",VLOOKUP(B11,'Datos Kandiko'!B13:BH50,59,0)) | BL11: =IF(A11="","",VLOOKUP(B11,'Datos Kandiko'!B13:BF50,55,0)) | BM11: =IF(A11="","",VLOOKUP(B11,'Datos Kandiko'!B13:BF50,56,0)) | BN11: =IF(A11="","",IF(VLOOKUP(B11,'Datos Kandiko'!B13:BF50,57,0)=0,IF(AO11>1,1,VLOOKUP(B11,'Datos Kandiko'!B13:BF50,57,0)))) | BP11: =+'Biyemas S.A.'!BP11 -> Mie/Wed
A12: =IF(BP12='Datos Kandiko'!A14,'Datos Kandiko'!A14,"") | B12: =IF(BP12=A12,'Datos Kandiko'!B14,"") | C12: =IF(BP12=A12,'Datos Kandiko'!C14,"") | D12: =IF(BP12=A12,VLOOKUP(B12,'Datos Kandiko'!B14:BB51,3,0),"") | E12: =IF(BP12=A12,VLOOKUP(B12,'Datos Kandiko'!B14:BB51,4,0),"") | F12: =IF(BP12=A12,VLOOKUP(B12,'Datos Kandiko'!B14:BB51,5,0),"") | G12: =IF(BP12=A12,VLOOKUP(B12,'Datos Kandiko'!B14:BB51,6,0),"") | H12: =IF(BP12=A12,IF(E12>0,+G12/E12,0),"") | I12: =IF(A12="","",IF(F12>0,+G12/F12,0)) | J12: =IF(A12="","",IF(G12>0,+G12/C12,0)) | K12: =IF(A12="","",IF(G12>0,+G12/D12,0)) | L12: =IF(A12="","",VLOOKUP(B12,'Datos Kandiko'!B14:BB51,11,0)) | M12: =IF(A12="","",VLOOKUP(B12,'Datos Kandiko'!B14:BB51,12,0)) | N12: =IF(A12="","",VLOOKUP(B12,'Datos Kandiko'!B14:BB51,13,0)) | O12: =IF(A12="","",VLOOKUP(B12,'Datos Kandiko'!B14:BB51,14,0)) | P12: =IF(A12="","",IF(M12>0,+O12/M12,0)) | Q12: =IF(A12="","",IF(N12>0,+O12/N12,0)) | R12: =IF(A12="","",IF(C12>0,+O12/C12,0)) | S12: =IF(A12="","",IF(C12>0,+O12/L12,0)) | T12: =IF(A12="","",IF(G12>0,(G12+O12)/(D12+L12),0)) | U12: =IF(A12="","",IF(D12>0,+L12+D12,0)) | V12: =IF(A12="","",VLOOKUP(B12,'Datos Kandiko'!B14:BB51,21,0)) | W12: =IF(A12="","",VLOOKUP(B12,'Datos Kandiko'!B14:BB51,22,0)) | X12: =IF(A12="","",VLOOKUP(B12,'Datos Kandiko'!B14:BB51,23,0)) | Y12: =IF(A12="","",VLOOKUP(B12,'Datos Kandiko'!B14:BB51,24,0)) | Z12: =IF(A12="","",IF(W12>0,+Y12/W12,0)) | AA12: =IF(A12="","",IF(X12>0,+Y12/X12,0)) | AB12: =IF(A12="","",IF(Y12>0,+Y12/K12,0)) | AC12: =IF(A12="","",IF(Y12>0,+Y12/V12,0)) | AD12: =IF(A12="","",+G12+O12+Y12) | AE12: =IF(A12="","",VLOOKUP(B12,'Datos Kandiko'!B14:BB51,30,0)) | AF12: =IF(A12="","",+AD12-AE12) | AG12: =IF(A12="","",VLOOKUP(B12,'Datos Kandiko'!B14:BB51,32,0)) | AH12: =IF(A12="","",VLOOKUP(B12,'Datos Kandiko'!B14:BB51,33,0)) | AI12: =IF(A12="","",VLOOKUP(B12,'Datos Kandiko'!B14:BB51,34,0)) | AJ12: =IF(A12="","",IF(AI12>0,+AI12/C12,0)) | AK12: =IF(A12="","",+G12+O12+AI12+Y12) | AL12: =IF(A12="","",VLOOKUP(B12,'Datos Kandiko'!B14:BB51,37,0)) | AM12: =IF(A12="","",IF(AL12>0,+AL12/C12,0)) | AN12: =IF(BP12=A12,'Datos Kandiko'!BL14,"") | AO12: =IF(A12="","",VLOOKUP(B12,'Datos Kandiko'!B14:BF51,39,0)) | AP12: =IF(A12="","",IF(AN12>0,+AO12/AN12,0)) | AQ12: =IF(A12="","",VLOOKUP(B12,'Datos Kandiko'!B14:BH51,41,0)) | AR12: =IF(A12="","",VLOOKUP(B12,'Datos Kandiko'!B14:BI51,42,0)) | AS12: =IF(A12="","",VLOOKUP(B12,'Datos Kandiko'!B14:BJ51,43,0)) | AT12: =IF(A12="","",VLOOKUP(B12,'Datos Kandiko'!B14:BK51,44,0)) | AV12: =IF(A12="","",+AD12+AI12+AL12+AO12) | AW12: =IF(A12="","",IF(AV12>0,+AV12/C12,0)) | AY12: =IF(A12="","",+'Datos Kandiko'!AY14) | AZ12: =IF(A12="","",IF($AZ$6>0,+AY12-$AZ$6,)) | BA12: =IF(A12="","",VLOOKUP(B12,'Datos Kandiko'!B14:BF51,51,0)) | BB12: =IF(A12="","",IF(BA12>0,(C12-BA12)/BA12,100%)) | BC12: =IF(BP12=A12,'Datos Kandiko'!BL14,"") | BD12: =IF(A12="","",IF(AN12=BC12,0,IF(BC12>0,(AN12-BC12)/BC12,1))) | BE12: =IF(A12="","",VLOOKUP(B12,'Datos Kandiko'!B14:BF51,53,0)) | BF12: =IF(A12="","",VLOOKUP(B12,'Datos Kandiko'!B14:BF51,54,0)) | BG12: =IF(A12="","",VLOOKUP(B12,'Datos Kandiko'!B14:BF51,55,0)) | BH12: =IF(A12="","",VLOOKUP(B12,'Datos Kandiko'!B14:BF51,51,0)) | BI12: =IF(A12="","",IF(VLOOKUP(B12,'Datos Kandiko'!B14:BF51,52,0)=0%,IF(AO12>1,1,VLOOKUP(B12,'Datos Kandiko'!B14:BF51,52,0)))) | BJ12: =IF(A12="","",VLOOKUP(B12,'Datos Kandiko'!B14:BH51,58,0)) | BK12: =IF(A12="","",VLOOKUP(B12,'Datos Kandiko'!B14:BH51,59,0)) | BL12: =IF(A12="","",VLOOKUP(B12,'Datos Kandiko'!B14:BF51,55,0)) | BM12: =IF(A12="","",VLOOKUP(B12,'Datos Kandiko'!B14:BF51,56,0)) | BN12: =IF(A12="","",IF(VLOOKUP(B12,'Datos Kandiko'!B14:BF51,57,0)=0,IF(AO12>1,1,VLOOKUP(B12,'Datos Kandiko'!B14:BF51,57,0)))) | BP12: =+'Biyemas S.A.'!BP12 -> Jue/Thu
