Workbook

Sheet Saldos
A1: codigo | B1: sociedad | C1: banco | D1: moneda | E1: tipo_cuenta | F1: concepto | G1: saldo_dia | H1: 46235 | I1: 46236 | J1: 46237 | K1: 46238 | L1: 46239 | M1: 46240 | N1: 46241 | O1: 46242 | P1: 46243 | Q1: 46244 | R1: 46245 | S1: 46246 | T1: 46247 | U1: 46248 | V1: 46249 | W1: 46250 | X1: 46251 | Y1: 46252 | Z1: 46253 | AA1: 46254 | AB1: 46255 | AC1: 46256 | AD1: 46257 | AE1: 46258 | AF1: 46259 | AG1: 46260 | AH1: 46261 | AI1: 46262 | AJ1: 46263 | AK1: 46264 | AL1: 46265
A2: BIY|MACRO|ARS|CC | B2: BIY | C2: MACRO | D2: ARS | E2: CC | F2: 1) PESOS (CC) | G2: =IFERROR(INDEX(H2:AL2,MATCH(Resumen!$E$1,H$1:AL$1,0)),0) | H2: -56288018 | I2: -56288018 | J2: 27202569 | K2: -5.8979353e+08 | L2: -5.4521001e+08 | M2: -3.9090648e+08 | N2: -4.7966385e+08 | O2: -4.7966385e+08 | P2: -4.7966385e+08 | Q2: -3.490023e+08 | R2: -8.8340077e+08 | S2: -9.5264849e+08 | T2: -7.6321248e+08 | U2: -7.6424123e+08 | V2: -7.6424123e+08 | W2: -7.6424123e+08 | X2: -8.5035631e+08 | Y2: -8.5035631e+08 | Z2: -8.8689709e+08 | AA2: -7.804563e+08 | AB2: -7.4498575e+08 | AC2: -7.4498575e+08 | AD2: -7.4498575e+08 | AE2: -5.4250756e+08 | AF2: -5.3247895e+08 | AG2: -4.684265e+08 | AH2: -2.8289046e+08 | AI2: -2.2386262e+08 | AJ2: -2.2386262e+08 | AK2: -2.2386262e+08 | AL2: -1.4609713e+08
A3: BIY|MACRO|ARS|TRANSITO | B3: BIY | C3: MACRO | D3: ARS | E3: TRANSITO | F3: Depósitos en Tránsito | G3: =IFERROR(INDEX(H3:AL3,MATCH(Resumen!$E$1,H$1:AL$1,0)),0) | H3: 0 | I3: 0 | J3: 0 | K3: 0 | L3: 0 | M3: 0 | N3: 0 | O3: 0 | P3: 0 | Q3: 0 | R3: 0 | S3: 0 | T3: 0 | U3: 0 | V3: 0 | W3: 0 | X3: 0 | Y3: 0 | Z3: 0 | AA3: 0 | AB3: 0 | AC3: 0 | AD3: 0 | AE3: 0 | AF3: 0 | AG3: 0 | AH3: 0 | AI3: 0 | AJ3: 0 | AK3: 0 | AL3: 0
A4: BIY|MACRO|USD|CC | B4: BIY | C4: MACRO | D4: USD | E4: CC | F4: 2) DOLARES (CC) | G4: =IFERROR(INDEX(H4:AL4,MATCH(Resumen!$E$1,H$1:AL$1,0)),0) | H4: 45197.68 | I4: 45197.68 | J4: 45197.68 | K4: 45197.68 | L4: 45197.68 | M4: 45197.68 | N4: 45197.68 | O4: 45197.68 | P4: 45197.68 | Q4: 45197.68 | R4: 45197.68 | S4: 45197.68 | T4: 45197.68 | U4: 45197.68 | V4: 45197.68 | W4: 45197.68 | X4: 45197.68 | Y4: 45197.68 | Z4: 45197.68 | AA4: 45197.68 | AB4: 45197.68 | AC4: 45197.68 | AD4: 45197.68 | AE4: 45197.68 | AF4: 45197.68 | AG4: 45197.68 | AH4: 45197.68 | AI4: 63888.17 | AJ4: 63888.17 | AK4: 63888.17 | AL4: 63856.78
A5: BIY|MACRO|USD|TRANSITO | B5: BIY | C5: MACRO | D5: USD | E5: TRANSITO | F5: Depósitos en Tránsito | G5: =IFERROR(INDEX(H5:AL5,MATCH(Resumen!$E$1,H$1:AL$1,0)),0) | H5: 0 | I5: 0 | J5: 0 | K5: 0 | L5: 0 | M5: 0 | N5: 0 | O5: 0 | P5: 0 | Q5: 0 | R5: 0 | S5: 0 | T5: 0 | U5: 0 | V5: 0 | W5: 0 | X5: 0 | Y5: 0 | Z5: 0 | AA5: 0 | AB5: 0 | AC5: 0 | AD5: 0 | AE5: 0 | AF5: 0 | AG5: 0 | AH5: 0 | AI5: 0 | AJ5: 0 | AK5: 0 | AL5: 0
A6: BIY|ITAU|ARS|CC | B6: BIY | C6: ITAU | D6: ARS | E6: CC | F6: 1) PESOS (CC) | G6: =IFERROR(INDEX(H6:AL6,MATCH(Resumen!$E$1,H$1:AL$1,0)),0) | H6: 13184911 | I6: 13184911 | J6: 10239674 | K6: 11329986 | L6: 3418663.9 | M6: 27131952 | N6: 11542871 | O6: 11542871 | P6: 11542871 | Q6: 6576873.7 | R6: 8799580.1 | S6: 6954585.3 | T6: 17038000 | U6: 15301649 | V6: 15301649 | W6: 15301649 | X6: 6272237.5 | Y6: 6272237.5 | Z6: 27194430 | AA6: 9147306 | AB6: 6906398.1 | AC6: 6906398.1 | AD6: 6906398.1 | AE6: 16123848 | AF6: 11138595 | AG6: 10843419 | AH6: 31082146 | AI6: 13119548 | AJ6: 13119548 | AK6: 13119548 | AL6: 41966137
A7: BIY|ITAU|ARS|TRANSITO | B7: BIY | C7: ITAU | D7: ARS | E7: TRANSITO | F7: Depósitos en Tránsito | G7: =IFERROR(INDEX(H7:AL7,MATCH(Resumen!$E$1,H$1:AL$1,0)),0) | H7: 0 | I7: 0 | J7: 0 | K7: 0 | L7: 0 | M7: 0 | N7: 0 | O7: 0 | P7: 0 | Q7: 0 | R7: 0 | S7: 0 | T7: 0 | U7: 0 | V7: 0 | W7: 0 | X7: 0 | Y7: 0 | Z7: 0 | AA7: 0 | AB7: 0 | AC7: 0 | AD7: 0 | AE7: 0 | AF7: 0 | AG7: 0 | AH7: 0 | AI7: 0 | AJ7: 0 | AK7: 0 | AL7: 0
A8: BIY|ITAU|ARS|AVELLANEDA | B8: BIY | C8: ITAU | D8: ARS | E8: AVELLANEDA | F8: 1) PESOS (AVELLANEDA) | G8: =IFERROR(INDEX(H8:AL8,MATCH(Resumen!$E$1,H$1:AL$1,0)),0) | H8: 0 | I8: 0 | J8: 0 | K8: 0 | L8: 0 | M8: 0 | N8: 0 | O8: 0 | P8: 0 | Q8: 0 | R8: 0 | S8: 0 | T8: 0 | U8: 0 | V8: 0 | W8: 0 | X8: 0 | Y8: 0 | Z8: 0 | AA8: 0 | AB8: 0 | AC8: 0 | AD8: 0 | AE8: 0 | AF8: 0 | AG8: 0 | AH8: 0 | AI8: 0 | AJ8: 0 | AK8: 0 | AL8: 0
A9: BIY|ITAU|USD|CC | B9: BIY | C9: ITAU | D9: USD | E9: CC | F9: 2) DOLARES (CC) | G9: =IFERROR(INDEX(H9:AL9,MATCH(Resumen!$E$1,H$1:AL$1,0)),0) | H9: 0 | I9: 0 | J9: 0 | K9: 0 | L9: 0 | M9: 0 | N9: 0 | O9: 0 | P9: 0 | Q9: 0 | R9: 0 | S9: 0 | T9: 0 | U9: 0 | V9: 0 | W9: 0 | X9: 0 | Y9: 0 | Z9: 0 | AA9: 0 | AB9: 0 | AC9: 0 | AD9: 0 | AE9: 0 | AF9: 0 | AG9: 0 | AH9: 0 | AI9: 0 | AJ9: 0 | AK9: 0 | AL9: 0
A10: BIY|ITAU|USD|TRANSITO | B10: BIY | C10: ITAU | D10: USD | E10: TRANSITO | F10: Depósitos en Tránsito | G10: =IFERROR(INDEX(H10:AL10,MATCH(Resumen!$E$1,H$1:AL$1,0)),0) | H10: 0 | I10: 0 | J10: 0 | K10: 0 | L10: 0 | M10: 0 | N10: 0 | O10: 0 | P10: 0 | Q10: 0 | R10: 0 | S10: 0 | T10: 0 | U10: 0 | V10: 0 | W10: 0 | X10: 0 | Y10: 0 | Z10: 0 | AA10: 0 | AB10: 0 | AC10: 0 | AD10: 0 | AE10: 0 | AF10: 0 | AG10: 0 | AH10: 0 | AI10: 0 | AJ10: 0 | AK10: 0 | AL10: 0
A11: BIY|FRANCES|ARS|CC | B11: BIY | C11: FRANCES | D11: ARS | E11: CC | F11: 1) PESOS | G11: =IFERROR(INDEX(H11:AL11,MATCH(Resumen!$E$1,H$1:AL$1,0)),0) | H11: 224995.26 | I11: 224995.26 | J11: 224995.26 | K11: 80435.26 | L11: 79567.91 | M11: 79567.91 | N11: 79567.91 | O11: 79567.91 | P11: 79567.91 | Q11: 79567.91 | R11: 79567.91 | S11: 79567.91 | T11: 79567.91 | U11: 79567.91 | V11: 79567.91 | W11: 79567.91 | X11: 79567.91 | Y11: 79567.91 | Z11: 79567.91 | AA11: 79567.91 | AB11: 79567.91 | AC11: 79567.91 | AD11: 79567.91 | AE11: 79567.91 | AF11: 79567.91 | AG11: 79567.91 | AH11: 79567.91 | AI11: 79567.91 | AJ11: 79567.91 | AK11: 79567.91 | AL11: 79567.91
A12: BIY|FRANCES|USD|CC | B12: BIY | C12: FRANCES | D12: USD | E12: CC | F12: 2) DOLARES | G12: =IFERROR(INDEX(H12:AL12,MATCH(Resumen!$E$1,H$1:AL$1,0)),0) | H12: 476.6 | I12: 476.6 | J12: 476.6 | K12: 476.6 | L12: 476.6 | M12: 476.6 | N12: 476.6 | O12: 476.6 | P12: 476.6 | Q12: 476.6 | R12: 476.6 | S12: 476.6 | T12: 476.6 | U12: 476.6 | V12: 476.6 | W12: 476.6 | X12: 476.6 | Y12: 476.6 | Z12: 476.6 | AA12: 476.6 | AB12: 476.6 | AC12: 476.6 | AD12: 476.6 | AE12: 476.6 | AF12: 476.6 | AG12: 476.6 | AH12: 476.6 | AI12: 476.6 | AJ12: 476.6 | AK12: 476.6 | AL12: 476.6
A13: BIY|FRANCES|EUR|CC | B13: BIY | C13: FRANCES | D13: EUR | E13: CC | F13: 3) EUROS | G13: =IFERROR(INDEX(H13:AL13,MATCH(Resumen!$E$1,H$1:AL$1,0)),0) | H13: 0 | I13: 0 | J13: 0 | K13: 0 | L13: 0 | M13: 0 | N13: 0 | O13: 0 | P13: 0 | Q13: 0 | R13: 0 | S13: 0 | T13: 0 | U13: 0 | V13: 0 | W13: 0 | X13: 0 | Y13: 0 | Z13: 0 | AA13: 0 | AB13: 0 | AC13: 0 | AD13: 0 | AE13: 0 | AF13: 0 | AG13: 0 | AH13: 0 | AI13: 0 | AJ13: 0 | AK13: 0 | AL13: 0
... A34: BIY|TESORERIA|EUR|CC | B34: BIY | C34: TESORERIA | D34: EUR | E34: CC | F34: 3) EUROS | G34: =IFERROR(INDEX(H34:AL34,MATCH(Resumen!$E$1,H$1:AL$1,0)),0) | H34: 0 | I34: 0 | J34: 0 | K34: 0 | L34: 0 | M34: 0 | N34: 0 | O34: 0 | P34: 0 | Q34: 0 | R34: 0 | S34: 0 | T34: 0 | U34: 0 | V34: 0 | W34: 0 | X34: 0 | Y34: 0 | Z34: 0 | AA34: 0 | AB34: 0 | AC34: 0 | AD34: 0 | AE34: 0 | AF34: 0 | AG34: 0 | AH34: 0 | AI34: 0 | AJ34: 0 | AK34: 0 | AL34: 0
A35: BIY|INVERSIONES|ARS|FCI_GOAL_RENTA_GLOBAL | B35: BIY | C35: INVERSIONES | D35: ARS | F35: FCI Goal renta global | G35: =IFERROR(INDEX(H35:AL35,MATCH(Resumen!$E$1,H$1:AL$1,0)),0) | H35: 0 | I35: 0 | J35: 0 | K35: 0 | L35: 0 | M35: 0 | N35: 0 | O35: 0 | P35: 0 | Q35: 0 | R35: 0 | S35: 0 | T35: 0 | U35: 0 | V35: 0 | W35: 0 | X35: 0 | Y35: 0 | Z35: 0 | AA35: 0 | AB35: 0 | AC35: 0 | AD35: 0 | AE35: 0 | AF35: 0 | AG35: 0 | AH35: 0 | AI35: 0 | AJ35: 0 | AK35: 0 | AL35: 0
A36: BIY|INVERSIONES|ARS|FCI_PIONERO_RENTA_AHORRO | B36: BIY | C36: INVERSIONES | D36: ARS | F36: FCI Pionero Renta Ahorro | G36: =IFERROR(INDEX(H36:AL36,MATCH(Resumen!$E$1,H$1:AL$1,0)),0) | H36: 0 | I36: 0 | J36: 0 | K36: 0 | L36: 0 | M36: 0 | N36: 0 | O36: 0 | P36: 0 | Q36: 0 | R36: 0 | S36: 0 | T36: 0 | U36: 0 | V36: 0 | W36: 0 | X36: 0 | Y36: 0 | Z36: 0 | AA36: 0 | AB36: 0 | AC36: 0 | AD36: 0 | AE36: 0 | AF36: 0 | AG36: 0 | AH36: 0 | AI36: 0 | AJ36: 0 | AK36: 0 | AL36: 0
A37: BIY|INVERSIONES|ARS|FCI_RENTA_CRECIMIENTO | B37: BIY | C37: INVERSIONES | D37: ARS | F37: FCI renta crecimiento | G37: =IFERROR(INDEX(H37:AL37,MATCH(Resumen!$E$1,H$1:AL$1,0)),0) | H37: 0 | I37: 0 | J37: 0 | K37: 0 | L37: 0 | M37: 0 | N37: 0 | O37: 0 | P37: 0 | Q37: 0 | R37: 0 | S37: 0 | T37: 0 | U37: 0 | V37: 0 | W37: 0 | X37: 0 | Y37: 0 | Z37: 0 | AA37: 0 | AB37: 0 | AC37: 0 | AD37: 0 | AE37: 0 | AF37: 0 | AG37: 0 | AH37: 0 | AI37: 0 | AJ37: 0 | AK37: 0 | AL37: 0
A38: BIY|INVERSIONES|ARS|FCI_GOAL_PESOS | B38: BIY | C38: INVERSIONES | D38: ARS | F38: FCI Goal Pesos | G38: =IFERROR(INDEX(H38:AL38,MATCH(Resumen!$E$1,H$1:AL$1,0)),0) | H38: 0 | I38: 0 | J38: 0 | K38: 0 | L38: 0 | M38: 0 | N38: 0 | O38: 0 | P38: 0 | Q38: 0 | R38: 0 | S38: 0 | T38: 0 | U38: 0 | V38: 0 | W38: 0 | X38: 0 | Y38: 0 | Z38: 0 | AA38: 0 | AB38: 0 | AC38: 0 | AD38: 0 | AE38: 0 | AF38: 0 | AG38: 0 | AH38: 0 | AI38: 0 | AJ38: 0 | AK38: 0 | AL38: 0
A39: BIY|INVERSIONES|ARS|FCI_ACCIONES_ARGENTINAS | B39: BIY | C39: INVERSIONES | D39: ARS | F39: FCI acciones argentinas | G39: =IFERROR(INDEX(H39:AL39,MATCH(Resumen!$E$1,H$1:AL$1,0)),0) | H39: 0 | I39: 0 | J39: 0 | K39: 0 | L39: 0 | M39: 0 | N39: 0 | O39: 0 | P39: 0 | Q39: 0 | R39: 0 | S39: 0 | T39: 0 | U39: 0 | V39: 0 | W39: 0 | X39: 0 | Y39: 0 | Z39: 0 | AA39: 0 | AB39: 0 | AC39: 0 | AD39: 0 | AE39: 0 | AF39: 0 | AG39: 0 | AH39: 0 | AI39: 0 | AJ39: 0 | AK39: 0 | AL39: 0
A40: BIY|INVERSIONES|ARS|IAM_AHORRO_PESOS | B40: BIY | C40: INVERSIONES | D40: ARS | F40: IAM Ahorro Pesos | G40: =IFERROR(INDEX(H40:AL40,MATCH(Resumen!$E$1,H$1:AL$1,0)),0) | H40: 0 | I40: 0 | J40: 0 | K40: 0 | L40: 0 | M40: 0 | N40: 0 | O40: 0 | P40: 0 | Q40: 0 | R40: 0 | S40: 0 | T40: 0 | U40: 0 | V40: 0 | W40: 0 | X40: 0 | Y40: 0 | Z40: 0 | AA40: 0 | AB40: 0 | AC40: 0 | AD40: 0 | AE40: 0 | AF40: 0 | AG40: 0 | AH40: 0 | AI40: 0 | AJ40: 0 | AK40: 0 | AL40: 0
A41: BIY|INVERSIONES|ARS|PLAZO_FIJO | B41: BIY | C41: INVERSIONES | D41: ARS | F41: Plazo Fijo | G41: =IFERROR(INDEX(H41:AL41,MATCH(Resumen!$E$1,H$1:AL$1,0)),0) | H41: 0 | I41: 0 | J41: 0 | K41: 0 | L41: 0 | M41: 0 | N41: 0 | O41: 0 | P41: 0 | Q41: 0 | R41: 0 | S41: 0 | T41: 0 | U41: 0 | V41: 0 | W41: 0 | X41: 0 | Y41: 0 | Z41: 0 | AA41: 0 | AB41: 0 | AC41: 0 | AD41: 0 | AE41: 0 | AF41: 0 | AG41: 0 | AH41: 0 | AI41: 0 | AJ41: 0 | AK41: 0 | AL41: 0
A42: BIY|INVERSIONES|ARS|OTROS | B42: BIY | C42: INVERSIONES | D42: ARS | F42: Otros | G42: =IFERROR(INDEX(H42:AL42,MATCH(Resumen!$E$1,H$1:AL$1,0)),0) | H42: 0 | I42: 0 | J42: 0 | K42: 0 | L42: 0 | M42: 0 | N42: 0 | O42: 0 | P42: 0 | Q42: 0 | R42: 0 | S42: 0 | T42: 0 | U42: 0 | V42: 0 | W42: 0 | X42: 0 | Y42: 0 | Z42: 0 | AA42: 0 | AB42: 0 | AC42: 0 | AD42: 0 | AE42: 0 | AF42: 0 | AG42: 0 | AH42: 0 | AI42: 0 | AJ42: 0 | AK42: 0 | AL42: 0
A43: KAN|MACRO|ARS|CC | B43: KAN | C43: MACRO | D43: ARS | E43: CC | F43: 1) PESOS (CC) | G43: =IFERROR(INDEX(H43:AL43,MATCH(Resumen!$E$1,H$1:AL$1,0)),0) | H43: -4.0978534e+08 | I43: -4.0978534e+08 | J43: -4.7125205e+08 | K43: -4.8442293e+08 | L43: -38771053 | M43: -14805486 | N43: -38889286 | O43: -38889286 | P43: -38889286 | Q43: -10300879 | R43: -67393815 | S43: -95294984 | T43: -68874455 | U43: -68932591 | V43: -68932591 | W43: -68932591 | X43: -1.2251235e+08 | Y43: -1.2251235e+08 | Z43: -1.1132271e+08 | AA43: -85196304 | AB43: -91057789 | AC43: -91057789 | AD43: -91057789 | AE43: -67610525 | AF43: -65042181 | AG43: -69152932 | AH43: -49990179 | AI43: -40070217 | AJ43: -40070217 | AK43: -40070217 | AL43: -23426881
A44: KAN|MACRO|ARS|TRANSITO | B44: KAN | C44: MACRO | D44: ARS | E44: TRANSITO | F44: Depósitos en Tránsito | G44: =IFERROR(INDEX(H44:AL44,MATCH(Resumen!$E$1,H$1:AL$1,0)),0) | H44: 0 | I44: 0 | J44: 0 | K44: 0 | L44: 0 | M44: 0 | N44: 0 | O44: 0 | P44: 0 | Q44: 0 | R44: 0 | S44: 0 | T44: 0 | U44: 0 | V44: 0 | W44: 0 | X44: 0 | Y44: 0 | Z44: 0 | AA44: 0 | AB44: 0 | AC44: 0 | AD44: 0 | AE44: 0 | AF44: 0 | AG44: 0 | AH44: 0 | AI44: 0 | AJ44: 0 | AK44: 0 | AL44: 0
A45: KAN|MACRO|ARS|CA | B45: KAN | C45: MACRO | D45: ARS | E45: CA | F45: 1) PESOS (CA) | G45: =IFERROR(INDEX(H45:AL45,MATCH(Resumen!$E$1,H$1:AL$1,0)),0) | H45: 0 | I45: 0 | J45: 0 | K45: 0 | L45: 0 | M45: 0 | N45: 0 | O45: 0 | P45: 0 | Q45: 0 | R45: 0 | S45: 0 | T45: 0 | U45: 0 | V45: 0 | W45: 0 | X45: 0 | Y45: 0 | Z45: 0 | AA45: 0 | AB45: 0 | AC45: 0 | AD45: 0 | AE45: 0 | AF45: 0 | AG45: 0 | AH45: 0 | AI45: 0 | AJ45: 0 | AK45: 0 | AL45: 0
A46: KAN|MACRO|USD|CC | B46: KAN | C46: MACRO | D46: USD | E46: CC | F46: 2) DOLARES (CC) | G46: =IFERROR(INDEX(H46:AL46,MATCH(Resumen!$E$1,H$1:AL$1,0)),0) | H46: 64.09 | I46: 64.09 | J46: 64.09 | K46: 64.09 | L46: 64.09 | M46: 64.09 | N46: 64.09 | O46: 64.09 | P46: 64.09 | Q46: 64.09 | R46: 64.09 | S46: 64.09 | T46: 64.09 | U46: 64.09 | V46: 64.09 | W46: 64.09 | X46: 64.09 | Y46: 64.09 | Z46: 64.09 | AA46: 64.09 | AB46: 64.09 | AC46: 64.09 | AD46: 64.09 | AE46: 64.09 | AF46: 64.09 | AG46: 64.09 | AH46: 64.09 | AI46: 64.09 | AJ46: 64.09 | AK46: 64.09 | AL46: 34.08
A47: KAN|MACRO|USD|TRANSITO | B47: KAN | C47: MACRO | D47: USD | E47: TRANSITO | F47: Depósitos en Tránsito | G47: =IFERROR(INDEX(H47:AL47,MATCH(Resumen!$E$1,H$1:AL$1,0)),0) | H47: 0 | I47: 0 | J47: 0 | K47: 0 | L47: 0 | M47: 0 | N47: 0 | O47: 0 | P47: 0 | Q47: 0 | R47: 0 | S47: 0 | T47: 0 | U47: 0 | V47: 0 | W47: 0 | X47: 0 | Y47: 0 | Z47: 0 | AA47: 0 | AB47: 0 | AC47: 0 | AD47: 0 | AE47: 0 | AF47: 0 | AG47: 0 | AH47: 0 | AI47: 0 | AJ47: 0 | AK47: 0 | AL47: 0
A48: KAN|MACRO|USD|CA | B48: KAN | C48: MACRO | D48: USD | E48: CA | F48: 2) DOLARES (CA) | G48: =IFERROR(INDEX(H48:AL48,MATCH(Resumen!$E$1,H$1:AL$1,0)),0) | H48: 0 | I48: 0 | J48: 0 | K48: 0 | L48: 0 | M48: 0 | N48: 0 | O48: 0 | P48: 0 | Q48: 0 | R48: 0 | S48: 0 | T48: 0 | U48: 0 | V48: 0 | W48: 0 | X48: 0 | Y48: 0 | Z48: 0 | AA48: 0 | AB48: 0 | AC48: 0 | AD48: 0 | AE48: 0 | AF48: 0 | AG48: 0 | AH48: 0 | AI48: 0 | AJ48: 0 | AK48: 0 | AL48: 0
A49: KAN|ITAU|ARS|CC | B49: KAN | C49: ITAU | D49: ARS | E49: CC | F49: 1) PESOS (CC) | G49: =IFERROR(INDEX(H49:AL49,MATCH(Resumen!$E$1,H$1:AL$1,0)),0) | H49: 2030713.4 | I49: 2030713.4 | J49: 3069968.6 | K49: 1729472.1 | L49: -558345.32 | M49: 4183500.2 | N49: 1590039.8 | O49: 1590039.8 | P49: 1590039.8 | Q49: 2763317.2 | R49: 4919704.7 | S49: 5739254.9 | T49: 2720175.8 | U49: 3004048.9 | V49: 3004048.9 | W49: 3004048.9 | X49: 5049169.1 | Y49: 5049169.1 | Z49: 6264208.1 | AA49: 3484435 | AB49: 3687893.5 | AC49: 3687893.5 | AD49: 3687893.5 | AE49: 5472515.2 | AF49: 2346715.8 | AG49: 2758477 | AH49: 2787542.5 | AI49: 3078197.5 | AJ49: 3078197.5 | AK49: 3078197.5 | AL49: 7524584.5
A50: KAN|ITAU|ARS|TRANSITO | B50: KAN | C50: ITAU | D50: ARS | E50: TRANSITO | F50: Depósitos en Tránsito | G50: =IFERROR(INDEX(H50:AL50,MATCH(Resumen!$E$1,H$1:AL$1,0)),0) | H50: 0 | I50: 0 | J50: 0 | K50: 0 | L50: 0 | M50: 0 | N50: 0 | O50: 0 | P50: 0 | Q50: 0 | R50: 0 | S50: 0 | T50: 0 | U50: 0 | V50: 0 | W50: 0 | X50: 0 | Y50: 0 | Z50: 0 | AA50: 0 | AB50: 0 | AC50: 0 | AD50: 0 | AE50: 0 | AF50: 0 | AG50: 0 | AH50: 0 | AI50: 0 | AJ50: 0 | AK50: 0 | AL50: 0
A51: KAN|ITAU|ARS|AVELLANEDA | B51: KAN | C51: ITAU | D51: ARS | E51: AVELLANEDA | F51: 1) PESOS (AVELLANEDA) | G51: =IFERROR(INDEX(H51:AL51,MATCH(Resumen!$E$1,H$1:AL$1,0)),0) | H51: 0 | I51: 0 | J51: 0 | K51: 0 | L51: 0 | M51: 0 | N51: 0 | O51: 0 | P51: 0 | Q51: 0 | R51: 0 | S51: 0 | T51: 0 | U51: 0 | V51: 0 | W51: 0 | X51: 0 | Y51: 0 | Z51: 0 | AA51: 0 | AB51: 0 | AC51: 0 | AD51: 0 | AE51: 0 | AF51: 0 | AG51: 0 | AH51: 0 | AI51: 0 | AJ51: 0 | AK51: 0 | AL51: 0
A52: KAN|ITAU|USD|CC | B52: KAN | C52: ITAU | D52: USD | E52: CC | F52: 2) DOLARES (CC) | G52: =IFERROR(INDEX(H52:AL52,MATCH(Resumen!$E$1,H$1:AL$1,0)),0) | H52: 0 | I52: 0 | J52: 0 | K52: 0 | L52: 0 | M52: 0 | N52: 0 | O52: 0 | P52: 0 | Q52: 0 | R52: 0 | S52: 0 | T52: 0 | U52: 0 | V52: 0 | W52: 0 | X52: 0 | Y52: 0 | Z52: 0 | AA52: 0 | AB52: 0 | AC52: 0 | AD52: 0 | AE52: 0 | AF52: 0 | AG52: 0 | AH52: 0 | AI52: 0 | AJ52: 0 | AK52: 0 | AL52: 0
A53: KAN|ITAU|USD|TRANSITO | B53: KAN | C53: ITAU | D53: USD | E53: TRANSITO | F53: Depósitos en Tránsito | G53: =IFERROR(INDEX(H53:AL53,MATCH(Resumen!$E$1,H$1:AL$1,0)),0) | H53: 0 | I53: 0 | J53: 0 | K53: 0 | L53: 0 | M53: 0 | N53: 0 | O53: 0 | P53: 0 | Q53: 0 | R53: 0 | S53: 0 | T53: 0 | U53: 0 | V53: 0 | W53: 0 | X53: 0 | Y53: 0 | Z53: 0 | AA53: 0 | AB53: 0 | AC53: 0 | AD53: 0 | AE53: 0 | AF53: 0 | AG53: 0 | AH53: 0 | AI53: 0 | AJ53: 0 | AK53: 0 | AL53: 0
A54: KAN|FRANCES|ARS|CC | B54: KAN | C54: FRANCES | D54: ARS | E54: CC | F54: 1) PESOS | G54: =IFERROR(INDEX(H54:AL54,MATCH(Resumen!$E$1,H$1:AL$1,0)),0) | H54: 310946.67 | I54: 310946.67 | J54: 320794.54 | K54: 182267.67 | L54: 181436.88 | M54: 295784.12 | N54: 295098.06 | O54: 295098.06 | P54: 295098.06 | Q54: 295098.06 | R54: 295098.06 | S54: 295098.06 | T54: 295098.06 | U54: 295098.06 | V54: 295098.06 | W54: 295098.06 | X54: 295098.06 | Y54: 295098.06 | Z54: 295098.06 | AA54: 295098.06 | AB54: 295098.06 | AC54: 295098.06 | AD54: 295098.06 | AE54: 295098.06 | AF54: 295098.06 | AG54: 295098.06 | AH54: 295098.06 | AI54: 295098.06 | AJ54: 295098.06 | AK54: 295098.06 | AL54: 295098.06
... A77: KAN|TESORERIA|EUR|CC | B77: KAN | C77: TESORERIA | D77: EUR | E77: CC | F77: 3) EUROS | G77: =IFERROR(INDEX(H77:AL77,MATCH(Resumen!$E$1,H$1:AL$1,0)),0) | H77: 0 | I77: 0 | J77: 0 | K77: 0 | L77: 0 | M77: 0 | N77: 0 | O77: 0 | P77: 0 | Q77: 0 | R77: 0 | S77: 0 | T77: 0 | U77: 0 | V77: 0 | W77: 0 | X77: 0 | Y77: 0 | Z77: 0 | AA77: 0 | AB77: 0 | AC77: 0 | AD77: 0 | AE77: 0 | AF77: 0 | AG77: 0 | AH77: 0 | AI77: 0 | AJ77: 0 | AK77: 0 | AL77: 0
A78: KAN|INVERSIONES|ARS|FCI_PIONERO_PESOS | B78: KAN | C78: INVERSIONES | D78: ARS | F78: FCI Pionero Pesos | G78: =IFERROR(INDEX(H78:AL78,MATCH(Resumen!$E$1,H$1:AL$1,0)),0) | H78: 0 | I78: 0 | J78: 0 | K78: 0 | L78: 0 | M78: 0 | N78: 0 | O78: 0 | P78: 0 | Q78: 0 | R78: 0 | S78: 0 | T78: 0 | U78: 0 | V78: 0 | W78: 0 | X78: 0 | Y78: 0 | Z78: 0 | AA78: 0 | AB78: 0 | AC78: 0 | AD78: 0 | AE78: 0 | AF78: 0 | AG78: 0 | AH78: 0 | AI78: 0 | AJ78: 0 | AK78: 0 | AL78: 0
A79: KAN|INVERSIONES|ARS|FCI_PIONERO_RENTA_AHORRO | B79: KAN | C79: INVERSIONES | D79: ARS | F79: FCI Pionero Renta Ahorro | G79: =IFERROR(INDEX(H79:AL79,MATCH(Resumen!$E$1,H$1:AL$1,0)),0) | H79: 0 | I79: 0 | J79: 0 | K79: 0 | L79: 0 | M79: 0 | N79: 0 | O79: 0 | P79: 0 | Q79: 0 | R79: 0 | S79: 0 | T79: 0 | U79: 0 | V79: 0 | W79: 0 | X79: 0 | Y79: 0 | Z79: 0 | AA79: 0 | AB79: 0 | AC79: 0 | AD79: 0 | AE79: 0 | AF79: 0 | AG79: 0 | AH79: 0 | AI79: 0 | AJ79: 0 | AK79: 0 | AL79: 0
A80: KAN|INVERSIONES|ARS|FCI_PELLEGRINI_RENTA_PESOS | B80: KAN | C80: INVERSIONES | D80: ARS | F80: FCI Pellegrini Renta Pesos | G80: =IFERROR(INDEX(H80:AL80,MATCH(Resumen!$E$1,H$1:AL$1,0)),0) | H80: 0 | I80: 0 | J80: 0 | K80: 0 | L80: 0 | M80: 0 | N80: 0 | O80: 0 | P80: 0 | Q80: 0 | R80: 0 | S80: 0 | T80: 0 | U80: 0 | V80: 0 | W80: 0 | X80: 0 | Y80: 0 | Z80: 0 | AA80: 0 | AB80: 0 | AC80: 0 | AD80: 0 | AE80: 0 | AF80: 0 | AG80: 0 | AH80: 0 | AI80: 0 | AJ80: 0 | AK80: 0 | AL80: 0
A81: KAN|INVERSIONES|ARS|FCI_GOAL_PESOS | B81: KAN | C81: INVERSIONES | D81: ARS | F81: FCI Goal Pesos | G81: =IFERROR(INDEX(H81:AL81,MATCH(Resumen!$E$1,H$1:AL$1,0)),0) | H81: 0 | I81: 0 | J81: 0 | K81: 0 | L81: 0 | M81: 0 | N81: 0 | O81: 0 | P81: 0 | Q81: 0 | R81: 0 | S81: 0 | T81: 0 | U81: 0 | V81: 0 | W81: 0 | X81: 0 | Y81: 0 | Z81: 0 | AA81: 0 | AB81: 0 | AC81: 0 | AD81: 0 | AE81: 0 | AF81: 0 | AG81: 0 | AH81: 0 | AI81: 0 | AJ81: 0 | AK81: 0 | AL81: 0
A82: KAN|INVERSIONES|ARS|FCI_GOAL_CAPITAL_PLUS | B82: KAN | C82: INVERSIONES | D82: ARS | F82: FCI Goal Capital Plus | G82: =IFERROR(INDEX(H82:AL82,MATCH(Resumen!$E$1,H$1:AL$1,0)),0) | H82: 0 | I82: 0 | J82: 0 | K82: 0 | L82: 0 | M82: 0 | N82: 0 | O82: 0 | P82: 0 | Q82: 0 | R82: 0 | S82: 0 | T82: 0 | U82: 0 | V82: 0 | W82: 0 | X82: 0 | Y82: 0 | Z82: 0 | AA82: 0 | AB82: 0 | AC82: 0 | AD82: 0 | AE82: 0 | AF82: 0 | AG82: 0 | AH82: 0 | AI82: 0 | AJ82: 0 | AK82: 0 | AL82: 0
A83: KAN|INVERSIONES|ARS|IAM_AHORRO_PESOS | B83: KAN | C83: INVERSIONES | D83: ARS | F83: IAM Ahorro Pesos | G83: =IFERROR(INDEX(H83:AL83,MATCH(Resumen!$E$1,H$1:AL$1,0)),0) | H83: 0 | I83: 0 | J83: 0 | K83: 0 | L83: 0 | M83: 0 | N83: 0 | O83: 0 | P83: 0 | Q83: 0 | R83: 0 | S83: 0 | T83: 0 | U83: 0 | V83: 0 | W83: 0 | X83: 0 | Y83: 0 | Z83: 0 | AA83: 0 | AB83: 0 | AC83: 0 | AD83: 0 | AE83: 0 | AF83: 0 | AG83: 0 | AH83: 0 | AI83: 0 | AJ83: 0 | AK83: 0 | AL83: 0
A84: KAN|INVERSIONES|ARS|PLAZO_FIJO | B84: KAN | C84: INVERSIONES | D84: ARS | F84: Plazo Fijo | G84: =IFERROR(INDEX(H84:AL84,MATCH(Resumen!$E$1,H$1:AL$1,0)),0) | H84: 0 | I84: 0 | J84: 0 | K84: 0 | L84: 0 | M84: 0 | N84: 0 | O84: 0 | P84: 0 | Q84: 0 | R84: 0 | S84: 0 | T84: 0 | U84: 0 | V84: 0 | W84: 0 | X84: 0 | Y84: 0 | Z84: 0 | AA84: 0 | AB84: 0 | AC84: 0 | AD84: 0 | AE84: 0 | AF84: 0 | AG84: 0 | AH84: 0 | AI84: 0 | AJ84: 0 | AK84: 0 | AL84: 0
A85: KAN|INVERSIONES|ARS|FCI_GOAL_PESOS#127 | B85: KAN | C85: INVERSIONES | D85: ARS | F85: FCI Goal Pesos | G85: =IFERROR(INDEX(H85:AL85,MATCH(Resumen!$E$1,H$1:AL$1,0)),0) | H85: 0 | I85: 0 | J85: 0 | K85: 0 | L85: 0 | M85: 0 | N85: 0 | O85: 0 | P85: 0 | Q85: 0 | R85: 0 | S85: 0 | T85: 0 | U85: 0 | V85: 0 | W85: 0 | X85: 0 | Y85: 0 | Z85: 0 | AA85: 0 | AB85: 0 | AC85: 0 | AD85: 0 | AE85: 0 | AF85: 0 | AG85: 0 | AH85: 0 | AI85: 0 | AJ85: 0 | AK85: 0 | AL85: 0
A86: REB|MACRO|ARS|CC | B86: REB | C86: MACRO | D86: ARS | E86: CC | F86: 1) PESOS (CC) | G86: =IFERROR(INDEX(H86:AL86,MATCH(Resumen!$E$1,H$1:AL$1,0)),0) | H86: -1.0962711e+08 | I86: -1.0962711e+08 | J86: -4.9595758e+08 | K86: -4.3854489e+08 | L86: 10838260 | M86: 50451369 | N86: 3562704.5 | O86: 3562704.5 | P86: 3562704.5 | Q86: 84490498 | R86: -1.2590546e+08 | S86: -1.670759e+08 | T86: -69875896 | U86: -48833224 | V86: -48833224 | W86: -48833224 | X86: -1.5159354e+08 | Y86: -1.5159354e+08 | Z86: -2.3698715e+08 | AA86: -2.1245817e+08 | AB86: -2.5081387e+08 | AC86: -2.5081387e+08 | AD86: -2.5081387e+08 | AE86: -2.1743987e+08 | AF86: -2.3171114e+08 | AG86: -2.2242294e+08 | AH86: -1.9077406e+08 | AI86: -1.8387214e+08 | AJ86: -1.8387214e+08 | AK86: -1.8387214e+08 | AL86: -1.5182624e+08
A87: REB|MACRO|ARS|TRANSITO | B87: REB | C87: MACRO | D87: ARS | E87: TRANSITO | F87: Depósitos en Tránsito | G87: =IFERROR(INDEX(H87:AL87,MATCH(Resumen!$E$1,H$1:AL$1,0)),0) | H87: 0 | I87: 0 | J87: 0 | K87: 0 | L87: 0 | M87: 0 | N87: 0 | O87: 0 | P87: 0 | Q87: 0 | R87: 0 | S87: 0 | T87: 0 | U87: 0 | V87: 0 | W87: 0 | X87: 0 | Y87: 0 | Z87: 0 | AA87: 0 | AB87: 0 | AC87: 0 | AD87: 0 | AE87: 0 | AF87: 0 | AG87: 0 | AH87: 0 | AI87: 0 | AJ87: 0 | AK87: 0 | AL87: 0
A88: REB|MACRO|ARS|CA | B88: REB | C88: MACRO | D88: ARS | E88: CA | F88: 1) PESOS (CA) | G88: =IFERROR(INDEX(H88:AL88,MATCH(Resumen!$E$1,H$1:AL$1,0)),0) | H88: 0 | I88: 0 | J88: 0 | K88: 0 | L88: 0 | M88: 0 | N88: 0 | O88: 0 | P88: 0 | Q88: 0 | R88: 0 | S88: 0 | T88: 0 | U88: 0 | V88: 0 | W88: 0 | X88: 0 | Y88: 0 | Z88: 0 | AA88: 0 | AB88: 0 | AC88: 0 | AD88: 0 | AE88: 0 | AF88: 0 | AG88: 0 | AH88: 0 | AI88: 0 | AJ88: 0 | AK88: 0 | AL88: 0
A89: REB|MACRO|USD|CC | B89: REB | C89: MACRO | D89: USD | E89: CC | F89: 2) DOLARES (CC) | G89: =IFERROR(INDEX(H89:AL89,MATCH(Resumen!$E$1,H$1:AL$1,0)),0) | H89: 2916.92 | I89: 2916.92 | J89: 2916.92 | K89: 2916.92 | L89: 2916.92 | M89: 2916.92 | N89: 2916.92 | O89: 2916.92 | P89: 2916.92 | Q89: 2916.92 | R89: 2916.92 | S89: 2916.92 | T89: 2916.92 | U89: 2916.92 | V89: 2916.92 | W89: 2916.92 | X89: 2916.92 | Y89: 2916.92 | Z89: 2916.92 | AA89: 2916.92 | AB89: 2916.92 | AC89: 2916.92 | AD89: 2916.92 | AE89: 2916.92 | AF89: 2916.92 | AG89: 2916.92 | AH89: 2916.92 | AI89: 2916.92 | AJ89: 2916.92 | AK89: 2916.92 | AL89: 2886.91
A90: REB|MACRO|USD|TRANSITO | B90: REB | C90: MACRO | D90: USD | E90: TRANSITO | F90: Depósitos en Tránsito | G90: =IFERROR(INDEX(H90:AL90,MATCH(Resumen!$E$1,H$1:AL$1,0)),0) | H90: 0 | I90: 0 | J90: 0 | K90: 0 | L90: 0 | M90: 0 | N90: 0 | O90: 0 | P90: 0 | Q90: 0 | R90: 0 | S90: 0 | T90: 0 | U90: 0 | V90: 0 | W90: 0 | X90: 0 | Y90: 0 | Z90: 0 | AA90: 0 | AB90: 0 | AC90: 0 | AD90: 0 | AE90: 0 | AF90: 0 | AG90: 0 | AH90: 0 | AI90: 0 | AJ90: 0 | AK90: 0 | AL90: 0
A91: REB|MACRO|USD|CA | B91: REB | C91: MACRO | D91: USD | E91: CA | F91: 2) DOLARES (CA) | G91: =IFERROR(INDEX(H91:AL91,MATCH(Resumen!$E$1,H$1:AL$1,0)),0) | H91: 0 | I91: 0 | J91: 0 | K91: 0 | L91: 0 | M91: 0 | N91: 0 | O91: 0 | P91: 0 | Q91: 0 | R91: 0 | S91: 0 | T91: 0 | U91: 0 | V91: 0 | W91: 0 | X91: 0 | Y91: 0 | Z91: 0 | AA91: 0 | AB91: 0 | AC91: 0 | AD91: 0 | AE91: 0 | AF91: 0 | AG91: 0 | AH91: 0 | AI91: 0 | AJ91: 0 | AK91: 0 | AL91: 0
A92: REB|ITAU|ARS|CC | B92: REB | C92: ITAU | D92: ARS | E92: CC | F92: 1) PESOS (CC) | G92: =IFERROR(INDEX(H92:AL92,MATCH(Resumen!$E$1,H$1:AL$1,0)),0) | H92: 2935264 | I92: 2935264 | J92: 2935264 | K92: 1411766.7 | L92: -1538500.3 | M92: 1461499.7 | N92: 1461499.7 | O92: 1461499.7 | P92: 1461499.7 | Q92: 1528262.9 | R92: 10251617 | S92: 1251239.9 | T92: 1251239.9 | U92: 1251239.9 | V92: 1251239.9 | W92: 1251239.9 | X92: 3204992.4 | Y92: 3204992.4 | Z92: 4515455.3 | AA92: 4515455.3 | AB92: 4515455.3 | AC92: 4515455.3 | AD92: 4515455.3 | AE92: 4515455.3 | AF92: 515077.99 | AG92: 515077.99 | AH92: 515077.99 | AI92: 515077.99 | AJ92: 515077.99 | AK92: 515077.99 | AL92: 12256068
A93: REB|ITAU|ARS|TRANSITO | B93: REB | C93: ITAU | D93: ARS | E93: TRANSITO | F93: Depósitos en Tránsito | G93: =IFERROR(INDEX(H93:AL93,MATCH(Resumen!$E$1,H$1:AL$1,0)),0) | H93: 0 | I93: 0 | J93: 0 | K93: 0 | L93: 0 | M93: 0 | N93: 0 | O93: 0 | P93: 0 | Q93: 0 | R93: 0 | S93: 0 | T93: 0 | U93: 0 | V93: 0 | W93: 0 | X93: 0 | Y93: 0 | Z93: 0 | AA93: 0 | AB93: 0 | AC93: 0 | AD93: 0 | AE93: 0 | AF93: 0 | AG93: 0 | AH93: 0 | AI93: 0 | AJ93: 0 | AK93: 0 | AL93: 0
A94: REB|ITAU|ARS|AVELLANEDA | B94: REB | C94: ITAU | D94: ARS | E94: AVELLANEDA | F94: 1) PESOS (AVELLANEDA) | G94: =IFERROR(INDEX(H94:AL94,MATCH(Resumen!$E$1,H$1:AL$1,0)),0) | H94: 0 | I94: 0 | J94: 0 | K94: 0 | L94: 0 | M94: 0 | N94: 0 | O94: 0 | P94: 0 | Q94: 0 | R94: 0 | S94: 0 | T94: 0 | U94: 0 | V94: 0 | W94: 0 | X94: 0 | Y94: 0 | Z94: 0 | AA94: 0 | AB94: 0 | AC94: 0 | AD94: 0 | AE94: 0 | AF94: 0 | AG94: 0 | AH94: 0 | AI94: 0 | AJ94: 0 | AK94: 0 | AL94: 0
A95: REB|ITAU|USD|CC | B95: REB | C95: ITAU | D95: USD | E95: CC | F95: 2) DOLARES (CC) | G95: =IFERROR(INDEX(H95:AL95,MATCH(Resumen!$E$1,H$1:AL$1,0)),0) | H95: 0 | I95: 0 | J95: 0 | K95: 0 | L95: 0 | M95: 0 | N95: 0 | O95: 0 | P95: 0 | Q95: 0 | R95: 0 | S95: 0 | T95: 0 | U95: 0 | V95: 0 | W95: 0 | X95: 0 | Y95: 0 | Z95: 0 | AA95: 0 | AB95: 0 | AC95: 0 | AD95: 0 | AE95: 0 | AF95: 0 | AG95: 0 | AH95: 0 | AI95: 0 | AJ95: 0 | AK95: 0 | AL95: 0
A96: REB|ITAU|USD|TRANSITO | B96: REB | C96: ITAU | D96: USD | E96: TRANSITO | F96: Depósitos en Tránsito | G96: =IFERROR(INDEX(H96:AL96,MATCH(Resumen!$E$1,H$1:AL$1,0)),0) | H96: 0 | I96: 0 | J96: 0 | K96: 0 | L96: 0 | M96: 0 | N96: 0 | O96: 0 | P96: 0 | Q96: 0 | R96: 0 | S96: 0 | T96: 0 | U96: 0 | V96: 0 | W96: 0 | X96: 0 | Y96: 0 | Z96: 0 | AA96: 0 | AB96: 0 | AC96: 0 | AD96: 0 | AE96: 0 | AF96: 0 | AG96: 0 | AH96: 0 | AI96: 0 | AJ96: 0 | AK96: 0 | AL96: 0
A97: REB|FRANCES|ARS|CC | B97: REB | C97: FRANCES | D97: ARS | E97: CC | F97: 1) PESOS | G97: =IFERROR(INDEX(H97:AL97,MATCH(Resumen!$E$1,H$1:AL$1,0)),0) | H97: 301994.7 | I97: 301994.7 | J97: 301990.7 | K97: 163769.1 | L97: 162939.78 | M97: 162939.78 | N97: 162939.78 | O97: 162939.78 | P97: 162939.78 | Q97: 162939.78 | R97: 162939.78 | S97: 162939.78 | T97: 162939.78 | U97: 162939.78 | V97: 162939.78 | W97: 162939.78 | X97: 162939.78 | Y97: 162939.78 | Z97: 162939.78 | AA97: 162939.78 | AB97: 162939.78 | AC97: 162939.78 | AD97: 162939.78 | AE97: 162939.78 | AF97: 162939.78 | AG97: 162939.78 | AH97: 162939.78 | AI97: 162939.78 | AJ97: 162939.78 | AK97: 162939.78 | AL97: 162939.78
... A120: REB|TESORERIA|EUR|CC | B120: REB | C120: TESORERIA | D120: EUR | E120: CC | F120: 3) EUROS | G120: =IFERROR(INDEX(H120:AL120,MATCH(Resumen!$E$1,H$1:AL$1,0)),0) | H120: 0 | I120: 0 | J120: 0 | K120: 0 | L120: 0 | M120: 0 | N120: 0 | O120: 0 | P120: 0 | Q120: 0 | R120: 0 | S120: 0 | T120: 0 | U120: 0 | V120: 0 | W120: 0 | X120: 0 | Y120: 0 | Z120: 0 | AA120: 0 | AB120: 0 | AC120: 0 | AD120: 0 | AE120: 0 | AF120: 0 | AG120: 0 | AH120: 0 | AI120: 0 | AJ120: 0 | AK120: 0 | AL120: 0
A121: REB|INVERSIONES|ARS|FCI_PIONERO_PESOS | B121: REB | C121: INVERSIONES | D121: ARS | F121: FCI Pionero Pesos | G121: =IFERROR(INDEX(H121:AL121,MATCH(Resumen!$E$1,H$1:AL$1,0)),0) | H121: 0 | I121: 0 | J121: 0 | K121: 0 | L121: 0 | M121: 0 | N121: 0 | O121: 0 | P121: 0 | Q121: 0 | R121: 0 | S121: 0 | T121: 0 | U121: 0 | V121: 0 | W121: 0 | X121: 0 | Y121: 0 | Z121: 0 | AA121: 0 | AB121: 0 | AC121: 0 | AD121: 0 | AE121: 0 | AF121: 0 | AG121: 0 | AH121: 0 | AI121: 0 | AJ121: 0 | AK121: 0 | AL121: 0
A122: REB|INVERSIONES|ARS|FCI_PIONERO_RENTA_AHORRO | B122: REB | C122: INVERSIONES | D122: ARS | F122: FCI Pionero Renta Ahorro | G122: =IFERROR(INDEX(H122:AL122,MATCH(Resumen!$E$1,H$1:AL$1,0)),0) | H122: 0 | I122: 0 | J122: 0 | K122: 0 | L122: 0 | M122: 0 | N122: 0 | O122: 0 | P122: 0 | Q122: 0 | R122: 0 | S122: 0 | T122: 0 | U122: 0 | V122: 0 | W122: 0 | X122: 0 | Y122: 0 | Z122: 0 | AA122: 0 | AB122: 0 | AC122: 0 | AD122: 0 | AE122: 0 | AF122: 0 | AG122: 0 | AH122: 0 | AI122: 0 | AJ122: 0 | AK122: 0 | AL122: 0
A123: REB|INVERSIONES|ARS|FCI_PELLEGRINI_RENTA_PESOS | B123: REB | C123: INVERSIONES | D123: ARS | F123: FCI Pellegrini Renta Pesos | G123: =IFERROR(INDEX(H123:AL123,MATCH(Resumen!$E$1,H$1:AL$1,0)),0) | H123: 0 | I123: 0 | J123: 0 | K123: 0 | L123: 0 | M123: 0 | N123: 0 | O123: 0 | P123: 0 | Q123: 0 | R123: 0 | S123: 0 | T123: 0 | U123: 0 | V123: 0 | W123: 0 | X123: 0 | Y123: 0 | Z123: 0 | AA123: 0 | AB123: 0 | AC123: 0 | AD123: 0 | AE123: 0 | AF123: 0 | AG123: 0 | AH123: 0 | AI123: 0 | AJ123: 0 | AK123: 0 | AL123: 0
A124: REB|INVERSIONES|ARS|FCI_GOAL_PESOS | B124: REB | C124: INVERSIONES | D124: ARS | F124: FCI Goal Pesos | G124: =IFERROR(INDEX(H124:AL124,MATCH(Resumen!$E$1,H$1:AL$1,0)),0) | H124: 0 | I124: 0 | J124: 0 | K124: 0 | L124: 0 | M124: 0 | N124: 0 | O124: 0 | P124: 0 | Q124: 0 | R124: 0 | S124: 0 | T124: 0 | U124: 0 | V124: 0 | W124: 0 | X124: 0 | Y124: 0 | Z124: 0 | AA124: 0 | AB124: 0 | AC124: 0 | AD124: 0 | AE124: 0 | AF124: 0 | AG124: 0 | AH124: 0 | AI124: 0 | AJ124: 0 | AK124: 0 | AL124: 0
A125: REB|INVERSIONES|ARS|FCI_GOAL_CAPITAL_PLUS | B125: REB | C125: INVERSIONES | D125: ARS | F125: FCI Goal Capital Plus | G125: =IFERROR(INDEX(H125:AL125,MATCH(Resumen!$E$1,H$1:AL$1,0)),0) | H125: 0 | I125: 0 | J125: 0 | K125: 0 | L125: 0 | M125: 0 | N125: 0 | O125: 0 | P125: 0 | Q125: 0 | R125: 0 | S125: 0 | T125: 0 | U125: 0 | V125: 0 | W125: 0 | X125: 0 | Y125: 0 | Z125: 0 | AA125: 0 | AB125: 0 | AC125: 0 | AD125: 0 | AE125: 0 | AF125: 0 | AG125: 0 | AH125: 0 | AI125: 0 | AJ125: 0 | AK125: 0 | AL125: 0
A126: REB|INVERSIONES|ARS|IAM_AHORRO_PESOS | B126: REB | C126: INVERSIONES | D126: ARS | F126: IAM Ahorro Pesos | G126: =IFERROR(INDEX(H126:AL126,MATCH(Resumen!$E$1,H$1:AL$1,0)),0) | H126: 0 | I126: 0 | J126: 0 | K126: 0 | L126: 0 | M126: 0 | N126: 0 | O126: 0 | P126: 0 | Q126: 0 | R126: 0 | S126: 0 | T126: 0 | U126: 0 | V126: 0 | W126: 0 | X126: 0 | Y126: 0 | Z126: 0 | AA126: 0 | AB126: 0 | AC126: 0 | AD126: 0 | AE126: 0 | AF126: 0 | AG126: 0 | AH126: 0 | AI126: 0 | AJ126: 0 | AK126: 0 | AL126: 0
A127: REB|INVERSIONES|ARS|PLAZO_FIJO | B127: REB | C127: INVERSIONES | D127: ARS | F127: Plazo Fijo | G127: =IFERROR(INDEX(H127:AL127,MATCH(Resumen!$E$1,H$1:AL$1,0)),0) | H127: 0 | I127: 0 | J127: 0 | K127: 0 | L127: 0 | M127: 0 | N127: 0 | O127: 0 | P127: 0 | Q127: 0 | R127: 0 | S127: 0 | T127: 0 | U127: 0 | V127: 0 | W127: 0 | X127: 0 | Y127: 0 | Z127: 0 | AA127: 0 | AB127: 0 | AC127: 0 | AD127: 0 | AE127: 0 | AF127: 0 | AG127: 0 | AH127: 0 | AI127: 0 | AJ127: 0 | AK127: 0 | AL127: 0
A128: REB|INVERSIONES|ARS|OTROS | B128: REB | C128: INVERSIONES | D128: ARS | F128: Otros | G128: =IFERROR(INDEX(H128:AL128,MATCH(Resumen!$E$1,H$1:AL$1,0)),0) | H128: 0 | I128: 0 | J128: 0 | K128: 0 | L128: 0 | M128: 0 | N128: 0 | O128: 0 | P128: 0 | Q128: 0 | R128: 0 | S128: 0 | T128: 0 | U128: 0 | V128: 0 | W128: 0 | X128: 0 | Y128: 0 | Z128: 0 | AA128: 0 | AB128: 0 | AC128: 0 | AD128: 0 | AE128: 0 | AF128: 0 | AG128: 0 | AH128: 0 | AI128: 0 | AJ128: 0 | AK128: 0 | AL128: 0
A129: UT|CIUDAD|ARS|CC | B129: UT | C129: CIUDAD | D129: ARS | E129: CC | F129: 1) PESOS | G129: =IFERROR(INDEX(H129:AL129,MATCH(Resumen!$E$1,H$1:AL$1,0)),0) | H129: 64792.22 | I129: 64792.22 | J129: -14197.91 | K129: -14215.89 | L129: -14215.89 | M129: -14215.89 | N129: -14215.89 | O129: -14215.89 | P129: -14215.89 | Q129: 485784.11 | R129: 485784.11 | S129: 485784.11 | T129: 485784.11 | U129: 485784.11 | V129: 485784.11 | W129: 485784.11 | X129: 485784.11 | Y129: 485784.11 | Z129: 485784.11 | AA129: 485784.11 | AB129: 485784.11 | AC129: 485784.11 | AD129: 485784.11 | AE129: 485784.11 | AF129: 485784.11 | AG129: 485784.11 | AH129: 485784.11 | AI129: 485784.11 | AJ129: 485784.11 | AK129: 485784.11 | AL129: 485784.11
A130: UT|CIUDAD|ARS|CC#198 | B130: UT | C130: CIUDAD | D130: ARS | E130: CC | F130: 1) PESOS | G130: =IFERROR(INDEX(H130:AL130,MATCH(Resumen!$E$1,H$1:AL$1,0)),0) | H130: 0 | I130: 0 | J130: 0 | K130: 0 | L130: 0 | M130: 0 | N130: 0 | O130: 0 | P130: 0 | Q130: 0 | R130: 0 | S130: 0 | T130: 0 | U130: 0 | V130: 0 | W130: 0 | X130: 0 | Y130: 0 | Z130: 0 | AA130: 0 | AB130: 0 | AC130: 0 | AD130: 0 | AE130: 0 | AF130: 0 | AG130: 0 | AH130: 0 | AI130: 0 | AJ130: 0 | AK130: 0 | AL130: 0
A131: UT|CIUDAD|USD|CC | B131: UT | C131: CIUDAD | D131: USD | E131: CC | F131: 2) DOLARES | G131: =IFERROR(INDEX(H131:AL131,MATCH(Resumen!$E$1,H$1:AL$1,0)),0) | H131: 0 | I131: 0 | J131: 0 | K131: 0 | L131: 0 | M131: 0 | N131: 0 | O131: 0 | P131: 0 | Q131: 0 | R131: 0 | S131: 0 | T131: 0 | U131: 0 | V131: 0 | W131: 0 | X131: 0 | Y131: 0 | Z131: 0 | AA131: 0 | AB131: 0 | AC131: 0 | AD131: 0 | AE131: 0 | AF131: 0 | AG131: 0 | AH131: 0 | AI131: 0 | AJ131: 0 | AK131: 0 | AL131: 0
A132: UT|CIUDAD|EUR|CC | B132: UT | C132: CIUDAD | D132: EUR | E132: CC | F132: 3) EUROS | G132: =IFERROR(INDEX(H132:AL132,MATCH(Resumen!$E$1,H$1:AL$1,0)),0) | H132: 0 | I132: 0 | J132: 0 | K132: 0 | L132: 0 | M132: 0 | N132: 0 | O132: 0 | P132: 0 | Q132: 0 | R132: 0 | S132: 0 | T132: 0 | U132: 0 | V132: 0 | W132: 0 | X132: 0 | Y132: 0 | Z132: 0 | AA132: 0 | AB132: 0 | AC132: 0 | AD132: 0 | AE132: 0 | AF132: 0 | AG132: 0 | AH132: 0 | AI132: 0 | AJ132: 0 | AK132: 0 | AL132: 0
A133: UT|CIUDAD|ARS|LOTBA | B133: UT | C133: CIUDAD | D133: ARS | E133: LOTBA | F133: 1) PESOS (LOTBA) | G133: =IFERROR(INDEX(H133:AL133,MATCH(Resumen!$E$1,H$1:AL$1,0)),0) | H133: 73357.94 | I133: 73357.94 | J133: -5632.19 | K133: -5639.33 | L133: -5639.33 | M133: -5639.33 | N133: -5639.33 | O133: -5639.33 | P133: -5639.33 | Q133: 494360.67 | R133: 494360.67 | S133: 494360.67 | T133: 494360.67 | U133: 494360.67 | V133: 494360.67 | W133: 494360.67 | X133: 494360.67 | Y133: 494360.67 | Z133: 494360.67 | AA133: 494360.67 | AB133: 494360.67 | AC133: 494360.67 | AD133: 494360.67 | AE133: 494360.67 | AF133: 494360.67 | AG133: 494360.67 | AH133: 494360.67 | AI133: 494360.67 | AJ133: 494360.67 | AK133: 494360.67 | AL133: 494360.67
A134: UT|CIUDAD|USD|CC#203 | B134: UT | C134: CIUDAD | D134: USD | E134: CC | F134: 2) DOLARES | G134: =IFERROR(INDEX(H134:AL134,MATCH(Resumen!$E$1,H$1:AL$1,0)),0) | H134: 0 | I134: 0 | J134: 0 | K134: 0 | L134: 0 | M134: 0 | N134: 0 | O134: 0 | P134: 0 | Q134: 0 | R134: 0 | S134: 0 | T134: 0 | U134: 0 | V134: 0 | W134: 0 | X134: 0 | Y134: 0 | Z134: 0 | AA134: 0 | AB134: 0 | AC134: 0 | AD134: 0 | AE134: 0 | AF134: 0 | AG134: 0 | AH134: 0 | AI134: 0 | AJ134: 0 | AK134: 0 | AL134: 0
A135: UT|CIUDAD|EUR|CC#204 | B135: UT | C135: CIUDAD | D135: EUR | E135: CC | F135: 3) EUROS | G135: =IFERROR(INDEX(H135:AL135,MATCH(Resumen!$E$1,H$1:AL$1,0)),0) | H135: 0 | I135: 0 | J135: 0 | K135: 0 | L135: 0 | M135: 0 | N135: 0 | O135: 0 | P135: 0 | Q135: 0 | R135: 0 | S135: 0 | T135: 0 | U135: 0 | V135: 0 | W135: 0 | X135: 0 | Y135: 0 | Z135: 0 | AA135: 0 | AB135: 0 | AC135: 0 | AD135: 0 | AE135: 0 | AF135: 0 | AG135: 0 | AH135: 0 | AI135: 0 | AJ135: 0 | AK135: 0 | AL135: 0
A136: UT|MACRO|ARS|CC | B136: UT | C136: MACRO | D136: ARS | E136: CC | F136: 1) PESOS | G136: =IFERROR(INDEX(H136:AL136,MATCH(Resumen!$E$1,H$1:AL$1,0)),0) | H136: 97301640 | I136: 97301640 | J136: 94354053 | K136: 38813829 | L136: 17200225 | M136: 18748484 | N136: 24136123 | O136: 24136123 | P136: 24136123 | Q136: 34777904 | R136: 56042947 | S136: 68984435 | T136: 62523799 | U136: 68510996 | V136: 68510996 | W136: 68510996 | X136: 73129063 | Y136: 73129063 | Z136: 1.1592018e+08 | AA136: 21658669 | AB136: 15436112 | AC136: 15436112 | AD136: 15436112 | AE136: 14962788 | AF136: 17930596 | AG136: 19201370 | AH136: 31298772 | AI136: 41686251 | AJ136: 41686251 | AK136: 41686251 | AL136: 53223827
A137: UT|MACRO|ARS|TRANSITO | B137: UT | C137: MACRO | D137: ARS | E137: TRANSITO | F137: Deposito en transito | G137: =IFERROR(INDEX(H137:AL137,MATCH(Resumen!$E$1,H$1:AL$1,0)),0) | H137: 0 | I137: 0 | J137: 68010654 | K137: 26917715 | L137: 26706412 | M137: 24035084 | N137: 30628848 | O137: 25693461 | P137: 23283963 | Q137: 26333989 | R137: 30135426 | S137: 25305222 | T137: 22917394 | U137: 24995630 | V137: 0 | W137: 0 | X137: 0 | Y137: 97602163 | Z137: 20976254 | AA137: 21973521 | AB137: 17824526 | AC137: 0 | AD137: 0 | AE137: 52606676 | AF137: 23761621 | AG137: 21622155 | AH137: 18122606 | AI137: 23237596 | AJ137: 0 | AK137: 0 | AL137: 53150120
A138: UT|MACRO|USD|CC | B138: UT | C138: MACRO | D138: USD | E138: CC | F138: 2) DOLARES | G138: =IFERROR(INDEX(H138:AL138,MATCH(Resumen!$E$1,H$1:AL$1,0)),0) | H138: 0 | I138: 0 | J138: 0 | K138: 0 | L138: 0 | M138: 0 | N138: 0 | O138: 0 | P138: 0 | Q138: 0 | R138: 0 | S138: 0 | T138: 0 | U138: 0 | V138: 0 | W138: 0 | X138: 0 | Y138: 0 | Z138: 0 | AA138: 0 | AB138: 0 | AC138: 0 | AD138: 0 | AE138: 0 | AF138: 0 | AG138: 0 | AH138: 0 | AI138: 0 | AJ138: 0 | AK138: 0 | AL138: 0
A139: UT|MACRO|EUR|CC | B139: UT | C139: MACRO | D139: EUR | E139: CC | F139: 3) EUROS | G139: =IFERROR(INDEX(H139:AL139,MATCH(Resumen!$E$1,H$1:AL$1,0)),0) | H139: 0 | I139: 0 | J139: 0 | K139: 0 | L139: 0 | M139: 0 | N139: 0 | O139: 0 | P139: 0 | Q139: 0 | R139: 0 | S139: 0 | T139: 0 | U139: 0 | V139: 0 | W139: 0 | X139: 0 | Y139: 0 | Z139: 0 | AA139: 0 | AB139: 0 | AC139: 0 | AD139: 0 | AE139: 0 | AF139: 0 | AG139: 0 | AH139: 0 | AI139: 0 | AJ139: 0 | AK139: 0 | AL139: 0
A140: UT|INVERSIONES|ARS|FCI_GOAL_PESOS | B140: UT | C140: INVERSIONES | D140: ARS | F140: FCI Goal Pesos | G140: =IFERROR(INDEX(H140:AL140,MATCH(Resumen!$E$1,H$1:AL$1,0)),0) | H140: 0 | I140: 0 | J140: 0 | K140: 155706848 | L140: 155784992 | M140: 155863616 | N140: 155941424 | O140: 155941424 | P140: 155941424 | Q140: 156175360 | R140: 116233168 | S140: 116291024 | T140: 116349496 | U140: 116417600 | V140: 0 | W140: 0 | X140: 0 | Y140: 116660400 | Z140: 116721792 | AA140: 216840976 | AB140: 166928240 | AC140: 0 | AD140: 0 | AE140: 167192640 | AF140: 167279184 | AG140: 167365744 | AH140: 167449872 | AI140: 167532112 | AJ140: 0 | AK140: 0 | AL140: 167786864
A141: BIY|MP|ARS|SALDO | B141: BIY | C141: MP | D141: ARS | F141: BIYEMAS | G141: =IFERROR(INDEX(H141:AL141,MATCH(Resumen!$E$1,H$1:AL$1,0)),0) | H141: 0 | I141: 0 | J141: 4964295 | K141: 1151927 | L141: 2411873 | M141: 3531579 | N141: 5109364 | O141: 0 | P141: 0 | Q141: 5718771 | R141: 1725800 | S141: 2868793 | T141: 0 | U141: 5021816 | V141: 0 | W141: 0 | X141: 0 | Y141: 7115817 | Z141: 892062 | AA141: 1927098 | AB141: 3550440 | AC141: 0 | AD141: 0 | AE141: 0 | AF141: 0 | AG141: 0 | AH141: 0 | AI141: 0 | AJ141: 0 | AK141: 0 | AL141: 0
A142: KAN|MP|ARS|SALDO | B142: KAN | C142: MP | D142: ARS | F142: KANDIKO | G142: =IFERROR(INDEX(H142:AL142,MATCH(Resumen!$E$1,H$1:AL$1,0)),0) | H142: 0 | I142: 0 | J142: 1781454 | K142: 387062 | L142: 837978 | M142: 1370686 | N142: 1765102 | O142: 0 | P142: 0 | Q142: 1853819 | R142: 214997 | S142: 494087 | T142: 0 | U142: 1111186 | V142: 0 | W142: 0 | X142: 0 | Y142: 226234 | Z142: 541570 | AA142: 870564 | AB142: 1141397 | AC142: 0 | AD142: 0 | AE142: 0 | AF142: 0 | AG142: 0 | AH142: 0 | AI142: 0 | AJ142: 0 | AK142: 0 | AL142: 0
A143: REB|MP|ARS|SALDO | B143: REB | C143: MP | D143: ARS | F143: REBISCO | G143: =IFERROR(INDEX(H143:AL143,MATCH(Resumen!$E$1,H$1:AL$1,0)),0) | H143: 0 | I143: 0 | J143: 2217032 | K143: 495420 | L143: 800140 | M143: 1186878 | N143: 1675904 | O143: 0 | P143: 0 | Q143: 2232923 | R143: 653720 | S143: 1292652 | T143: 0 | U143: 2577036 | V143: 0 | W143: 0 | X143: 0 | Y143: 3289002 | Z143: 632946 | AA143: 1215613 | AB143: 1754031 | AC143: 0 | AD143: 0 | AE143: 0 | AF143: 0 | AG143: 0 | AH143: 0 | AI143: 0 | AJ143: 0 | AK143: 0 | AL143: 0
A144: TOT_BINGOS|TOTAL|ARS|CC | B144: TOT_BINGOS | C144: TOTAL | D144: ARS | E144: CC | F144: Pesos | G144: =IFERROR(INDEX(H144:AL144,MATCH(Resumen!$E$1,H$1:AL$1,0)),0) | H144: -79539232 | I144: -39422442 | J144: -4.228572e+08 | K144: -1.1858593e+09 | L144: -43167519 | M144: 2.1570021e+08 | N144: -1.3167187e+08 | O144: -1.2209859e+08 | P144: -1.0388118e+08 | Q144: 2.338821e+08 | R144: -5.4065235e+08 | S144: -7.3645005e+08 | T144: -4.0823443e+08 | U144: -3.6978893e+08 | V144: -3.6218724e+08 | W144: -3.4067403e+08 | X144: -6.6672078e+08 | Y144: -6.0306846e+08 | Z144: -5.8619819e+08 | AA144: -4.2909582e+08 | AB144: -2.5282614e+08 | AC144: -8.36727e+08 | AD144: -8.1538268e+08 | AE144: -5.3258977e+08 | AF144: -5.2655582e+08 | AG144: -4.9517799e+08 | AH144: -1.9991632e+08 | AI144: -92631018 | AJ144: -74860958 | AK144: 50013823 | AL144: 2.0140938e+08
A145: TOT_BINGOS|TOTAL|USD|TOTAL | B145: TOT_BINGOS | C145: TOTAL | D145: USD | F145: USD | G145: =IFERROR(INDEX(H145:AL145,MATCH(Resumen!$E$1,H$1:AL$1,0)),0) | H145: 76764.383 | I145: 76764.383 | J145: 76764.383 | K145: 77561.383 | L145: 77561.383 | M145: 77561.383 | N145: 77561.383 | O145: 77561.383 | P145: 77561.383 | Q145: 77561.383 | R145: 78511.383 | S145: 78511.383 | T145: 79738.383 | U145: 80108.383 | V145: 80108.383 | W145: 80108.383 | X145: 49378.39 | Y145: 80108.383 | Z145: 81505.383 | AA145: 81505.383 | AB145: 81895.383 | AC145: 81941.383 | AD145: 81941.383 | AE145: 81941.383 | AF145: 84145.383 | AG145: 84716.383 | AH145: 65662.383 | AI145: 84658.873 | AJ145: 84748.873 | AK145: 84787.543 | AL145: 84696.133
A146: TOT_BINGOS|TOTAL|EUR|CC | B146: TOT_BINGOS | C146: TOTAL | D146: EUR | E146: CC | F146: Euros | G146: =IFERROR(INDEX(H146:AL146,MATCH(Resumen!$E$1,H$1:AL$1,0)),0) | H146: 0 | I146: 0 | J146: 0 | K146: 0 | L146: 0 | M146: 0 | N146: 0 | O146: 0 | P146: 0 | Q146: 0 | R146: 0 | S146: 0 | T146: 0 | U146: 0 | V146: 0 | W146: 0 | X146: 0 | Y146: 0 | Z146: 0 | AA146: 0 | AB146: 0 | AC146: 0 | AD146: 0 | AE146: 0 | AF146: 0 | AG146: 0 | AH146: 0 | AI146: 0 | AJ146: 0 | AK146: 0 | AL146: 0
A147: UT|TOTAL|ARS|CC | B147: UT | C147: TOTAL | D147: ARS | E147: CC | F147: Pesos | G147: =IFERROR(INDEX(H147:AL147,MATCH(Resumen!$E$1,H$1:AL$1,0)),0) | H147: 97439790 | I147: 97439790 | J147: 1.6234488e+08 | K147: 65711689 | L147: 43886782 | M147: 42763713 | N147: 54745116 | O147: 49809728 | P147: 47400231 | Q147: 62092038 | R147: 87158517 | S147: 95269802 | T147: 86421338 | U147: 94486771 | V147: 69491141 | W147: 69491141 | X147: 74109208 | Y147: 1.7171137e+08 | Z147: 1.3787658e+08 | AA147: 44612335 | AB147: 34240782 | AC147: 16416257 | AD147: 16416257 | AE147: 68549608 | AF147: 42672362 | AG147: 41803670 | AH147: 50401523 | AI147: 65903992 | AJ147: 42666396 | AK147: 42666396 | AL147: 1.0735409e+08
A148: UT|TOTAL|USD|TOTAL | B148: UT | C148: TOTAL | D148: USD | F148: USD | G148: =IFERROR(INDEX(H148:AL148,MATCH(Resumen!$E$1,H$1:AL$1,0)),0) | H148: 0 | I148: 0 | J148: 0 | K148: 0 | L148: 0 | M148: 0 | N148: 0 | O148: 0 | P148: 0 | Q148: 0 | R148: 0 | S148: 0 | T148: 0 | U148: 0 | V148: 0 | W148: 0 | X148: 0 | Y148: 0 | Z148: 0 | AA148: 0 | AB148: 0 | AC148: 0 | AD148: 0 | AE148: 0 | AF148: 0 | AG148: 0 | AH148: 0 | AI148: 0 | AJ148: 0 | AK148: 0 | AL148: 0
A149: UT|TOTAL|EUR|CC | B149: UT | C149: TOTAL | D149: EUR | E149: CC | F149: Euros | G149: =IFERROR(INDEX(H149:AL149,MATCH(Resumen!$E$1,H$1:AL$1,0)),0) | H149: 0 | I149: 0 | J149: 0 | K149: 0 | L149: 0 | M149: 0 | N149: 0 | O149: 0 | P149: 0 | Q149: 0 | R149: 0 | S149: 0 | T149: 0 | U149: 0 | V149: 0 | W149: 0 | X149: 0 | Y149: 0 | Z149: 0 | AA149: 0 | AB149: 0 | AC149: 0 | AD149: 0 | AE149: 0 | AF149: 0 | AG149: 0 | AH149: 0 | AI149: 0 | AJ149: 0 | AK149: 0 | AL149: 0

Sheet Resumen
A1: RESUMEN POSICIONES BANCARIAS Y TESORERIA | D1: Fecha | E1: 46265
A3: 1) Posiciones por Moneda
A5: PESOS | B5: Biyemas | C5: Kandiko | D5: Rebisco | E5: Total | G5: Biyemas Skill ON NET UT
A6: Banco Macro | B6: =SUMIF(Saldos!$A:$A,"BIY|MACRO|ARS|CC",Saldos!$G:$G)+SUMIF(Saldos!$A:$A,"BIY|MACRO|ARS|TRANSITO",Saldos!$G:$G) | C6: =SUMIF(Saldos!$A:$A,"KAN|MACRO|ARS|CC",Saldos!$G:$G)+SUMIF(Saldos!$A:$A,"KAN|MACRO|ARS|TRANSITO",Saldos!$G:$G)+SUMIF(Saldos!$A:$A,"KAN|MACRO|ARS|CA",Saldos!$G:$G) | D6: =SUMIF(Saldos!$A:$A,"REB|MACRO|ARS|CC",Saldos!$G:$G)+SUMIF(Saldos!$A:$A,"REB|MACRO|ARS|TRANSITO",Saldos!$G:$G)+SUMIF(Saldos!$A:$A,"REB|MACRO|ARS|CA",Saldos!$G:$G) | E6: =SUM(B6:D6) | G6: =SUMIF(Saldos!$A:$A,"UT|MACRO|ARS|CC",Saldos!$G:$G)
A7: Banco ITAU | B7: =SUMIF(Saldos!$A:$A,"BIY|ITAU|ARS|CC",Saldos!$G:$G)+SUMIF(Saldos!$A:$A,"BIY|ITAU|ARS|TRANSITO",Saldos!$G:$G)+SUMIF(Saldos!$A:$A,"BIY|ITAU|ARS|AVELLANEDA",Saldos!$G:$G) | C7: =SUMIF(Saldos!$A:$A,"KAN|ITAU|ARS|CC",Saldos!$G:$G) | D7: =SUMIF(Saldos!$A:$A,"REB|ITAU|ARS|CC",Saldos!$G:$G)+SUMIF(Saldos!$A:$A,"REB|ITAU|ARS|TRANSITO",Saldos!$G:$G)+SUMIF(Saldos!$A:$A,"REB|ITAU|ARS|AVELLANEDA",Saldos!$G:$G) | E7: =SUM(B7:D7) | G7: 0
A8: Banco Francés | B8: =SUMIF(Saldos!$A:$A,"BIY|FRANCES|ARS|CC",Saldos!$G:$G) | C8: =SUMIF(Saldos!$A:$A,"KAN|FRANCES|ARS|CC",Saldos!$G:$G) | D8: =SUMIF(Saldos!$A:$A,"REB|FRANCES|ARS|CC",Saldos!$G:$G) | E8: =SUM(B8:D8)
A9: Banco Provincia | B9: =SUMIF(Saldos!$A:$A,"BIY|BAPRO|ARS|CC",Saldos!$G:$G)+SUMIF(Saldos!$A:$A,"BIY|BAPRO|ARS|TRANSITO",Saldos!$G:$G) | C9: =SUMIF(Saldos!$A:$A,"KAN|BAPRO|ARS|CC",Saldos!$G:$G)+SUMIF(Saldos!$A:$A,"KAN|BAPRO|ARS|TRANSITO",Saldos!$G:$G) | D9: =SUMIF(Saldos!$A:$A,"REB|BAPRO|ARS|CC",Saldos!$G:$G)+SUMIF(Saldos!$A:$A,"REB|BAPRO|ARS|TRANSITO",Saldos!$G:$G) | E9: =SUM(B9:D9)
A10: BNA | B10: =SUMIF(Saldos!$A:$A,"BIY|BNA|ARS|CC",Saldos!$G:$G)+SUMIF(Saldos!$A:$A,"BIY|BNA|ARS|TRANSITO",Saldos!$G:$G) | C10: =SUMIF(Saldos!$A:$A,"KAN|BNA|ARS|CC",Saldos!$G:$G)+SUMIF(Saldos!$A:$A,"KAN|BNA|ARS|TRANSITO",Saldos!$G:$G) | D10: =SUMIF(Saldos!$A:$A,"REB|BNA|ARS|CC",Saldos!$G:$G)+SUMIF(Saldos!$A:$A,"REB|BNA|ARS|TRANSITO",Saldos!$G:$G) | E10: =SUM(B10:D10)
A11: Bi Bank | B11: =SUMIF(Saldos!$A:$A,"BIY|BIBANK|ARS|CC",Saldos!$G:$G)+SUMIF(Saldos!$A:$A,"BIY|BIBANK|ARS|TRANSITO",Saldos!$G:$G) | C11: =SUMIF(Saldos!$A:$A,"KAN|BIBANK|ARS|CC",Saldos!$G:$G)+SUMIF(Saldos!$A:$A,"KAN|BIBANK|ARS|TRANSITO",Saldos!$G:$G) | D11: =SUMIF(Saldos!$A:$A,"REB|BIBANK|ARS|CC",Saldos!$G:$G)+SUMIF(Saldos!$A:$A,"REB|BIBANK|ARS|TRANSITO",Saldos!$G:$G) | E11: =SUM(B11:D11)
A12: Banco Industrial | B12: =SUMIF(Saldos!$A:$A,"BIY|BIND|ARS|CC",Saldos!$G:$G)+SUMIF(Saldos!$A:$A,"BIY|BIND|ARS|TRANSITO",Saldos!$G:$G) | C12: =SUMIF(Saldos!$A:$A,"KAN|BIND|ARS|CC",Saldos!$G:$G)+SUMIF(Saldos!$A:$A,"KAN|BIND|ARS|TRANSITO",Saldos!$G:$G) | D12: =SUMIF(Saldos!$A:$A,"REB|BIND|ARS|CC",Saldos!$G:$G)+SUMIF(Saldos!$A:$A,"REB|BIND|ARS|TRANSITO",Saldos!$G:$G) | E12: =SUM(B12:D12)
A13: Maco | B13: =SUMIF(Saldos!$A:$A,"BIY|MACO|ARS|CC",Saldos!$G:$G) | C13: =SUMIF(Saldos!$A:$A,"KAN|MACO|ARS|CC",Saldos!$G:$G) | D13: =SUMIF(Saldos!$A:$A,"REB|MACO|ARS|CC",Saldos!$G:$G) | E13: =SUM(B13:D13)
A14: Banco Ciudad | B14: 0 | C14: 0 | D14: 0 | E14: =SUM(B14:D14) | G14: =SUMIF(Saldos!$A:$A,"UT|CIUDAD|ARS|CC",Saldos!$G:$G)+SUMIF(Saldos!$A:$A,"UT|CIUDAD|ARS|LOTBA",Saldos!$G:$G)
A15: Mercado Pago | B15: =SUMIF(Saldos!$A:$A,"BIY|MP|ARS|SALDO",Saldos!$G:$G) | C15: =SUMIF(Saldos!$A:$A,"KAN|MP|ARS|SALDO",Saldos!$G:$G) | D15: =SUMIF(Saldos!$A:$A,"REB|MP|ARS|SALDO",Saldos!$G:$G) | E15: =SUM(B15:D15) | G15: =SUMIF(Saldos!$A:$A,"UT|MACRO|ARS|TRANSITO",Saldos!$G:$G)
A16: Tesorería | B16: =SUMIF(Saldos!$A:$A,"BIY|TESORERIA|ARS|CC",Saldos!$G:$G) | C16: =SUMIF(Saldos!$A:$A,"KAN|TESORERIA|ARS|CC",Saldos!$G:$G) | D16: =SUMIF(Saldos!$A:$A,"REB|TESORERIA|ARS|CC",Saldos!$G:$G) | E16: =SUM(B16:D16)
A17: Total | B17: =SUM(B6:B16) | C17: =SUM(C6:C16) | D17: =SUM(D6:D16) | E17: =SUM(E6:E16) | G17: =SUM(G6:G16)
A19: DOLARES | B19: Biyemas | C19: Kandiko | D19: Rebisco | E19: Total | G19: Biyemas Skill ON NET UT
A20: Banco Macro | B20: =SUMIF(Saldos!$A:$A,"BIY|MACRO|USD|CC",Saldos!$G:$G) | C20: =SUMIF(Saldos!$A:$A,"KAN|MACRO|USD|CC",Saldos!$G:$G) | D20: =SUMIF(Saldos!$A:$A,"REB|MACRO|USD|CC",Saldos!$G:$G) | E20: =SUM(B20:D20) | G20: 0
A21: Banco ITAU | B21: =SUMIF(Saldos!$A:$A,"BIY|ITAU|USD|CC",Saldos!$G:$G) | C21: =SUMIF(Saldos!$A:$A,"KAN|ITAU|USD|CC",Saldos!$G:$G) | D21: =SUMIF(Saldos!$A:$A,"REB|ITAU|USD|CC",Saldos!$G:$G) | E21: =SUM(B21:D21) | G21: 0
A22: Banco Francés | B22: =SUMIF(Saldos!$A:$A,"BIY|FRANCES|USD|CC",Saldos!$G:$G) | C22: =SUMIF(Saldos!$A:$A,"KAN|FRANCES|USD|CC",Saldos!$G:$G) | D22: =SUMIF(Saldos!$A:$A,"REB|FRANCES|USD|CC",Saldos!$G:$G) | E22: =SUM(B22:D22) | G22: 0
A23: Banco Provincia | B23: =SUMIF(Saldos!$A:$A,"BIY|BAPRO|USD|CC",Saldos!$G:$G) | C23: =SUMIF(Saldos!$A:$A,"KAN|BAPRO|USD|CC",Saldos!$G:$G) | D23: =SUMIF(Saldos!$A:$A,"REB|BAPRO|USD|CC",Saldos!$G:$G) | E23: =SUM(B23:D23) | G23: 0
A24: BNA | B24: =SUMIF(Saldos!$A:$A,"BIY|BNA|USD|CC",Saldos!$G:$G) | C24: =SUMIF(Saldos!$A:$A,"KAN|BNA|USD|CC",Saldos!$G:$G) | D24: =SUMIF(Saldos!$A:$A,"REB|BNA|USD|CC",Saldos!$G:$G) | E24: =SUM(B24:D24) | G24: 0
A25: Bi Bank | B25: =SUMIF(Saldos!$A:$A,"BIY|BIBANK|USD|CC",Saldos!$G:$G) | C25: =SUMIF(Saldos!$A:$A,"KAN|BIBANK|USD|CC",Saldos!$G:$G) | D25: =SUMIF(Saldos!$A:$A,"REB|BIBANK|USD|CC",Saldos!$G:$G) | E25: =SUM(B25:D25) | G25: 0
A26: Banco Industrial | B26: =SUMIF(Saldos!$A:$A,"BIY|BIND|USD|CC",Saldos!$G:$G) | C26: =SUMIF(Saldos!$A:$A,"KAN|BIND|USD|CC",Saldos!$G:$G) | D26: =SUMIF(Saldos!$A:$A,"REB|BIND|USD|CC",Saldos!$G:$G) | E26: =SUM(B26:D26) | G26: 0
A27: Maco | B27: =SUMIF(Saldos!$A:$A,"BIY|MACO|USD|CC",Saldos!$G:$G) | C27: =SUMIF(Saldos!$A:$A,"KAN|MACO|USD|CC",Saldos!$G:$G) | D27: =SUMIF(Saldos!$A:$A,"REB|MACO|USD|CC",Saldos!$G:$G) | E27: =SUM(B27:D27) | G27: 0
A28: Tesorería | B28: =SUMIF(Saldos!$A:$A,"BIY|TESORERIA|USD|CC",Saldos!$G:$G) | C28: =SUMIF(Saldos!$A:$A,"KAN|TESORERIA|USD|CC",Saldos!$G:$G) | D28: =SUMIF(Saldos!$A:$A,"REB|TESORERIA|USD|CC",Saldos!$G:$G) | E28: =SUM(B28:D28) | G28: 0
A29: Total | B29: =SUM(B20:B28) | C29: =SUM(C20:C28) | D29: =SUM(D20:D28) | E29: =SUM(E20:E28) | G29: =SUM(G20:G28)
A31: EUROS | B31: Biyemas | C31: Kandiko | D31: Rebisco | E31: Total | G31: Biyemas Skill ON NET UT
A32: Banco Macro | B32: =SUMIF(Saldos!$A:$A,"BIY|MACRO|EUR|CC",Saldos!$G:$G) | C32: =SUMIF(Saldos!$A:$A,"KAN|MACRO|EUR|CC",Saldos!$G:$G) | D32: =SUMIF(Saldos!$A:$A,"REB|MACRO|EUR|CC",Saldos!$G:$G) | E32: =SUM(B32:D32) | G32: 0
A33: Banco Francés | B33: =SUMIF(Saldos!$A:$A,"BIY|FRANCES|EUR|CC",Saldos!$G:$G) | C33: =SUMIF(Saldos!$A:$A,"KAN|FRANCES|EUR|CC",Saldos!$G:$G) | D33: =SUMIF(Saldos!$A:$A,"REB|FRANCES|EUR|CC",Saldos!$G:$G) | E33: =SUM(B33:D33) | G33: 0
A34: Banco Provincia | B34: =SUMIF(Saldos!$A:$A,"BIY|BAPRO|EUR|CC",Saldos!$G:$G) | C34: =SUMIF(Saldos!$A:$A,"KAN|BAPRO|EUR|CC",Saldos!$G:$G) | D34: =SUMIF(Saldos!$A:$A,"REB|BAPRO|EUR|CC",Saldos!$G:$G) | E34: =SUM(B34:D34) | G34: 0
A35: Maco | B35: =SUMIF(Saldos!$A:$A,"BIY|MACO|EUR|CC",Saldos!$G:$G) | C35: =SUMIF(Saldos!$A:$A,"KAN|MACO|EUR|CC",Saldos!$G:$G) | D35: =SUMIF(Saldos!$A:$A,"REB|MACO|EUR|CC",Saldos!$G:$G) | E35: =SUM(B35:D35) | G35: 0
A36: Tesorería | B36: =SUMIF(Saldos!$A:$A,"BIY|TESORERIA|EUR|CC",Saldos!$G:$G) | C36: =SUMIF(Saldos!$A:$A,"KAN|TESORERIA|EUR|CC",Saldos!$G:$G) | D36: =SUMIF(Saldos!$A:$A,"REB|TESORERIA|EUR|CC",Saldos!$G:$G) | E36: =SUM(B36:D36) | G36: 0
A37: Total | B37: =SUM(B32:B36) | C37: =SUM(C32:C36) | D37: =SUM(D32:D36) | E37: =SUM(E32:E36) | G37: =SUM(G32:G36)
A39: 2) Posiciones Bancarias (Saldos Pesificados)
A41: Cotización Dólar Comprador: | B41: 1400
A42: Cotización Euro Comprador: | B42: 1500
A44: Banco | B44: Biyemas | C44: Kandiko | D44: Rebisco | E44: Total | G44: Biyemas Skill ON NET UT
A45: Macro (PESOS) | B45: =B6 | C45: =C6 | D45: =D6 | E45: =SUM(B45:D45) | G45: 0
A46: ITAU (PESOS) | B46: =B7 | C46: =C7 | D46: =D7 | E46: =SUM(B46:D46) | G46: 0
A47: Francés (PESOS) | B47: =B8 | C47: =C8 | D47: =D8 | E47: =SUM(B47:D47) | G47: 0
A48: Provincia (PESOS) | B48: =B9 | C48: =C9 | D48: =D9 | E48: =SUM(B48:D48) | G48: 0
A49: BNA (PESOS) | B49: =B10 | C49: =C10 | D49: =D10 | E49: =SUM(B49:D49) | G49: 0
A50: BIND (PESOS) | B50: =B12 | C50: =C12 | D50: =D12 | E50: =SUM(B50:D50) | G50: 0
A51: Macro (DOLARES) | B51: =B20*$B$41 | C51: =C20*$B$41 | D51: =D20*$B$41 | E51: =SUM(B51:D51) | G51: 0
A52: ITAU (DOLARES) | B52: =B21*$B$41 | C52: =C21*$B$41 | D52: =D21*$B$41 | E52: =SUM(B52:D52) | G52: 0
A53: Francés (DOLARES) | B53: =B22*$B$41 | C53: =C22*$B$41 | D53: =D22*$B$41 | E53: =SUM(B53:D53) | G53: 0
A54: Provincia (DOLARES) | B54: =B23*$B$41 | C54: =C23*$B$41 | D54: =D23*$B$41 | E54: =SUM(B54:D54) | G54: 0
A55: BNA (DOLARES) | B55: =B24*$B$41 | C55: =C24*$B$41 | D55: =D24*$B$41 | E55: =SUM(B55:D55) | G55: 0
A56: Macro (EUROS) | B56: =B32*$B$42 | C56: =C32*$B$42 | D56: =D32*$B$42 | E56: =SUM(B56:D56) | G56: 0
A57: Francés (EUROS) | B57: =B33*$B$42 | C57: =C33*$B$42 | D57: =D33*$B$42 | E57: =SUM(B57:D57) | G57: 0
A58: Provincia (EUROS) | B58: =B34*$B$42 | C58: =C34*$B$42 | D58: =D34*$B$42 | E58: =SUM(B58:D58) | G58: 0
A59: Ciudad UT (PESOS) | B59: 0 | C59: 0 | D59: 0 | E59: =SUM(B59:D59) | G59: 0
A60: Bi Bank (PESOS) ref | B60: 0 | C60: 0 | D60: 0 | E60: =SUM(B60:D60) | G60: =G16
A61: Total | B61: =SUM(B45:B60) | C61: =SUM(C45:C60) | D61: =SUM(D45:D60) | E61: =SUM(E45:E60) | G61: =SUM(G45:G60)
A63: 3) Resumen Inversiones
A65: Fondo | B65: Biyemas | C65: Kandiko | D65: Rebisco | E65: Total | G65: Biyemas Skill ON NET UT
A66: FCI Pionero Pesos / Goal renta global (slot) | B66: =SUMIF(Saldos!$A:$A,"BIY|INVERSIONES|ARS|FCI_GOAL_RENTA_GLOBAL",Saldos!$G:$G) | C66: =SUMIF(Saldos!$A:$A,"KAN|INVERSIONES|ARS|FCI_PIONERO_PESOS",Saldos!$G:$G) | D66: =SUMIF(Saldos!$A:$A,"REB|INVERSIONES|ARS|FCI_PIONERO_PESOS",Saldos!$G:$G) | E66: =SUM(B66:D66) | G66: 0
A67: FCI Pionero Renta Ahorro | B67: =SUMIF(Saldos!$A:$A,"BIY|INVERSIONES|ARS|FCI_PIONERO_RENTA_AHORRO",Saldos!$G:$G) | C67: =SUMIF(Saldos!$A:$A,"KAN|INVERSIONES|ARS|FCI_PIONERO_RENTA_AHORRO",Saldos!$G:$G) | D67: =SUMIF(Saldos!$A:$A,"REB|INVERSIONES|ARS|FCI_PIONERO_RENTA_AHORRO",Saldos!$G:$G) | E67: =SUM(B67:D67) | G67: 0
A68: FCI Pellegrini / renta crecimiento (slot) | B68: =SUMIF(Saldos!$A:$A,"BIY|INVERSIONES|ARS|FCI_RENTA_CRECIMIENTO",Saldos!$G:$G) | C68: =SUMIF(Saldos!$A:$A,"KAN|INVERSIONES|ARS|FCI_PELLEGRINI_RENTA_PESOS",Saldos!$G:$G) | D68: =SUMIF(Saldos!$A:$A,"REB|INVERSIONES|ARS|FCI_PELLEGRINI_RENTA_PESOS",Saldos!$G:$G) | E68: =SUM(B68:D68) | G68: 0
A69: FCI Goal Pesos | B69: =SUMIF(Saldos!$A:$A,"BIY|INVERSIONES|ARS|FCI_GOAL_PESOS",Saldos!$G:$G) | C69: =SUMIF(Saldos!$A:$A,"KAN|INVERSIONES|ARS|FCI_GOAL_PESOS",Saldos!$G:$G) | D69: =SUMIF(Saldos!$A:$A,"REB|INVERSIONES|ARS|FCI_GOAL_PESOS",Saldos!$G:$G) | E69: =SUM(B69:D69) | G69: =SUMIF(Saldos!$A:$A,"UT|INVERSIONES|ARS|FCI_GOAL_PESOS",Saldos!$G:$G)
A70: FCI acciones / Goal Capital Plus (slot) | B70: =SUMIF(Saldos!$A:$A,"BIY|INVERSIONES|ARS|FCI_ACCIONES_ARGENTINAS",Saldos!$G:$G) | C70: =SUMIF(Saldos!$A:$A,"KAN|INVERSIONES|ARS|FCI_GOAL_CAPITAL_PLUS",Saldos!$G:$G) | D70: =SUMIF(Saldos!$A:$A,"REB|INVERSIONES|ARS|FCI_GOAL_CAPITAL_PLUS",Saldos!$G:$G) | E70: =SUM(B70:D70) | G70: 0
A71: IAM Ahorro Pesos | B71: =SUMIF(Saldos!$A:$A,"BIY|INVERSIONES|ARS|IAM_AHORRO_PESOS",Saldos!$G:$G) | C71: =SUMIF(Saldos!$A:$A,"KAN|INVERSIONES|ARS|IAM_AHORRO_PESOS",Saldos!$G:$G) | D71: =SUMIF(Saldos!$A:$A,"REB|INVERSIONES|ARS|IAM_AHORRO_PESOS",Saldos!$G:$G) | E71: =SUM(B71:D71) | G71: 0
A72: Plazo fijo | B72: =SUMIF(Saldos!$A:$A,"BIY|INVERSIONES|ARS|PLAZO_FIJO",Saldos!$G:$G) | C72: =SUMIF(Saldos!$A:$A,"KAN|INVERSIONES|ARS|PLAZO_FIJO",Saldos!$G:$G) | D72: =SUMIF(Saldos!$A:$A,"REB|INVERSIONES|ARS|PLAZO_FIJO",Saldos!$G:$G) | E72: =SUM(B72:D72) | G72: 0
A73: Otros | B73: =SUMIF(Saldos!$A:$A,"BIY|INVERSIONES|ARS|OTROS",Saldos!$G:$G) | C73: =SUMIF(Saldos!$A:$A,"KAN|INVERSIONES|ARS|FCI_GOAL_PESOS#127",Saldos!$G:$G) | D73: =SUMIF(Saldos!$A:$A,"REB|INVERSIONES|ARS|OTROS",Saldos!$G:$G) | E73: =SUM(B73:D73) | G73: 0
A74: Total | B74: =SUM(B66:B73) | C74: =SUM(C66:C73) | D74: =SUM(D66:D73) | E74: =SUM(E66:E73) | G74: =SUM(G66:G73)
A76: 4) Cheques y proyecciones — pendiente Fase 2/3
A78: Notas
A79: Saldos es el dato base. Cambiar E1 (fecha) actualiza saldo_dia. Provincia USD Kan/Reb corregidos (ya no apuntan a Francés EUR / Macro tránsito).

Sheet _MapaCodigos
A1: celda_resumen | B1: codigos | C1: nota
A2: B6 | B2: BIY|MACRO|ARS|CC + BIY|MACRO|ARS|TRANSITO
A3: C6 | B3: KAN|MACRO|ARS|CC + KAN|MACRO|ARS|TRANSITO + KAN|MACRO|ARS|CA
A4: D6 | B4: REB|MACRO|ARS|CC + REB|MACRO|ARS|TRANSITO + REB|MACRO|ARS|CA
A5: G6 | B5: UT|MACRO|ARS|CC
A6: B7 | B6: BIY|ITAU|ARS|CC + BIY|ITAU|ARS|TRANSITO + BIY|ITAU|ARS|AVELLANEDA
A7: C7 | B7: KAN|ITAU|ARS|CC
A8: D7 | B8: REB|ITAU|ARS|CC + REB|ITAU|ARS|TRANSITO + REB|ITAU|ARS|AVELLANEDA
A9: B8 | B9: BIY|FRANCES|ARS|CC
A10: C8 | B10: KAN|FRANCES|ARS|CC
A11: D8 | B11: REB|FRANCES|ARS|CC
A12: B9 | B12: BIY|BAPRO|ARS|CC + BIY|BAPRO|ARS|TRANSITO
A13: C9 | B13: KAN|BAPRO|ARS|CC + KAN|BAPRO|ARS|TRANSITO
... A44: B23 | B44: BIY|BAPRO|USD|CC
A45: C23 | B45: KAN|BAPRO|USD|CC | C45: FIX vs Excel viejo (antes fila 84 Francés EUR)
A46: D23 | B46: REB|BAPRO|USD|CC | C46: FIX vs Excel viejo (antes fila 135 Macro tránsito)
A47: B24 | B47: BIY|BNA|USD|CC
A48: C24 | B48: KAN|BNA|USD|CC
A49: D24 | B49: REB|BNA|USD|CC
A50: B25 | B50: BIY|BIBANK|USD|CC
A51: C25 | B51: KAN|BIBANK|USD|CC
A52: D25 | B52: REB|BIBANK|USD|CC
A53: B26 | B53: BIY|BIND|USD|CC
A54: C26 | B54: KAN|BIND|USD|CC
A55: D26 | B55: REB|BIND|USD|CC
A56: B27 | B56: BIY|MACO|USD|CC
A57: C27 | B57: KAN|MACO|USD|CC
A58: D27 | B58: REB|MACO|USD|CC
... A86: D73 | B86: REB|INVERSIONES|ARS|OTROS

Sheet _Instrucciones
A1: Cómo usar esta plantilla
A3: 1. Hoja Saldos = dato base. Pegar/importar saldos Interbanking en las columnas de fecha (desde H).
A4: 2. Cada fila tiene un codigo estable (col A). No insertar filas a mano sin mantener el codigo.
A5: 3. Columna G (saldo_dia) toma el valor de la fecha indicada en Resumen!E1.
A6: 4. Resumen no usa HLOOKUP por número de fila: usa SUMIF por codigo.
A7: 5. Completar cotizaciones en Resumen!B41 (USD) y B42 (EUR).
A8: 6. Cheques y hojas por banco se agregan en Fase 2/3.
A9: 7. Generado desde docs/tesoreria/posicion-bancaria-diaria/generar_plantilla_posicion.py
